Workbook

Sheet Conciliacao
A1: Data | B1: Extrato Zig (Saques) | C1: Faturam Dinheiro | D1: Receitas Extraord | E1: Eventos | F1: Entradas Mútuos | G1: Desbloqueios Judiciais | H1: Extrato Bancário (Crédito) | I1: Diferenças (Contas a Receber) | J1: Custos Sem Parcelamento | K1: Custos Com Parcelamento | L1: Saídas Mútuos | M1: Bloqueios Judiciais | N1: Extrato Bancário (Débito) | O1: Diferenças (Contas a Pagar) | P1: Ajustes Conciliação | Q1: Conciliação | BE1: Coluna Auxiliar Data | BF1: Coluna Auxiliar Data 2 | BG1: Coluna Auxiliar Data 3 | BH1: Coluna Auxiliar Data 4
A2: 45658 | B2: =-SUMIFS(df_extrato_zig!G:G,df_extrato_zig!E:E,Conciliacao!A2,df_extrato_zig!D:D,"Saque")-SUMIFS(df_extrato_zig!G:G,df_extrato_zig!E:E,Conciliacao!A2,df_extrato_zig!D:D,"Antecipação") | C2: =SUMIFS(df_extrato_zig!E:E,df_extrato_zig!L:L,Conciliacao!A2,df_extrato_zig!F:F,"DINHEIRO") | D2: =SUMIFS(view_parc_agrup!H:H,view_parc_agrup!G:G,Conciliacao!A2) | E2: =SUMIFS(df_eventos!F:F,df_eventos!H:H,Conciliacao!A2) | F2: =SUMIFS(df_mutuos!M:M,df_mutuos!B:B,Conciliacao!A2) | G2: =SUMIFS(df_bloqueios_judiciais!G:G,df_bloqueios_judiciais!D:D,Conciliacao!A2,df_bloqueios_judiciais!G:G,">0") | H2: =SUMIFS(df_extratos!I:I,df_extratos!F:F,">="&Conciliacao!BE2,df_extratos!F:F,"<"&Conciliacao!BE2+1,df_extratos!G:G,"CREDITO") +SUMIFS(df_extratos!I:I,df_extratos!F:F,">="&Conciliacao!A2, df_extratos!F:F,"<"&Conciliacao!A2+1, df_extratos!G:G,"CREDITO") +SUMIFS(df_extratos!I:I,df_extratos!F:F,">="&Conciliacao!BF2,df_extratos!F:F,"<"&Conciliacao!BF2+1,df_extratos!G:G,"CREDITO") +SUMIFS(df_extratos!I:I,df_extratos!F:F,">="&Conciliacao!BG2,df_extratos!F:F,"<"&Conciliacao!BG2+1,df_extratos!G:G,"CREDITO") +SUMIFS(df_extratos!I:I,df_extratos!F:F,">="&Conciliacao!BH2,df_extratos!F:F,"<"&Conciliacao!BH2+1,df_extratos!G:G,"CREDITO") | I2: =H2-SUM(B2:G2) | J2: =SUMIFS(df_blueme_sem_parcelamento!E:E,df_blueme_sem_parcelamento!H:H,Conciliacao!A2)*(-1) | K2: =SUMIFS(df_blueme_com_parcelamento!J:J,df_blueme_com_parcelamento!M:M,Conciliacao!A2)*(-1) | L2: =SUMIFS(df_mutuos!N:N,df_mutuos!B:B,Conciliacao!A2)*(-1) | M2: =SUMIFS(df_bloqueios_judiciais!E:E,df_bloqueios_judiciais!D:D,Conciliacao!A2,df_bloqueios_judiciais!E:E,"<0") | N2: =SUMIFS(df_extratos!I:I,df_extratos!F:F,">="&Conciliacao!BE2,df_extratos!F:F,"<"&Conciliacao!BE2+1,df_extratos!G:G,"DEBITO") +SUMIFS(df_extratos!I:I,df_extratos!F:F,">="&Conciliacao!A2, df_extratos!F:F,"<"&Conciliacao!A2+1, df_extratos!G:G,"DEBITO") +SUMIFS(df_extratos!I:I,df_extratos!F:F,">="&Conciliacao!BF2,df_extratos!F:F,"<"&Conciliacao!BF2+1,df_extratos!G:G,"DEBITO") +SUMIFS(df_extratos!I:I,df_extratos!F:F,">="&Conciliacao!BG2,df_extratos!F:F,"<"&Conciliacao!BG2+1,df_extratos!G:G,"DEBITO") +SUMIFS(df_extratos!I:I,df_extratos!F:F,">="&Conciliacao!BH2,df_extratos!F:F,"<"&Conciliacao!BH2+1,df_extratos!G:G,"DEBITO") | O2: =N2-SUM(J2:M2) | P2: =SUMIFS(df_ajustes_conciliaco!D:D,df_ajustes_conciliaco!C:C,Conciliacao!A2) | Q2: =O2+I2-P2 | BE2: 45658.5 | BF2: 45658.125 | BG2: 45658.542 | BH2: 45658.625
A3: =A2+1 | B3: =-SUMIFS(df_extrato_zig!G:G,df_extrato_zig!E:E,Conciliacao!A3,df_extrato_zig!D:D,"Saque")-SUMIFS(df_extrato_zig!G:G,df_extrato_zig!E:E,Conciliacao!A3,df_extrato_zig!D:D,"Antecipação") | C3: =SUMIFS(df_extrato_zig!E:E,df_extrato_zig!L:L,Conciliacao!A3,df_extrato_zig!F:F,"DINHEIRO") | D3: =SUMIFS(view_parc_agrup!H:H,view_parc_agrup!G:G,Conciliacao!A3) | E3: =SUMIFS(df_eventos!F:F,df_eventos!H:H,Conciliacao!A3) | F3: =SUMIFS(df_mutuos!M:M,df_mutuos!B:B,Conciliacao!A3) | G3: =SUMIFS(df_bloqueios_judiciais!G:G,df_bloqueios_judiciais!D:D,Conciliacao!A3,df_bloqueios_judiciais!G:G,">0") | H3: =SUMIFS(df_extratos!I:I,df_extratos!F:F,">="&Conciliacao!BE3,df_extratos!F:F,"<"&Conciliacao!BE3+1,df_extratos!G:G,"CREDITO") +SUMIFS(df_extratos!I:I,df_extratos!F:F,">="&Conciliacao!A3, df_extratos!F:F,"<"&Conciliacao!A3+1, df_extratos!G:G,"CREDITO") +SUMIFS(df_extratos!I:I,df_extratos!F:F,">="&Conciliacao!BF3,df_extratos!F:F,"<"&Conciliacao!BF3+1,df_extratos!G:G,"CREDITO") +SUMIFS(df_extratos!I:I,df_extratos!F:F,">="&Conciliacao!BG3,df_extratos!F:F,"<"&Conciliacao!BG3+1,df_extratos!G:G,"CREDITO") +SUMIFS(df_extratos!I:I,df_extratos!F:F,">="&Conciliacao!BH3,df_extratos!F:F,"<"&Conciliacao!BH3+1,df_extratos!G:G,"CREDITO") | I3: =H3-SUM(B3:G3) | J3: =SUMIFS(df_blueme_sem_parcelamento!E:E,df_blueme_sem_parcelamento!H:H,Conciliacao!A3)*(-1) | K3: =SUMIFS(df_blueme_com_parcelamento!J:J,df_blueme_com_parcelamento!M:M,Conciliacao!A3)*(-1) | L3: =SUMIFS(df_mutuos!N:N,df_mutuos!B:B,Conciliacao!A3)*(-1) | M3: =SUMIFS(df_bloqueios_judiciais!E:E,df_bloqueios_judiciais!D:D,Conciliacao!A3,df_bloqueios_judiciais!E:E,"<0") | N3: =SUMIFS(df_extratos!I:I,df_extratos!F:F,">="&Conciliacao!BE3,df_extratos!F:F,"<"&Conciliacao!BE3+1,df_extratos!G:G,"DEBITO") +SUMIFS(df_extratos!I:I,df_extratos!F:F,">="&Conciliacao!A3, df_extratos!F:F,"<"&Conciliacao!A3+1, df_extratos!G:G,"DEBITO") +SUMIFS(df_extratos!I:I,df_extratos!F:F,">="&Conciliacao!BF3,df_extratos!F:F,"<"&Conciliacao!BF3+1,df_extratos!G:G,"DEBITO") +SUMIFS(df_extratos!I:I,df_extratos!F:F,">="&Conciliacao!BG3,df_extratos!F:F,"<"&Conciliacao!BG3+1,df_extratos!G:G,"DEBITO") +SUMIFS(df_extratos!I:I,df_extratos!F:F,">="&Conciliacao!BH3,df_extratos!F:F,"<"&Conciliacao!BH3+1,df_extratos!G:G,"DEBITO") | O3: =N3-SUM(J3:M3) | P3: =SUMIFS(df_ajustes_conciliaco!D:D,df_ajustes_conciliaco!C:C,Conciliacao!A3) | Q3: =O3+I3-P3 | BE3: 45659.5 | BF3: 45659.125 | BG3: 45659.542 | BH3: 45659.625
A4: =A3+1 | B4: =-SUMIFS(df_extrato_zig!G:G,df_extrato_zig!E:E,Conciliacao!A4,df_extrato_zig!D:D,"Saque")-SUMIFS(df_extrato_zig!G:G,df_extrato_zig!E:E,Conciliacao!A4,df_extrato_zig!D:D,"Antecipação") | C4: =SUMIFS(df_extrato_zig!E:E,df_extrato_zig!L:L,Conciliacao!A4,df_extrato_zig!F:F,"DINHEIRO") | D4: =SUMIFS(view_parc_agrup!H:H,view_parc_agrup!G:G,Conciliacao!A4) | E4: =SUMIFS(df_eventos!F:F,df_eventos!H:H,Conciliacao!A4) | F4: =SUMIFS(df_mutuos!M:M,df_mutuos!B:B,Conciliacao!A4) | G4: =SUMIFS(df_bloqueios_judiciais!G:G,df_bloqueios_judiciais!D:D,Conciliacao!A4,df_bloqueios_judiciais!G:G,">0") | H4: =SUMIFS(df_extratos!I:I,df_extratos!F:F,">="&Conciliacao!BE4,df_extratos!F:F,"<"&Conciliacao!BE4+1,df_extratos!G:G,"CREDITO") +SUMIFS(df_extratos!I:I,df_extratos!F:F,">="&Conciliacao!A4, df_extratos!F:F,"<"&Conciliacao!A4+1, df_extratos!G:G,"CREDITO") +SUMIFS(df_extratos!I:I,df_extratos!F:F,">="&Conciliacao!BF4,df_extratos!F:F,"<"&Conciliacao!BF4+1,df_extratos!G:G,"CREDITO") +SUMIFS(df_extratos!I:I,df_extratos!F:F,">="&Conciliacao!BG4,df_extratos!F:F,"<"&Conciliacao!BG4+1,df_extratos!G:G,"CREDITO") +SUMIFS(df_extratos!I:I,df_extratos!F:F,">="&Conciliacao!BH4,df_extratos!F:F,"<"&Conciliacao!BH4+1,df_extratos!G:G,"CREDITO") | I4: =H4-SUM(B4:G4) | J4: =SUMIFS(df_blueme_sem_parcelamento!E:E,df_blueme_sem_parcelamento!H:H,Conciliacao!A4)*(-1) | K4: =SUMIFS(df_blueme_com_parcelamento!J:J,df_blueme_com_parcelamento!M:M,Conciliacao!A4)*(-1) | L4: =SUMIFS(df_mutuos!N:N,df_mutuos!B:B,Conciliacao!A4)*(-1) | M4: =SUMIFS(df_bloqueios_judiciais!E:E,df_bloqueios_judiciais!D:D,Conciliacao!A4,df_bloqueios_judiciais!E:E,"<0") | N4: =SUMIFS(df_extratos!I:I,df_extratos!F:F,">="&Conciliacao!BE4,df_extratos!F:F,"<"&Conciliacao!BE4+1,df_extratos!G:G,"DEBITO") +SUMIFS(df_extratos!I:I,df_extratos!F:F,">="&Conciliacao!A4, df_extratos!F:F,"<"&Conciliacao!A4+1, df_extratos!G:G,"DEBITO") +SUMIFS(df_extratos!I:I,df_extratos!F:F,">="&Conciliacao!BF4,df_extratos!F:F,"<"&Conciliacao!BF4+1,df_extratos!G:G,"DEBITO") +SUMIFS(df_extratos!I:I,df_extratos!F:F,">="&Conciliacao!BG4,df_extratos!F:F,"<"&Conciliacao!BG4+1,df_extratos!G:G,"DEBITO") +SUMIFS(df_extratos!I:I,df_extratos!F:F,">="&Conciliacao!BH4,df_extratos!F:F,"<"&Conciliacao!BH4+1,df_extratos!G:G,"DEBITO") | O4: =N4-SUM(J4:M4) | P4: =SUMIFS(df_ajustes_conciliaco!D:D,df_ajustes_conciliaco!C:C,Conciliacao!A4) | Q4: =O4+I4-P4 | BE4: 45660.5 | BF4: 45660.125 | BG4: 45660.542 | BH4: 45660.625
A5: =A4+1 | B5: =-SUMIFS(df_extrato_zig!G:G,df_extrato_zig!E:E,Conciliacao!A5,df_extrato_zig!D:D,"Saque")-SUMIFS(df_extrato_zig!G:G,df_extrato_zig!E:E,Conciliacao!A5,df_extrato_zig!D:D,"Antecipação") | C5: =SUMIFS(df_extrato_zig!E:E,df_extrato_zig!L:L,Conciliacao!A5,df_extrato_zig!F:F,"DINHEIRO") | D5: =SUMIFS(view_parc_agrup!H:H,view_parc_agrup!G:G,Conciliacao!A5) | E5: =SUMIFS(df_eventos!F:F,df_eventos!H:H,Conciliacao!A5) | F5: =SUMIFS(df_mutuos!M:M,df_mutuos!B:B,Conciliacao!A5) | G5: =SUMIFS(df_bloqueios_judiciais!G:G,df_bloqueios_judiciais!D:D,Conciliacao!A5,df_bloqueios_judiciais!G:G,">0") | H5: =SUMIFS(df_extratos!I:I,df_extratos!F:F,">="&Conciliacao!BE5,df_extratos!F:F,"<"&Conciliacao!BE5+1,df_extratos!G:G,"CREDITO") +SUMIFS(df_extratos!I:I,df_extratos!F:F,">="&Conciliacao!A5, df_extratos!F:F,"<"&Conciliacao!A5+1, df_extratos!G:G,"CREDITO") +SUMIFS(df_extratos!I:I,df_extratos!F:F,">="&Conciliacao!BF5,df_extratos!F:F,"<"&Conciliacao!BF5+1,df_extratos!G:G,"CREDITO") +SUMIFS(df_extratos!I:I,df_extratos!F:F,">="&Conciliacao!BG5,df_extratos!F:F,"<"&Conciliacao!BG5+1,df_extratos!G:G,"CREDITO") +SUMIFS(df_extratos!I:I,df_extratos!F:F,">="&Conciliacao!BH5,df_extratos!F:F,"<"&Conciliacao!BH5+1,df_extratos!G:G,"CREDITO") | I5: =H5-SUM(B5:G5) | J5: =SUMIFS(df_blueme_sem_parcelamento!E:E,df_blueme_sem_parcelamento!H:H,Conciliacao!A5)*(-1) | K5: =SUMIFS(df_blueme_com_parcelamento!J:J,df_blueme_com_parcelamento!M:M,Conciliacao!A5)*(-1) | L5: =SUMIFS(df_mutuos!N:N,df_mutuos!B:B,Conciliacao!A5)*(-1) | M5: =SUMIFS(df_bloqueios_judiciais!E:E,df_bloqueios_judiciais!D:D,Conciliacao!A5,df_bloqueios_judiciais!E:E,"<0") | N5: =SUMIFS(df_extratos!I:I,df_extratos!F:F,">="&Conciliacao!BE5,df_extratos!F:F,"<"&Conciliacao!BE5+1,df_extratos!G:G,"DEBITO") +SUMIFS(df_extratos!I:I,df_extratos!F:F,">="&Conciliacao!A5, df_extratos!F:F,"<"&Conciliacao!A5+1, df_extratos!G:G,"DEBITO") +SUMIFS(df_extratos!I:I,df_extratos!F:F,">="&Conciliacao!BF5,df_extratos!F:F,"<"&Conciliacao!BF5+1,df_extratos!G:G,"DEBITO") +SUMIFS(df_extratos!I:I,df_extratos!F:F,">="&Conciliacao!BG5,df_extratos!F:F,"<"&Conciliacao!BG5+1,df_extratos!G:G,"DEBITO") +SUMIFS(df_extratos!I:I,df_extratos!F:F,">="&Conciliacao!BH5,df_extratos!F:F,"<"&Conciliacao!BH5+1,df_extratos!G:G,"DEBITO") | O5: =N5-SUM(J5:M5) | P5: =SUMIFS(df_ajustes_conciliaco!D:D,df_ajustes_conciliaco!C:C,Conciliacao!A5) | Q5: =O5+I5-P5 | BE5: 45661.5 | BF5: 45661.125 | BG5: 45661.542 | BH5: 45661.625
A6: =A5+1 | B6: =-SUMIFS(df_extrato_zig!G:G,df_extrato_zig!E:E,Conciliacao!A6,df_extrato_zig!D:D,"Saque")-SUMIFS(df_extrato_zig!G:G,df_extrato_zig!E:E,Conciliacao!A6,df_extrato_zig!D:D,"Antecipação") | C6: =SUMIFS(df_extrato_zig!E:E,df_extrato_zig!L:L,Conciliacao!A6,df_extrato_zig!F:F,"DINHEIRO") | D6: =SUMIFS(view_parc_agrup!H:H,view_parc_agrup!G:G,Conciliacao!A6) | E6: =SUMIFS(df_eventos!F:F,df_eventos!H:H,Conciliacao!A6) | F6: =SUMIFS(df_mutuos!M:M,df_mutuos!B:B,Conciliacao!A6) | G6: =SUMIFS(df_bloqueios_judiciais!G:G,df_bloqueios_judiciais!D:D,Conciliacao!A6,df_bloqueios_judiciais!G:G,">0") | H6: =SUMIFS(df_extratos!I:I,df_extratos!F:F,">="&Conciliacao!BE6,df_extratos!F:F,"<"&Conciliacao!BE6+1,df_extratos!G:G,"CREDITO") +SUMIFS(df_extratos!I:I,df_extratos!F:F,">="&Conciliacao!A6, df_extratos!F:F,"<"&Conciliacao!A6+1, df_extratos!G:G,"CREDITO") +SUMIFS(df_extratos!I:I,df_extratos!F:F,">="&Conciliacao!BF6,df_extratos!F:F,"<"&Conciliacao!BF6+1,df_extratos!G:G,"CREDITO") +SUMIFS(df_extratos!I:I,df_extratos!F:F,">="&Conciliacao!BG6,df_extratos!F:F,"<"&Conciliacao!BG6+1,df_extratos!G:G,"CREDITO") +SUMIFS(df_extratos!I:I,df_extratos!F:F,">="&Conciliacao!BH6,df_extratos!F:F,"<"&Conciliacao!BH6+1,df_extratos!G:G,"CREDITO") | I6: =H6-SUM(B6:G6) | J6: =SUMIFS(df_blueme_sem_parcelamento!E:E,df_blueme_sem_parcelamento!H:H,Conciliacao!A6)*(-1) | K6: =SUMIFS(df_blueme_com_parcelamento!J:J,df_blueme_com_parcelamento!M:M,Conciliacao!A6)*(-1) | L6: =SUMIFS(df_mutuos!N:N,df_mutuos!B:B,Conciliacao!A6)*(-1) | M6: =SUMIFS(df_bloqueios_judiciais!E:E,df_bloqueios_judiciais!D:D,Conciliacao!A6,df_bloqueios_judiciais!E:E,"<0") | N6: =SUMIFS(df_extratos!I:I,df_extratos!F:F,">="&Conciliacao!BE6,df_extratos!F:F,"<"&Conciliacao!BE6+1,df_extratos!G:G,"DEBITO") +SUMIFS(df_extratos!I:I,df_extratos!F:F,">="&Conciliacao!A6, df_extratos!F:F,"<"&Conciliacao!A6+1, df_extratos!G:G,"DEBITO") +SUMIFS(df_extratos!I:I,df_extratos!F:F,">="&Conciliacao!BF6,df_extratos!F:F,"<"&Conciliacao!BF6+1,df_extratos!G:G,"DEBITO") +SUMIFS(df_extratos!I:I,df_extratos!F:F,">="&Conciliacao!BG6,df_extratos!F:F,"<"&Conciliacao!BG6+1,df_extratos!G:G,"DEBITO") +SUMIFS(df_extratos!I:I,df_extratos!F:F,">="&Conciliacao!BH6,df_extratos!F:F,"<"&Conciliacao!BH6+1,df_extratos!G:G,"DEBITO") | O6: =N6-SUM(J6:M6) | P6: =SUMIFS(df_ajustes_conciliaco!D:D,df_ajustes_conciliaco!C:C,Conciliacao!A6) | Q6: =O6+I6-P6 | BE6: 45662.5 | BF6: 45662.125 | BG6: 45662.542 | BH6: 45662.625
A7: =A6+1 | B7: =-SUMIFS(df_extrato_zig!G:G,df_extrato_zig!E:E,Conciliacao!A7,df_extrato_zig!D:D,"Saque")-SUMIFS(df_extrato_zig!G:G,df_extrato_zig!E:E,Conciliacao!A7,df_extrato_zig!D:D,"Antecipação") | C7: =SUMIFS(df_extrato_zig!E:E,df_extrato_zig!L:L,Conciliacao!A7,df_extrato_zig!F:F,"DINHEIRO") | D7: =SUMIFS(view_parc_agrup!H:H,view_parc_agrup!G:G,Conciliacao!A7) | E7: =SUMIFS(df_eventos!F:F,df_eventos!H:H,Conciliacao!A7) | F7: =SUMIFS(df_mutuos!M:M,df_mutuos!B:B,Conciliacao!A7) | G7: =SUMIFS(df_bloqueios_judiciais!G:G,df_bloqueios_judiciais!D:D,Conciliacao!A7,df_bloqueios_judiciais!G:G,">0") | H7: =SUMIFS(df_extratos!I:I,df_extratos!F:F,">="&Conciliacao!BE7,df_extratos!F:F,"<"&Conciliacao!BE7+1,df_extratos!G:G,"CREDITO") +SUMIFS(df_extratos!I:I,df_extratos!F:F,">="&Conciliacao!A7, df_extratos!F:F,"<"&Conciliacao!A7+1, df_extratos!G:G,"CREDITO") +SUMIFS(df_extratos!I:I,df_extratos!F:F,">="&Conciliacao!BF7,df_extratos!F:F,"<"&Conciliacao!BF7+1,df_extratos!G:G,"CREDITO") +SUMIFS(df_extratos!I:I,df_extratos!F:F,">="&Conciliacao!BG7,df_extratos!F:F,"<"&Conciliacao!BG7+1,df_extratos!G:G,"CREDITO") +SUMIFS(df_extratos!I:I,df_extratos!F:F,">="&Conciliacao!BH7,df_extratos!F:F,"<"&Conciliacao!BH7+1,df_extratos!G:G,"CREDITO") | I7: =H7-SUM(B7:G7) | J7: =SUMIFS(df_blueme_sem_parcelamento!E:E,df_blueme_sem_parcelamento!H:H,Conciliacao!A7)*(-1) | K7: =SUMIFS(df_blueme_com_parcelamento!J:J,df_blueme_com_parcelamento!M:M,Conciliacao!A7)*(-1) | L7: =SUMIFS(df_mutuos!N:N,df_mutuos!B:B,Conciliacao!A7)*(-1) | M7: =SUMIFS(df_bloqueios_judiciais!E:E,df_bloqueios_judiciais!D:D,Conciliacao!A7,df_bloqueios_judiciais!E:E,"<0") | N7: =SUMIFS(df_extratos!I:I,df_extratos!F:F,">="&Conciliacao!BE7,df_extratos!F:F,"<"&Conciliacao!BE7+1,df_extratos!G:G,"DEBITO") +SUMIFS(df_extratos!I:I,df_extratos!F:F,">="&Conciliacao!A7, df_extratos!F:F,"<"&Conciliacao!A7+1, df_extratos!G:G,"DEBITO") +SUMIFS(df_extratos!I:I,df_extratos!F:F,">="&Conciliacao!BF7,df_extratos!F:F,"<"&Conciliacao!BF7+1,df_extratos!G:G,"DEBITO") +SUMIFS(df_extratos!I:I,df_extratos!F:F,">="&Conciliacao!BG7,df_extratos!F:F,"<"&Conciliacao!BG7+1,df_extratos!G:G,"DEBITO") +SUMIFS(df_extratos!I:I,df_extratos!F:F,">="&Conciliacao!BH7,df_extratos!F:F,"<"&Conciliacao!BH7+1,df_extratos!G:G,"DEBITO") | O7: =N7-SUM(J7:M7) | P7: =SUMIFS(df_ajustes_conciliaco!D:D,df_ajustes_conciliaco!C:C,Conciliacao!A7) | Q7: =O7+I7-P7 | BE7: 45663.5 | BF7: 45663.125 | BG7: 45663.542 | BH7: 45663.625
A8: =A7+1 | B8: =-SUMIFS(df_extrato_zig!G:G,df_extrato_zig!E:E,Conciliacao!A8,df_extrato_zig!D:D,"Saque")-SUMIFS(df_extrato_zig!G:G,df_extrato_zig!E:E,Conciliacao!A8,df_extrato_zig!D:D,"Antecipação") | C8: =SUMIFS(df_extrato_zig!E:E,df_extrato_zig!L:L,Conciliacao!A8,df_extrato_zig!F:F,"DINHEIRO") | D8: =SUMIFS(view_parc_agrup!H:H,view_parc_agrup!G:G,Conciliacao!A8) | E8: =SUMIFS(df_eventos!F:F,df_eventos!H:H,Conciliacao!A8) | F8: =SUMIFS(df_mutuos!M:M,df_mutuos!B:B,Conciliacao!A8) | G8: =SUMIFS(df_bloqueios_judiciais!G:G,df_bloqueios_judiciais!D:D,Conciliacao!A8,df_bloqueios_judiciais!G:G,">0") | H8: =SUMIFS(df_extratos!I:I,df_extratos!F:F,">="&Conciliacao!BE8,df_extratos!F:F,"<"&Conciliacao!BE8+1,df_extratos!G:G,"CREDITO") +SUMIFS(df_extratos!I:I,df_extratos!F:F,">="&Conciliacao!A8, df_extratos!F:F,"<"&Conciliacao!A8+1, df_extratos!G:G,"CREDITO") +SUMIFS(df_extratos!I:I,df_extratos!F:F,">="&Conciliacao!BF8,df_extratos!F:F,"<"&Conciliacao!BF8+1,df_extratos!G:G,"CREDITO") +SUMIFS(df_extratos!I:I,df_extratos!F:F,">="&Conciliacao!BG8,df_extratos!F:F,"<"&Conciliacao!BG8+1,df_extratos!G:G,"CREDITO") +SUMIFS(df_extratos!I:I,df_extratos!F:F,">="&Conciliacao!BH8,df_extratos!F:F,"<"&Conciliacao!BH8+1,df_extratos!G:G,"CREDITO") | I8: =H8-SUM(B8:G8) | J8: =SUMIFS(df_blueme_sem_parcelamento!E:E,df_blueme_sem_parcelamento!H:H,Conciliacao!A8)*(-1) | K8: =SUMIFS(df_blueme_com_parcelamento!J:J,df_blueme_com_parcelamento!M:M,Conciliacao!A8)*(-1) | L8: =SUMIFS(df_mutuos!N:N,df_mutuos!B:B,Conciliacao!A8)*(-1) | M8: =SUMIFS(df_bloqueios_judiciais!E:E,df_bloqueios_judiciais!D:D,Conciliacao!A8,df_bloqueios_judiciais!E:E,"<0") | N8: =SUMIFS(df_extratos!I:I,df_extratos!F:F,">="&Conciliacao!BE8,df_extratos!F:F,"<"&Conciliacao!BE8+1,df_extratos!G:G,"DEBITO") +SUMIFS(df_extratos!I:I,df_extratos!F:F,">="&Conciliacao!A8, df_extratos!F:F,"<"&Conciliacao!A8+1, df_extratos!G:G,"DEBITO") +SUMIFS(df_extratos!I:I,df_extratos!F:F,">="&Conciliacao!BF8,df_extratos!F:F,"<"&Conciliacao!BF8+1,df_extratos!G:G,"DEBITO") +SUMIFS(df_extratos!I:I,df_extratos!F:F,">="&Conciliacao!BG8,df_extratos!F:F,"<"&Conciliacao!BG8+1,df_extratos!G:G,"DEBITO") +SUMIFS(df_extratos!I:I,df_extratos!F:F,">="&Conciliacao!BH8,df_extratos!F:F,"<"&Conciliacao!BH8+1,df_extratos!G:G,"DEBITO") | O8: =N8-SUM(J8:M8) | P8: =SUMIFS(df_ajustes_conciliaco!D:D,df_ajustes_conciliaco!C:C,Conciliacao!A8) | Q8: =O8+I8-P8 | BE8: 45664.5 | BF8: 45664.125 | BG8: 45664.542 | BH8: 45664.625
A9: =A8+1 | B9: =-SUMIFS(df_extrato_zig!G:G,df_extrato_zig!E:E,Conciliacao!A9,df_extrato_zig!D:D,"Saque")-SUMIFS(df_extrato_zig!G:G,df_extrato_zig!E:E,Conciliacao!A9,df_extrato_zig!D:D,"Antecipação") | C9: =SUMIFS(df_extrato_zig!E:E,df_extrato_zig!L:L,Conciliacao!A9,df_extrato_zig!F:F,"DINHEIRO") | D9: =SUMIFS(view_parc_agrup!H:H,view_parc_agrup!G:G,Conciliacao!A9) | E9: =SUMIFS(df_eventos!F:F,df_eventos!H:H,Conciliacao!A9) | F9: =SUMIFS(df_mutuos!M:M,df_mutuos!B:B,Conciliacao!A9) | G9: =SUMIFS(df_bloqueios_judiciais!G:G,df_bloqueios_judiciais!D:D,Conciliacao!A9,df_bloqueios_judiciais!G:G,">0") | H9: =SUMIFS(df_extratos!I:I,df_extratos!F:F,">="&Conciliacao!BE9,df_extratos!F:F,"<"&Conciliacao!BE9+1,df_extratos!G:G,"CREDITO") +SUMIFS(df_extratos!I:I,df_extratos!F:F,">="&Conciliacao!A9, df_extratos!F:F,"<"&Conciliacao!A9+1, df_extratos!G:G,"CREDITO") +SUMIFS(df_extratos!I:I,df_extratos!F:F,">="&Conciliacao!BF9,df_extratos!F:F,"<"&Conciliacao!BF9+1,df_extratos!G:G,"CREDITO") +SUMIFS(df_extratos!I:I,df_extratos!F:F,">="&Conciliacao!BG9,df_extratos!F:F,"<"&Conciliacao!BG9+1,df_extratos!G:G,"CREDITO") +SUMIFS(df_extratos!I:I,df_extratos!F:F,">="&Conciliacao!BH9,df_extratos!F:F,"<"&Conciliacao!BH9+1,df_extratos!G:G,"CREDITO") | I9: =H9-SUM(B9:G9) | J9: =SUMIFS(df_blueme_sem_parcelamento!E:E,df_blueme_sem_parcelamento!H:H,Conciliacao!A9)*(-1) | K9: =SUMIFS(df_blueme_com_parcelamento!J:J,df_blueme_com_parcelamento!M:M,Conciliacao!A9)*(-1) | L9: =SUMIFS(df_mutuos!N:N,df_mutuos!B:B,Conciliacao!A9)*(-1) | M9: =SUMIFS(df_bloqueios_judiciais!E:E,df_bloqueios_judiciais!D:D,Conciliacao!A9,df_bloqueios_judiciais!E:E,"<0") | N9: =SUMIFS(df_extratos!I:I,df_extratos!F:F,">="&Conciliacao!BE9,df_extratos!F:F,"<"&Conciliacao!BE9+1,df_extratos!G:G,"DEBITO") +SUMIFS(df_extratos!I:I,df_extratos!F:F,">="&Conciliacao!A9, df_extratos!F:F,"<"&Conciliacao!A9+1, df_extratos!G:G,"DEBITO") +SUMIFS(df_extratos!I:I,df_extratos!F:F,">="&Conciliacao!BF9,df_extratos!F:F,"<"&Conciliacao!BF9+1,df_extratos!G:G,"DEBITO") +SUMIFS(df_extratos!I:I,df_extratos!F:F,">="&Conciliacao!BG9,df_extratos!F:F,"<"&Conciliacao!BG9+1,df_extratos!G:G,"DEBITO") +SUMIFS(df_extratos!I:I,df_extratos!F:F,">="&Conciliacao!BH9,df_extratos!F:F,"<"&Conciliacao!BH9+1,df_extratos!G:G,"DEBITO") | O9: =N9-SUM(J9:M9) | P9: =SUMIFS(df_ajustes_conciliaco!D:D,df_ajustes_conciliaco!C:C,Conciliacao!A9) | Q9: =O9+I9-P9 | BE9: 45665.5 | BF9: 45665.125 | BG9: 45665.542 | BH9: 45665.625
A10: =A9+1 | B10: =-SUMIFS(df_extrato_zig!G:G,df_extrato_zig!E:E,Conciliacao!A10,df_extrato_zig!D:D,"Saque")-SUMIFS(df_extrato_zig!G:G,df_extrato_zig!E:E,Conciliacao!A10,df_extrato_zig!D:D,"Antecipação") | C10: =SUMIFS(df_extrato_zig!E:E,df_extrato_zig!L:L,Conciliacao!A10,df_extrato_zig!F:F,"DINHEIRO") | D10: =SUMIFS(view_parc_agrup!H:H,view_parc_agrup!G:G,Conciliacao!A10) | E10: =SUMIFS(df_eventos!F:F,df_eventos!H:H,Conciliacao!A10) | F10: =SUMIFS(df_mutuos!M:M,df_mutuos!B:B,Conciliacao!A10) | G10: =SUMIFS(df_bloqueios_judiciais!G:G,df_bloqueios_judiciais!D:D,Conciliacao!A10,df_bloqueios_judiciais!G:G,">0") | H10: =SUMIFS(df_extratos!I:I,df_extratos!F:F,">="&Conciliacao!BE10,df_extratos!F:F,"<"&Conciliacao!BE10+1,df_extratos!G:G,"CREDITO") +SUMIFS(df_extratos!I:I,df_extratos!F:F,">="&Conciliacao!A10, df_extratos!F:F,"<"&Conciliacao!A10+1, df_extratos!G:G,"CREDITO") +SUMIFS(df_extratos!I:I,df_extratos!F:F,">="&Conciliacao!BF10,df_extratos!F:F,"<"&Conciliacao!BF10+1,df_extratos!G:G,"CREDITO") +SUMIFS(df_extratos!I:I,df_extratos!F:F,">="&Conciliacao!BG10,df_extratos!F:F,"<"&Conciliacao!BG10+1,df_extratos!G:G,"CREDITO") +SUMIFS(df_extratos!I:I,df_extratos!F:F,">="&Conciliacao!BH10,df_extratos!F:F,"<"&Conciliacao!BH10+1,df_extratos!G:G,"CREDITO") | I10: =H10-SUM(B10:G10) | J10: =SUMIFS(df_blueme_sem_parcelamento!E:E,df_blueme_sem_parcelamento!H:H,Conciliacao!A10)*(-1) | K10: =SUMIFS(df_blueme_com_parcelamento!J:J,df_blueme_com_parcelamento!M:M,Conciliacao!A10)*(-1) | L10: =SUMIFS(df_mutuos!N:N,df_mutuos!B:B,Conciliacao!A10)*(-1) | M10: =SUMIFS(df_bloqueios_judiciais!E:E,df_bloqueios_judiciais!D:D,Conciliacao!A10,df_bloqueios_judiciais!E:E,"<0") | N10: =SUMIFS(df_extratos!I:I,df_extratos!F:F,">="&Conciliacao!BE10,df_extratos!F:F,"<"&Conciliacao!BE10+1,df_extratos!G:G,"DEBITO") +SUMIFS(df_extratos!I:I,df_extratos!F:F,">="&Conciliacao!A10, df_extratos!F:F,"<"&Conciliacao!A10+1, df_extratos!G:G,"DEBITO") +SUMIFS(df_extratos!I:I,df_extratos!F:F,">="&Conciliacao!BF10,df_extratos!F:F,"<"&Conciliacao!BF10+1,df_extratos!G:G,"DEBITO") +SUMIFS(df_extratos!I:I,df_extratos!F:F,">="&Conciliacao!BG10,df_extratos!F:F,"<"&Conciliacao!BG10+1,df_extratos!G:G,"DEBITO") +SUMIFS(df_extratos!I:I,df_extratos!F:F,">="&Conciliacao!BH10,df_extratos!F:F,"<"&Conciliacao!BH10+1,df_extratos!G:G,"DEBITO") | O10: =N10-SUM(J10:M10) | P10: =SUMIFS(df_ajustes_conciliaco!D:D,df_ajustes_conciliaco!C:C,Conciliacao!A10) | Q10: =O10+I10-P10 | BE10: 45666.5 | BF10: 45666.125 | BG10: 45666.542 | BH10: 45666.625
A11: =A10+1 | B11: =-SUMIFS(df_extrato_zig!G:G,df_extrato_zig!E:E,Conciliacao!A11,df_extrato_zig!D:D,"Saque")-SUMIFS(df_extrato_zig!G:G,df_extrato_zig!E:E,Conciliacao!A11,df_extrato_zig!D:D,"Antecipação") | C11: =SUMIFS(df_extrato_zig!E:E,df_extrato_zig!L:L,Conciliacao!A11,df_extrato_zig!F:F,"DINHEIRO") | D11: =SUMIFS(view_parc_agrup!H:H,view_parc_agrup!G:G,Conciliacao!A11) | E11: =SUMIFS(df_eventos!F:F,df_eventos!H:H,Conciliacao!A11) | F11: =SUMIFS(df_mutuos!M:M,df_mutuos!B:B,Conciliacao!A11) | G11: =SUMIFS(df_bloqueios_judiciais!G:G,df_bloqueios_judiciais!D:D,Conciliacao!A11,df_bloqueios_judiciais!G:G,">0") | H11: =SUMIFS(df_extratos!I:I,df_extratos!F:F,">="&Conciliacao!BE11,df_extratos!F:F,"<"&Conciliacao!BE11+1,df_extratos!G:G,"CREDITO") +SUMIFS(df_extratos!I:I,df_extratos!F:F,">="&Conciliacao!A11, df_extratos!F:F,"<"&Conciliacao!A11+1, df_extratos!G:G,"CREDITO") +SUMIFS(df_extratos!I:I,df_extratos!F:F,">="&Conciliacao!BF11,df_extratos!F:F,"<"&Conciliacao!BF11+1,df_extratos!G:G,"CREDITO") +SUMIFS(df_extratos!I:I,df_extratos!F:F,">="&Conciliacao!BG11,df_extratos!F:F,"<"&Conciliacao!BG11+1,df_extratos!G:G,"CREDITO") +SUMIFS(df_extratos!I:I,df_extratos!F:F,">="&Conciliacao!BH11,df_extratos!F:F,"<"&Conciliacao!BH11+1,df_extratos!G:G,"CREDITO") | I11: =H11-SUM(B11:G11) | J11: =SUMIFS(df_blueme_sem_parcelamento!E:E,df_blueme_sem_parcelamento!H:H,Conciliacao!A11)*(-1) | K11: =SUMIFS(df_blueme_com_parcelamento!J:J,df_blueme_com_parcelamento!M:M,Conciliacao!A11)*(-1) | L11: =SUMIFS(df_mutuos!N:N,df_mutuos!B:B,Conciliacao!A11)*(-1) | M11: =SUMIFS(df_bloqueios_judiciais!E:E,df_bloqueios_judiciais!D:D,Conciliacao!A11,df_bloqueios_judiciais!E:E,"<0") | N11: =SUMIFS(df_extratos!I:I,df_extratos!F:F,">="&Conciliacao!BE11,df_extratos!F:F,"<"&Conciliacao!BE11+1,df_extratos!G:G,"DEBITO") +SUMIFS(df_extratos!I:I,df_extratos!F:F,">="&Conciliacao!A11, df_extratos!F:F,"<"&Conciliacao!A11+1, df_extratos!G:G,"DEBITO") +SUMIFS(df_extratos!I:I,df_extratos!F:F,">="&Conciliacao!BF11,df_extratos!F:F,"<"&Conciliacao!BF11+1,df_extratos!G:G,"DEBITO") +SUMIFS(df_extratos!I:I,df_extratos!F:F,">="&Conciliacao!BG11,df_extratos!F:F,"<"&Conciliacao!BG11+1,df_extratos!G:G,"DEBITO") +SUMIFS(df_extratos!I:I,df_extratos!F:F,">="&Conciliacao!BH11,df_extratos!F:F,"<"&Conciliacao!BH11+1,df_extratos!G:G,"DEBITO") | O11: =N11-SUM(J11:M11) | P11: =SUMIFS(df_ajustes_conciliaco!D:D,df_ajustes_conciliaco!C:C,Conciliacao!A11) | Q11: =O11+I11-P11 | BE11: 45667.5 | BF11: 45667.125 | BG11: 45667.542 | BH11: 45667.625
A12: =A11+1 | B12: =-SUMIFS(df_extrato_zig!G:G,df_extrato_zig!E:E,Conciliacao!A12,df_extrato_zig!D:D,"Saque")-SUMIFS(df_extrato_zig!G:G,df_extrato_zig!E:E,Conciliacao!A12,df_extrato_zig!D:D,"Antecipação") | C12: =SUMIFS(df_extrato_zig!E:E,df_extrato_zig!L:L,Conciliacao!A12,df_extrato_zig!F:F,"DINHEIRO") | D12: =SUMIFS(view_parc_agrup!H:H,view_parc_agrup!G:G,Conciliacao!A12) | E12: =SUMIFS(df_eventos!F:F,df_eventos!H:H,Conciliacao!A12) | F12: =SUMIFS(df_mutuos!M:M,df_mutuos!B:B,Conciliacao!A12) | G12: =SUMIFS(df_bloqueios_judiciais!G:G,df_bloqueios_judiciais!D:D,Conciliacao!A12,df_bloqueios_judiciais!G:G,">0") | H12: =SUMIFS(df_extratos!I:I,df_extratos!F:F,">="&Conciliacao!BE12,df_extratos!F:F,"<"&Conciliacao!BE12+1,df_extratos!G:G,"CREDITO") +SUMIFS(df_extratos!I:I,df_extratos!F:F,">="&Conciliacao!A12, df_extratos!F:F,"<"&Conciliacao!A12+1, df_extratos!G:G,"CREDITO") +SUMIFS(df_extratos!I:I,df_extratos!F:F,">="&Conciliacao!BF12,df_extratos!F:F,"<"&Conciliacao!BF12+1,df_extratos!G:G,"CREDITO") +SUMIFS(df_extratos!I:I,df_extratos!F:F,">="&Conciliacao!BG12,df_extratos!F:F,"<"&Conciliacao!BG12+1,df_extratos!G:G,"CREDITO") +SUMIFS(df_extratos!I:I,df_extratos!F:F,">="&Conciliacao!BH12,df_extratos!F:F,"<"&Conciliacao!BH12+1,df_extratos!G:G,"CREDITO") | I12: =H12-SUM(B12:G12) | J12: =SUMIFS(df_blueme_sem_parcelamento!E:E,df_blueme_sem_parcelamento!H:H,Conciliacao!A12)*(-1) | K12: =SUMIFS(df_blueme_com_parcelamento!J:J,df_blueme_com_parcelamento!M:M,Conciliacao!A12)*(-1) | L12: =SUMIFS(df_mutuos!N:N,df_mutuos!B:B,Conciliacao!A12)*(-1) | M12: =SUMIFS(df_bloqueios_judiciais!E:E,df_bloqueios_judiciais!D:D,Conciliacao!A12,df_bloqueios_judiciais!E:E,"<0") | N12: =SUMIFS(df_extratos!I:I,df_extratos!F:F,">="&Conciliacao!BE12,df_extratos!F:F,"<"&Conciliacao!BE12+1,df_extratos!G:G,"DEBITO") +SUMIFS(df_extratos!I:I,df_extratos!F:F,">="&Conciliacao!A12, df_extratos!F:F,"<"&Conciliacao!A12+1, df_extratos!G:G,"DEBITO") +SUMIFS(df_extratos!I:I,df_extratos!F:F,">="&Conciliacao!BF12,df_extratos!F:F,"<"&Conciliacao!BF12+1,df_extratos!G:G,"DEBITO") +SUMIFS(df_extratos!I:I,df_extratos!F:F,">="&Conciliacao!BG12,df_extratos!F:F,"<"&Conciliacao!BG12+1,df_extratos!G:G,"DEBITO") +SUMIFS(df_extratos!I:I,df_extratos!F:F,">="&Conciliacao!BH12,df_extratos!F:F,"<"&Conciliacao!BH12+1,df_extratos!G:G,"DEBITO") | O12: =N12-SUM(J12:M12) | P12: =SUMIFS(df_ajustes_conciliaco!D:D,df_ajustes_conciliaco!C:C,Conciliacao!A12) | Q12: =O12+I12-P12 | BE12: 45668.5 | BF12: 45668.125 | BG12: 45668.542 | BH12: 45668.625
A13: =A12+1 | B13: =-SUMIFS(df_extrato_zig!G:G,df_extrato_zig!E:E,Conciliacao!A13,df_extrato_zig!D:D,"Saque")-SUMIFS(df_extrato_zig!G:G,df_extrato_zig!E:E,Conciliacao!A13,df_extrato_zig!D:D,"Antecipação") | C13: =SUMIFS(df_extrato_zig!E:E,df_extrato_zig!L:L,Conciliacao!A13,df_extrato_zig!F:F,"DINHEIRO") | D13: =SUMIFS(view_parc_agrup!H:H,view_parc_agrup!G:G,Conciliacao!A13) | E13: =SUMIFS(df_eventos!F:F,df_eventos!H:H,Conciliacao!A13) | F13: =SUMIFS(df_mutuos!M:M,df_mutuos!B:B,Conciliacao!A13) | G13: =SUMIFS(df_bloqueios_judiciais!G:G,df_bloqueios_judiciais!D:D,Conciliacao!A13,df_bloqueios_judiciais!G:G,">0") | H13: =SUMIFS(df_extratos!I:I,df_extratos!F:F,">="&Conciliacao!BE13,df_extratos!F:F,"<"&Conciliacao!BE13+1,df_extratos!G:G,"CREDITO") +SUMIFS(df_extratos!I:I,df_extratos!F:F,">="&Conciliacao!A13, df_extratos!F:F,"<"&Conciliacao!A13+1, df_extratos!G:G,"CREDITO") +SUMIFS(df_extratos!I:I,df_extratos!F:F,">="&Conciliacao!BF13,df_extratos!F:F,"<"&Conciliacao!BF13+1,df_extratos!G:G,"CREDITO") +SUMIFS(df_extratos!I:I,df_extratos!F:F,">="&Conciliacao!BG13,df_extratos!F:F,"<"&Conciliacao!BG13+1,df_extratos!G:G,"CREDITO") +SUMIFS(df_extratos!I:I,df_extratos!F:F,">="&Conciliacao!BH13,df_extratos!F:F,"<"&Conciliacao!BH13+1,df_extratos!G:G,"CREDITO") | I13: =H13-SUM(B13:G13) | J13: =SUMIFS(df_blueme_sem_parcelamento!E:E,df_blueme_sem_parcelamento!H:H,Conciliacao!A13)*(-1) | K13: =SUMIFS(df_blueme_com_parcelamento!J:J,df_blueme_com_parcelamento!M:M,Conciliacao!A13)*(-1) | L13: =SUMIFS(df_mutuos!N:N,df_mutuos!B:B,Conciliacao!A13)*(-1) | M13: =SUMIFS(df_bloqueios_judiciais!E:E,df_bloqueios_judiciais!D:D,Conciliacao!A13,df_bloqueios_judiciais!E:E,"<0") | N13: =SUMIFS(df_extratos!I:I,df_extratos!F:F,">="&Conciliacao!BE13,df_extratos!F:F,"<"&Conciliacao!BE13+1,df_extratos!G:G,"DEBITO") +SUMIFS(df_extratos!I:I,df_extratos!F:F,">="&Conciliacao!A13, df_extratos!F:F,"<"&Conciliacao!A13+1, df_extratos!G:G,"DEBITO") +SUMIFS(df_extratos!I:I,df_extratos!F:F,">="&Conciliacao!BF13,df_extratos!F:F,"<"&Conciliacao!BF13+1,df_extratos!G:G,"DEBITO") +SUMIFS(df_extratos!I:I,df_extratos!F:F,">="&Conciliacao!BG13,df_extratos!F:F,"<"&Conciliacao!BG13+1,df_extratos!G:G,"DEBITO") +SUMIFS(df_extratos!I:I,df_extratos!F:F,">="&Conciliacao!BH13,df_extratos!F:F,"<"&Conciliacao!BH13+1,df_extratos!G:G,"DEBITO") | O13: =N13-SUM(J13:M13) | P13: =SUMIFS(df_ajustes_conciliaco!D:D,df_ajustes_conciliaco!C:C,Conciliacao!A13) | Q13: =O13+I13-P13 | BE13: 45669.5 | BF13: 45669.125 | BG13: 45669.542 | BH13: 45669.625
A14: =A13+1 | B14: =-SUMIFS(df_extrato_zig!G:G,df_extrato_zig!E:E,Conciliacao!A14,df_extrato_zig!D:D,"Saque")-SUMIFS(df_extrato_zig!G:G,df_extrato_zig!E:E,Conciliacao!A14,df_extrato_zig!D:D,"Antecipação") | C14: =SUMIFS(df_extrato_zig!E:E,df_extrato_zig!L:L,Conciliacao!A14,df_extrato_zig!F:F,"DINHEIRO") | D14: =SUMIFS(view_parc_agrup!H:H,view_parc_agrup!G:G,Conciliacao!A14) | E14: =SUMIFS(df_eventos!F:F,df_eventos!H:H,Conciliacao!A14) | F14: =SUMIFS(df_mutuos!M:M,df_mutuos!B:B,Conciliacao!A14) | G14: =SUMIFS(df_bloqueios_judiciais!G:G,df_bloqueios_judiciais!D:D,Conciliacao!A14,df_bloqueios_judiciais!G:G,">0") | H14: =SUMIFS(df_extratos!I:I,df_extratos!F:F,">="&Conciliacao!BE14,df_extratos!F:F,"<"&Conciliacao!BE14+1,df_extratos!G:G,"CREDITO") +SUMIFS(df_extratos!I:I,df_extratos!F:F,">="&Conciliacao!A14, df_extratos!F:F,"<"&Conciliacao!A14+1, df_extratos!G:G,"CREDITO") +SUMIFS(df_extratos!I:I,df_extratos!F:F,">="&Conciliacao!BF14,df_extratos!F:F,"<"&Conciliacao!BF14+1,df_extratos!G:G,"CREDITO") +SUMIFS(df_extratos!I:I,df_extratos!F:F,">="&Conciliacao!BG14,df_extratos!F:F,"<"&Conciliacao!BG14+1,df_extratos!G:G,"CREDITO") +SUMIFS(df_extratos!I:I,df_extratos!F:F,">="&Conciliacao!BH14,df_extratos!F:F,"<"&Conciliacao!BH14+1,df_extratos!G:G,"CREDITO") | I14: =H14-SUM(B14:G14) | J14: =SUMIFS(df_blueme_sem_parcelamento!E:E,df_blueme_sem_parcelamento!H:H,Conciliacao!A14)*(-1) | K14: =SUMIFS(df_blueme_com_parcelamento!J:J,df_blueme_com_parcelamento!M:M,Conciliacao!A14)*(-1) | L14: =SUMIFS(df_mutuos!N:N,df_mutuos!B:B,Conciliacao!A14)*(-1) | M14: =SUMIFS(df_bloqueios_judiciais!E:E,df_bloqueios_judiciais!D:D,Conciliacao!A14,df_bloqueios_judiciais!E:E,"<0") | N14: =SUMIFS(df_extratos!I:I,df_extratos!F:F,">="&Conciliacao!BE14,df_extratos!F:F,"<"&Conciliacao!BE14+1,df_extratos!G:G,"DEBITO") +SUMIFS(df_extratos!I:I,df_extratos!F:F,">="&Conciliacao!A14, df_extratos!F:F,"<"&Conciliacao!A14+1, df_extratos!G:G,"DEBITO") +SUMIFS(df_extratos!I:I,df_extratos!F:F,">="&Conciliacao!BF14,df_extratos!F:F,"<"&Conciliacao!BF14+1,df_extratos!G:G,"DEBITO") +SUMIFS(df_extratos!I:I,df_extratos!F:F,">="&Conciliacao!BG14,df_extratos!F:F,"<"&Conciliacao!BG14+1,df_extratos!G:G,"DEBITO") +SUMIFS(df_extratos!I:I,df_extratos!F:F,">="&Conciliacao!BH14,df_extratos!F:F,"<"&Conciliacao!BH14+1,df_extratos!G:G,"DEBITO") | O14: =N14-SUM(J14:M14) | P14: =SUMIFS(df_ajustes_conciliaco!D:D,df_ajustes_conciliaco!C:C,Conciliacao!A14) | Q14: =O14+I14-P14 | BE14: 45670.5 | BF14: 45670.125 | BG14: 45670.542 | BH14: 45670.625
... A34: =A33+1 | B34: =-SUMIFS(df_extrato_zig!G:G,df_extrato_zig!E:E,Conciliacao!A34,df_extrato_zig!D:D,"Saque")-SUMIFS(df_extrato_zig!G:G,df_extrato_zig!E:E,Conciliacao!A34,df_extrato_zig!D:D,"Antecipação") | C34: =SUMIFS(df_extrato_zig!E:E,df_extrato_zig!L:L,Conciliacao!A34,df_extrato_zig!F:F,"DINHEIRO") | D34: =SUMIFS(view_parc_agrup!H:H,view_parc_agrup!G:G,Conciliacao!A34) | E34: =SUMIFS(df_eventos!F:F,df_eventos!H:H,Conciliacao!A34) | F34: =SUMIFS(df_mutuos!M:M,df_mutuos!B:B,Conciliacao!A34) | G34: =SUMIFS(df_bloqueios_judiciais!G:G,df_bloqueios_judiciais!D:D,Conciliacao!A34,df_bloqueios_judiciais!G:G,">0") | H34: =SUMIFS(df_extratos!I:I,df_extratos!F:F,">="&Conciliacao!BE34,df_extratos!F:F,"<"&Conciliacao!BE34+1,df_extratos!G:G,"CREDITO") +SUMIFS(df_extratos!I:I,df_extratos!F:F,">="&Conciliacao!A34, df_extratos!F:F,"<"&Conciliacao!A34+1, df_extratos!G:G,"CREDITO") +SUMIFS(df_extratos!I:I,df_extratos!F:F,">="&Conciliacao!BF34,df_extratos!F:F,"<"&Conciliacao!BF34+1,df_extratos!G:G,"CREDITO") +SUMIFS(df_extratos!I:I,df_extratos!F:F,">="&Conciliacao!BG34,df_extratos!F:F,"<"&Conciliacao!BG34+1,df_extratos!G:G,"CREDITO") +SUMIFS(df_extratos!I:I,df_extratos!F:F,">="&Conciliacao!BH34,df_extratos!F:F,"<"&Conciliacao!BH34+1,df_extratos!G:G,"CREDITO") | I34: =H34-SUM(B34:G34) | J34: =SUMIFS(df_blueme_sem_parcelamento!E:E,df_blueme_sem_parcelamento!H:H,Conciliacao!A34)*(-1) | K34: =SUMIFS(df_blueme_com_parcelamento!J:J,df_blueme_com_parcelamento!M:M,Conciliacao!A34)*(-1) | L34: =SUMIFS(df_mutuos!N:N,df_mutuos!B:B,Conciliacao!A34)*(-1) | M34: =SUMIFS(df_bloqueios_judiciais!E:E,df_bloqueios_judiciais!D:D,Conciliacao!A34,df_bloqueios_judiciais!E:E,"<0") | N34: =SUMIFS(df_extratos!I:I,df_extratos!F:F,">="&Conciliacao!BE34,df_extratos!F:F,"<"&Conciliacao!BE34+1,df_extratos!G:G,"DEBITO") +SUMIFS(df_extratos!I:I,df_extratos!F:F,">="&Conciliacao!A34, df_extratos!F:F,"<"&Conciliacao!A34+1, df_extratos!G:G,"DEBITO") +SUMIFS(df_extratos!I:I,df_extratos!F:F,">="&Conciliacao!BF34,df_extratos!F:F,"<"&Conciliacao!BF34+1,df_extratos!G:G,"DEBITO") +SUMIFS(df_extratos!I:I,df_extratos!F:F,">="&Conciliacao!BG34,df_extratos!F:F,"<"&Conciliacao!BG34+1,df_extratos!G:G,"DEBITO") +SUMIFS(df_extratos!I:I,df_extratos!F:F,">="&Conciliacao!BH34,df_extratos!F:F,"<"&Conciliacao!BH34+1,df_extratos!G:G,"DEBITO") | O34: =N34-SUM(J34:M34) | P34: =SUMIFS(df_ajustes_conciliaco!D:D,df_ajustes_conciliaco!C:C,Conciliacao!A34) | Q34: =O34+I34-P34 | BE34: 45690.5 | BF34: 45690.125 | BG34: 45690.542 | BH34: 45690.625
A35: =A34+1 | B35: =-SUMIFS(df_extrato_zig!G:G,df_extrato_zig!E:E,Conciliacao!A35,df_extrato_zig!D:D,"Saque")-SUMIFS(df_extrato_zig!G:G,df_extrato_zig!E:E,Conciliacao!A35,df_extrato_zig!D:D,"Antecipação") | C35: =SUMIFS(df_extrato_zig!E:E,df_extrato_zig!L:L,Conciliacao!A35,df_extrato_zig!F:F,"DINHEIRO") | D35: =SUMIFS(view_parc_agrup!H:H,view_parc_agrup!G:G,Conciliacao!A35) | E35: =SUMIFS(df_eventos!F:F,df_eventos!H:H,Conciliacao!A35) | F35: =SUMIFS(df_mutuos!M:M,df_mutuos!B:B,Conciliacao!A35) | G35: =SUMIFS(df_bloqueios_judiciais!G:G,df_bloqueios_judiciais!D:D,Conciliacao!A35,df_bloqueios_judiciais!G:G,">0") | H35: =SUMIFS(df_extratos!I:I,df_extratos!F:F,">="&Conciliacao!BE35,df_extratos!F:F,"<"&Conciliacao!BE35+1,df_extratos!G:G,"CREDITO") +SUMIFS(df_extratos!I:I,df_extratos!F:F,">="&Conciliacao!A35, df_extratos!F:F,"<"&Conciliacao!A35+1, df_extratos!G:G,"CREDITO") +SUMIFS(df_extratos!I:I,df_extratos!F:F,">="&Conciliacao!BF35,df_extratos!F:F,"<"&Conciliacao!BF35+1,df_extratos!G:G,"CREDITO") +SUMIFS(df_extratos!I:I,df_extratos!F:F,">="&Conciliacao!BG35,df_extratos!F:F,"<"&Conciliacao!BG35+1,df_extratos!G:G,"CREDITO") +SUMIFS(df_extratos!I:I,df_extratos!F:F,">="&Conciliacao!BH35,df_extratos!F:F,"<"&Conciliacao!BH35+1,df_extratos!G:G,"CREDITO") | I35: =H35-SUM(B35:G35) | J35: =SUMIFS(df_blueme_sem_parcelamento!E:E,df_blueme_sem_parcelamento!H:H,Conciliacao!A35)*(-1) | K35: =SUMIFS(df_blueme_com_parcelamento!J:J,df_blueme_com_parcelamento!M:M,Conciliacao!A35)*(-1) | L35: =SUMIFS(df_mutuos!N:N,df_mutuos!B:B,Conciliacao!A35)*(-1) | M35: =SUMIFS(df_bloqueios_judiciais!G:G,df_bloqueios_judiciais!D:D,Conciliacao!A35,df_bloqueios_judiciais!G:G,"<0") | N35: =SUMIFS(df_extratos!I:I,df_extratos!F:F,">="&Conciliacao!BE35,df_extratos!F:F,"<"&Conciliacao!BE35+1,df_extratos!G:G,"DEBITO") +SUMIFS(df_extratos!I:I,df_extratos!F:F,">="&Conciliacao!A35, df_extratos!F:F,"<"&Conciliacao!A35+1, df_extratos!G:G,"DEBITO") +SUMIFS(df_extratos!I:I,df_extratos!F:F,">="&Conciliacao!BF35,df_extratos!F:F,"<"&Conciliacao!BF35+1,df_extratos!G:G,"DEBITO") +SUMIFS(df_extratos!I:I,df_extratos!F:F,">="&Conciliacao!BG35,df_extratos!F:F,"<"&Conciliacao!BG35+1,df_extratos!G:G,"DEBITO") +SUMIFS(df_extratos!I:I,df_extratos!F:F,">="&Conciliacao!BH35,df_extratos!F:F,"<"&Conciliacao!BH35+1,df_extratos!G:G,"DEBITO") | O35: =N35-SUM(J35:M35) | P35: =SUMIFS(df_ajustes_conciliaco!D:D,df_ajustes_conciliaco!C:C,Conciliacao!A35) | Q35: =O35+I35-P35 | BE35: 45691.5 | BF35: 45691.125 | BG35: 45691.542 | BH35: 45691.625
A36: =A35+1 | B36: =-SUMIFS(df_extrato_zig!G:G,df_extrato_zig!E:E,Conciliacao!A36,df_extrato_zig!D:D,"Saque")-SUMIFS(df_extrato_zig!G:G,df_extrato_zig!E:E,Conciliacao!A36,df_extrato_zig!D:D,"Antecipação") | C36: =SUMIFS(df_extrato_zig!E:E,df_extrato_zig!L:L,Conciliacao!A36,df_extrato_zig!F:F,"DINHEIRO") | D36: =SUMIFS(view_parc_agrup!H:H,view_parc_agrup!G:G,Conciliacao!A36) | E36: =SUMIFS(df_eventos!F:F,df_eventos!H:H,Conciliacao!A36) | F36: =SUMIFS(df_mutuos!M:M,df_mutuos!B:B,Conciliacao!A36) | G36: =SUMIFS(df_bloqueios_judiciais!G:G,df_bloqueios_judiciais!D:D,Conciliacao!A36,df_bloqueios_judiciais!G:G,">0") | H36: =SUMIFS(df_extratos!I:I,df_extratos!F:F,">="&Conciliacao!BE36,df_extratos!F:F,"<"&Conciliacao!BE36+1,df_extratos!G:G,"CREDITO") +SUMIFS(df_extratos!I:I,df_extratos!F:F,">="&Conciliacao!A36, df_extratos!F:F,"<"&Conciliacao!A36+1, df_extratos!G:G,"CREDITO") +SUMIFS(df_extratos!I:I,df_extratos!F:F,">="&Conciliacao!BF36,df_extratos!F:F,"<"&Conciliacao!BF36+1,df_extratos!G:G,"CREDITO") +SUMIFS(df_extratos!I:I,df_extratos!F:F,">="&Conciliacao!BG36,df_extratos!F:F,"<"&Conciliacao!BG36+1,df_extratos!G:G,"CREDITO") +SUMIFS(df_extratos!I:I,df_extratos!F:F,">="&Conciliacao!BH36,df_extratos!F:F,"<"&Conciliacao!BH36+1,df_extratos!G:G,"CREDITO") | I36: =H36-SUM(B36:G36) | J36: =SUMIFS(df_blueme_sem_parcelamento!E:E,df_blueme_sem_parcelamento!H:H,Conciliacao!A36)*(-1) | K36: =SUMIFS(df_blueme_com_parcelamento!J:J,df_blueme_com_parcelamento!M:M,Conciliacao!A36)*(-1) | L36: =SUMIFS(df_mutuos!N:N,df_mutuos!B:B,Conciliacao!A36)*(-1) | M36: =SUMIFS(df_bloqueios_judiciais!G:G,df_bloqueios_judiciais!D:D,Conciliacao!A36,df_bloqueios_judiciais!G:G,"<0") | N36: =SUMIFS(df_extratos!I:I,df_extratos!F:F,">="&Conciliacao!BE36,df_extratos!F:F,"<"&Conciliacao!BE36+1,df_extratos!G:G,"DEBITO") +SUMIFS(df_extratos!I:I,df_extratos!F:F,">="&Conciliacao!A36, df_extratos!F:F,"<"&Conciliacao!A36+1, df_extratos!G:G,"DEBITO") +SUMIFS(df_extratos!I:I,df_extratos!F:F,">="&Conciliacao!BF36,df_extratos!F:F,"<"&Conciliacao!BF36+1,df_extratos!G:G,"DEBITO") +SUMIFS(df_extratos!I:I,df_extratos!F:F,">="&Conciliacao!BG36,df_extratos!F:F,"<"&Conciliacao!BG36+1,df_extratos!G:G,"DEBITO") +SUMIFS(df_extratos!I:I,df_extratos!F:F,">="&Conciliacao!BH36,df_extratos!F:F,"<"&Conciliacao!BH36+1,df_extratos!G:G,"DEBITO") | O36: =N36-SUM(J36:M36) | P36: =SUMIFS(df_ajustes_conciliaco!D:D,df_ajustes_conciliaco!C:C,Conciliacao!A36) | Q36: =O36+I36-P36 | BE36: 45692.5 | BF36: 45692.125 | BG36: 45692.542 | BH36: 45692.625
A37: =A36+1 | B37: =-SUMIFS(df_extrato_zig!G:G,df_extrato_zig!E:E,Conciliacao!A37,df_extrato_zig!D:D,"Saque")-SUMIFS(df_extrato_zig!G:G,df_extrato_zig!E:E,Conciliacao!A37,df_extrato_zig!D:D,"Antecipação") | C37: =SUMIFS(df_extrato_zig!E:E,df_extrato_zig!L:L,Conciliacao!A37,df_extrato_zig!F:F,"DINHEIRO") | D37: =SUMIFS(view_parc_agrup!H:H,view_parc_agrup!G:G,Conciliacao!A37) | E37: =SUMIFS(df_eventos!F:F,df_eventos!H:H,Conciliacao!A37) | F37: =SUMIFS(df_mutuos!M:M,df_mutuos!B:B,Conciliacao!A37) | G37: =SUMIFS(df_bloqueios_judiciais!G:G,df_bloqueios_judiciais!D:D,Conciliacao!A37,df_bloqueios_judiciais!G:G,">0") | H37: =SUMIFS(df_extratos!I:I,df_extratos!F:F,">="&Conciliacao!BE37,df_extratos!F:F,"<"&Conciliacao!BE37+1,df_extratos!G:G,"CREDITO") +SUMIFS(df_extratos!I:I,df_extratos!F:F,">="&Conciliacao!A37, df_extratos!F:F,"<"&Conciliacao!A37+1, df_extratos!G:G,"CREDITO") +SUMIFS(df_extratos!I:I,df_extratos!F:F,">="&Conciliacao!BF37,df_extratos!F:F,"<"&Conciliacao!BF37+1,df_extratos!G:G,"CREDITO") +SUMIFS(df_extratos!I:I,df_extratos!F:F,">="&Conciliacao!BG37,df_extratos!F:F,"<"&Conciliacao!BG37+1,df_extratos!G:G,"CREDITO") +SUMIFS(df_extratos!I:I,df_extratos!F:F,">="&Conciliacao!BH37,df_extratos!F:F,"<"&Conciliacao!BH37+1,df_extratos!G:G,"CREDITO") | I37: =H37-SUM(B37:G37) | J37: =SUMIFS(df_blueme_sem_parcelamento!E:E,df_blueme_sem_parcelamento!H:H,Conciliacao!A37)*(-1) | K37: =SUMIFS(df_blueme_com_parcelamento!J:J,df_blueme_com_parcelamento!M:M,Conciliacao!A37)*(-1) | L37: =SUMIFS(df_mutuos!N:N,df_mutuos!B:B,Conciliacao!A37)*(-1) | M37: =SUMIFS(df_bloqueios_judiciais!G:G,df_bloqueios_judiciais!D:D,Conciliacao!A37,df_bloqueios_judiciais!G:G,"<0") | N37: =SUMIFS(df_extratos!I:I,df_extratos!F:F,">="&Conciliacao!BE37,df_extratos!F:F,"<"&Conciliacao!BE37+1,df_extratos!G:G,"DEBITO") +SUMIFS(df_extratos!I:I,df_extratos!F:F,">="&Conciliacao!A37, df_extratos!F:F,"<"&Conciliacao!A37+1, df_extratos!G:G,"DEBITO") +SUMIFS(df_extratos!I:I,df_extratos!F:F,">="&Conciliacao!BF37,df_extratos!F:F,"<"&Conciliacao!BF37+1,df_extratos!G:G,"DEBITO") +SUMIFS(df_extratos!I:I,df_extratos!F:F,">="&Conciliacao!BG37,df_extratos!F:F,"<"&Conciliacao!BG37+1,df_extratos!G:G,"DEBITO") +SUMIFS(df_extratos!I:I,df_extratos!F:F,">="&Conciliacao!BH37,df_extratos!F:F,"<"&Conciliacao!BH37+1,df_extratos!G:G,"DEBITO") | O37: =N37-SUM(J37:M37) | P37: =SUMIFS(df_ajustes_conciliaco!D:D,df_ajustes_conciliaco!C:C,Conciliacao!A37) | Q37: =O37+I37-P37 | BE37: 45693.5 | BF37: 45693.125 | BG37: 45693.542 | BH37: 45693.625
A38: =A37+1 | B38: =-SUMIFS(df_extrato_zig!G:G,df_extrato_zig!E:E,Conciliacao!A38,df_extrato_zig!D:D,"Saque")-SUMIFS(df_extrato_zig!G:G,df_extrato_zig!E:E,Conciliacao!A38,df_extrato_zig!D:D,"Antecipação") | C38: =SUMIFS(df_extrato_zig!E:E,df_extrato_zig!L:L,Conciliacao!A38,df_extrato_zig!F:F,"DINHEIRO") | D38: =SUMIFS(view_parc_agrup!H:H,view_parc_agrup!G:G,Conciliacao!A38) | E38: =SUMIFS(df_eventos!F:F,df_eventos!H:H,Conciliacao!A38) | F38: =SUMIFS(df_mutuos!M:M,df_mutuos!B:B,Conciliacao!A38) | G38: =SUMIFS(df_bloqueios_judiciais!G:G,df_bloqueios_judiciais!D:D,Conciliacao!A38,df_bloqueios_judiciais!G:G,">0") | H38: =SUMIFS(df_extratos!I:I,df_extratos!F:F,">="&Conciliacao!BE38,df_extratos!F:F,"<"&Conciliacao!BE38+1,df_extratos!G:G,"CREDITO") +SUMIFS(df_extratos!I:I,df_extratos!F:F,">="&Conciliacao!A38, df_extratos!F:F,"<"&Conciliacao!A38+1, df_extratos!G:G,"CREDITO") +SUMIFS(df_extratos!I:I,df_extratos!F:F,">="&Conciliacao!BF38,df_extratos!F:F,"<"&Conciliacao!BF38+1,df_extratos!G:G,"CREDITO") +SUMIFS(df_extratos!I:I,df_extratos!F:F,">="&Conciliacao!BG38,df_extratos!F:F,"<"&Conciliacao!BG38+1,df_extratos!G:G,"CREDITO") +SUMIFS(df_extratos!I:I,df_extratos!F:F,">="&Conciliacao!BH38,df_extratos!F:F,"<"&Conciliacao!BH38+1,df_extratos!G:G,"CREDITO") | I38: =H38-SUM(B38:G38) | J38: =SUMIFS(df_blueme_sem_parcelamento!E:E,df_blueme_sem_parcelamento!H:H,Conciliacao!A38)*(-1) | K38: =SUMIFS(df_blueme_com_parcelamento!J:J,df_blueme_com_parcelamento!M:M,Conciliacao!A38)*(-1) | L38: =SUMIFS(df_mutuos!N:N,df_mutuos!B:B,Conciliacao!A38)*(-1) | M38: =SUMIFS(df_bloqueios_judiciais!G:G,df_bloqueios_judiciais!D:D,Conciliacao!A38,df_bloqueios_judiciais!G:G,"<0") | N38: =SUMIFS(df_extratos!I:I,df_extratos!F:F,">="&Conciliacao!BE38,df_extratos!F:F,"<"&Conciliacao!BE38+1,df_extratos!G:G,"DEBITO") +SUMIFS(df_extratos!I:I,df_extratos!F:F,">="&Conciliacao!A38, df_extratos!F:F,"<"&Conciliacao!A38+1, df_extratos!G:G,"DEBITO") +SUMIFS(df_extratos!I:I,df_extratos!F:F,">="&Conciliacao!BF38,df_extratos!F:F,"<"&Conciliacao!BF38+1,df_extratos!G:G,"DEBITO") +SUMIFS(df_extratos!I:I,df_extratos!F:F,">="&Conciliacao!BG38,df_extratos!F:F,"<"&Conciliacao!BG38+1,df_extratos!G:G,"DEBITO") +SUMIFS(df_extratos!I:I,df_extratos!F:F,">="&Conciliacao!BH38,df_extratos!F:F,"<"&Conciliacao!BH38+1,df_extratos!G:G,"DEBITO") | O38: =N38-SUM(J38:M38) | P38: =SUMIFS(df_ajustes_conciliaco!D:D,df_ajustes_conciliaco!C:C,Conciliacao!A38) | Q38: =O38+I38-P38 | BE38: 45694.5 | BF38: 45694.125 | BG38: 45694.542 | BH38: 45694.625
A39: =A38+1 | B39: =-SUMIFS(df_extrato_zig!G:G,df_extrato_zig!E:E,Conciliacao!A39,df_extrato_zig!D:D,"Saque")-SUMIFS(df_extrato_zig!G:G,df_extrato_zig!E:E,Conciliacao!A39,df_extrato_zig!D:D,"Antecipação") | C39: =SUMIFS(df_extrato_zig!E:E,df_extrato_zig!L:L,Conciliacao!A39,df_extrato_zig!F:F,"DINHEIRO") | D39: =SUMIFS(view_parc_agrup!H:H,view_parc_agrup!G:G,Conciliacao!A39) | E39: =SUMIFS(df_eventos!F:F,df_eventos!H:H,Conciliacao!A39) | F39: =SUMIFS(df_mutuos!M:M,df_mutuos!B:B,Conciliacao!A39) | G39: =SUMIFS(df_bloqueios_judiciais!G:G,df_bloqueios_judiciais!D:D,Conciliacao!A39,df_bloqueios_judiciais!G:G,">0") | H39: =SUMIFS(df_extratos!I:I,df_extratos!F:F,">="&Conciliacao!BE39,df_extratos!F:F,"<"&Conciliacao!BE39+1,df_extratos!G:G,"CREDITO") +SUMIFS(df_extratos!I:I,df_extratos!F:F,">="&Conciliacao!A39, df_extratos!F:F,"<"&Conciliacao!A39+1, df_extratos!G:G,"CREDITO") +SUMIFS(df_extratos!I:I,df_extratos!F:F,">="&Conciliacao!BF39,df_extratos!F:F,"<"&Conciliacao!BF39+1,df_extratos!G:G,"CREDITO") +SUMIFS(df_extratos!I:I,df_extratos!F:F,">="&Conciliacao!BG39,df_extratos!F:F,"<"&Conciliacao!BG39+1,df_extratos!G:G,"CREDITO") +SUMIFS(df_extratos!I:I,df_extratos!F:F,">="&Conciliacao!BH39,df_extratos!F:F,"<"&Conciliacao!BH39+1,df_extratos!G:G,"CREDITO") | I39: =H39-SUM(B39:G39) | J39: =SUMIFS(df_blueme_sem_parcelamento!E:E,df_blueme_sem_parcelamento!H:H,Conciliacao!A39)*(-1) | K39: =SUMIFS(df_blueme_com_parcelamento!J:J,df_blueme_com_parcelamento!M:M,Conciliacao!A39)*(-1) | L39: =SUMIFS(df_mutuos!N:N,df_mutuos!B:B,Conciliacao!A39)*(-1) | M39: =SUMIFS(df_bloqueios_judiciais!G:G,df_bloqueios_judiciais!D:D,Conciliacao!A39,df_bloqueios_judiciais!G:G,"<0") | N39: =SUMIFS(df_extratos!I:I,df_extratos!F:F,">="&Conciliacao!BE39,df_extratos!F:F,"<"&Conciliacao!BE39+1,df_extratos!G:G,"DEBITO") +SUMIFS(df_extratos!I:I,df_extratos!F:F,">="&Conciliacao!A39, df_extratos!F:F,"<"&Conciliacao!A39+1, df_extratos!G:G,"DEBITO") +SUMIFS(df_extratos!I:I,df_extratos!F:F,">="&Conciliacao!BF39,df_extratos!F:F,"<"&Conciliacao!BF39+1,df_extratos!G:G,"DEBITO") +SUMIFS(df_extratos!I:I,df_extratos!F:F,">="&Conciliacao!BG39,df_extratos!F:F,"<"&Conciliacao!BG39+1,df_extratos!G:G,"DEBITO") +SUMIFS(df_extratos!I:I,df_extratos!F:F,">="&Conciliacao!BH39,df_extratos!F:F,"<"&Conciliacao!BH39+1,df_extratos!G:G,"DEBITO") | O39: =N39-SUM(J39:M39) | P39: =SUMIFS(df_ajustes_conciliaco!D:D,df_ajustes_conciliaco!C:C,Conciliacao!A39) | Q39: =O39+I39-P39 | BE39: 45695.5 | BF39: 45695.125 | BG39: 45695.542 | BH39: 45695.625
A40: =A39+1 | B40: =-SUMIFS(df_extrato_zig!G:G,df_extrato_zig!E:E,Conciliacao!A40,df_extrato_zig!D:D,"Saque")-SUMIFS(df_extrato_zig!G:G,df_extrato_zig!E:E,Conciliacao!A40,df_extrato_zig!D:D,"Antecipação") | C40: =SUMIFS(df_extrato_zig!E:E,df_extrato_zig!L:L,Conciliacao!A40,df_extrato_zig!F:F,"DINHEIRO") | D40: =SUMIFS(view_parc_agrup!H:H,view_parc_agrup!G:G,Conciliacao!A40) | E40: =SUMIFS(df_eventos!F:F,df_eventos!H:H,Conciliacao!A40) | F40: =SUMIFS(df_mutuos!M:M,df_mutuos!B:B,Conciliacao!A40) | G40: =SUMIFS(df_bloqueios_judiciais!G:G,df_bloqueios_judiciais!D:D,Conciliacao!A40,df_bloqueios_judiciais!G:G,">0") | H40: =SUMIFS(df_extratos!I:I,df_extratos!F:F,">="&Conciliacao!BE40,df_extratos!F:F,"<"&Conciliacao!BE40+1,df_extratos!G:G,"CREDITO") +SUMIFS(df_extratos!I:I,df_extratos!F:F,">="&Conciliacao!A40, df_extratos!F:F,"<"&Conciliacao!A40+1, df_extratos!G:G,"CREDITO") +SUMIFS(df_extratos!I:I,df_extratos!F:F,">="&Conciliacao!BF40,df_extratos!F:F,"<"&Conciliacao!BF40+1,df_extratos!G:G,"CREDITO") +SUMIFS(df_extratos!I:I,df_extratos!F:F,">="&Conciliacao!BG40,df_extratos!F:F,"<"&Conciliacao!BG40+1,df_extratos!G:G,"CREDITO") +SUMIFS(df_extratos!I:I,df_extratos!F:F,">="&Conciliacao!BH40,df_extratos!F:F,"<"&Conciliacao!BH40+1,df_extratos!G:G,"CREDITO") | I40: =H40-SUM(B40:G40) | J40: =SUMIFS(df_blueme_sem_parcelamento!E:E,df_blueme_sem_parcelamento!H:H,Conciliacao!A40)*(-1) | K40: =SUMIFS(df_blueme_com_parcelamento!J:J,df_blueme_com_parcelamento!M:M,Conciliacao!A40)*(-1) | L40: =SUMIFS(df_mutuos!N:N,df_mutuos!B:B,Conciliacao!A40)*(-1) | M40: =SUMIFS(df_bloqueios_judiciais!G:G,df_bloqueios_judiciais!D:D,Conciliacao!A40,df_bloqueios_judiciais!G:G,"<0") | N40: =SUMIFS(df_extratos!I:I,df_extratos!F:F,">="&Conciliacao!BE40,df_extratos!F:F,"<"&Conciliacao!BE40+1,df_extratos!G:G,"DEBITO") +SUMIFS(df_extratos!I:I,df_extratos!F:F,">="&Conciliacao!A40, df_extratos!F:F,"<"&Conciliacao!A40+1, df_extratos!G:G,"DEBITO") +SUMIFS(df_extratos!I:I,df_extratos!F:F,">="&Conciliacao!BF40,df_extratos!F:F,"<"&Conciliacao!BF40+1,df_extratos!G:G,"DEBITO") +SUMIFS(df_extratos!I:I,df_extratos!F:F,">="&Conciliacao!BG40,df_extratos!F:F,"<"&Conciliacao!BG40+1,df_extratos!G:G,"DEBITO") +SUMIFS(df_extratos!I:I,df_extratos!F:F,">="&Conciliacao!BH40,df_extratos!F:F,"<"&Conciliacao!BH40+1,df_extratos!G:G,"DEBITO") | O40: =N40-SUM(J40:M40) | P40: =SUMIFS(df_ajustes_conciliaco!D:D,df_ajustes_conciliaco!C:C,Conciliacao!A40) | Q40: =O40+I40-P40 | BE40: 45696.5 | BF40: 45696.125 | BG40: 45696.542 | BH40: 45696.625
A41: =A40+1 | B41: =-SUMIFS(df_extrato_zig!G:G,df_extrato_zig!E:E,Conciliacao!A41,df_extrato_zig!D:D,"Saque")-SUMIFS(df_extrato_zig!G:G,df_extrato_zig!E:E,Conciliacao!A41,df_extrato_zig!D:D,"Antecipação") | C41: =SUMIFS(df_extrato_zig!E:E,df_extrato_zig!L:L,Conciliacao!A41,df_extrato_zig!F:F,"DINHEIRO") | D41: =SUMIFS(view_parc_agrup!H:H,view_parc_agrup!G:G,Conciliacao!A41) | E41: =SUMIFS(df_eventos!F:F,df_eventos!H:H,Conciliacao!A41) | F41: =SUMIFS(df_mutuos!M:M,df_mutuos!B:B,Conciliacao!A41) | G41: =SUMIFS(df_bloqueios_judiciais!G:G,df_bloqueios_judiciais!D:D,Conciliacao!A41,df_bloqueios_judiciais!G:G,">0") | H41: =SUMIFS(df_extratos!I:I,df_extratos!F:F,">="&Conciliacao!BE41,df_extratos!F:F,"<"&Conciliacao!BE41+1,df_extratos!G:G,"CREDITO") +SUMIFS(df_extratos!I:I,df_extratos!F:F,">="&Conciliacao!A41, df_extratos!F:F,"<"&Conciliacao!A41+1, df_extratos!G:G,"CREDITO") +SUMIFS(df_extratos!I:I,df_extratos!F:F,">="&Conciliacao!BF41,df_extratos!F:F,"<"&Conciliacao!BF41+1,df_extratos!G:G,"CREDITO") +SUMIFS(df_extratos!I:I,df_extratos!F:F,">="&Conciliacao!BG41,df_extratos!F:F,"<"&Conciliacao!BG41+1,df_extratos!G:G,"CREDITO") +SUMIFS(df_extratos!I:I,df_extratos!F:F,">="&Conciliacao!BH41,df_extratos!F:F,"<"&Conciliacao!BH41+1,df_extratos!G:G,"CREDITO") | I41: =H41-SUM(B41:G41) | J41: =SUMIFS(df_blueme_sem_parcelamento!E:E,df_blueme_sem_parcelamento!H:H,Conciliacao!A41)*(-1) | K41: =SUMIFS(df_blueme_com_parcelamento!J:J,df_blueme_com_parcelamento!M:M,Conciliacao!A41)*(-1) | L41: =SUMIFS(df_mutuos!N:N,df_mutuos!B:B,Conciliacao!A41)*(-1) | M41: =SUMIFS(df_bloqueios_judiciais!G:G,df_bloqueios_judiciais!D:D,Conciliacao!A41,df_bloqueios_judiciais!G:G,"<0") | N41: =SUMIFS(df_extratos!I:I,df_extratos!F:F,">="&Conciliacao!BE41,df_extratos!F:F,"<"&Conciliacao!BE41+1,df_extratos!G:G,"DEBITO") +SUMIFS(df_extratos!I:I,df_extratos!F:F,">="&Conciliacao!A41, df_extratos!F:F,"<"&Conciliacao!A41+1, df_extratos!G:G,"DEBITO") +SUMIFS(df_extratos!I:I,df_extratos!F:F,">="&Conciliacao!BF41,df_extratos!F:F,"<"&Conciliacao!BF41+1,df_extratos!G:G,"DEBITO") +SUMIFS(df_extratos!I:I,df_extratos!F:F,">="&Conciliacao!BG41,df_extratos!F:F,"<"&Conciliacao!BG41+1,df_extratos!G:G,"DEBITO") +SUMIFS(df_extratos!I:I,df_extratos!F:F,">="&Conciliacao!BH41,df_extratos!F:F,"<"&Conciliacao!BH41+1,df_extratos!G:G,"DEBITO") | O41: =N41-SUM(J41:M41) | P41: =SUMIFS(df_ajustes_conciliaco!D:D,df_ajustes_conciliaco!C:C,Conciliacao!A41) | Q41: =O41+I41-P41 | BE41: 45697.5 | BF41: 45697.125 | BG41: 45697.542 | BH41: 45697.625
A42: =A41+1 | B42: =-SUMIFS(df_extrato_zig!G:G,df_extrato_zig!E:E,Conciliacao!A42,df_extrato_zig!D:D,"Saque")-SUMIFS(df_extrato_zig!G:G,df_extrato_zig!E:E,Conciliacao!A42,df_extrato_zig!D:D,"Antecipação") | C42: =SUMIFS(df_extrato_zig!E:E,df_extrato_zig!L:L,Conciliacao!A42,df_extrato_zig!F:F,"DINHEIRO") | D42: =SUMIFS(view_parc_agrup!H:H,view_parc_agrup!G:G,Conciliacao!A42) | E42: =SUMIFS(df_eventos!F:F,df_eventos!H:H,Conciliacao!A42) | F42: =SUMIFS(df_mutuos!M:M,df_mutuos!B:B,Conciliacao!A42) | G42: =SUMIFS(df_bloqueios_judiciais!G:G,df_bloqueios_judiciais!D:D,Conciliacao!A42,df_bloqueios_judiciais!G:G,">0") | H42: =SUMIFS(df_extratos!I:I,df_extratos!F:F,">="&Conciliacao!BE42,df_extratos!F:F,"<"&Conciliacao!BE42+1,df_extratos!G:G,"CREDITO") +SUMIFS(df_extratos!I:I,df_extratos!F:F,">="&Conciliacao!A42, df_extratos!F:F,"<"&Conciliacao!A42+1, df_extratos!G:G,"CREDITO") +SUMIFS(df_extratos!I:I,df_extratos!F:F,">="&Conciliacao!BF42,df_extratos!F:F,"<"&Conciliacao!BF42+1,df_extratos!G:G,"CREDITO") +SUMIFS(df_extratos!I:I,df_extratos!F:F,">="&Conciliacao!BG42,df_extratos!F:F,"<"&Conciliacao!BG42+1,df_extratos!G:G,"CREDITO") +SUMIFS(df_extratos!I:I,df_extratos!F:F,">="&Conciliacao!BH42,df_extratos!F:F,"<"&Conciliacao!BH42+1,df_extratos!G:G,"CREDITO") | I42: =H42-SUM(B42:G42) | J42: =SUMIFS(df_blueme_sem_parcelamento!E:E,df_blueme_sem_parcelamento!H:H,Conciliacao!A42)*(-1) | K42: =SUMIFS(df_blueme_com_parcelamento!J:J,df_blueme_com_parcelamento!M:M,Conciliacao!A42)*(-1) | L42: =SUMIFS(df_mutuos!N:N,df_mutuos!B:B,Conciliacao!A42)*(-1) | M42: =SUMIFS(df_bloqueios_judiciais!G:G,df_bloqueios_judiciais!D:D,Conciliacao!A42,df_bloqueios_judiciais!G:G,"<0") | N42: =SUMIFS(df_extratos!I:I,df_extratos!F:F,">="&Conciliacao!BE42,df_extratos!F:F,"<"&Conciliacao!BE42+1,df_extratos!G:G,"DEBITO") +SUMIFS(df_extratos!I:I,df_extratos!F:F,">="&Conciliacao!A42, df_extratos!F:F,"<"&Conciliacao!A42+1, df_extratos!G:G,"DEBITO") +SUMIFS(df_extratos!I:I,df_extratos!F:F,">="&Conciliacao!BF42,df_extratos!F:F,"<"&Conciliacao!BF42+1,df_extratos!G:G,"DEBITO") +SUMIFS(df_extratos!I:I,df_extratos!F:F,">="&Conciliacao!BG42,df_extratos!F:F,"<"&Conciliacao!BG42+1,df_extratos!G:G,"DEBITO") +SUMIFS(df_extratos!I:I,df_extratos!F:F,">="&Conciliacao!BH42,df_extratos!F:F,"<"&Conciliacao!BH42+1,df_extratos!G:G,"DEBITO") | O42: =N42-SUM(J42:M42) | P42: =SUMIFS(df_ajustes_conciliaco!D:D,df_ajustes_conciliaco!C:C,Conciliacao!A42) | Q42: =O42+I42-P42 | BE42: 45698.5 | BF42: 45698.125 | BG42: 45698.542 | BH42: 45698.625
A43: =A42+1 | B43: =-SUMIFS(df_extrato_zig!G:G,df_extrato_zig!E:E,Conciliacao!A43,df_extrato_zig!D:D,"Saque")-SUMIFS(df_extrato_zig!G:G,df_extrato_zig!E:E,Conciliacao!A43,df_extrato_zig!D:D,"Antecipação") | C43: =SUMIFS(df_extrato_zig!E:E,df_extrato_zig!L:L,Conciliacao!A43,df_extrato_zig!F:F,"DINHEIRO") | D43: =SUMIFS(view_parc_agrup!H:H,view_parc_agrup!G:G,Conciliacao!A43) | E43: =SUMIFS(df_eventos!F:F,df_eventos!H:H,Conciliacao!A43) | F43: =SUMIFS(df_mutuos!M:M,df_mutuos!B:B,Conciliacao!A43) | G43: =SUMIFS(df_bloqueios_judiciais!G:G,df_bloqueios_judiciais!D:D,Conciliacao!A43,df_bloqueios_judiciais!G:G,">0") | H43: =SUMIFS(df_extratos!I:I,df_extratos!F:F,">="&Conciliacao!BE43,df_extratos!F:F,"<"&Conciliacao!BE43+1,df_extratos!G:G,"CREDITO") +SUMIFS(df_extratos!I:I,df_extratos!F:F,">="&Conciliacao!A43, df_extratos!F:F,"<"&Conciliacao!A43+1, df_extratos!G:G,"CREDITO") +SUMIFS(df_extratos!I:I,df_extratos!F:F,">="&Conciliacao!BF43,df_extratos!F:F,"<"&Conciliacao!BF43+1,df_extratos!G:G,"CREDITO") +SUMIFS(df_extratos!I:I,df_extratos!F:F,">="&Conciliacao!BG43,df_extratos!F:F,"<"&Conciliacao!BG43+1,df_extratos!G:G,"CREDITO") +SUMIFS(df_extratos!I:I,df_extratos!F:F,">="&Conciliacao!BH43,df_extratos!F:F,"<"&Conciliacao!BH43+1,df_extratos!G:G,"CREDITO") | I43: =H43-SUM(B43:G43) | J43: =SUMIFS(df_blueme_sem_parcelamento!E:E,df_blueme_sem_parcelamento!H:H,Conciliacao!A43)*(-1) | K43: =SUMIFS(df_blueme_com_parcelamento!J:J,df_blueme_com_parcelamento!M:M,Conciliacao!A43)*(-1) | L43: =SUMIFS(df_mutuos!N:N,df_mutuos!B:B,Conciliacao!A43)*(-1) | M43: =SUMIFS(df_bloqueios_judiciais!G:G,df_bloqueios_judiciais!D:D,Conciliacao!A43,df_bloqueios_judiciais!G:G,"<0") | N43: =SUMIFS(df_extratos!I:I,df_extratos!F:F,">="&Conciliacao!BE43,df_extratos!F:F,"<"&Conciliacao!BE43+1,df_extratos!G:G,"DEBITO") +SUMIFS(df_extratos!I:I,df_extratos!F:F,">="&Conciliacao!A43, df_extratos!F:F,"<"&Conciliacao!A43+1, df_extratos!G:G,"DEBITO") +SUMIFS(df_extratos!I:I,df_extratos!F:F,">="&Conciliacao!BF43,df_extratos!F:F,"<"&Conciliacao!BF43+1,df_extratos!G:G,"DEBITO") +SUMIFS(df_extratos!I:I,df_extratos!F:F,">="&Conciliacao!BG43,df_extratos!F:F,"<"&Conciliacao!BG43+1,df_extratos!G:G,"DEBITO") +SUMIFS(df_extratos!I:I,df_extratos!F:F,">="&Conciliacao!BH43,df_extratos!F:F,"<"&Conciliacao!BH43+1,df_extratos!G:G,"DEBITO") | O43: =N43-SUM(J43:M43) | P43: =SUMIFS(df_ajustes_conciliaco!D:D,df_ajustes_conciliaco!C:C,Conciliacao!A43) | Q43: =O43+I43-P43 | BE43: 45699.5 | BF43: 45699.125 | BG43: 45699.542 | BH43: 45699.625
A44: =A43+1 | B44: =-SUMIFS(df_extrato_zig!G:G,df_extrato_zig!E:E,Conciliacao!A44,df_extrato_zig!D:D,"Saque")-SUMIFS(df_extrato_zig!G:G,df_extrato_zig!E:E,Conciliacao!A44,df_extrato_zig!D:D,"Antecipação") | C44: =SUMIFS(df_extrato_zig!E:E,df_extrato_zig!L:L,Conciliacao!A44,df_extrato_zig!F:F,"DINHEIRO") | D44: =SUMIFS(view_parc_agrup!H:H,view_parc_agrup!G:G,Conciliacao!A44) | E44: =SUMIFS(df_eventos!F:F,df_eventos!H:H,Conciliacao!A44) | F44: =SUMIFS(df_mutuos!M:M,df_mutuos!B:B,Conciliacao!A44) | G44: =SUMIFS(df_bloqueios_judiciais!G:G,df_bloqueios_judiciais!D:D,Conciliacao!A44,df_bloqueios_judiciais!G:G,">0") | H44: =SUMIFS(df_extratos!I:I,df_extratos!F:F,">="&Conciliacao!BE44,df_extratos!F:F,"<"&Conciliacao!BE44+1,df_extratos!G:G,"CREDITO") +SUMIFS(df_extratos!I:I,df_extratos!F:F,">="&Conciliacao!A44, df_extratos!F:F,"<"&Conciliacao!A44+1, df_extratos!G:G,"CREDITO") +SUMIFS(df_extratos!I:I,df_extratos!F:F,">="&Conciliacao!BF44,df_extratos!F:F,"<"&Conciliacao!BF44+1,df_extratos!G:G,"CREDITO") +SUMIFS(df_extratos!I:I,df_extratos!F:F,">="&Conciliacao!BG44,df_extratos!F:F,"<"&Conciliacao!BG44+1,df_extratos!G:G,"CREDITO") +SUMIFS(df_extratos!I:I,df_extratos!F:F,">="&Conciliacao!BH44,df_extratos!F:F,"<"&Conciliacao!BH44+1,df_extratos!G:G,"CREDITO") | I44: =H44-SUM(B44:G44) | J44: =SUMIFS(df_blueme_sem_parcelamento!E:E,df_blueme_sem_parcelamento!H:H,Conciliacao!A44)*(-1) | K44: =SUMIFS(df_blueme_com_parcelamento!J:J,df_blueme_com_parcelamento!M:M,Conciliacao!A44)*(-1) | L44: =SUMIFS(df_mutuos!N:N,df_mutuos!B:B,Conciliacao!A44)*(-1) | M44: =SUMIFS(df_bloqueios_judiciais!G:G,df_bloqueios_judiciais!D:D,Conciliacao!A44,df_bloqueios_judiciais!G:G,"<0") | N44: =SUMIFS(df_extratos!I:I,df_extratos!F:F,">="&Conciliacao!BE44,df_extratos!F:F,"<"&Conciliacao!BE44+1,df_extratos!G:G,"DEBITO") +SUMIFS(df_extratos!I:I,df_extratos!F:F,">="&Conciliacao!A44, df_extratos!F:F,"<"&Conciliacao!A44+1, df_extratos!G:G,"DEBITO") +SUMIFS(df_extratos!I:I,df_extratos!F:F,">="&Conciliacao!BF44,df_extratos!F:F,"<"&Conciliacao!BF44+1,df_extratos!G:G,"DEBITO") +SUMIFS(df_extratos!I:I,df_extratos!F:F,">="&Conciliacao!BG44,df_extratos!F:F,"<"&Conciliacao!BG44+1,df_extratos!G:G,"DEBITO") +SUMIFS(df_extratos!I:I,df_extratos!F:F,">="&Conciliacao!BH44,df_extratos!F:F,"<"&Conciliacao!BH44+1,df_extratos!G:G,"DEBITO") | O44: =N44-SUM(J44:M44) | P44: =SUMIFS(df_ajustes_conciliaco!D:D,df_ajustes_conciliaco!C:C,Conciliacao!A44) | Q44: =O44+I44-P44 | BE44: 45700.5 | BF44: 45700.125 | BG44: 45700.542 | BH44: 45700.625
A45: =A44+1 | B45: =-SUMIFS(df_extrato_zig!G:G,df_extrato_zig!E:E,Conciliacao!A45,df_extrato_zig!D:D,"Saque")-SUMIFS(df_extrato_zig!G:G,df_extrato_zig!E:E,Conciliacao!A45,df_extrato_zig!D:D,"Antecipação") | C45: =SUMIFS(df_extrato_zig!E:E,df_extrato_zig!L:L,Conciliacao!A45,df_extrato_zig!F:F,"DINHEIRO") | D45: =SUMIFS(view_parc_agrup!H:H,view_parc_agrup!G:G,Conciliacao!A45) | E45: =SUMIFS(df_eventos!F:F,df_eventos!H:H,Conciliacao!A45) | F45: =SUMIFS(df_mutuos!M:M,df_mutuos!B:B,Conciliacao!A45) | G45: =SUMIFS(df_bloqueios_judiciais!G:G,df_bloqueios_judiciais!D:D,Conciliacao!A45,df_bloqueios_judiciais!G:G,">0") | H45: =SUMIFS(df_extratos!I:I,df_extratos!F:F,">="&Conciliacao!BE45,df_extratos!F:F,"<"&Conciliacao!BE45+1,df_extratos!G:G,"CREDITO") +SUMIFS(df_extratos!I:I,df_extratos!F:F,">="&Conciliacao!A45, df_extratos!F:F,"<"&Conciliacao!A45+1, df_extratos!G:G,"CREDITO") +SUMIFS(df_extratos!I:I,df_extratos!F:F,">="&Conciliacao!BF45,df_extratos!F:F,"<"&Conciliacao!BF45+1,df_extratos!G:G,"CREDITO") +SUMIFS(df_extratos!I:I,df_extratos!F:F,">="&Conciliacao!BG45,df_extratos!F:F,"<"&Conciliacao!BG45+1,df_extratos!G:G,"CREDITO") +SUMIFS(df_extratos!I:I,df_extratos!F:F,">="&Conciliacao!BH45,df_extratos!F:F,"<"&Conciliacao!BH45+1,df_extratos!G:G,"CREDITO") | I45: =H45-SUM(B45:G45) | J45: =SUMIFS(df_blueme_sem_parcelamento!E:E,df_blueme_sem_parcelamento!H:H,Conciliacao!A45)*(-1) | K45: =SUMIFS(df_blueme_com_parcelamento!J:J,df_blueme_com_parcelamento!M:M,Conciliacao!A45)*(-1) | L45: =SUMIFS(df_mutuos!N:N,df_mutuos!B:B,Conciliacao!A45)*(-1) | M45: =SUMIFS(df_bloqueios_judiciais!G:G,df_bloqueios_judiciais!D:D,Conciliacao!A45,df_bloqueios_judiciais!G:G,"<0") | N45: =SUMIFS(df_extratos!I:I,df_extratos!F:F,">="&Conciliacao!BE45,df_extratos!F:F,"<"&Conciliacao!BE45+1,df_extratos!G:G,"DEBITO") +SUMIFS(df_extratos!I:I,df_extratos!F:F,">="&Conciliacao!A45, df_extratos!F:F,"<"&Conciliacao!A45+1, df_extratos!G:G,"DEBITO") +SUMIFS(df_extratos!I:I,df_extratos!F:F,">="&Conciliacao!BF45,df_extratos!F:F,"<"&Conciliacao!BF45+1,df_extratos!G:G,"DEBITO") +SUMIFS(df_extratos!I:I,df_extratos!F:F,">="&Conciliacao!BG45,df_extratos!F:F,"<"&Conciliacao!BG45+1,df_extratos!G:G,"DEBITO") +SUMIFS(df_extratos!I:I,df_extratos!F:F,">="&Conciliacao!BH45,df_extratos!F:F,"<"&Conciliacao!BH45+1,df_extratos!G:G,"DEBITO") | O45: =N45-SUM(J45:M45) | P45: =SUMIFS(df_ajustes_conciliaco!D:D,df_ajustes_conciliaco!C:C,Conciliacao!A45) | Q45: =O45+I45-P45 | BE45: 45701.5 | BF45: 45701.125 | BG45: 45701.542 | BH45: 45701.625
A46: =A45+1 | B46: =-SUMIFS(df_extrato_zig!G:G,df_extrato_zig!E:E,Conciliacao!A46,df_extrato_zig!D:D,"Saque")-SUMIFS(df_extrato_zig!G:G,df_extrato_zig!E:E,Conciliacao!A46,df_extrato_zig!D:D,"Antecipação") | C46: =SUMIFS(df_extrato_zig!E:E,df_extrato_zig!L:L,Conciliacao!A46,df_extrato_zig!F:F,"DINHEIRO") | D46: =SUMIFS(view_parc_agrup!H:H,view_parc_agrup!G:G,Conciliacao!A46) | E46: =SUMIFS(df_eventos!F:F,df_eventos!H:H,Conciliacao!A46) | F46: =SUMIFS(df_mutuos!M:M,df_mutuos!B:B,Conciliacao!A46) | G46: =SUMIFS(df_bloqueios_judiciais!G:G,df_bloqueios_judiciais!D:D,Conciliacao!A46,df_bloqueios_judiciais!G:G,">0") | H46: =SUMIFS(df_extratos!I:I,df_extratos!F:F,">="&Conciliacao!BE46,df_extratos!F:F,"<"&Conciliacao!BE46+1,df_extratos!G:G,"CREDITO") +SUMIFS(df_extratos!I:I,df_extratos!F:F,">="&Conciliacao!A46, df_extratos!F:F,"<"&Conciliacao!A46+1, df_extratos!G:G,"CREDITO") +SUMIFS(df_extratos!I:I,df_extratos!F:F,">="&Conciliacao!BF46,df_extratos!F:F,"<"&Conciliacao!BF46+1,df_extratos!G:G,"CREDITO") +SUMIFS(df_extratos!I:I,df_extratos!F:F,">="&Conciliacao!BG46,df_extratos!F:F,"<"&Conciliacao!BG46+1,df_extratos!G:G,"CREDITO") +SUMIFS(df_extratos!I:I,df_extratos!F:F,">="&Conciliacao!BH46,df_extratos!F:F,"<"&Conciliacao!BH46+1,df_extratos!G:G,"CREDITO") | I46: =H46-SUM(B46:G46) | J46: =SUMIFS(df_blueme_sem_parcelamento!E:E,df_blueme_sem_parcelamento!H:H,Conciliacao!A46)*(-1) | K46: =SUMIFS(df_blueme_com_parcelamento!J:J,df_blueme_com_parcelamento!M:M,Conciliacao!A46)*(-1) | L46: =SUMIFS(df_mutuos!N:N,df_mutuos!B:B,Conciliacao!A46)*(-1) | M46: =SUMIFS(df_bloqueios_judiciais!G:G,df_bloqueios_judiciais!D:D,Conciliacao!A46,df_bloqueios_judiciais!G:G,"<0") | N46: =SUMIFS(df_extratos!I:I,df_extratos!F:F,">="&Conciliacao!BE46,df_extratos!F:F,"<"&Conciliacao!BE46+1,df_extratos!G:G,"DEBITO") +SUMIFS(df_extratos!I:I,df_extratos!F:F,">="&Conciliacao!A46, df_extratos!F:F,"<"&Conciliacao!A46+1, df_extratos!G:G,"DEBITO") +SUMIFS(df_extratos!I:I,df_extratos!F:F,">="&Conciliacao!BF46,df_extratos!F:F,"<"&Conciliacao!BF46+1,df_extratos!G:G,"DEBITO") +SUMIFS(df_extratos!I:I,df_extratos!F:F,">="&Conciliacao!BG46,df_extratos!F:F,"<"&Conciliacao!BG46+1,df_extratos!G:G,"DEBITO") +SUMIFS(df_extratos!I:I,df_extratos!F:F,">="&Conciliacao!BH46,df_extratos!F:F,"<"&Conciliacao!BH46+1,df_extratos!G:G,"DEBITO") | O46: =N46-SUM(J46:M46) | P46: =SUMIFS(df_ajustes_conciliaco!D:D,df_ajustes_conciliaco!C:C,Conciliacao!A46) | Q46: =O46+I46-P46 | BE46: 45702.5 | BF46: 45702.125 | BG46: 45702.542 | BH46: 45702.625
... A366: =A365+1 | B366: =-SUMIFS(df_extrato_zig!G:G,df_extrato_zig!E:E,Conciliacao!A366,df_extrato_zig!D:D,"Saque")-SUMIFS(df_extrato_zig!G:G,df_extrato_zig!E:E,Conciliacao!A366,df_extrato_zig!D:D,"Antecipação") | C366: =SUMIFS(df_extrato_zig!E:E,df_extrato_zig!L:L,Conciliacao!A366,df_extrato_zig!F:F,"DINHEIRO") | D366: =SUMIFS(view_parc_agrup!H:H,view_parc_agrup!G:G,Conciliacao!A366) | E366: =SUMIFS(df_eventos!F:F,df_eventos!H:H,Conciliacao!A366) | F366: =SUMIFS(df_mutuos!M:M,df_mutuos!B:B,Conciliacao!A366) | G366: =SUMIFS(df_bloqueios_judiciais!G:G,df_bloqueios_judiciais!D:D,Conciliacao!A366,df_bloqueios_judiciais!G:G,">0") | H366: =SUMIFS(df_extratos!I:I,df_extratos!F:F,">="&Conciliacao!BE366,df_extratos!F:F,"<"&Conciliacao!BE366+1,df_extratos!G:G,"CREDITO") +SUMIFS(df_extratos!I:I,df_extratos!F:F,">="&Conciliacao!A366, df_extratos!F:F,"<"&Conciliacao!A366+1, df_extratos!G:G,"CREDITO") +SUMIFS(df_extratos!I:I,df_extratos!F:F,">="&Conciliacao!BF366,df_extratos!F:F,"<"&Conciliacao!BF366+1,df_extratos!G:G,"CREDITO") +SUMIFS(df_extratos!I:I,df_extratos!F:F,">="&Conciliacao!BG366,df_extratos!F:F,"<"&Conciliacao!BG366+1,df_extratos!G:G,"CREDITO") +SUMIFS(df_extratos!I:I,df_extratos!F:F,">="&Conciliacao!BH366,df_extratos!F:F,"<"&Conciliacao!BH366+1,df_extratos!G:G,"CREDITO") | I366: =H366-SUM(B366:G366) | J366: =SUMIFS(df_blueme_sem_parcelamento!E:E,df_blueme_sem_parcelamento!H:H,Conciliacao!A366)*(-1) | K366: =SUMIFS(df_blueme_com_parcelamento!J:J,df_blueme_com_parcelamento!M:M,Conciliacao!A366)*(-1) | L366: =SUMIFS(df_mutuos!N:N,df_mutuos!B:B,Conciliacao!A366)*(-1) | M366: =SUMIFS(df_bloqueios_judiciais!G:G,df_bloqueios_judiciais!D:D,Conciliacao!A366,df_bloqueios_judiciais!G:G,"<0") | N366: =SUMIFS(df_extratos!I:I,df_extratos!F:F,">="&Conciliacao!BE366,df_extratos!F:F,"<"&Conciliacao!BE366+1,df_extratos!G:G,"DEBITO") +SUMIFS(df_extratos!I:I,df_extratos!F:F,">="&Conciliacao!A366, df_extratos!F:F,"<"&Conciliacao!A366+1, df_extratos!G:G,"DEBITO") +SUMIFS(df_extratos!I:I,df_extratos!F:F,">="&Conciliacao!BF366,df_extratos!F:F,"<"&Conciliacao!BF366+1,df_extratos!G:G,"DEBITO") +SUMIFS(df_extratos!I:I,df_extratos!F:F,">="&Conciliacao!BG366,df_extratos!F:F,"<"&Conciliacao!BG366+1,df_extratos!G:G,"DEBITO") +SUMIFS(df_extratos!I:I,df_extratos!F:F,">="&Conciliacao!BH366,df_extratos!F:F,"<"&Conciliacao!BH366+1,df_extratos!G:G,"DEBITO") | O366: =N366-SUM(J366:M366) | P366: =SUMIFS(df_ajustes_conciliaco!D:D,df_ajustes_conciliaco!C:C,Conciliacao!A366) | Q366: =O366+I366-P366 | BE366: 46022.5 | BF366: 46022.125 | BG366: 46022.542 | BH366: 46022.625
A367: =A366+1 | B367: =-SUMIFS(df_extrato_zig!G:G,df_extrato_zig!E:E,Conciliacao!A367,df_extrato_zig!D:D,"Saque")-SUMIFS(df_extrato_zig!G:G,df_extrato_zig!E:E,Conciliacao!A367,df_extrato_zig!D:D,"Antecipação") | C367: =SUMIFS(df_extrato_zig!E:E,df_extrato_zig!L:L,Conciliacao!A367,df_extrato_zig!F:F,"DINHEIRO") | D367: =SUMIFS(view_parc_agrup!H:H,view_parc_agrup!G:G,Conciliacao!A367) | E367: =SUMIFS(df_eventos!F:F,df_eventos!H:H,Conciliacao!A367) | F367: =SUMIFS(df_mutuos!M:M,df_mutuos!B:B,Conciliacao!A367) | G367: =SUMIFS(df_bloqueios_judiciais!G:G,df_bloqueios_judiciais!D:D,Conciliacao!A367,df_bloqueios_judiciais!G:G,">0") | H367: =SUMIFS(df_extratos!I:I,df_extratos!F:F,">="&Conciliacao!BE367,df_extratos!F:F,"<"&Conciliacao!BE367+1,df_extratos!G:G,"CREDITO") +SUMIFS(df_extratos!I:I,df_extratos!F:F,">="&Conciliacao!A367, df_extratos!F:F,"<"&Conciliacao!A367+1, df_extratos!G:G,"CREDITO") +SUMIFS(df_extratos!I:I,df_extratos!F:F,">="&Conciliacao!BF367,df_extratos!F:F,"<"&Conciliacao!BF367+1,df_extratos!G:G,"CREDITO") +SUMIFS(df_extratos!I:I,df_extratos!F:F,">="&Conciliacao!BG367,df_extratos!F:F,"<"&Conciliacao!BG367+1,df_extratos!G:G,"CREDITO") +SUMIFS(df_extratos!I:I,df_extratos!F:F,">="&Conciliacao!BH367,df_extratos!F:F,"<"&Conciliacao!BH367+1,df_extratos!G:G,"CREDITO") | I367: =H367-SUM(B367:G367) | J367: =SUMIFS(df_blueme_sem_parcelamento!E:E,df_blueme_sem_parcelamento!H:H,Conciliacao!A367)*(-1) | K367: =SUMIFS(df_blueme_com_parcelamento!J:J,df_blueme_com_parcelamento!M:M,Conciliacao!A367)*(-1) | L367: =SUMIFS(df_mutuos!N:N,df_mutuos!B:B,Conciliacao!A367)*(-1) | M367: =SUMIFS(df_bloqueios_judiciais!G:G,df_bloqueios_judiciais!D:D,Conciliacao!A367,df_bloqueios_judiciais!G:G,"<0") | N367: =SUMIFS(df_extratos!I:I,df_extratos!F:F,">="&Conciliacao!BE367,df_extratos!F:F,"<"&Conciliacao!BE367+1,df_extratos!G:G,"DEBITO") +SUMIFS(df_extratos!I:I,df_extratos!F:F,">="&Conciliacao!A367, df_extratos!F:F,"<"&Conciliacao!A367+1, df_extratos!G:G,"DEBITO") +SUMIFS(df_extratos!I:I,df_extratos!F:F,">="&Conciliacao!BF367,df_extratos!F:F,"<"&Conciliacao!BF367+1,df_extratos!G:G,"DEBITO") +SUMIFS(df_extratos!I:I,df_extratos!F:F,">="&Conciliacao!BG367,df_extratos!F:F,"<"&Conciliacao!BG367+1,df_extratos!G:G,"DEBITO") +SUMIFS(df_extratos!I:I,df_extratos!F:F,">="&Conciliacao!BH367,df_extratos!F:F,"<"&Conciliacao!BH367+1,df_extratos!G:G,"DEBITO") | O367: =N367-SUM(J367:M367) | P367: =SUMIFS(df_ajustes_conciliaco!D:D,df_ajustes_conciliaco!C:C,Conciliacao!A367) | Q367: =O367+I367-P367
A368: =A367+1 | B368: =-SUMIFS(df_extrato_zig!G:G,df_extrato_zig!E:E,Conciliacao!A368,df_extrato_zig!D:D,"Saque")-SUMIFS(df_extrato_zig!G:G,df_extrato_zig!E:E,Conciliacao!A368,df_extrato_zig!D:D,"Antecipação") | C368: =SUMIFS(df_extrato_zig!E:E,df_extrato_zig!L:L,Conciliacao!A368,df_extrato_zig!F:F,"DINHEIRO") | D368: =SUMIFS(view_parc_agrup!H:H,view_parc_agrup!G:G,Conciliacao!A368) | E368: =SUMIFS(df_eventos!F:F,df_eventos!H:H,Conciliacao!A368) | F368: =SUMIFS(df_mutuos!M:M,df_mutuos!B:B,Conciliacao!A368) | G368: =SUMIFS(df_bloqueios_judiciais!G:G,df_bloqueios_judiciais!D:D,Conciliacao!A368,df_bloqueios_judiciais!G:G,">0") | H368: =SUMIFS(df_extratos!I:I,df_extratos!F:F,">="&Conciliacao!BE368,df_extratos!F:F,"<"&Conciliacao!BE368+1,df_extratos!G:G,"CREDITO") +SUMIFS(df_extratos!I:I,df_extratos!F:F,">="&Conciliacao!A368, df_extratos!F:F,"<"&Conciliacao!A368+1, df_extratos!G:G,"CREDITO") +SUMIFS(df_extratos!I:I,df_extratos!F:F,">="&Conciliacao!BF368,df_extratos!F:F,"<"&Conciliacao!BF368+1,df_extratos!G:G,"CREDITO") +SUMIFS(df_extratos!I:I,df_extratos!F:F,">="&Conciliacao!BG368,df_extratos!F:F,"<"&Conciliacao!BG368+1,df_extratos!G:G,"CREDITO") +SUMIFS(df_extratos!I:I,df_extratos!F:F,">="&Conciliacao!BH368,df_extratos!F:F,"<"&Conciliacao!BH368+1,df_extratos!G:G,"CREDITO") | I368: =H368-SUM(B368:G368) | J368: =SUMIFS(df_blueme_sem_parcelamento!E:E,df_blueme_sem_parcelamento!H:H,Conciliacao!A368)*(-1) | K368: =SUMIFS(df_blueme_com_parcelamento!J:J,df_blueme_com_parcelamento!M:M,Conciliacao!A368)*(-1) | L368: =SUMIFS(df_mutuos!N:N,df_mutuos!B:B,Conciliacao!A368)*(-1) | M368: =SUMIFS(df_bloqueios_judiciais!G:G,df_bloqueios_judiciais!D:D,Conciliacao!A368,df_bloqueios_judiciais!G:G,"<0") | N368: =SUMIFS(df_extratos!I:I,df_extratos!F:F,">="&Conciliacao!BE368,df_extratos!F:F,"<"&Conciliacao!BE368+1,df_extratos!G:G,"DEBITO") +SUMIFS(df_extratos!I:I,df_extratos!F:F,">="&Conciliacao!A368, df_extratos!F:F,"<"&Conciliacao!A368+1, df_extratos!G:G,"DEBITO") +SUMIFS(df_extratos!I:I,df_extratos!F:F,">="&Conciliacao!BF368,df_extratos!F:F,"<"&Conciliacao!BF368+1,df_extratos!G:G,"DEBITO") +SUMIFS(df_extratos!I:I,df_extratos!F:F,">="&Conciliacao!BG368,df_extratos!F:F,"<"&Conciliacao!BG368+1,df_extratos!G:G,"DEBITO") +SUMIFS(df_extratos!I:I,df_extratos!F:F,">="&Conciliacao!BH368,df_extratos!F:F,"<"&Conciliacao!BH368+1,df_extratos!G:G,"DEBITO") | O368: =N368-SUM(J368:M368) | P368: =SUMIFS(df_ajustes_conciliaco!D:D,df_ajustes_conciliaco!C:C,Conciliacao!A368) | Q368: =O368+I368-P368
A369: =A368+1 | B369: =-SUMIFS(df_extrato_zig!G:G,df_extrato_zig!E:E,Conciliacao!A369,df_extrato_zig!D:D,"Saque")-SUMIFS(df_extrato_zig!G:G,df_extrato_zig!E:E,Conciliacao!A369,df_extrato_zig!D:D,"Antecipação") | C369: =SUMIFS(df_extrato_zig!E:E,df_extrato_zig!L:L,Conciliacao!A369,df_extrato_zig!F:F,"DINHEIRO") | D369: =SUMIFS(view_parc_agrup!H:H,view_parc_agrup!G:G,Conciliacao!A369) | E369: =SUMIFS(df_eventos!F:F,df_eventos!H:H,Conciliacao!A369) | F369: =SUMIFS(df_mutuos!M:M,df_mutuos!B:B,Conciliacao!A369) | G369: =SUMIFS(df_bloqueios_judiciais!G:G,df_bloqueios_judiciais!D:D,Conciliacao!A369,df_bloqueios_judiciais!G:G,">0") | H369: =SUMIFS(df_extratos!I:I,df_extratos!F:F,">="&Conciliacao!BE369,df_extratos!F:F,"<"&Conciliacao!BE369+1,df_extratos!G:G,"CREDITO") +SUMIFS(df_extratos!I:I,df_extratos!F:F,">="&Conciliacao!A369, df_extratos!F:F,"<"&Conciliacao!A369+1, df_extratos!G:G,"CREDITO") +SUMIFS(df_extratos!I:I,df_extratos!F:F,">="&Conciliacao!BF369,df_extratos!F:F,"<"&Conciliacao!BF369+1,df_extratos!G:G,"CREDITO") +SUMIFS(df_extratos!I:I,df_extratos!F:F,">="&Conciliacao!BG369,df_extratos!F:F,"<"&Conciliacao!BG369+1,df_extratos!G:G,"CREDITO") +SUMIFS(df_extratos!I:I,df_extratos!F:F,">="&Conciliacao!BH369,df_extratos!F:F,"<"&Conciliacao!BH369+1,df_extratos!G:G,"CREDITO") | I369: =H369-SUM(B369:G369) | J369: =SUMIFS(df_blueme_sem_parcelamento!E:E,df_blueme_sem_parcelamento!H:H,Conciliacao!A369)*(-1) | K369: =SUMIFS(df_blueme_com_parcelamento!J:J,df_blueme_com_parcelamento!M:M,Conciliacao!A369)*(-1) | L369: =SUMIFS(df_mutuos!N:N,df_mutuos!B:B,Conciliacao!A369)*(-1) | M369: =SUMIFS(df_bloqueios_judiciais!G:G,df_bloqueios_judiciais!D:D,Conciliacao!A369,df_bloqueios_judiciais!G:G,"<0") | N369: =SUMIFS(df_extratos!I:I,df_extratos!F:F,">="&Conciliacao!BE369,df_extratos!F:F,"<"&Conciliacao!BE369+1,df_extratos!G:G,"DEBITO") +SUMIFS(df_extratos!I:I,df_extratos!F:F,">="&Conciliacao!A369, df_extratos!F:F,"<"&Conciliacao!A369+1, df_extratos!G:G,"DEBITO") +SUMIFS(df_extratos!I:I,df_extratos!F:F,">="&Conciliacao!BF369,df_extratos!F:F,"<"&Conciliacao!BF369+1,df_extratos!G:G,"DEBITO") +SUMIFS(df_extratos!I:I,df_extratos!F:F,">="&Conciliacao!BG369,df_extratos!F:F,"<"&Conciliacao!BG369+1,df_extratos!G:G,"DEBITO") +SUMIFS(df_extratos!I:I,df_extratos!F:F,">="&Conciliacao!BH369,df_extratos!F:F,"<"&Conciliacao!BH369+1,df_extratos!G:G,"DEBITO") | O369: =N369-SUM(J369:M369) | P369: =SUMIFS(df_ajustes_conciliaco!D:D,df_ajustes_conciliaco!C:C,Conciliacao!A369) | Q369: =O369+I369-P369
A370: =A369+1 | B370: =-SUMIFS(df_extrato_zig!G:G,df_extrato_zig!E:E,Conciliacao!A370,df_extrato_zig!D:D,"Saque")-SUMIFS(df_extrato_zig!G:G,df_extrato_zig!E:E,Conciliacao!A370,df_extrato_zig!D:D,"Antecipação") | C370: =SUMIFS(df_extrato_zig!E:E,df_extrato_zig!L:L,Conciliacao!A370,df_extrato_zig!F:F,"DINHEIRO") | D370: =SUMIFS(view_parc_agrup!H:H,view_parc_agrup!G:G,Conciliacao!A370) | E370: =SUMIFS(df_eventos!F:F,df_eventos!H:H,Conciliacao!A370) | F370: =SUMIFS(df_mutuos!M:M,df_mutuos!B:B,Conciliacao!A370) | G370: =SUMIFS(df_bloqueios_judiciais!G:G,df_bloqueios_judiciais!D:D,Conciliacao!A370,df_bloqueios_judiciais!G:G,">0") | H370: =SUMIFS(df_extratos!I:I,df_extratos!F:F,">="&Conciliacao!BE370,df_extratos!F:F,"<"&Conciliacao!BE370+1,df_extratos!G:G,"CREDITO") +SUMIFS(df_extratos!I:I,df_extratos!F:F,">="&Conciliacao!A370, df_extratos!F:F,"<"&Conciliacao!A370+1, df_extratos!G:G,"CREDITO") +SUMIFS(df_extratos!I:I,df_extratos!F:F,">="&Conciliacao!BF370,df_extratos!F:F,"<"&Conciliacao!BF370+1,df_extratos!G:G,"CREDITO") +SUMIFS(df_extratos!I:I,df_extratos!F:F,">="&Conciliacao!BG370,df_extratos!F:F,"<"&Conciliacao!BG370+1,df_extratos!G:G,"CREDITO") +SUMIFS(df_extratos!I:I,df_extratos!F:F,">="&Conciliacao!BH370,df_extratos!F:F,"<"&Conciliacao!BH370+1,df_extratos!G:G,"CREDITO") | I370: =H370-SUM(B370:G370) | J370: =SUMIFS(df_blueme_sem_parcelamento!E:E,df_blueme_sem_parcelamento!H:H,Conciliacao!A370)*(-1) | K370: =SUMIFS(df_blueme_com_parcelamento!J:J,df_blueme_com_parcelamento!M:M,Conciliacao!A370)*(-1) | L370: =SUMIFS(df_mutuos!N:N,df_mutuos!B:B,Conciliacao!A370)*(-1) | M370: =SUMIFS(df_bloqueios_judiciais!G:G,df_bloqueios_judiciais!D:D,Conciliacao!A370,df_bloqueios_judiciais!G:G,"<0") | N370: =SUMIFS(df_extratos!I:I,df_extratos!F:F,">="&Conciliacao!BE370,df_extratos!F:F,"<"&Conciliacao!BE370+1,df_extratos!G:G,"DEBITO") +SUMIFS(df_extratos!I:I,df_extratos!F:F,">="&Conciliacao!A370, df_extratos!F:F,"<"&Conciliacao!A370+1, df_extratos!G:G,"DEBITO") +SUMIFS(df_extratos!I:I,df_extratos!F:F,">="&Conciliacao!BF370,df_extratos!F:F,"<"&Conciliacao!BF370+1,df_extratos!G:G,"DEBITO") +SUMIFS(df_extratos!I:I,df_extratos!F:F,">="&Conciliacao!BG370,df_extratos!F:F,"<"&Conciliacao!BG370+1,df_extratos!G:G,"DEBITO") +SUMIFS(df_extratos!I:I,df_extratos!F:F,">="&Conciliacao!BH370,df_extratos!F:F,"<"&Conciliacao!BH370+1,df_extratos!G:G,"DEBITO") | O370: =N370-SUM(J370:M370) | P370: =SUMIFS(df_ajustes_conciliaco!D:D,df_ajustes_conciliaco!C:C,Conciliacao!A370) | Q370: =O370+I370-P370
A371: =A370+1 | B371: =-SUMIFS(df_extrato_zig!G:G,df_extrato_zig!E:E,Conciliacao!A371,df_extrato_zig!D:D,"Saque")-SUMIFS(df_extrato_zig!G:G,df_extrato_zig!E:E,Conciliacao!A371,df_extrato_zig!D:D,"Antecipação") | C371: =SUMIFS(df_extrato_zig!E:E,df_extrato_zig!L:L,Conciliacao!A371,df_extrato_zig!F:F,"DINHEIRO") | D371: =SUMIFS(view_parc_agrup!H:H,view_parc_agrup!G:G,Conciliacao!A371) | E371: =SUMIFS(df_eventos!F:F,df_eventos!H:H,Conciliacao!A371) | F371: =SUMIFS(df_mutuos!M:M,df_mutuos!B:B,Conciliacao!A371) | G371: =SUMIFS(df_bloqueios_judiciais!G:G,df_bloqueios_judiciais!D:D,Conciliacao!A371,df_bloqueios_judiciais!G:G,">0") | H371: =SUMIFS(df_extratos!I:I,df_extratos!F:F,">="&Conciliacao!BE371,df_extratos!F:F,"<"&Conciliacao!BE371+1,df_extratos!G:G,"CREDITO") +SUMIFS(df_extratos!I:I,df_extratos!F:F,">="&Conciliacao!A371, df_extratos!F:F,"<"&Conciliacao!A371+1, df_extratos!G:G,"CREDITO") +SUMIFS(df_extratos!I:I,df_extratos!F:F,">="&Conciliacao!BF371,df_extratos!F:F,"<"&Conciliacao!BF371+1,df_extratos!G:G,"CREDITO") +SUMIFS(df_extratos!I:I,df_extratos!F:F,">="&Conciliacao!BG371,df_extratos!F:F,"<"&Conciliacao!BG371+1,df_extratos!G:G,"CREDITO") +SUMIFS(df_extratos!I:I,df_extratos!F:F,">="&Conciliacao!BH371,df_extratos!F:F,"<"&Conciliacao!BH371+1,df_extratos!G:G,"CREDITO") | I371: =H371-SUM(B371:G371) | J371: =SUMIFS(df_blueme_sem_parcelamento!E:E,df_blueme_sem_parcelamento!H:H,Conciliacao!A371)*(-1) | K371: =SUMIFS(df_blueme_com_parcelamento!J:J,df_blueme_com_parcelamento!M:M,Conciliacao!A371)*(-1) | L371: =SUMIFS(df_mutuos!N:N,df_mutuos!B:B,Conciliacao!A371)*(-1) | M371: =SUMIFS(df_bloqueios_judiciais!G:G,df_bloqueios_judiciais!D:D,Conciliacao!A371,df_bloqueios_judiciais!G:G,"<0") | N371: =SUMIFS(df_extratos!I:I,df_extratos!F:F,">="&Conciliacao!BE371,df_extratos!F:F,"<"&Conciliacao!BE371+1,df_extratos!G:G,"DEBITO") +SUMIFS(df_extratos!I:I,df_extratos!F:F,">="&Conciliacao!A371, df_extratos!F:F,"<"&Conciliacao!A371+1, df_extratos!G:G,"DEBITO") +SUMIFS(df_extratos!I:I,df_extratos!F:F,">="&Conciliacao!BF371,df_extratos!F:F,"<"&Conciliacao!BF371+1,df_extratos!G:G,"DEBITO") +SUMIFS(df_extratos!I:I,df_extratos!F:F,">="&Conciliacao!BG371,df_extratos!F:F,"<"&Conciliacao!BG371+1,df_extratos!G:G,"DEBITO") +SUMIFS(df_extratos!I:I,df_extratos!F:F,">="&Conciliacao!BH371,df_extratos!F:F,"<"&Conciliacao!BH371+1,df_extratos!G:G,"DEBITO") | O371: =N371-SUM(J371:M371) | P371: =SUMIFS(df_ajustes_conciliaco!D:D,df_ajustes_conciliaco!C:C,Conciliacao!A371) | Q371: =O371+I371-P371
A372: =A371+1 | B372: =-SUMIFS(df_extrato_zig!G:G,df_extrato_zig!E:E,Conciliacao!A372,df_extrato_zig!D:D,"Saque")-SUMIFS(df_extrato_zig!G:G,df_extrato_zig!E:E,Conciliacao!A372,df_extrato_zig!D:D,"Antecipação") | C372: =SUMIFS(df_extrato_zig!E:E,df_extrato_zig!L:L,Conciliacao!A372,df_extrato_zig!F:F,"DINHEIRO") | D372: =SUMIFS(view_parc_agrup!H:H,view_parc_agrup!G:G,Conciliacao!A372) | E372: =SUMIFS(df_eventos!F:F,df_eventos!H:H,Conciliacao!A372) | F372: =SUMIFS(df_mutuos!M:M,df_mutuos!B:B,Conciliacao!A372) | G372: =SUMIFS(df_bloqueios_judiciais!G:G,df_bloqueios_judiciais!D:D,Conciliacao!A372,df_bloqueios_judiciais!G:G,">0") | H372: =SUMIFS(df_extratos!I:I,df_extratos!F:F,">="&Conciliacao!BE372,df_extratos!F:F,"<"&Conciliacao!BE372+1,df_extratos!G:G,"CREDITO") +SUMIFS(df_extratos!I:I,df_extratos!F:F,">="&Conciliacao!A372, df_extratos!F:F,"<"&Conciliacao!A372+1, df_extratos!G:G,"CREDITO") +SUMIFS(df_extratos!I:I,df_extratos!F:F,">="&Conciliacao!BF372,df_extratos!F:F,"<"&Conciliacao!BF372+1,df_extratos!G:G,"CREDITO") +SUMIFS(df_extratos!I:I,df_extratos!F:F,">="&Conciliacao!BG372,df_extratos!F:F,"<"&Conciliacao!BG372+1,df_extratos!G:G,"CREDITO") +SUMIFS(df_extratos!I:I,df_extratos!F:F,">="&Conciliacao!BH372,df_extratos!F:F,"<"&Conciliacao!BH372+1,df_extratos!G:G,"CREDITO") | I372: =H372-SUM(B372:G372) | J372: =SUMIFS(df_blueme_sem_parcelamento!E:E,df_blueme_sem_parcelamento!H:H,Conciliacao!A372)*(-1) | K372: =SUMIFS(df_blueme_com_parcelamento!J:J,df_blueme_com_parcelamento!M:M,Conciliacao!A372)*(-1) | L372: =SUMIFS(df_mutuos!N:N,df_mutuos!B:B,Conciliacao!A372)*(-1) | M372: =SUMIFS(df_bloqueios_judiciais!G:G,df_bloqueios_judiciais!D:D,Conciliacao!A372,df_bloqueios_judiciais!G:G,"<0") | N372: =SUMIFS(df_extratos!I:I,df_extratos!F:F,">="&Conciliacao!BE372,df_extratos!F:F,"<"&Conciliacao!BE372+1,df_extratos!G:G,"DEBITO") +SUMIFS(df_extratos!I:I,df_extratos!F:F,">="&Conciliacao!A372, df_extratos!F:F,"<"&Conciliacao!A372+1, df_extratos!G:G,"DEBITO") +SUMIFS(df_extratos!I:I,df_extratos!F:F,">="&Conciliacao!BF372,df_extratos!F:F,"<"&Conciliacao!BF372+1,df_extratos!G:G,"DEBITO") +SUMIFS(df_extratos!I:I,df_extratos!F:F,">="&Conciliacao!BG372,df_extratos!F:F,"<"&Conciliacao!BG372+1,df_extratos!G:G,"DEBITO") +SUMIFS(df_extratos!I:I,df_extratos!F:F,">="&Conciliacao!BH372,df_extratos!F:F,"<"&Conciliacao!BH372+1,df_extratos!G:G,"DEBITO") | O372: =N372-SUM(J372:M372) | P372: =SUMIFS(df_ajustes_conciliaco!D:D,df_ajustes_conciliaco!C:C,Conciliacao!A372) | Q372: =O372+I372-P372
A373: =A372+1 | B373: =-SUMIFS(df_extrato_zig!G:G,df_extrato_zig!E:E,Conciliacao!A373,df_extrato_zig!D:D,"Saque")-SUMIFS(df_extrato_zig!G:G,df_extrato_zig!E:E,Conciliacao!A373,df_extrato_zig!D:D,"Antecipação") | C373: =SUMIFS(df_extrato_zig!E:E,df_extrato_zig!L:L,Conciliacao!A373,df_extrato_zig!F:F,"DINHEIRO") | D373: =SUMIFS(view_parc_agrup!H:H,view_parc_agrup!G:G,Conciliacao!A373) | E373: =SUMIFS(df_eventos!F:F,df_eventos!H:H,Conciliacao!A373) | F373: =SUMIFS(df_mutuos!M:M,df_mutuos!B:B,Conciliacao!A373) | G373: =SUMIFS(df_bloqueios_judiciais!G:G,df_bloqueios_judiciais!D:D,Conciliacao!A373,df_bloqueios_judiciais!G:G,">0") | H373: =SUMIFS(df_extratos!I:I,df_extratos!F:F,">="&Conciliacao!BE373,df_extratos!F:F,"<"&Conciliacao!BE373+1,df_extratos!G:G,"CREDITO") +SUMIFS(df_extratos!I:I,df_extratos!F:F,">="&Conciliacao!A373, df_extratos!F:F,"<"&Conciliacao!A373+1, df_extratos!G:G,"CREDITO") +SUMIFS(df_extratos!I:I,df_extratos!F:F,">="&Conciliacao!BF373,df_extratos!F:F,"<"&Conciliacao!BF373+1,df_extratos!G:G,"CREDITO") +SUMIFS(df_extratos!I:I,df_extratos!F:F,">="&Conciliacao!BG373,df_extratos!F:F,"<"&Conciliacao!BG373+1,df_extratos!G:G,"CREDITO") +SUMIFS(df_extratos!I:I,df_extratos!F:F,">="&Conciliacao!BH373,df_extratos!F:F,"<"&Conciliacao!BH373+1,df_extratos!G:G,"CREDITO") | I373: =H373-SUM(B373:G373) | J373: =SUMIFS(df_blueme_sem_parcelamento!E:E,df_blueme_sem_parcelamento!H:H,Conciliacao!A373)*(-1) | K373: =SUMIFS(df_blueme_com_parcelamento!J:J,df_blueme_com_parcelamento!M:M,Conciliacao!A373)*(-1) | L373: =SUMIFS(df_mutuos!N:N,df_mutuos!B:B,Conciliacao!A373)*(-1) | M373: =SUMIFS(df_bloqueios_judiciais!G:G,df_bloqueios_judiciais!D:D,Conciliacao!A373,df_bloqueios_judiciais!G:G,"<0") | N373: =SUMIFS(df_extratos!I:I,df_extratos!F:F,">="&Conciliacao!BE373,df_extratos!F:F,"<"&Conciliacao!BE373+1,df_extratos!G:G,"DEBITO") +SUMIFS(df_extratos!I:I,df_extratos!F:F,">="&Conciliacao!A373, df_extratos!F:F,"<"&Conciliacao!A373+1, df_extratos!G:G,"DEBITO") +SUMIFS(df_extratos!I:I,df_extratos!F:F,">="&Conciliacao!BF373,df_extratos!F:F,"<"&Conciliacao!BF373+1,df_extratos!G:G,"DEBITO") +SUMIFS(df_extratos!I:I,df_extratos!F:F,">="&Conciliacao!BG373,df_extratos!F:F,"<"&Conciliacao!BG373+1,df_extratos!G:G,"DEBITO") +SUMIFS(df_extratos!I:I,df_extratos!F:F,">="&Conciliacao!BH373,df_extratos!F:F,"<"&Conciliacao!BH373+1,df_extratos!G:G,"DEBITO") | O373: =N373-SUM(J373:M373) | P373: =SUMIFS(df_ajustes_conciliaco!D:D,df_ajustes_conciliaco!C:C,Conciliacao!A373) | Q373: =O373+I373-P373
A374: =A373+1 | B374: =-SUMIFS(df_extrato_zig!G:G,df_extrato_zig!E:E,Conciliacao!A374,df_extrato_zig!D:D,"Saque")-SUMIFS(df_extrato_zig!G:G,df_extrato_zig!E:E,Conciliacao!A374,df_extrato_zig!D:D,"Antecipação") | C374: =SUMIFS(df_extrato_zig!E:E,df_extrato_zig!L:L,Conciliacao!A374,df_extrato_zig!F:F,"DINHEIRO") | D374: =SUMIFS(view_parc_agrup!H:H,view_parc_agrup!G:G,Conciliacao!A374) | E374: =SUMIFS(df_eventos!F:F,df_eventos!H:H,Conciliacao!A374) | F374: =SUMIFS(df_mutuos!M:M,df_mutuos!B:B,Conciliacao!A374) | G374: =SUMIFS(df_bloqueios_judiciais!G:G,df_bloqueios_judiciais!D:D,Conciliacao!A374,df_bloqueios_judiciais!G:G,">0") | H374: =SUMIFS(df_extratos!I:I,df_extratos!F:F,">="&Conciliacao!BE374,df_extratos!F:F,"<"&Conciliacao!BE374+1,df_extratos!G:G,"CREDITO") +SUMIFS(df_extratos!I:I,df_extratos!F:F,">="&Conciliacao!A374, df_extratos!F:F,"<"&Conciliacao!A374+1, df_extratos!G:G,"CREDITO") +SUMIFS(df_extratos!I:I,df_extratos!F:F,">="&Conciliacao!BF374,df_extratos!F:F,"<"&Conciliacao!BF374+1,df_extratos!G:G,"CREDITO") +SUMIFS(df_extratos!I:I,df_extratos!F:F,">="&Conciliacao!BG374,df_extratos!F:F,"<"&Conciliacao!BG374+1,df_extratos!G:G,"CREDITO") +SUMIFS(df_extratos!I:I,df_extratos!F:F,">="&Conciliacao!BH374,df_extratos!F:F,"<"&Conciliacao!BH374+1,df_extratos!G:G,"CREDITO") | I374: =H374-SUM(B374:G374) | J374: =SUMIFS(df_blueme_sem_parcelamento!E:E,df_blueme_sem_parcelamento!H:H,Conciliacao!A374)*(-1) | K374: =SUMIFS(df_blueme_com_parcelamento!J:J,df_blueme_com_parcelamento!M:M,Conciliacao!A374)*(-1) | L374: =SUMIFS(df_mutuos!N:N,df_mutuos!B:B,Conciliacao!A374)*(-1) | M374: =SUMIFS(df_bloqueios_judiciais!G:G,df_bloqueios_judiciais!D:D,Conciliacao!A374,df_bloqueios_judiciais!G:G,"<0") | N374: =SUMIFS(df_extratos!I:I,df_extratos!F:F,">="&Conciliacao!BE374,df_extratos!F:F,"<"&Conciliacao!BE374+1,df_extratos!G:G,"DEBITO") +SUMIFS(df_extratos!I:I,df_extratos!F:F,">="&Conciliacao!A374, df_extratos!F:F,"<"&Conciliacao!A374+1, df_extratos!G:G,"DEBITO") +SUMIFS(df_extratos!I:I,df_extratos!F:F,">="&Conciliacao!BF374,df_extratos!F:F,"<"&Conciliacao!BF374+1,df_extratos!G:G,"DEBITO") +SUMIFS(df_extratos!I:I,df_extratos!F:F,">="&Conciliacao!BG374,df_extratos!F:F,"<"&Conciliacao!BG374+1,df_extratos!G:G,"DEBITO") +SUMIFS(df_extratos!I:I,df_extratos!F:F,">="&Conciliacao!BH374,df_extratos!F:F,"<"&Conciliacao!BH374+1,df_extratos!G:G,"DEBITO") | O374: =N374-SUM(J374:M374) | P374: =SUMIFS(df_ajustes_conciliaco!D:D,df_ajustes_conciliaco!C:C,Conciliacao!A374) | Q374: =O374+I374-P374
A375: =A374+1 | B375: =-SUMIFS(df_extrato_zig!G:G,df_extrato_zig!E:E,Conciliacao!A375,df_extrato_zig!D:D,"Saque")-SUMIFS(df_extrato_zig!G:G,df_extrato_zig!E:E,Conciliacao!A375,df_extrato_zig!D:D,"Antecipação") | C375: =SUMIFS(df_extrato_zig!E:E,df_extrato_zig!L:L,Conciliacao!A375,df_extrato_zig!F:F,"DINHEIRO") | D375: =SUMIFS(view_parc_agrup!H:H,view_parc_agrup!G:G,Conciliacao!A375) | E375: =SUMIFS(df_eventos!F:F,df_eventos!H:H,Conciliacao!A375) | F375: =SUMIFS(df_mutuos!M:M,df_mutuos!B:B,Conciliacao!A375) | G375: =SUMIFS(df_bloqueios_judiciais!G:G,df_bloqueios_judiciais!D:D,Conciliacao!A375,df_bloqueios_judiciais!G:G,">0") | H375: =SUMIFS(df_extratos!I:I,df_extratos!F:F,">="&Conciliacao!BE375,df_extratos!F:F,"<"&Conciliacao!BE375+1,df_extratos!G:G,"CREDITO") +SUMIFS(df_extratos!I:I,df_extratos!F:F,">="&Conciliacao!A375, df_extratos!F:F,"<"&Conciliacao!A375+1, df_extratos!G:G,"CREDITO") +SUMIFS(df_extratos!I:I,df_extratos!F:F,">="&Conciliacao!BF375,df_extratos!F:F,"<"&Conciliacao!BF375+1,df_extratos!G:G,"CREDITO") +SUMIFS(df_extratos!I:I,df_extratos!F:F,">="&Conciliacao!BG375,df_extratos!F:F,"<"&Conciliacao!BG375+1,df_extratos!G:G,"CREDITO") +SUMIFS(df_extratos!I:I,df_extratos!F:F,">="&Conciliacao!BH375,df_extratos!F:F,"<"&Conciliacao!BH375+1,df_extratos!G:G,"CREDITO") | I375: =H375-SUM(B375:G375) | J375: =SUMIFS(df_blueme_sem_parcelamento!E:E,df_blueme_sem_parcelamento!H:H,Conciliacao!A375)*(-1) | K375: =SUMIFS(df_blueme_com_parcelamento!J:J,df_blueme_com_parcelamento!M:M,Conciliacao!A375)*(-1) | L375: =SUMIFS(df_mutuos!N:N,df_mutuos!B:B,Conciliacao!A375)*(-1) | M375: =SUMIFS(df_bloqueios_judiciais!G:G,df_bloqueios_judiciais!D:D,Conciliacao!A375,df_bloqueios_judiciais!G:G,"<0") | N375: =SUMIFS(df_extratos!I:I,df_extratos!F:F,">="&Conciliacao!BE375,df_extratos!F:F,"<"&Conciliacao!BE375+1,df_extratos!G:G,"DEBITO") +SUMIFS(df_extratos!I:I,df_extratos!F:F,">="&Conciliacao!A375, df_extratos!F:F,"<"&Conciliacao!A375+1, df_extratos!G:G,"DEBITO") +SUMIFS(df_extratos!I:I,df_extratos!F:F,">="&Conciliacao!BF375,df_extratos!F:F,"<"&Conciliacao!BF375+1,df_extratos!G:G,"DEBITO") +SUMIFS(df_extratos!I:I,df_extratos!F:F,">="&Conciliacao!BG375,df_extratos!F:F,"<"&Conciliacao!BG375+1,df_extratos!G:G,"DEBITO") +SUMIFS(df_extratos!I:I,df_extratos!F:F,">="&Conciliacao!BH375,df_extratos!F:F,"<"&Conciliacao!BH375+1,df_extratos!G:G,"DEBITO") | O375: =N375-SUM(J375:M375) | P375: =SUMIFS(df_ajustes_conciliaco!D:D,df_ajustes_conciliaco!C:C,Conciliacao!A375) | Q375: =O375+I375-P375
A376: =A375+1 | B376: =-SUMIFS(df_extrato_zig!G:G,df_extrato_zig!E:E,Conciliacao!A376,df_extrato_zig!D:D,"Saque")-SUMIFS(df_extrato_zig!G:G,df_extrato_zig!E:E,Conciliacao!A376,df_extrato_zig!D:D,"Antecipação") | C376: =SUMIFS(df_extrato_zig!E:E,df_extrato_zig!L:L,Conciliacao!A376,df_extrato_zig!F:F,"DINHEIRO") | D376: =SUMIFS(view_parc_agrup!H:H,view_parc_agrup!G:G,Conciliacao!A376) | E376: =SUMIFS(df_eventos!F:F,df_eventos!H:H,Conciliacao!A376) | F376: =SUMIFS(df_mutuos!M:M,df_mutuos!B:B,Conciliacao!A376) | G376: =SUMIFS(df_bloqueios_judiciais!G:G,df_bloqueios_judiciais!D:D,Conciliacao!A376,df_bloqueios_judiciais!G:G,">0") | H376: =SUMIFS(df_extratos!I:I,df_extratos!F:F,">="&Conciliacao!BE376,df_extratos!F:F,"<"&Conciliacao!BE376+1,df_extratos!G:G,"CREDITO") +SUMIFS(df_extratos!I:I,df_extratos!F:F,">="&Conciliacao!A376, df_extratos!F:F,"<"&Conciliacao!A376+1, df_extratos!G:G,"CREDITO") +SUMIFS(df_extratos!I:I,df_extratos!F:F,">="&Conciliacao!BF376,df_extratos!F:F,"<"&Conciliacao!BF376+1,df_extratos!G:G,"CREDITO") +SUMIFS(df_extratos!I:I,df_extratos!F:F,">="&Conciliacao!BG376,df_extratos!F:F,"<"&Conciliacao!BG376+1,df_extratos!G:G,"CREDITO") +SUMIFS(df_extratos!I:I,df_extratos!F:F,">="&Conciliacao!BH376,df_extratos!F:F,"<"&Conciliacao!BH376+1,df_extratos!G:G,"CREDITO") | I376: =H376-SUM(B376:G376) | J376: =SUMIFS(df_blueme_sem_parcelamento!E:E,df_blueme_sem_parcelamento!H:H,Conciliacao!A376)*(-1) | K376: =SUMIFS(df_blueme_com_parcelamento!J:J,df_blueme_com_parcelamento!M:M,Conciliacao!A376)*(-1) | L376: =SUMIFS(df_mutuos!N:N,df_mutuos!B:B,Conciliacao!A376)*(-1) | M376: =SUMIFS(df_bloqueios_judiciais!G:G,df_bloqueios_judiciais!D:D,Conciliacao!A376,df_bloqueios_judiciais!G:G,"<0") | N376: =SUMIFS(df_extratos!I:I,df_extratos!F:F,">="&Conciliacao!BE376,df_extratos!F:F,"<"&Conciliacao!BE376+1,df_extratos!G:G,"DEBITO") +SUMIFS(df_extratos!I:I,df_extratos!F:F,">="&Conciliacao!A376, df_extratos!F:F,"<"&Conciliacao!A376+1, df_extratos!G:G,"DEBITO") +SUMIFS(df_extratos!I:I,df_extratos!F:F,">="&Conciliacao!BF376,df_extratos!F:F,"<"&Conciliacao!BF376+1,df_extratos!G:G,"DEBITO") +SUMIFS(df_extratos!I:I,df_extratos!F:F,">="&Conciliacao!BG376,df_extratos!F:F,"<"&Conciliacao!BG376+1,df_extratos!G:G,"DEBITO") +SUMIFS(df_extratos!I:I,df_extratos!F:F,">="&Conciliacao!BH376,df_extratos!F:F,"<"&Conciliacao!BH376+1,df_extratos!G:G,"DEBITO") | O376: =N376-SUM(J376:M376) | P376: =SUMIFS(df_ajustes_conciliaco!D:D,df_ajustes_conciliaco!C:C,Conciliacao!A376) | Q376: =O376+I376-P376
A377: =A376+1 | B377: =-SUMIFS(df_extrato_zig!G:G,df_extrato_zig!E:E,Conciliacao!A377,df_extrato_zig!D:D,"Saque")-SUMIFS(df_extrato_zig!G:G,df_extrato_zig!E:E,Conciliacao!A377,df_extrato_zig!D:D,"Antecipação") | C377: =SUMIFS(df_extrato_zig!E:E,df_extrato_zig!L:L,Conciliacao!A377,df_extrato_zig!F:F,"DINHEIRO") | D377: =SUMIFS(view_parc_agrup!H:H,view_parc_agrup!G:G,Conciliacao!A377) | E377: =SUMIFS(df_eventos!F:F,df_eventos!H:H,Conciliacao!A377) | F377: =SUMIFS(df_mutuos!M:M,df_mutuos!B:B,Conciliacao!A377) | G377: =SUMIFS(df_bloqueios_judiciais!G:G,df_bloqueios_judiciais!D:D,Conciliacao!A377,df_bloqueios_judiciais!G:G,">0") | H377: =SUMIFS(df_extratos!I:I,df_extratos!F:F,">="&Conciliacao!BE377,df_extratos!F:F,"<"&Conciliacao!BE377+1,df_extratos!G:G,"CREDITO") +SUMIFS(df_extratos!I:I,df_extratos!F:F,">="&Conciliacao!A377, df_extratos!F:F,"<"&Conciliacao!A377+1, df_extratos!G:G,"CREDITO") +SUMIFS(df_extratos!I:I,df_extratos!F:F,">="&Conciliacao!BF377,df_extratos!F:F,"<"&Conciliacao!BF377+1,df_extratos!G:G,"CREDITO") +SUMIFS(df_extratos!I:I,df_extratos!F:F,">="&Conciliacao!BG377,df_extratos!F:F,"<"&Conciliacao!BG377+1,df_extratos!G:G,"CREDITO") +SUMIFS(df_extratos!I:I,df_extratos!F:F,">="&Conciliacao!BH377,df_extratos!F:F,"<"&Conciliacao!BH377+1,df_extratos!G:G,"CREDITO") | I377: =H377-SUM(B377:G377) | J377: =SUMIFS(df_blueme_sem_parcelamento!E:E,df_blueme_sem_parcelamento!H:H,Conciliacao!A377)*(-1) | K377: =SUMIFS(df_blueme_com_parcelamento!J:J,df_blueme_com_parcelamento!M:M,Conciliacao!A377)*(-1) | L377: =SUMIFS(df_mutuos!N:N,df_mutuos!B:B,Conciliacao!A377)*(-1) | M377: =SUMIFS(df_bloqueios_judiciais!G:G,df_bloqueios_judiciais!D:D,Conciliacao!A377,df_bloqueios_judiciais!G:G,"<0") | N377: =SUMIFS(df_extratos!I:I,df_extratos!F:F,">="&Conciliacao!BE377,df_extratos!F:F,"<"&Conciliacao!BE377+1,df_extratos!G:G,"DEBITO") +SUMIFS(df_extratos!I:I,df_extratos!F:F,">="&Conciliacao!A377, df_extratos!F:F,"<"&Conciliacao!A377+1, df_extratos!G:G,"DEBITO") +SUMIFS(df_extratos!I:I,df_extratos!F:F,">="&Conciliacao!BF377,df_extratos!F:F,"<"&Conciliacao!BF377+1,df_extratos!G:G,"DEBITO") +SUMIFS(df_extratos!I:I,df_extratos!F:F,">="&Conciliacao!BG377,df_extratos!F:F,"<"&Conciliacao!BG377+1,df_extratos!G:G,"DEBITO") +SUMIFS(df_extratos!I:I,df_extratos!F:F,">="&Conciliacao!BH377,df_extratos!F:F,"<"&Conciliacao!BH377+1,df_extratos!G:G,"DEBITO") | O377: =N377-SUM(J377:M377) | P377: =SUMIFS(df_ajustes_conciliaco!D:D,df_ajustes_conciliaco!C:C,Conciliacao!A377) | Q377: =O377+I377-P377
A378: =A377+1 | B378: =-SUMIFS(df_extrato_zig!G:G,df_extrato_zig!E:E,Conciliacao!A378,df_extrato_zig!D:D,"Saque")-SUMIFS(df_extrato_zig!G:G,df_extrato_zig!E:E,Conciliacao!A378,df_extrato_zig!D:D,"Antecipação") | C378: =SUMIFS(df_extrato_zig!E:E,df_extrato_zig!L:L,Conciliacao!A378,df_extrato_zig!F:F,"DINHEIRO") | D378: =SUMIFS(view_parc_agrup!H:H,view_parc_agrup!G:G,Conciliacao!A378) | E378: =SUMIFS(df_eventos!F:F,df_eventos!H:H,Conciliacao!A378) | F378: =SUMIFS(df_mutuos!M:M,df_mutuos!B:B,Conciliacao!A378) | G378: =SUMIFS(df_bloqueios_judiciais!G:G,df_bloqueios_judiciais!D:D,Conciliacao!A378,df_bloqueios_judiciais!G:G,">0") | H378: =SUMIFS(df_extratos!I:I,df_extratos!F:F,">="&Conciliacao!BE378,df_extratos!F:F,"<"&Conciliacao!BE378+1,df_extratos!G:G,"CREDITO") +SUMIFS(df_extratos!I:I,df_extratos!F:F,">="&Conciliacao!A378, df_extratos!F:F,"<"&Conciliacao!A378+1, df_extratos!G:G,"CREDITO") +SUMIFS(df_extratos!I:I,df_extratos!F:F,">="&Conciliacao!BF378,df_extratos!F:F,"<"&Conciliacao!BF378+1,df_extratos!G:G,"CREDITO") +SUMIFS(df_extratos!I:I,df_extratos!F:F,">="&Conciliacao!BG378,df_extratos!F:F,"<"&Conciliacao!BG378+1,df_extratos!G:G,"CREDITO") +SUMIFS(df_extratos!I:I,df_extratos!F:F,">="&Conciliacao!BH378,df_extratos!F:F,"<"&Conciliacao!BH378+1,df_extratos!G:G,"CREDITO") | I378: =H378-SUM(B378:G378) | J378: =SUMIFS(df_blueme_sem_parcelamento!E:E,df_blueme_sem_parcelamento!H:H,Conciliacao!A378)*(-1) | K378: =SUMIFS(df_blueme_com_parcelamento!J:J,df_blueme_com_parcelamento!M:M,Conciliacao!A378)*(-1) | L378: =SUMIFS(df_mutuos!N:N,df_mutuos!B:B,Conciliacao!A378)*(-1) | M378: =SUMIFS(df_bloqueios_judiciais!G:G,df_bloqueios_judiciais!D:D,Conciliacao!A378,df_bloqueios_judiciais!G:G,"<0") | N378: =SUMIFS(df_extratos!I:I,df_extratos!F:F,">="&Conciliacao!BE378,df_extratos!F:F,"<"&Conciliacao!BE378+1,df_extratos!G:G,"DEBITO") +SUMIFS(df_extratos!I:I,df_extratos!F:F,">="&Conciliacao!A378, df_extratos!F:F,"<"&Conciliacao!A378+1, df_extratos!G:G,"DEBITO") +SUMIFS(df_extratos!I:I,df_extratos!F:F,">="&Conciliacao!BF378,df_extratos!F:F,"<"&Conciliacao!BF378+1,df_extratos!G:G,"DEBITO") +SUMIFS(df_extratos!I:I,df_extratos!F:F,">="&Conciliacao!BG378,df_extratos!F:F,"<"&Conciliacao!BG378+1,df_extratos!G:G,"DEBITO") +SUMIFS(df_extratos!I:I,df_extratos!F:F,">="&Conciliacao!BH378,df_extratos!F:F,"<"&Conciliacao!BH378+1,df_extratos!G:G,"DEBITO") | O378: =N378-SUM(J378:M378) | P378: =SUMIFS(df_ajustes_conciliaco!D:D,df_ajustes_conciliaco!C:C,Conciliacao!A378) | Q378: =O378+I378-P378
... A731: =A730+1 | B731: =-SUMIFS(df_extrato_zig!G:G,df_extrato_zig!E:E,Conciliacao!A731,df_extrato_zig!D:D,"Saque")-SUMIFS(df_extrato_zig!G:G,df_extrato_zig!E:E,Conciliacao!A731,df_extrato_zig!D:D,"Antecipação") | C731: =SUMIFS(df_extrato_zig!E:E,df_extrato_zig!L:L,Conciliacao!A731,df_extrato_zig!F:F,"DINHEIRO") | D731: =SUMIFS(view_parc_agrup!H:H,view_parc_agrup!G:G,Conciliacao!A731) | E731: =SUMIFS(df_eventos!F:F,df_eventos!H:H,Conciliacao!A731) | F731: =SUMIFS(df_mutuos!M:M,df_mutuos!B:B,Conciliacao!A731) | G731: =SUMIFS(df_bloqueios_judiciais!G:G,df_bloqueios_judiciais!D:D,Conciliacao!A731,df_bloqueios_judiciais!G:G,">0") | H731: =SUMIFS(df_extratos!I:I,df_extratos!F:F,">="&Conciliacao!BE731,df_extratos!F:F,"<"&Conciliacao!BE731+1,df_extratos!G:G,"CREDITO") +SUMIFS(df_extratos!I:I,df_extratos!F:F,">="&Conciliacao!A731, df_extratos!F:F,"<"&Conciliacao!A731+1, df_extratos!G:G,"CREDITO") +SUMIFS(df_extratos!I:I,df_extratos!F:F,">="&Conciliacao!BF731,df_extratos!F:F,"<"&Conciliacao!BF731+1,df_extratos!G:G,"CREDITO") +SUMIFS(df_extratos!I:I,df_extratos!F:F,">="&Conciliacao!BG731,df_extratos!F:F,"<"&Conciliacao!BG731+1,df_extratos!G:G,"CREDITO") +SUMIFS(df_extratos!I:I,df_extratos!F:F,">="&Conciliacao!BH731,df_extratos!F:F,"<"&Conciliacao!BH731+1,df_extratos!G:G,"CREDITO") | I731: =H731-SUM(B731:G731) | J731: =SUMIFS(df_blueme_sem_parcelamento!E:E,df_blueme_sem_parcelamento!H:H,Conciliacao!A731)*(-1) | K731: =SUMIFS(df_blueme_com_parcelamento!J:J,df_blueme_com_parcelamento!M:M,Conciliacao!A731)*(-1) | L731: =SUMIFS(df_mutuos!N:N,df_mutuos!B:B,Conciliacao!A731)*(-1) | M731: =SUMIFS(df_bloqueios_judiciais!G:G,df_bloqueios_judiciais!D:D,Conciliacao!A731,df_bloqueios_judiciais!G:G,"<0") | N731: =SUMIFS(df_extratos!I:I,df_extratos!F:F,">="&Conciliacao!BE731,df_extratos!F:F,"<"&Conciliacao!BE731+1,df_extratos!G:G,"DEBITO") +SUMIFS(df_extratos!I:I,df_extratos!F:F,">="&Conciliacao!A731, df_extratos!F:F,"<"&Conciliacao!A731+1, df_extratos!G:G,"DEBITO") +SUMIFS(df_extratos!I:I,df_extratos!F:F,">="&Conciliacao!BF731,df_extratos!F:F,"<"&Conciliacao!BF731+1,df_extratos!G:G,"DEBITO") +SUMIFS(df_extratos!I:I,df_extratos!F:F,">="&Conciliacao!BG731,df_extratos!F:F,"<"&Conciliacao!BG731+1,df_extratos!G:G,"DEBITO") +SUMIFS(df_extratos!I:I,df_extratos!F:F,">="&Conciliacao!BH731,df_extratos!F:F,"<"&Conciliacao!BH731+1,df_extratos!G:G,"DEBITO") | O731: =N731-SUM(J731:M731) | P731: =SUMIFS(df_ajustes_conciliaco!D:D,df_ajustes_conciliaco!C:C,Conciliacao!A731) | Q731: =O731+I731-P731

Sheet df_extrato_zig
A1: ID_Extrato | B1: ID_Casa | C1: Casa | D1: Descricao | E1: Data_Liquidacao | F1: Data_Transacao | G1: Valor
A2: 49795 | B2: 149 | C2: Priceless | D2: Saldo Inicial | E2: 46057 | F2: 46057 | G2: -61117.47
A3: 49796 | B3: 149 | C3: Priceless | D3: Saldo Inicial | E3: 46057 | F3: 46057 | G3: -3115822.3
A4: 49797 | B4: 149 | C4: Priceless | D4: Saque | E4: 46057 | F4: 46057 | G4: -9152
A5: 49766 | B5: 149 | C5: Priceless | D5: Saque | E5: 46056 | F5: 46056 | G5: -1642
A6: 49764 | B6: 149 | C6: Priceless | D6: Saldo Inicial | E6: 46056 | F6: 46056 | G6: -61117.47
A7: 49765 | B7: 149 | C7: Priceless | D7: Saldo Inicial | E7: 46056 | F7: 46056 | G7: -3114180.3
A8: 49734 | B8: 149 | C8: Priceless | D8: Saque | E8: 46055 | F8: 46055 | G8: -35514
A9: 49732 | B9: 149 | C9: Priceless | D9: Saldo Inicial | E9: 46055 | F9: 46055 | G9: -61117.47
A10: 49733 | B10: 149 | C10: Priceless | D10: Saldo Inicial | E10: 46055 | F10: 46055 | G10: -3078666.3
A11: 49692 | B11: 149 | C11: Priceless | D11: Saldo Inicial | E11: 46054 | F11: 46054 | G11: -61117.47
A12: 49693 | B12: 149 | C12: Priceless | D12: Saldo Inicial | E12: 46054 | F12: 46054 | G12: -3078666.3
A13: 49670 | B13: 149 | C13: Priceless | D13: Saldo Inicial | E13: 46053 | F13: 46053 | G13: -3078666.3
... A2710: 13848 | B2710: 149 | C2710: Priceless | D2710: Saldo Inicial | E2710: 45658 | F2710: 45658 | G2710: -197.06

Sheet df_zig_faturam
A1: ID_Casa | B1: Casa | C1: Data_Venda | D1: Valor | E1: Tipo_Pagamento
A2: 149 | B2: Priceless | C2: 46056 | D2: 0 | E2: ANTECIPADO
A3: 149 | B3: Priceless | C3: 46056 | D3: 0 | E3: MBWAY
A4: 149 | B4: Priceless | C4: 46056 | D4: 0 | E4: VOUCHER INTEGRADO
A5: 149 | B5: Priceless | C5: 46056 | D5: 0 | E5: RECARGAS DEVOLVIDAS
A6: 149 | B6: Priceless | C6: 46056 | D6: 0 | E6: AME
A7: 149 | B7: Priceless | C7: 46056 | D7: 13421.87 | E7: CRÉDITO
A8: 149 | B8: Priceless | C8: 46056 | D8: 0 | E8: DINHEIRO
A9: 149 | B9: Priceless | C9: 46056 | D9: 0 | E9: APP
A10: 149 | B10: Priceless | C10: 46056 | D10: 0 | E10: DELIVERY ONLINE
A11: 149 | B11: Priceless | C11: 46056 | D11: 0 | E11: IFOOD
A12: 149 | B12: Priceless | C12: 46056 | D12: 124.3 | E12: PIX
A13: 149 | B13: Priceless | C13: 46056 | D13: 0 | E13: RAPPI
... A11306: 149 | B11306: Priceless | C11306: 45663 | D11306: 0 | E11306: BÔNUS

Sheet view_parc_agrup
A1: ID_Receita | B1: ID_Casa | C1: Casa | D1: Cliente | E1: Data_Ocorrencia | F1: Vencimento_Parcela | G1: Recebimento_Parcela | H1: Valor_Parcela | I1: Doc_NF | J1: Classif_Receita | K1: Forma_Pagamento | L1: Status_Pgto | M1: Conta_Bancaria | N1: Observacoes
A2: 5187 | B2: 149 | C2: Priceless | D2: CIELO | E2: 45701 | F2: 45701 | G2: 45701 | H2: 2294.64 | J2: Voucher | K2: Transferência Bancária ou Pix | L2: Pago | M2: Orfeu - 318 Bar - Caixa | N2: CIELO
A3: 9504 | B3: 149 | C3: Priceless | D3: MASTERCARD BRASIL SOLUÇÕES DE PAGAMENTO LTDA | E3: 45931 | F3: 46024 | G3: 46024 | H3: 1100000 | J3: Patrocínio | K3: Transferência Bancária ou Pix | L3: Pago | M3: Priceless - Bem Mais - Itaú | N3: ATIVAÇÃO PRICELESS FERNANDO DE NORORNHA - CONTRATO 310297 - PARCELA 2/2 - REPASSE ONILDO
A4: 9153 | B4: 149 | C4: Priceless | D4: MASTERCARD BRASIL SOLUÇÕES DE PAGAMENTO LTDA | E4: 45950 | F4: 46024 | G4: 46024 | H4: 61000 | J4: Patrocínio | K4: Transferência Bancária ou Pix | L4: Pago | M4: Priceless - Bem Mais - Santander | N4: CONTRATO DE PATROCINIO ASSINADO 01/07/2025 - NUMERO 295468 - PARCELA 1/3
A5: 10696 | B5: 149 | C5: Priceless | D5: PLUXEE BENEFICIOS BRASIL S.A. (SODEXO) | E5: 46021 | F5: 46021 | G5: 46021 | H5: 374.06 | J5: Voucher | K5: Transferência Bancária ou Pix | L5: Pago | M5: Priceless - Bem Mais - Santander | N5: VOUCHER
A6: 10695 | B6: 149 | C6: Priceless | D6: GETNET | E6: 46020 | F6: 46020 | G6: 46020 | H6: 62.29 | J6: Voucher | K6: Transferência Bancária ou Pix | L6: Pago | M6: Priceless - Bem Mais - Santander | N6: VOUCHER
A7: 10693 | B7: 149 | C7: Priceless | D7: TICKET SERVICO SA | E7: 46020 | F7: 46020 | G7: 46020 | H7: 306.05 | J7: Voucher | K7: Transferência Bancária ou Pix | L7: Pago | M7: Priceless - Bem Mais - Itaú | N7: VOUCHER
A8: 10694 | B8: 149 | C8: Priceless | D8: PLUXEE BENEFICIOS BRASIL S.A. (SODEXO) | E8: 46020 | F8: 46020 | G8: 46020 | H8: 283.89 | J8: Voucher | K8: Transferência Bancária ou Pix | L8: Pago | M8: Priceless - Bem Mais - Santander | N8: VOUCHER
A9: 10688 | B9: 149 | C9: Priceless | D9: ALELO | E9: 46017 | F9: 46017 | G9: 46017 | H9: 2512.8 | J9: Voucher | K9: Transferência Bancária ou Pix | L9: Pago | M9: Priceless - Bem Mais - Santander | N9: VOUCHER
A10: 10689 | B10: 149 | C10: Priceless | D10: PLUXEE BENEFICIOS BRASIL S.A. (SODEXO) | E10: 46017 | F10: 46017 | G10: 46017 | H10: 793.14 | J10: Voucher | K10: Transferência Bancária ou Pix | L10: Pago | M10: Priceless - Bem Mais - Santander | N10: VOUCHER
A11: 10690 | B11: 149 | C11: Priceless | D11: TORANJA | E11: 46017 | F11: 46017 | G11: 46017 | H11: 375 | J11: Reembolso | K11: Transferência Bancária ou Pix | L11: Pago | M11: Priceless - Bem Mais - Itaú | N11: VOUCHER
A12: 10691 | B12: 149 | C12: Priceless | D12: TICKET SERVICO SA | E12: 46017 | F12: 46017 | G12: 46017 | H12: 187.86 | J12: Voucher | K12: Transferência Bancária ou Pix | L12: Pago | M12: Priceless - Bem Mais - Santander | N12: VOUCHER
A13: 10692 | B13: 149 | C13: Priceless | D13: VR Benefícios e Serviços | E13: 46017 | F13: 46017 | G13: 46017 | H13: 85.87 | J13: Voucher | K13: Transferência Bancária ou Pix | L13: Pago | M13: Priceless - Bem Mais - Itaú | N13: VOUCHER
... A30: 9986 | B30: 149 | C30: Priceless | D30: MERCADO PAGO | E30: 46003 | F30: 46003 | G30: 46003 | H30: 56.99 | J30: Reembolso | K30: Transferência Bancária ou Pix | L30: Pago | M30: Priceless - Bem Mais - Kamino | N30: DEVOLUCAO DE PIX
A31: 9988 | B31: 149 | C31: Priceless | D31: ALELO | E31: 46003 | F31: 46003 | G31: 46003 | H31: 205.62 | J31: Voucher | K31: Transferência Bancária ou Pix | L31: Pago | M31: Priceless - Bem Mais - Santander
A32: 10670 | B32: 149 | C32: Priceless | D32: PLUXEE BENEFICIOS BRASIL S.A. (SODEXO) | E32: 46002 | F32: 46002 | G32: 46002 | H32: 3114.36 | J32: Voucher | K32: Transferência Bancária ou Pix | L32: Pago | M32: Priceless - Bem Mais - Santander | N32: VOUCHER
A33: 10669 | B33: 149 | C33: Priceless | D33: ALELO | E33: 46002 | F33: 46002 | G33: 46002 | H33: 242.42 | J33: Voucher | K33: Transferência Bancária ou Pix | L33: Pago | M33: Priceless - Bem Mais - Santander | N33: VOUCHER
A34: 9917 | B34: 149 | C34: Priceless | D34: VR Benefícios e Serviços | E34: 46002 | F34: 46002 | G34: 46002 | H34: 60.61 | J34: Voucher | K34: Transferência Bancária ou Pix | L34: Pago | M34: Priceless - Bem Mais - Itaú
A35: 9951 | B35: 149 | C35: Priceless | D35: ALELO | E35: 46001 | F35: 46001 | G35: 46001 | H35: 1158.15 | J35: Voucher | K35: Transferência Bancária ou Pix | L35: Pago | M35: Priceless - Bem Mais - Santander
A36: 9897 | B36: 149 | C36: Priceless | D36: ZOOP TECNOLOGIA & INSTITUICAO DE PAGAMENTO S.A | E36: 46000 | F36: 46000 | G36: 46000 | H36: 533.64 | J36: Crédito Indevido | K36: Transferência Bancária ou Pix | L36: Pago | M36: Priceless - Bem Mais - Itaú | N36: CREDITO ZOOP TECNOLOGIA
A37: 9831 | B37: 149 | C37: Priceless | D37: TICKET SERVICO SA | E37: 45999 | F37: 45999 | G37: 45999 | H37: 2261.65 | J37: Voucher | K37: Transferência Bancária ou Pix | L37: Pago | M37: Priceless - Bem Mais - Itaú
A38: 9950 | B38: 149 | C38: Priceless | D38: ALELO | E38: 45999 | F38: 45999 | G38: 45999 | H38: 1071.41 | J38: Voucher | K38: Transferência Bancária ou Pix | L38: Pago | M38: Priceless - Bem Mais - Santander
A39: 10011 | B39: 149 | C39: Priceless | D39: KAMINO | E39: 45997 | F39: 45997 | G39: 45997 | H39: 178.89 | J39: Crédito Indevido | K39: Transferência Bancária ou Pix | L39: Pago | M39: Priceless - Bem Mais - Kamino | N39: Devolução de Pix Enviado para Pix Marketplace
A40: 9949 | B40: 149 | C40: Priceless | D40: ALELO | E40: 45996 | F40: 45996 | G40: 45996 | H40: 673.03 | J40: Voucher | K40: Transferência Bancária ou Pix | L40: Pago | M40: Priceless - Bem Mais - Santander
A41: 10668 | B41: 149 | C41: Priceless | D41: TICKET SERVICO SA | E41: 45996 | F41: 45996 | G41: 45996 | H41: 2373.11 | J41: Voucher | K41: Transferência Bancária ou Pix | L41: Pago | M41: Priceless - Bem Mais - Santander | N41: VOUCHER
A42: 9798 | B42: 149 | C42: Priceless | D42: TICKET SERVICO SA | E42: 45996 | F42: 45996 | G42: 45996 | H42: 187.07 | J42: Voucher | K42: Taxas Automáticas ZigPay | L42: Pago | M42: Priceless - Bem Mais - Itaú
A43: 9810 | B43: 149 | C43: Priceless | D43: TORANJA | E43: 45996 | F43: 45996 | G43: 45996 | H43: 375 | J43: Reembolso | K43: Transferência Bancária ou Pix | L43: Pago | M43: Priceless - Bem Mais - Itaú | N43: CREDITO FORNECEDOR HOMOLOGADO CLT GERADORES
A44: 9948 | B44: 149 | C44: Priceless | D44: ALELO | E44: 45995 | F44: 45995 | G44: 45995 | H44: 206.85 | J44: Voucher | K44: Transferência Bancária ou Pix | L44: Pago | M44: Priceless - Bem Mais - Santander
A45: 9947 | B45: 149 | C45: Priceless | D45: PLUXEE BENEFICIOS BRASIL S.A. (SODEXO) | E45: 45995 | F45: 45995 | G45: 45995 | H45: 121.9 | J45: Voucher | K45: Transferência Bancária ou Pix | L45: Pago | M45: Priceless - Bem Mais - Santander
A46: 9946 | B46: 149 | C46: Priceless | D46: PLUXEE BENEFICIOS BRASIL S.A. (SODEXO) | E46: 45995 | F46: 45995 | G46: 45995 | H46: 1132.97 | J46: Voucher | K46: Transferência Bancária ou Pix | L46: Pago | M46: Priceless - Bem Mais - Santander
A47: 9791 | B47: 149 | C47: Priceless | F47: 45995 | G47: 45995 | H47: 490.89 | J47: Voucher | K47: Transferência Bancária ou Pix | L47: Pago | M47: Priceless - Bem Mais - Itaú
A48: 10667 | B48: 149 | C48: Priceless | D48: TICKET SERVICO SA | E48: 45994 | F48: 45994 | G48: 45994 | H48: 8288.27 | J48: Voucher | K48: Transferência Bancária ou Pix | L48: Pago | M48: Priceless - Bem Mais - Santander | N48: VOUCHER
A49: 9944 | B49: 149 | C49: Priceless | D49: GETNET | E49: 45994 | F49: 45994 | G49: 45994 | H49: 95 | J49: Voucher | K49: Transferência Bancária ou Pix | L49: Pago | M49: Priceless - Bem Mais - Santander
A50: 9745 | B50: 149 | C50: Priceless | D50: MERCADO PAGO | E50: 45993 | F50: 45993 | G50: 45993 | H50: 644.1 | J50: Reembolso | K50: Transferência Bancária ou Pix | L50: Pago | M50: Priceless - Bem Mais - Kamino | N50: ESTORNO MERCADO PAGO - ID 1089
A51: 9945 | B51: 149 | C51: Priceless | D51: ALELO | E51: 45992 | F51: 45992 | G51: 45992 | H51: 245.57 | J51: Voucher | K51: Transferência Bancária ou Pix | L51: Pago | M51: Priceless - Bem Mais - Santander
A52: 9723 | B52: 149 | C52: Priceless | D52: TICKET SERVICO SA | F52: 45992 | G52: 45992 | H52: 0 | J52: Voucher | K52: Transferência Bancária ou Pix | L52: Pago | M52: Priceless - Bem Mais - Itaú
A53: 9736 | B53: 149 | C53: Priceless | D53: GUILHERME MEDON | E53: 45992 | F53: 45992 | G53: 45992 | H53: 27.85 | J53: Voucher | K53: Transferência Bancária ou Pix | L53: Pago | M53: Priceless - Bem Mais - Kamino
A54: 9735 | B54: 149 | C54: Priceless | D54: TICKET SERVICO SA | E54: 45992 | F54: 45992 | G54: 45992 | H54: 135.43 | J54: Voucher | K54: Transferência Bancária ou Pix | L54: Pago | M54: Priceless - Bem Mais - Itaú
A55: 9734 | B55: 149 | C55: Priceless | D55: iFood | E55: 45992 | F55: 45992 | G55: 45992 | H55: 0.01 | J55: Voucher | K55: Transferência Bancária ou Pix | L55: Pago | M55: Priceless - Bem Mais - Itaú
A56: 3463 | B56: 149 | C56: Priceless | D56: AMBEV S/A | E56: 46001 | F56: 45992 | G56: 45992 | H56: 285000 | J56: Patrocínio | K56: Transferência Bancária ou Pix | L56: Pago | M56: Priceless - Bem Mais - Kamino | N56: CONTRATO AMBEV – VIGENCIA 01/11/2024 A 01/11/2026 - PARCELA 2/3
A57: 9968 | B57: 149 | C57: Priceless | D57: ALELO | E57: 45989 | F57: 45989 | G57: 45989 | H57: 247.92 | J57: Voucher | K57: Transferência Bancária ou Pix | L57: Pago | M57: Priceless - Bem Mais - Santander
A58: 10621 | B58: 149 | C58: Priceless | D58: SILVIA DURLO SANTOS LIMA | E58: 45989 | F58: 45989 | G58: 45989 | H58: 487.03 | J58: Crédito Indevido | K58: Transferência Bancária ou Pix | L58: Pago | M58: Priceless - Bem Mais - Kamino | N58: NÃO IDENTIFICADO
A59: 9983 | B59: 149 | C59: Priceless | D59: VR Benefícios e Serviços | E59: 45988 | F59: 45988 | G59: 45988 | H59: 94.62 | J59: Voucher | K59: Transferência Bancária ou Pix | L59: Pago | M59: Priceless - Bem Mais - Itaú
A60: 10238 | B60: 149 | C60: Priceless | D60: ALELO | E60: 45988 | F60: 45988 | G60: 45988 | H60: 0 | J60: Voucher | K60: Transferência Bancária ou Pix | L60: Pago | M60: Priceless - Bem Mais - Santander | N60: VOUCHER
A61: 9967 | B61: 149 | C61: Priceless | D61: GETNET | E61: 45988 | F61: 45988 | G61: 45988 | H61: 59.66 | J61: Voucher | K61: Transferência Bancária ou Pix | L61: Pago | M61: Priceless - Bem Mais - Santander
A62: 9692 | B62: 149 | C62: Priceless | D62: KAMINO | E62: 45988 | F62: 45988 | G62: 45988 | H62: 0.01 | J62: Juros de Aplicações Financeiras | K62: Transferência Bancária ou Pix | L62: Pago | M62: Priceless - Bem Mais - Kamino | N62: Remuneração conta Kamino
A63: 9965 | B63: 149 | C63: Priceless | D63: PLUXEE BENEFICIOS BRASIL S.A. (SODEXO) | E63: 45988 | F63: 45988 | G63: 45988 | H63: 1558.26 | J63: Voucher | K63: Transferência Bancária ou Pix | L63: Pago | M63: Priceless - Bem Mais - Santander
A64: 9964 | B64: 149 | C64: Priceless | D64: PLUXEE BENEFICIOS BRASIL S.A. (SODEXO) | E64: 45988 | F64: 45988 | G64: 45988 | H64: 199.69 | J64: Voucher | K64: Transferência Bancária ou Pix | L64: Pago | M64: Priceless - Bem Mais - Santander
A65: 9698 | B65: 149 | C65: Priceless | D65: Mercado Livre | E65: 45986 | F65: 45986 | G65: 45986 | H65: 1072.45 | J65: Reembolso | K65: Transferência Bancária ou Pix | L65: Pago | M65: Priceless - Bem Mais - Kamino | N65: COMPRA NO MERCADO LIVRE QUE FOI CANCELADA ID DO A VISTA 1.109 - 11/2025
A66: 9963 | B66: 149 | C66: Priceless | D66: GETNET | E66: 45986 | F66: 45986 | G66: 45986 | H66: 133.68 | J66: Voucher | K66: Transferência Bancária ou Pix | L66: Pago | M66: Priceless - Bem Mais - Santander
A67: 9982 | B67: 149 | C67: Priceless | D67: TICKET SERVICO SA | E67: 45985 | F67: 45985 | G67: 45985 | H67: 563.29 | J67: Voucher | K67: Transferência Bancária ou Pix | L67: Pago | M67: Priceless - Bem Mais - Itaú
A68: 9981 | B68: 149 | C68: Priceless | D68: VR Benefícios e Serviços | E68: 45982 | F68: 45982 | G68: 45982 | H68: 244.54 | J68: Voucher | K68: Transferência Bancária ou Pix | L68: Pago | M68: Priceless - Bem Mais - Itaú
A69: 10237 | B69: 149 | C69: Priceless | D69: ALELO | E69: 45982 | F69: 45982 | G69: 45982 | H69: 1587.71 | J69: Voucher | K69: Transferência Bancária ou Pix | L69: Pago | M69: Priceless - Bem Mais - Santander | N69: VOUCHER
A70: 9962 | B70: 149 | C70: Priceless | D70: PLUXEE BENEFICIOS BRASIL S.A. (SODEXO) | E70: 45982 | F70: 45982 | G70: 45982 | H70: 107.87 | J70: Voucher | K70: Transferência Bancária ou Pix | L70: Pago | M70: Priceless - Bem Mais - Santander
A71: 9961 | B71: 149 | C71: Priceless | D71: PLUXEE BENEFICIOS BRASIL S.A. (SODEXO) | E71: 45982 | F71: 45982 | G71: 45982 | H71: 803.94 | J71: Voucher | K71: Transferência Bancária ou Pix | L71: Pago | M71: Priceless - Bem Mais - Santander
A72: 9960 | B72: 149 | C72: Priceless | D72: PLUXEE BENEFICIOS BRASIL S.A. (SODEXO) | E72: 45982 | F72: 45982 | G72: 45982 | H72: 82.22 | J72: Voucher | K72: Transferência Bancária ou Pix | L72: Pago | M72: Priceless - Bem Mais - Santander
A73: 9959 | B73: 149 | C73: Priceless | D73: ALELO | E73: 45980 | F73: 45980 | G73: 45980 | H73: 91.98 | J73: Voucher | K73: Transferência Bancária ou Pix | L73: Pago | M73: Priceless - Bem Mais - Santander
A74: 9958 | B74: 149 | C74: Priceless | D74: ALELO | E74: 45979 | F74: 45979 | G74: 45979 | H74: 659.49 | J74: Voucher | K74: Transferência Bancária ou Pix | L74: Pago | M74: Priceless - Bem Mais - Santander
A75: 9957 | B75: 149 | C75: Priceless | D75: Banco Santander | E75: 45978 | F75: 45978 | G75: 45978 | H75: 327.05 | J75: Voucher | K75: Transferência Bancária ou Pix | L75: Pago | M75: Priceless - Bem Mais - Santander
A76: 9980 | B76: 149 | C76: Priceless | D76: TICKET SERVICO SA | E76: 45978 | F76: 45978 | G76: 45978 | H76: 95.07 | J76: Voucher | K76: Transferência Bancária ou Pix | L76: Pago | M76: Priceless - Bem Mais - Itaú
A77: 10236 | B77: 149 | C77: Priceless | D77: ALELO | E77: 45978 | F77: 45978 | G77: 45978 | H77: 0 | J77: Voucher | K77: Transferência Bancária ou Pix | L77: Pago | M77: Priceless - Bem Mais - Santander | N77: VOUCHER
A78: 9956 | B78: 149 | C78: Priceless | D78: ALELO | E78: 45975 | F78: 45975 | G78: 45975 | H78: 623.71 | J78: Voucher | K78: Transferência Bancária ou Pix | L78: Pago | M78: Priceless - Bem Mais - Santander
A79: 9979 | B79: 149 | C79: Priceless | D79: TICKET SERVICO SA | E79: 45975 | F79: 45975 | G79: 45975 | H79: 144.56 | J79: Voucher | K79: Transferência Bancária ou Pix | L79: Pago | M79: Priceless - Bem Mais - Itaú
A80: 9955 | B80: 149 | C80: Priceless | D80: PLUXEE BENEFICIOS BRASIL S.A. (SODEXO) | E80: 45974 | F80: 45974 | G80: 45974 | H80: 176.2 | J80: Voucher | K80: Transferência Bancária ou Pix | L80: Pago | M80: Priceless - Bem Mais - Santander
A81: 9954 | B81: 149 | C81: Priceless | D81: PLUXEE BENEFICIOS BRASIL S.A. (SODEXO) | E81: 45974 | F81: 45974 | G81: 45974 | H81: 2094.64 | J81: Voucher | K81: Transferência Bancária ou Pix | L81: Pago | M81: Priceless - Bem Mais - Santander
A82: 9978 | B82: 149 | C82: Priceless | D82: VR Benefícios e Serviços | E82: 45974 | F82: 45974 | G82: 45974 | H82: 299.12 | J82: Voucher | K82: Transferência Bancária ou Pix | L82: Pago | M82: Priceless - Bem Mais - Itaú
A83: 9953 | B83: 149 | C83: Priceless | D83: ALELO | E83: 45972 | F83: 45972 | G83: 45972 | H83: 240.29 | J83: Voucher | K83: Transferência Bancária ou Pix | L83: Pago | M83: Priceless - Bem Mais - Santander
A84: 9952 | B84: 149 | C84: Priceless | D84: ALELO | E84: 45971 | F84: 45971 | G84: 45971 | H84: 591.1 | J84: Voucher | K84: Transferência Bancária ou Pix | L84: Pago | M84: Priceless - Bem Mais - Santander
A85: 9972 | B85: 149 | C85: Priceless | D85: GETNET | E85: 45971 | F85: 45971 | G85: 45971 | H85: 448.84 | J85: Voucher | K85: Transferência Bancária ou Pix | L85: Pago | M85: Priceless - Bem Mais - Santander
A86: 9971 | B86: 149 | C86: Priceless | D86: ALELO | E86: 45968 | F86: 45968 | G86: 45968 | H86: 102.43 | J86: Voucher | K86: Transferência Bancária ou Pix | L86: Pago | M86: Priceless - Bem Mais - Santander
A87: 9970 | B87: 149 | C87: Priceless | D87: ALELO | E87: 45967 | F87: 45967 | G87: 45967 | H87: 367.51 | J87: Voucher | K87: Transferência Bancária ou Pix | L87: Pago | M87: Priceless - Bem Mais - Santander
A88: 9969 | B88: 149 | C88: Priceless | D88: ALELO | E88: 45964 | F88: 45964 | G88: 45964 | H88: 177.58 | J88: Voucher | K88: Transferência Bancária ou Pix | L88: Pago | M88: Priceless - Bem Mais - Santander
A89: 10231 | B89: 149 | C89: Priceless | D89: ALELO | E89: 45964 | F89: 45964 | G89: 45964 | H89: 391.37 | J89: Voucher | K89: Transferência Bancária ou Pix | L89: Pago | M89: Priceless - Bem Mais - Santander | N89: VOUCHER
A90: 10230 | B90: 149 | C90: Priceless | D90: ALELO | E90: 45961 | F90: 45961 | G90: 45961 | H90: 2692.15 | J90: Voucher | K90: Transferência Bancária ou Pix | L90: Pago | M90: Priceless - Bem Mais - Santander | N90: VOUCHER
A91: 9976 | B91: 149 | C91: Priceless | D91: ALELO | E91: 45960 | F91: 45960 | G91: 45960 | H91: 100.23 | J91: Voucher | K91: Transferência Bancária ou Pix | L91: Pago | M91: Priceless - Bem Mais - Santander
A92: 9975 | B92: 149 | C92: Priceless | D92: ALELO | E92: 45959 | F92: 45959 | G92: 45959 | H92: 70.03 | J92: Voucher | K92: Transferência Bancária ou Pix | L92: Pago | M92: Priceless - Bem Mais - Santander
A93: 9974 | B93: 149 | C93: Priceless | D93: ALELO | E93: 45958 | F93: 45958 | G93: 45958 | H93: 95.03 | J93: Voucher | K93: Transferência Bancária ou Pix | L93: Pago | M93: Priceless - Bem Mais - Santander
A94: 9973 | B94: 149 | C94: Priceless | D94: ALELO | E94: 45957 | F94: 45957 | G94: 45957 | H94: 47.05 | J94: Voucher | K94: Transferência Bancária ou Pix | L94: Pago | M94: Priceless - Bem Mais - Santander
A95: 9789 | B95: 149 | C95: Priceless | D95: TICKET SERVICO SA | E95: 45957 | F95: 45957 | G95: 45957 | H95: 96.23 | J95: Voucher | K95: Transferência Bancária ou Pix | L95: Pago | M95: Priceless - Bem Mais - Itaú | N95: VOUCHER
A96: 9896 | B96: 149 | C96: Priceless | D96: TORANJA | E96: 45954 | F96: 45954 | G96: 45954 | H96: 375 | J96: Reembolso | K96: Transferência Bancária ou Pix | L96: Pago | M96: Priceless - Bem Mais - Itaú | N96: CREDITO FORNECEDOR HOMOLOGADO CLT GERADORES
A97: 10222 | B97: 149 | C97: Priceless | D97: TICKET SERVICO SA | E97: 45950 | F97: 45950 | G97: 45950 | H97: 71.81 | J97: Voucher | K97: Transferência Bancária ou Pix | L97: Pago | M97: Blue Note SP - Spjazz - Banco do Brasil | N97: VOUCHER
A98: 9797 | B98: 149 | C98: Priceless | D98: MERCADO PAGO | E98: 45948 | F98: 45948 | G98: 45948 | H98: 1446.8 | J98: Reembolso | K98: Transferência Bancária ou Pix | L98: Pago | M98: Priceless - Bem Mais - Kamino | N98: DEVOLUÇÃO DO MERCADO LIVRE
A99: 10221 | B99: 149 | C99: Priceless | D99: ALELO | E99: 45946 | F99: 45946 | G99: 45946 | H99: 9650.34 | J99: Voucher | K99: Transferência Bancária ou Pix | L99: Pago | M99: Blue Note SP - Spjazz - Banco do Brasil | N99: VOUCHER
A100: 9130 | B100: 149 | C100: Priceless | D100: TICKET SERVICO SA | E100: 45943 | F100: 45943 | G100: 45943 | H100: 1395.91 | J100: Voucher | K100: Transferência Bancária ou Pix | L100: Pago | M100: Priceless - Bem Mais - Itaú
A101: 9129 | B101: 149 | C101: Priceless | D101: TICKET SERVICO SA | E101: 45940 | F101: 45940 | G101: 45940 | H101: 377.94 | J101: Voucher | K101: Transferência Bancária ou Pix | L101: Pago | M101: Priceless - Bem Mais - Itaú
A102: 9124 | B102: 149 | C102: Priceless | D102: ALELO | E102: 45939 | F102: 45939 | G102: 45939 | H102: 2178.68 | J102: Voucher | K102: Transferência Bancária ou Pix | L102: Pago | M102: Priceless - Bem Mais - Santander
A103: 9123 | B103: 149 | C103: Priceless | D103: CIELO | E103: 45936 | F103: 45936 | G103: 45936 | H103: 96.36 | J103: Voucher | K103: Transferência Bancária ou Pix | L103: Pago | M103: Priceless - Bem Mais - Santander
A104: 9119 | B104: 149 | C104: Priceless | D104: TICKET SERVICO SA | E104: 45936 | F104: 45936 | G104: 45936 | H104: 2886.97 | J104: Voucher | K104: Transferência Bancária ou Pix | L104: Pago | M104: Priceless - Bem Mais - Itaú
A105: 9117 | B105: 149 | C105: Priceless | D105: TICKET SERVICO SA | E105: 45933 | F105: 45933 | G105: 45933 | H105: 179.61 | J105: Voucher | K105: Transferência Bancária ou Pix | L105: Pago | M105: Priceless - Bem Mais - Itaú
A106: 9118 | B106: 149 | C106: Priceless | D106: TORANJA | E106: 45933 | F106: 45933 | G106: 45933 | H106: 450 | J106: Reembolso | K106: Transferência Bancária ou Pix | L106: Pago | M106: Priceless - Bem Mais - Itaú | N106: CREDITO FORNECEDOR HOMOLOGADO CLT GERADORES
A107: 9116 | B107: 149 | C107: Priceless | D107: VR Benefícios e Serviços | E107: 45932 | F107: 45932 | G107: 45932 | H107: 321.54 | J107: Voucher | K107: Transferência Bancária ou Pix | L107: Pago | M107: Priceless - Bem Mais - Itaú
A108: 9122 | B108: 149 | C108: Priceless | D108: ALELO | E108: 45932 | F108: 45932 | G108: 45932 | H108: 4255.52 | J108: Voucher | K108: Transferência Bancária ou Pix | L108: Pago | M108: Priceless - Bem Mais - Santander
A109: 9007 | B109: 149 | C109: Priceless | D109: ALELO | E109: 45929 | F109: 45929 | G109: 45929 | H109: 739.08 | J109: Voucher | K109: Transferência Bancária ou Pix | L109: Pago | M109: Priceless - Bem Mais - Santander
A110: 8915 | B110: 149 | C110: Priceless | D110: VR Benefícios e Serviços | E110: 45925 | F110: 45925 | G110: 45925 | H110: 99.68 | J110: Voucher | K110: Transferência Bancária ou Pix | L110: Pago | M110: Priceless - Bem Mais - Itaú
A111: 8996 | B111: 149 | C111: Priceless | D111: ALELO | E111: 45925 | F111: 45925 | G111: 45925 | H111: 2622.23 | J111: Voucher | K111: Transferência Bancária ou Pix | L111: Pago | M111: Priceless - Bem Mais - Santander
A112: 8250 | B112: 149 | C112: Priceless | D112: MASTERCARD BRASIL SOLUÇÕES DE PAGAMENTO LTDA | E112: 45905 | F112: 45924 | G112: 45924 | H112: 1082482.7 | J112: Patrocínio | K112: Transferência Bancária ou Pix | L112: Pago | M112: Priceless - Bem Mais - Itaú | N112: CONTRATO DE PATROCINIO - VIDENCIA 01/07/2025 A 01/07/2027 - PARCELA 1/2 - VALOR ENTRARÁ VIA ENTREPAY (R$ 17.710 DESCONTO TAXA ADQUIRENCIA) TOTAL RECEBIDO 1.082.290,00
A113: 8855 | B113: 149 | C113: Priceless | D113: TORANJA | E113: 45923 | F113: 45923 | G113: 45923 | H113: 375 | J113: Reembolso | K113: Transferência Bancária ou Pix | L113: Pago | M113: Priceless - Bem Mais - Itaú | N113: CREDITO FORNECEDOR HOMOLOGADO CLT GERADORES
A114: 9646 | B114: 149 | C114: Priceless | D114: Vinicius Dionisio dos Santos | E114: 45923 | F114: 45923 | G114: 45923 | H114: 284.8 | J114: Reembolso | K114: Transferência Bancária ou Pix | L114: Pago | M114: Priceless - Duroc Filial Dois - Kamino | N114: DEVOLUÇÃO PIX
A115: 8825 | B115: 149 | C115: Priceless | D115: TICKET SERVICO SA | E115: 45922 | F115: 45922 | G115: 45922 | H115: 1232.08 | J115: Voucher | K115: Transferência Bancária ou Pix | L115: Pago | M115: Priceless - Bem Mais - Itaú
A116: 8874 | B116: 149 | C116: Priceless | D116: ALELO | E116: 45922 | F116: 45922 | G116: 45922 | H116: 469.08 | J116: Voucher | K116: Transferência Bancária ou Pix | L116: Pago | M116: Priceless - Bem Mais - Santander
...

Sheet df_eventos
A1: ID_Evento | B1: Nome_Evento | C1: ID_Casa | D1: Casa | E1: ID_Parcela | F1: Valor_Parcela | G1: Vencimento_Parcela | H1: Recebimento_Parcela | I1: Status_Pgto | J1: Forma_Pgto | K1: ID_Conta_Bancaria | L1: Conta_Bancaria | M1: Observacoes
A2: 2543 | B2: ADITIVO_PRO_250700_Agencia Loi_Aline_Restaurante Mirante_26.01.26_50pax | C2: 149 | D2: Priceless | E2: 1298 | F2: 4500 | G2: 46048 | H2: 46050 | I2: Pago | J2: Transferência Bancária ou Pix | K2: 133 | L2: Priceless - Bem Mais - Itaú
A3: 2536 | B3: PRO_260043_ID 2536_Unique Chic_Ensaio_Terraço e Aroo1_28.01.25 | C3: 149 | D3: Priceless | E3: 1296 | F3: 4290 | G3: 46050 | H3: 46050 | I3: Pago | J3: Transferência Bancária ou Pix | K3: 133 | L3: Priceless - Bem Mais - Itaú | M3: CNPJ: 08.622.108/0001-28 Inscrição Estadual SP: 149.572.611.112 Razão Social: UNIQUE CHIC CONFECCOES LTDA LOCALIZAÇÃO Logradouro: Rua Anhaia, 58 - andar 1 e 3 Bairro: Bom Retiro São Paulo/SP CEP: 01130-000 E-mail: edilene.melo@uniquechic.com.br
A4: 2536 | B4: PRO_260043_ID 2536_Unique Chic_Ensaio_Terraço e Aroo1_28.01.25 | C4: 149 | D4: Priceless | E4: 1297 | F4: 8710 | G4: 46050 | H4: 46050 | I4: Pago | J4: Transferência Bancária ou Pix | K4: 133 | L4: Priceless - Bem Mais - Itaú | M4: CNPJ: 08.622.108/0001-28 Inscrição Estadual SP: 149.572.611.112 Razão Social: UNIQUE CHIC CONFECCOES LTDA LOCALIZAÇÃO Logradouro: Rua Anhaia, 58 - andar 1 e 3 Bairro: Bom Retiro São Paulo/SP CEP: 01130-000 E-mail: edilene.melo@uniquechic.com.br
A5: 2246 | B5: PRO_250699_ID2246_Formatura_Isabelli_Alvaro_Mirante e Notiê_16.12.25_100pax | C5: 149 | D5: Priceless | E5: 1201 | F5: 5250 | G5: 46007 | H5: 46050 | I5: Desconto | J5: Transferência Bancária ou Pix | K5: 133 | L5: Priceless - Bem Mais - Itaú
A6: 2442 | B6: PRO_260024 ID 2242_DIVERTI_CBB 2026_DIVERTI_EXTERNO_13 14 15 21.02.26 | C6: 149 | D6: Priceless | E6: 1254 | F6: 225000 | G6: 46044 | H6: 46044 | I6: Pago | J6: Transferência Bancária ou Pix | K6: 133 | L6: Priceless - Bem Mais - Itaú | M6: Por favor emitir 3 DANFE conforme vencimento de cada parcela. Razão Social: SUKSES EVENTOS LTDA Avenida Ipiranga, 795 | 1 andar CEP 01039-000 | São Paulo | SP 1ª parcela R$ 225.000,00 vencimento 05.02.2026 2ª parcela R$ 180.000,00 vencimento 19.02.2026 3ª parcela R$ 51.941,94 vencimento 26.02.2026
A7: 2294 | B7: PRO_250550_ID_2294_Festa Floresta_Bar_Sala_AROO Completo_25abril26_300pax | C7: 149 | D7: Priceless | E7: 1152 | F7: 11453.55 | G7: 46044 | H7: 46044 | I7: Pago | J7: Boleto Bancário | K7: 133 | L7: Priceless - Bem Mais - Itaú
A8: 2294 | B8: PRO_250550_ID_2294_Festa Floresta_Bar_Sala_AROO Completo_25abril26_300pax | C8: 149 | D8: Priceless | E8: 1157 | F8: 37509.32 | G8: 46044 | H8: 46044 | I8: Pago | J8: Boleto Bancário | K8: 133 | L8: Priceless - Bem Mais - Itaú
A9: 2316 | B9: PRO_250700_Agencia Loi_Aline_Restaurante Mirante_26.01.26_50pax | C9: 149 | D9: Priceless | E9: 1193 | F9: 20375 | G9: 46041 | H9: 46043 | I9: Pago | J9: Transferência Bancária ou Pix | K9: 133 | L9: Priceless - Bem Mais - Itaú
A10: 2316 | B10: PRO_250700_Agencia Loi_Aline_Restaurante Mirante_26.01.26_50pax | C10: 149 | D10: Priceless | E10: 1195 | F10: 24625 | G10: 46041 | H10: 46043 | I10: Pago | J10: Transferência Bancária ou Pix | K10: 133 | L10: Priceless - Bem Mais - Itaú
A11: 1855 | B11: PRO_250622_ID_1855_Bayer_almoço_Reserva_Terraço_28jan26_17pax | C11: 149 | D11: Priceless | E11: 1140 | F11: 4054.5 | G11: 46042 | H11: 46042 | I11: Pago | J11: Boleto Bancário | K11: 133 | L11: Priceless - Bem Mais - Itaú
A12: 2335 | B12: PRO_250714_ID_2335_ADITIVO_HORAEXTRA | C12: 149 | D12: Priceless | E12: 1233 | F12: 850 | G12: 46034 | H12: 46034 | I12: Pago | J12: Transferência Bancária ou Pix | K12: 133 | L12: Priceless - Bem Mais - Itaú | M12: Aditivo de 1 hora extra 850,00 de locação 2350,00 de bebida
A13: 2325 | B13: PRO_250712_ID_2325_Capelozza_Sala de Música_6maio26_70pax | C13: 149 | D13: Priceless | E13: 1250 | F13: 22211 | G13: 46042 | H13: 46034 | I13: Pago | J13: Transferência Bancária ou Pix | K13: 133 | L13: Priceless - Bem Mais - Itaú | M13: Evento em negociação, em breve será feita as devidas alterações referentes as condições de pagamento.
A14: 2325 | B14: PRO_250712_ID_2325_Capelozza_Sala de Música_6maio26_70pax | C14: 149 | D14: Priceless | E14: 1248 | F14: 7837.5 | G14: 46042 | H14: 46034 | I14: Pago | J14: Transferência Bancária ou Pix | K14: 133 | L14: Priceless - Bem Mais - Itaú | M14: Evento em negociação, em breve será feita as devidas alterações referentes as condições de pagamento.
A15: 1544 | B15: PRO_250567_ID_1544_BTO+_Sala de Música_19dez_50pax | C15: 149 | D15: Priceless | E15: 1236 | F15: 4250 | G15: 46034 | H15: 46034 | I15: Pago | J15: Transferência Bancária ou Pix | K15: 133 | L15: Priceless - Bem Mais - Itaú
A16: 2335 | B16: PRO_250714_ID_2335_ADITIVO_HORAEXTRA | C16: 149 | D16: Priceless | E16: 1234 | F16: 2350 | G16: 46034 | H16: 46034 | I16: Pago | J16: Transferência Bancária ou Pix | K16: 133 | L16: Priceless - Bem Mais - Itaú | M16: Aditivo de 1 hora extra 850,00 de locação 2350,00 de bebida
A17: 1544 | B17: PRO_250567_ID_1544_BTO+_Sala de Música_19dez_50pax | C17: 149 | D17: Priceless | E17: 1235 | F17: 20750 | G17: 46034 | H17: 46034 | I17: Pago | J17: Transferência Bancária ou Pix | K17: 133 | L17: Priceless - Bem Mais - Itaú
A18: 2294 | B18: PRO_250550_ID_2294_Festa Floresta_Bar_Sala_AROO Completo_25abril26_300pax | C18: 149 | D18: Priceless | E18: 1239 | F18: 64301.69 | G18: 46032 | H18: 46029 | I18: Pago | J18: Transferência Bancária ou Pix | K18: 133 | L18: Priceless - Bem Mais - Itaú
A19: 2294 | B19: PRO_250550_ID_2294_Festa Floresta_Bar_Sala_AROO Completo_25abril26_300pax | C19: 149 | D19: Priceless | E19: 1238 | F19: 19635 | G19: 46032 | H19: 46029 | I19: Pago | J19: Transferência Bancária ou Pix | K19: 133 | L19: Priceless - Bem Mais - Itaú
A20: 2133 | B20: ADITIVO_PRO_250236_ID 119 (V2)_Cebrasse_Celso_Aroo 1 e 2_Coquetel+bar_01.12.25 | C20: 149 | D20: Priceless | E20: 1126 | F20: 8608 | G20: 46027 | H20: 46027 | I20: Pago | J20: Boleto Bancário | K20: 134 | L20: Priceless - Bem Mais - Kamino | M20: Aditivo referente ao excedentes de 32 convidados Emitir um boleto bancário Valor R$ 17.216,00 Vencimento 15/12/2025 Enviar nos emails: eventos@cebrasse.org.br | financeiro@cebrasse.org.br | institucional@cebrasse.org.br
A21: 2287 | B21: PRO_250705_ID_2287_Aniversário_RayAlvaro_Sala de Música_21.12.25_35pax | C21: 149 | D21: Priceless | E21: 1186 | F21: 22000 | G21: 46015 | H21: 46017 | I21: Pago | J21: Transferência Bancária ou Pix | K21: 133 | L21: Priceless - Bem Mais - Itaú
A22: 2297 | B22: PRO_250708_ID_ADITIVO_SABESP_16DEZ_8PAX | C22: 149 | D22: Priceless | E22: 1162 | F22: 4456 | G22: 46015 | H22: 46015 | I22: Pago | J22: Boleto Bancário | K22: 134 | L22: Priceless - Bem Mais - Kamino
A23: 2315 | B23: ADITIVO_PRO_250642_ID 1985_Inteegra_Carol Méllo_Notie e Mirante_18.12.25_50pax | C23: 149 | D23: Priceless | E23: 1180 | F23: 5300 | G23: 46013 | H23: 46014 | I23: Pago | J23: Transferência Bancária ou Pix | K23: 133 | L23: Priceless - Bem Mais - Itaú
A24: 2316 | B24: PRO_250700_Agencia Loi_Aline_Restaurante Mirante_26.01.26_50pax | C24: 149 | D24: Priceless | E24: 1194 | F24: 24625 | G24: 46027 | H24: 46014 | I24: Pago | J24: Transferência Bancária ou Pix | K24: 133 | L24: Priceless - Bem Mais - Itaú
A25: 2316 | B25: PRO_250700_Agencia Loi_Aline_Restaurante Mirante_26.01.26_50pax | C25: 149 | D25: Priceless | E25: 1192 | F25: 20375 | G25: 46027 | H25: 46014 | I25: Pago | J25: Transferência Bancária ou Pix | K25: 133 | L25: Priceless - Bem Mais - Itaú
A26: 1855 | B26: PRO_250622_ID_1855_Bayer_almoço_Reserva_Terraço_28jan26_17pax | C26: 149 | D26: Priceless | E26: 1139 | F26: 4054.5 | G26: 46014 | H26: 46014 | I26: Pago | J26: Boleto Bancário | K26: 133 | L26: Priceless - Bem Mais - Itaú
A27: 2286 | B27: PRO_250707_ID_2286_ADITIVO_12DEZ_SALA DE MUSICA_4PAX | C27: 149 | D27: Priceless | E27: 1132 | F27: 1580 | G27: 46010 | H27: 46013 | I27: Pago | J27: Boleto Bancário | K27: 134 | L27: Priceless - Bem Mais - Kamino | M27: Aditivo de 4 pessoas excedentes
A28: 1949 | B28: PRO_250654_ID_1949_Somauma_Sala de música_17dez_60pax | C28: 149 | D28: Priceless | E28: 1075 | F28: 6100 | G28: 46010 | H28: 46010 | I28: Pago | J28: Boleto Bancário | K28: 134 | L28: Priceless - Bem Mais - Kamino
A29: 2132 | B29: PRO_250679_Oracle_Leandro_Sala de Música_02.12.25_30pax | C29: 149 | D29: Priceless | E29: 1164 | F29: 5792.5 | G29: 46038 | H29: 46010 | I29: Pago | J29: Cartão de Crédito | K29: 132 | L29: Priceless - Bem Mais - Santander
A30: 2132 | B30: PRO_250679_Oracle_Leandro_Sala de Música_02.12.25_30pax | C30: 149 | D30: Priceless | E30: 1116 | F30: 5792.5 | G30: 46039 | H30: 46010 | I30: Pago | J30: Transferência Bancária ou Pix | K30: 134 | L30: Priceless - Bem Mais - Kamino
A31: 2132 | B31: PRO_250679_Oracle_Leandro_Sala de Música_02.12.25_30pax | C31: 149 | D31: Priceless | E31: 1163 | F31: 5792.5 | G31: 46038 | H31: 46009 | I31: Pago | J31: Cartão de Crédito | K31: 132 | L31: Priceless - Bem Mais - Santander
A32: 2133 | B32: ADITIVO_PRO_250236_ID 119 (V2)_Cebrasse_Celso_Aroo 1 e 2_Coquetel+bar_01.12.25 | C32: 149 | D32: Priceless | E32: 1034 | F32: 8608 | G32: 46008 | H32: 46009 | I32: Pago | J32: Boleto Bancário | K32: 134 | L32: Priceless - Bem Mais - Kamino | M32: Aditivo referente ao excedentes de 32 convidados Emitir um boleto bancário Valor R$ 17.216,00 Vencimento 15/12/2025 Enviar nos emails: eventos@cebrasse.org.br | financeiro@cebrasse.org.br | institucional@cebrasse.org.br
A33: 2099 | B33: PRO_250692_Denise Mesquita_Almoço Executivo_Notiê_18.12_20pax | C33: 149 | D33: Priceless | E33: 1017 | F33: 1540 | G33: 46009 | H33: 46009 | I33: Pago | J33: Cartão de Débito | K33: 134 | L33: Priceless - Bem Mais - Kamino
A34: 2208 | B34: PRO_250701_ID_2208_Denise_Terraço da sala_17dez_20pax | C34: 149 | D34: Priceless | E34: 1106 | F34: 8700 | G34: 46036 | H34: 46008 | I34: Pago | J34: Boleto Bancário | K34: 132 | L34: Priceless - Bem Mais - Santander
A35: 2208 | B35: PRO_250701_ID_2208_Denise_Terraço da sala_17dez_20pax | C35: 149 | D35: Priceless | E35: 1105 | F35: 6000 | G35: 46036 | H35: 46008 | I35: Pago | J35: Boleto Bancário | K35: 132 | L35: Priceless - Bem Mais - Santander
A36: 2001 | B36: PRO_250611_ID_2001_IPSEN_AROO 1_19dez_27px | C36: 149 | D36: Priceless | E36: 984 | F36: 7800 | G36: 46006 | H36: 46007 | I36: Pago | J36: Boleto Bancário | K36: 134 | L36: Priceless - Bem Mais - Kamino | M36: extras serão para telão, projetor e montagem
A37: 2001 | B37: PRO_250611_ID_2001_IPSEN_AROO 1_19dez_27px | C37: 149 | D37: Priceless | E37: 982 | F37: 3975 | G37: 46006 | H37: 46007 | I37: Pago | J37: Boleto Bancário | K37: 134 | L37: Priceless - Bem Mais - Kamino | M37: extras serão para telão, projetor e montagem
A38: 2246 | B38: PRO_250699_ID2246_Formatura_Isabelli_Alvaro_Mirante e Notiê_16.12.25_100pax | C38: 149 | D38: Priceless | E38: 1138 | F38: 5000 | G38: 46007 | H38: 46007 | I38: Pago | J38: Transferência Bancária ou Pix | K38: 133 | L38: Priceless - Bem Mais - Itaú
A39: 2246 | B39: PRO_250699_ID2246_Formatura_Isabelli_Alvaro_Mirante e Notiê_16.12.25_100pax | C39: 149 | D39: Priceless | E39: 1120 | F39: 23000 | G39: 46007 | H39: 46007 | I39: Pago | J39: Transferência Bancária ou Pix | K39: 133 | L39: Priceless - Bem Mais - Itaú
A40: 2134 | B40: ADITIVO_PRO_250683_Corclub Assessoria_Patricio_Terraço_04.12.25_30pax | C40: 149 | D40: Priceless | E40: 1035 | F40: 5025 | G40: 46003 | H40: 46007 | I40: Pago | J40: Transferência Bancária ou Pix | K40: 133 | L40: Priceless - Bem Mais - Itaú
A41: 1949 | B41: PRO_250654_ID_1949_Somauma_Sala de música_17dez_60pax | C41: 149 | D41: Priceless | E41: 1074 | F41: 14000 | G41: 46003 | H41: 46006 | I41: Pago | J41: Boleto Bancário | K41: 134 | L41: Priceless - Bem Mais - Kamino
A42: 1996 | B42: PRO_250675_iD 1996 Inst Locomotiva_Fernanda_Sala de Música_16.12.25_30pax | C42: 149 | D42: Priceless | E42: 1104 | F42: 8000 | G42: 46003 | H42: 46003 | I42: Pago | J42: Transferência Bancária ou Pix | K42: 133 | L42: Priceless - Bem Mais - Itaú
A43: 2076 | B43: PRO_250674 Hectare Capital_Flavia_Mirante_17.12.25_25pax | C43: 149 | D43: Priceless | E43: 1003 | F43: 7640 | G43: 46006 | H43: 46003 | I43: Pago | J43: Transferência Bancária ou Pix | K43: 133 | L43: Priceless - Bem Mais - Itaú
A44: 1937 | B44: PRO_250649_ID_1937_SABESP_AROO 1 e 2_16dez_200pax | C44: 149 | D44: Priceless | E44: 1050 | F44: 35130 | G44: 46003 | H44: 46003 | I44: Pago | J44: Boleto Bancário | K44: 134 | L44: Priceless - Bem Mais - Kamino
A45: 2076 | B45: PRO_250674 Hectare Capital_Flavia_Mirante_17.12.25_25pax | C45: 149 | D45: Priceless | E45: 1004 | F45: 5000 | G45: 46001 | H45: 46003 | I45: Pago | J45: Transferência Bancária ou Pix | K45: 133 | L45: Priceless - Bem Mais - Itaú
A46: 1985 | B46: PRO_250642_ID 1985_Inteegra_Carol Méllo_Notie e Mirante_18.12.25_50pax | C46: 149 | D46: Priceless | E46: 934 | F46: 9375 | G46: 46003 | H46: 46003 | I46: Pago | J46: Transferência Bancária ou Pix | K46: 133 | L46: Priceless - Bem Mais - Itaú
A47: 1937 | B47: PRO_250649_ID_1937_SABESP_AROO 1 e 2_16dez_200pax | C47: 149 | D47: Priceless | E47: 1051 | F47: 111400 | G47: 46003 | H47: 46003 | I47: Pago | J47: Boleto Bancário | K47: 134 | L47: Priceless - Bem Mais - Kamino
A48: 1985 | B48: PRO_250642_ID 1985_Inteegra_Carol Méllo_Notie e Mirante_18.12.25_50pax | C48: 149 | D48: Priceless | E48: 936 | F48: 2500 | G48: 46003 | H48: 46003 | I48: Pago | J48: Transferência Bancária ou Pix | K48: 133 | L48: Priceless - Bem Mais - Itaú
A49: 1967 | B49: PRO_250578_ID_1967_Shirley_Almoço_NOtiê_12dez_20pax | C49: 149 | D49: Priceless | E49: 926 | F49: 3900 | G49: 46002 | H49: 46002 | I49: Pago | J49: Boleto Bancário | K49: 134 | L49: Priceless - Bem Mais - Kamino | M49: Pacote exclusivo. Reserva dentro do Notiê
A50: 1673 | B50: PRO_250601_ID_1673_Coquetel_Cristiane_Sala de música e terraço_12dez_80pax | C50: 149 | D50: Priceless | E50: 802 | F50: 6600 | G50: 46001 | H50: 46002 | I50: Pago | J50: Boleto Bancário | K50: 134 | L50: Priceless - Bem Mais - Kamino
A51: 1938 | B51: PRO_250653_ID_1938_TAO_Terraço do bar_09dez_20pax | C51: 149 | D51: Priceless | E51: 986 | F51: 1850 | G51: 45996 | H51: 46002 | I51: Pago | J51: Transferência Bancária ou Pix | K51: 133 | L51: Priceless - Bem Mais - Itaú
A52: 1673 | B52: PRO_250601_ID_1673_Coquetel_Cristiane_Sala de música e terraço_12dez_80pax | C52: 149 | D52: Priceless | E52: 800 | F52: 15800 | G52: 46001 | H52: 46002 | I52: Pago | J52: Boleto Bancário | K52: 134 | L52: Priceless - Bem Mais - Kamino
A53: 2224 | B53: PRO_250704_ID_2224_ADITIVO_TAO_9DEZ_20PAX | C53: 149 | D53: Priceless | E53: 1091 | F53: 1595 | G53: 46003 | H53: 46002 | I53: Pago | J53: Transferência Bancária ou Pix | K53: 133 | L53: Priceless - Bem Mais - Itaú | M53: Valor de vinhos adicionais
A54: 2097 | B54: ADITIVO | PRO_250578_ID_1967_Shirley_Almoço_NOtiê_12dez_20pax | C54: 149 | D54: Priceless | E54: 1014 | F54: 1300 | G54: 46002 | H54: 46002 | I54: Pago | J54: Boleto Bancário | K54: 134 | L54: Priceless - Bem Mais - Kamino | M54: Acrescentamos o pacote de soft drinks
A55: 1520 | B55: PRO_250546_ID_1520_NIver Gustavo_Sala de música e terraço_07nov_70pax | C55: 149 | D55: Priceless | E55: 776 | F55: 7000 | G55: 45998 | H55: 45999 | I55: Pago | J55: Cartão de Crédito | K55: 132 | L55: Priceless - Bem Mais - Santander
A56: 2223 | B56: PRO_250703_ID_2223_ADITIVO_MARI_6DEZ_22PAX | C56: 149 | D56: Priceless | E56: 1090 | F56: 405 | G56: 46000 | H56: 45999 | I56: Pago | J56: Transferência Bancária ou Pix | K56: 133 | L56: Priceless - Bem Mais - Itaú | M56: Valor de rolha
A57: 2099 | B57: PRO_250692_Denise Mesquita_Almoço Executivo_Notiê_18.12_20pax | C57: 149 | D57: Priceless | E57: 1018 | F57: 5500 | G57: 46008 | H57: 45999 | I57: Pago | J57: Dinheiro em Espécie | K57: 143 | L57: Tesouraria
A58: 1768 | B58: PRO_250602_ID 1768_LUPPO_Davi_Capitação_10.11.25_20pax | C58: 149 | D58: Priceless | E58: 796 | F58: 15000 | G58: 45999 | H58: 45999 | I58: Pago | J58: Boleto Bancário | K58: 134 | L58: Priceless - Bem Mais - Kamino | M58: Repasse de R$ 4.000,00 para Gazitt devido a capitação no 7 andar alinhado com email entre o shopping e Fernanda gerente de eventos
A59: 1817 | B59: PRO_250616_ID_1817_Vanessa Faria_Restaurante Notiê_05dez_45pax | C59: 149 | D59: Priceless | E59: 951 | F59: 15615 | G59: 45994 | H59: 45995 | I59: Pago | J59: Boleto Bancário | K59: 134 | L59: Priceless - Bem Mais - Kamino
A60: 1817 | B60: PRO_250616_ID_1817_Vanessa Faria_Restaurante Notiê_05dez_45pax | C60: 149 | D60: Priceless | E60: 952 | F60: 8000 | G60: 45994 | H60: 45995 | I60: Pago | J60: Boleto Bancário | K60: 134 | L60: Priceless - Bem Mais - Kamino
A61: 1998 | B61: ADITIVO_PRO_250236_ID 1998_Cebrasse_Celso_Aroo 1 e 2_Coquetel+bar_01.12.25 | C61: 149 | D61: Priceless | E61: 959 | F61: 2125 | G61: 45994 | H61: 45994 | I61: Pago | J61: Boleto Bancário | K61: 134 | L61: Priceless - Bem Mais - Kamino | M61: Aditivo referente ao aumento de convidados + espaço. Emitir um boleto bancário Valor R$ 8.550,00 Vencimento 03/12/2025 CEBRASSE - CENTRAL BRASILEIRA DO SETOR DE SERVICOS CNPJ 06.306.546/0001-51 R BARONESA DE BELA VISTA, 411 - ANDAR 3 CONJ 304 E 305 - VILA CONGONHAS, SÃO PAULO, SP CEP: 04.612-001
A62: 1998 | B62: ADITIVO_PRO_250236_ID 1998_Cebrasse_Celso_Aroo 1 e 2_Coquetel+bar_01.12.25 | C62: 149 | D62: Priceless | E62: 958 | F62: 6725 | G62: 45994 | H62: 45994 | I62: Pago | J62: Boleto Bancário | K62: 134 | L62: Priceless - Bem Mais - Kamino | M62: Aditivo referente ao aumento de convidados + espaço. Emitir um boleto bancário Valor R$ 8.550,00 Vencimento 03/12/2025 CEBRASSE - CENTRAL BRASILEIRA DO SETOR DE SERVICOS CNPJ 06.306.546/0001-51 R BARONESA DE BELA VISTA, 411 - ANDAR 3 CONJ 304 E 305 - VILA CONGONHAS, SÃO PAULO, SP CEP: 04.612-001
A63: 2074 | B63: PRO_250683_ID 2074_Corclub Assessoria_Patricio_Terraço_04.12.25_30pax | C63: 149 | D63: Priceless | E63: 1000 | F63: 5000 | G63: 45993 | H63: 45993 | I63: Pago | J63: Transferência Bancária ou Pix | K63: 133 | L63: Priceless - Bem Mais - Itaú | M63: Taxa de 5% R$ 450,00 pagamento com o cartão de crédito. Foi lançada na ultima parcela
A64: 2001 | B64: PRO_250611_ID_2001_IPSEN_AROO 1_19dez_27px | C64: 149 | D64: Priceless | E64: 983 | F64: 7800 | G64: 45992 | H64: 45993 | I64: Pago | J64: Boleto Bancário | K64: 134 | L64: Priceless - Bem Mais - Kamino | M64: extras serão para telão, projetor e montagem
A65: 2001 | B65: PRO_250611_ID_2001_IPSEN_AROO 1_19dez_27px | C65: 149 | D65: Priceless | E65: 981 | F65: 3975 | G65: 45992 | H65: 45993 | I65: Pago | J65: Boleto Bancário | K65: 134 | L65: Priceless - Bem Mais - Kamino | M65: extras serão para telão, projetor e montagem
A66: 1188 | B66: PRO_250512_ID_1188_Mastercard_Coquetel_14out_68pax | C66: 149 | D66: Priceless | E66: 590 | F66: 54808 | G66: 45989 | H66: 45992 | I66: Pago | J66: Cartão de Crédito | K66: 132 | L66: Priceless - Bem Mais - Santander
A67: 1277 | B67: PRO_250520_ID_1277_Confraternização_Terraço da sala de Música_T4W_11dez_26pax | C67: 149 | D67: Priceless | E67: 852 | F67: 5135 | G67: 45994 | H67: 45992 | I67: Pago | J67: Boleto Bancário | K67: 134 | L67: Priceless - Bem Mais - Kamino | M67: Cliente antigo que prospectamos
A68: 1771 | B68: PRO_250626 ID 1771 Ed Abril_Vania_Mirante Noitê_Jantar_03.12.25_50pax | C68: 149 | D68: Priceless | E68: 953 | F68: 29200 | G68: 45992 | H68: 45992 | I68: Pago | J68: Transferência Bancária ou Pix | K68: 134 | L68: Priceless - Bem Mais - Kamino
A69: 1277 | B69: PRO_250520_ID_1277_Confraternização_Terraço da sala de Música_T4W_11dez_26pax | C69: 149 | D69: Priceless | E69: 759 | F69: 2500 | G69: 45994 | H69: 45992 | I69: Pago | J69: Boleto Bancário | K69: 134 | L69: Priceless - Bem Mais - Kamino | M69: Cliente antigo que prospectamos
A70: 1134 | B70: PRO_250502_ID_1134_Mari Khozondar_Confraternização_Mirante_06dez_22pax | C70: 149 | D70: Priceless | E70: 1019 | F70: 4950 | G70: 45992 | H70: 45992 | I70: Pago | J70: Transferência Bancária ou Pix | K70: 133 | L70: Priceless - Bem Mais - Itaú | M70: Reserva com pacote exclusivo no Terraço Notiê
A71: 1814 | B71: PRO_250549_ID_1814_Fundação Dom Cabral_Restaurante Notie e terraço_jantar_1dez_35pax | C71: 149 | D71: Priceless | E71: 950 | F71: 28595 | G71: 45989 | H71: 45989 | I71: Pago | J71: Boleto Bancário | K71: 134 | L71: Priceless - Bem Mais - Kamino
A72: 1998 | B72: ADITIVO_PRO_250236_ID 1998_Cebrasse_Celso_Aroo 1 e 2_Coquetel+bar_01.12.25 | C72: 149 | D72: Priceless | E72: 956 | F72: 6725 | G72: 45989 | H72: 45989 | I72: Pago | J72: Transferência Bancária ou Pix | K72: 133 | L72: Priceless - Bem Mais - Itaú | M72: Aditivo referente ao aumento de convidados + espaço. Emitir um boleto bancário Valor R$ 8.550,00 Vencimento 03/12/2025 CEBRASSE - CENTRAL BRASILEIRA DO SETOR DE SERVICOS CNPJ 06.306.546/0001-51 R BARONESA DE BELA VISTA, 411 - ANDAR 3 CONJ 304 E 305 - VILA CONGONHAS, SÃO PAULO, SP CEP: 04.612-001
A73: 1998 | B73: ADITIVO_PRO_250236_ID 1998_Cebrasse_Celso_Aroo 1 e 2_Coquetel+bar_01.12.25 | C73: 149 | D73: Priceless | E73: 957 | F73: 2125 | G73: 45989 | H73: 45989 | I73: Pago | J73: Transferência Bancária ou Pix | K73: 133 | L73: Priceless - Bem Mais - Itaú | M73: Aditivo referente ao aumento de convidados + espaço. Emitir um boleto bancário Valor R$ 8.550,00 Vencimento 03/12/2025 CEBRASSE - CENTRAL BRASILEIRA DO SETOR DE SERVICOS CNPJ 06.306.546/0001-51 R BARONESA DE BELA VISTA, 411 - ANDAR 3 CONJ 304 E 305 - VILA CONGONHAS, SÃO PAULO, SP CEP: 04.612-001
A74: 1938 | B74: PRO_250653_ID_1938_TAO_Terraço do bar_09dez_20pax | C74: 149 | D74: Priceless | E74: 985 | F74: 1850 | G74: 45989 | H74: 45989 | I74: Pago | J74: Transferência Bancária ou Pix | K74: 133 | L74: Priceless - Bem Mais - Itaú
A75: 1814 | B75: PRO_250549_ID_1814_Fundação Dom Cabral_Restaurante Notie e terraço_jantar_1dez_35pax | C75: 149 | D75: Priceless | E75: 949 | F75: 9000 | G75: 45989 | H75: 45989 | I75: Pago | J75: Boleto Bancário | K75: 134 | L75: Priceless - Bem Mais - Kamino
A76: 1615 | B76: PRO 250587_ ID_1615_ Proposta Notiê 1Momento Casa Vogue + UBS 30_10_25_ Externo 50pax | C76: 149 | D76: Priceless | E76: 989 | F76: 8300 | G76: 45989 | H76: 45989 | I76: Pago | J76: Transferência Bancária ou Pix | K76: 134 | L76: Priceless - Bem Mais - Kamino
A77: 1985 | B77: PRO_250642_ID 1985_Inteegra_Carol Méllo_Notie e Mirante_18.12.25_50pax | C77: 149 | D77: Priceless | E77: 933 | F77: 9375 | G77: 45988 | H77: 45988 | I77: Pago | J77: Transferência Bancária ou Pix | K77: 134 | L77: Priceless - Bem Mais - Kamino
A78: 1188 | B78: PRO_250512_ID_1188_Mastercard_Coquetel_14out_68pax | C78: 149 | D78: Priceless | E78: 591 | F78: 12800 | G78: 45989 | H78: 45988 | I78: Pago | J78: Cartão de Crédito | K78: 132 | L78: Priceless - Bem Mais - Santander
A79: 1985 | B79: PRO_250642_ID 1985_Inteegra_Carol Méllo_Notie e Mirante_18.12.25_50pax | C79: 149 | D79: Priceless | E79: 935 | F79: 2500 | G79: 45988 | H79: 45988 | I79: Pago | J79: Transferência Bancária ou Pix | K79: 134 | L79: Priceless - Bem Mais - Kamino
A80: 1895 | B80: ADITIVO_PRO_250518 ID 1282 TARKEN_Jantar_Notiê_Mirante_11.11.25_60pax | C80: 149 | D80: Priceless | E80: 879 | F80: 20000 | G80: 45988 | H80: 45988 | I80: Pago | J80: Transferência Bancária ou Pix | K80: 133 | L80: Priceless - Bem Mais - Itaú | M80: Aditivo finalizado no final do evento e assinado. Favor emitir nota e boletos conforme dados abaixo: TARKEN SOFTWARE LTDA CNPJ/MF sob o n.º 25.033.061/0001-86, RUA: SANTA RITA DURAO, nº 20, ANDAR 5, FUNCIONARIOS, Belo Horizonte – MG, CEP 30.140-110, Pessoa responsável: Luciana Silva | Email: Luciana.silva@tarken.ag
A81: 119 | B81: PRO_250236_ID 119 (V2)_Cebrasse_Celso_Aroo 1 e 2_Coquetel+bar_01.12.25 | C81: 149 | D81: Priceless | E81: 264 | F81: 9415 | G81: 45982 | H81: 45982 | I81: Pago | J81: Boleto Bancário | K81: 134 | L81: Priceless - Bem Mais - Kamino | M81: CEBRASSE - CENTRAL BRASILEIRA DO SETOR DE SERVICOS CNPJ 06.306.546/0001-51 R BARONESA DE BELA VISTA, 411 - ANDAR 3 CONJ 304 E 305 - VILA CONGONHAS, SÃO PAULO, SP CEP: 04.612-001
A82: 1858 | B82: EVENTO MASTERCARD PATROCÍNIO 28/10 - Jantar Magno - PRAZERES DA MESA (PRO_ 250639)_ ID _ 1858 | C82: 149 | D82: Priceless | E82: 866 | F82: 5942.5 | G82: 45978 | H82: 45979 | I82: Pago | J82: Transferência Bancária ou Pix | K82: 134 | L82: Priceless - Bem Mais - Kamino | M82: Evento interno R$ 27500,00 paragamento através da Bem São Paulo ( MAstercard)- está contabilizado no EPM no ID do Chef Convida de 2024. R$ 5.950,00 ( pagamento através do Sympla- venda de ingressos_ pacote para o evento)
A83: 139 | B83: Evento Chefe Convida - 2024 | C83: 149 | D83: Priceless | E83: 1211 | F83: 50 | G83: 45966 | H83: 45978 | I83: Pago | J83: Encontro de Contas | K83: 132 | L83: Priceless - Bem Mais - Santander | M83: Evento Chefe Convida Eventos de Marketing Obs. Financeira: DIFERENÇA DE 50,00 COBRADO NO EVENTO 1.858
A84: 1277 | B84: PRO_250520_ID_1277_Confraternização_Terraço da sala de Música_T4W_11dez_26pax | C84: 149 | D84: Priceless | E84: 853 | F84: 2500 | G84: 45975 | H84: 45978 | I84: Pago | J84: Boleto Bancário | K84: 134 | L84: Priceless - Bem Mais - Kamino | M84: Cliente antigo que prospectamos
A85: 139 | B85: Evento Chefe Convida - 2024 | C85: 149 | D85: Priceless | E85: 135 | F85: 27450 | G85: 45966 | H85: 45978 | I85: Pago | J85: Transferência Bancária ou Pix | K85: 134 | L85: Priceless - Bem Mais - Kamino | M85: Evento Chefe Convida Eventos de Marketing Obs. Financeira: DIFERENÇA DE 50,00 COBRADO NO EVENTO 1.858
A86: 1277 | B86: PRO_250520_ID_1277_Confraternização_Terraço da sala de Música_T4W_11dez_26pax | C86: 149 | D86: Priceless | E86: 851 | F86: 5135 | G86: 45975 | H86: 45978 | I86: Pago | J86: Boleto Bancário | K86: 134 | L86: Priceless - Bem Mais - Kamino | M86: Cliente antigo que prospectamos
A87: 1520 | B87: PRO_250546_ID_1520_NIver Gustavo_Sala de música e terraço_07nov_70pax | C87: 149 | D87: Priceless | E87: 777 | F87: 7000 | G87: 46005 | H87: 45978 | I87: Pago | J87: Cartão de Crédito | K87: 132 | L87: Priceless - Bem Mais - Santander
A88: 1529 | B88: PRO_250571_ID 1529_ Proposta Notiê 1 Momento_Casa Vogue + UBS 30_10_25_ Externo 50pax | C88: 149 | D88: Priceless | E88: 719 | F88: 104737.5 | G88: 45980 | H88: 45975 | I88: Pago | J88: Boleto Bancário | K88: 134 | L88: Priceless - Bem Mais - Kamino | M88: Por gentileza emitir um boleto bancário para vencimento em 13.11.2025 EDIÇÕES GLOBO CONDÉ NAST S.A. inscrita no CNPJ/MF sob o n.º 10.739.386/0001-01, com sede na Rua Gerivatiba, 207 Conj. 112 Ed. River One – Butantã – São Paulo/SP, CEP 05.501-900
A89: 1673 | B89: PRO_250601_ID_1673_Coquetel_Cristiane_Sala de música e terraço_12dez_80pax | C89: 149 | D89: Priceless | E89: 801 | F89: 6600 | G89: 45971 | H89: 45972 | I89: Pago | J89: Boleto Bancário | K89: 134 | L89: Priceless - Bem Mais - Kamino
A90: 1673 | B90: PRO_250601_ID_1673_Coquetel_Cristiane_Sala de música e terraço_12dez_80pax | C90: 149 | D90: Priceless | E90: 799 | F90: 15800 | G90: 45971 | H90: 45972 | I90: Pago | J90: Boleto Bancário | K90: 134 | L90: Priceless - Bem Mais - Kamino
A91: 1434 | B91: PRO_250551 ID 1434_Ed Abril_4 Rodas_Jantar_Notiê e Mirante_06.11.25_35pax | C91: 149 | D91: Priceless | E91: 764 | F91: 17800 | G91: 45966 | H91: 45966 | I91: Pago | J91: Transferência Bancária ou Pix | K91: 134 | L91: Priceless - Bem Mais - Kamino
A92: 1482 | B92: PRO_250562 ID 1482 OCTAGON_Alcides_Jantar_Valido 3 meses 31.01.26_2 pax | C92: 149 | D92: Priceless | E92: 677 | F92: 1240 | G92: 45966 | H92: 45966 | I92: Pago | J92: Boleto Bancário | K92: 134 | L92: Priceless - Bem Mais - Kamino | M92: Emitir um boleto bancário com vencimento em 05/11/2025 ODDZ Network Ltda. CNPJ: 09.262.440/0001-91 Rua Gomes de Carvalho, 151, Cj 62 Vila Olimpia - CEP 04547-005 Responsável Alcides Santos
A93: 1629 | B93: PRO_250590_ID_1629_Lançamento de livro_Sala de Música_11nov_50pax | C93: 149 | D93: Priceless | E93: 739 | F93: 1000 | G93: 45966 | H93: 45965 | I93: Pago | J93: Transferência Bancária ou Pix | K93: 134 | L93: Priceless - Bem Mais - Kamino | M93: Evento institucional e cultural Cobrado somente R$ 1000,00 por 10 garrafas de espumantes que serão servidos em welcome drinks.
A94: 1521 | B94: PRO_250556_ID_1521_Vivian Gomes_Sala de Música e Terraço_Coquetel_23pax | C94: 149 | D94: Priceless | E94: 691 | F94: 1500 | G94: 45958 | H94: 45965 | I94: Pago | J94: Boleto Bancário | K94: 134 | L94: Priceless - Bem Mais - Kamino
A95: 1521 | B95: PRO_250556_ID_1521_Vivian Gomes_Sala de Música e Terraço_Coquetel_23pax | C95: 149 | D95: Priceless | E95: 690 | F95: 4197.5 | G95: 45964 | H95: 45965 | I95: Pago | J95: Boleto Bancário | K95: 134 | L95: Priceless - Bem Mais - Kamino
A96: 1521 | B96: PRO_250556_ID_1521_Vivian Gomes_Sala de Música e Terraço_Coquetel_23pax | C96: 149 | D96: Priceless | E96: 689 | F96: 4197.5 | G96: 45958 | H96: 45965 | I96: Pago | J96: Boleto Bancário | K96: 134 | L96: Priceless - Bem Mais - Kamino
A97: 1521 | B97: PRO_250556_ID_1521_Vivian Gomes_Sala de Música e Terraço_Coquetel_23pax | C97: 149 | D97: Priceless | E97: 692 | F97: 1500 | G97: 45964 | H97: 45965 | I97: Pago | J97: Boleto Bancário | K97: 134 | L97: Priceless - Bem Mais - Kamino
A98: 527 | B98: PRO_250459 ID 527 Tarket_Luciana_Conquetel_Espaço de Eventos_12.11.25_300pax | C98: 149 | D98: Priceless | E98: 479 | F98: 80650 | G98: 45960 | H98: 45961 | I98: Pago | J98: Boleto Bancário | K98: 134 | L98: Priceless - Bem Mais - Kamino | M98: Contrato fechado conforme parcelas acordadas 50% AeB e Locação com vencimento no dia 22/09 e quitação no dia 30/09 em boleto bacário. Favor emitir nota e boletos conforme dados abaixo: TARKEN SOFTWARE LTDA CNPJ/MF sob o n.º 25.033.061/0001-86, RUA: SANTA RITA DURAO, nº 20, ANDAR 5, FUNCIONARIOS, Belo Horizonte – MG, CEP 30.140-110, Pessoa responsável: Luciana Silva | Email: Luciana.silva@tarken.ag
A99: 527 | B99: PRO_250459 ID 527 Tarket_Luciana_Conquetel_Espaço de Eventos_12.11.25_300pax | C99: 149 | D99: Priceless | E99: 481 | F99: 7500 | G99: 45960 | H99: 45961 | I99: Pago | J99: Boleto Bancário | K99: 134 | L99: Priceless - Bem Mais - Kamino | M99: Contrato fechado conforme parcelas acordadas 50% AeB e Locação com vencimento no dia 22/09 e quitação no dia 30/09 em boleto bacário. Favor emitir nota e boletos conforme dados abaixo: TARKEN SOFTWARE LTDA CNPJ/MF sob o n.º 25.033.061/0001-86, RUA: SANTA RITA DURAO, nº 20, ANDAR 5, FUNCIONARIOS, Belo Horizonte – MG, CEP 30.140-110, Pessoa responsável: Luciana Silva | Email: Luciana.silva@tarken.ag
A100: 119 | B100: PRO_250236_ID 119 (V2)_Cebrasse_Celso_Aroo 1 e 2_Coquetel+bar_01.12.25 | C100: 149 | D100: Priceless | E100: 263 | F100: 9415 | G100: 45951 | H100: 45951 | I100: Pago | J100: Boleto Bancário | K100: 134 | L100: Priceless - Bem Mais - Kamino | M100: CEBRASSE - CENTRAL BRASILEIRA DO SETOR DE SERVICOS CNPJ 06.306.546/0001-51 R BARONESA DE BELA VISTA, 411 - ANDAR 3 CONJ 304 E 305 - VILA CONGONHAS, SÃO PAULO, SP CEP: 04.612-001
...

Sheet df_blueme_sem_parcelamento
A1: ID_Despesa | B1: ID_Casa | C1: Casa | D1: Fornecedor | E1: Valor | F1: Data_Vencimento | G1: Previsao_Pgto | H1: Realizacao_Pgto | I1: Data_Competencia | J1: Data_Lancamento | K1: Forma_Pagamento | L1: Class_Cont_1 | M1: Class_Cont_2 | N1: Doc_NF | O1: Status_Conf_Document | P1: Status_Aprov_Diret | Q1: Status_Aprov_Caixa | R1: Status_Pgto | S1: ID_Conta_Bancaria | T1: Conta_Bancaria | U1: CNPJ_Loja
A2: 158243 | B2: 149 | C2: Priceless | D2: ZIGPAY LTDAS -ME | E2: 0 | F2: 45900 | H2: 45900 | I2: 45900 | K2: Encontro de Contas | L2: Deduções sobre Venda | M2: Meios de pagamento | N2: 082025 | R2: Pago
A3: 150791 | B3: 149 | C3: Priceless | D3: ZIGPAY LTDAS -ME | E3: 0 | F3: 45869 | H3: 45869 | I3: 45869 | K3: Encontro de Contas | L3: Deduções sobre Venda | M3: Meios de pagamento | N3: 072025 | P3: Aprovado Diretoria | R3: Pago
A4: 142926 | B4: 149 | C4: Priceless | D4: ZIGPAY LTDAS -ME | E4: 0 | F4: 45838 | H4: 45838 | I4: 45838 | K4: Encontro de Contas | L4: Deduções sobre Venda | M4: Meios de pagamento | N4: 062025 | P4: Aprovado Diretoria | R4: Pago
A5: 135689 | B5: 149 | C5: Priceless | D5: ZIGPAY LTDAS -ME | E5: 0 | F5: 45808 | H5: 45808 | I5: 45808 | K5: Encontro de Contas | L5: Deduções sobre Venda | M5: Meios de pagamento | N5: 052025 | P5: Aprovado Diretoria | R5: Pago
A6: 124597 | B6: 149 | C6: Priceless | D6: ZIGPAY LTDAS -ME | E6: 1860.38 | F6: 45747 | G6: 45762 | H6: 45747 | I6: 45747 | K6: Encontro de Contas | L6: Deduções sobre Venda | M6: Meios de pagamento | N6: 032025 | P6: Aprovado Diretoria | R6: Pago
A7: 204075 | B7: 149 | C7: Priceless | D7: ZIGPAY LTDAS -ME | E7: 16564.11 | F7: 46052 | H7: 46052 | I7: 46052 | K7: Debito Automático | L7: Deduções sobre Venda | M7: Meios de pagamento | O7: Documentação Aprovada | P7: Aprovado Diretoria | Q7: Aprovado Caixa | R7: Pago | S7: 216 | T7: Priceless - Zigpay
A8: 203234 | B8: 149 | C8: Priceless | D8: FILIPE OLBERG ZALEWSKA MEI | E8: 1801.87 | F8: 46052 | H8: 46052 | I8: 46052 | K8: Debito Automático | L8: Deduções sobre Venda | M8: Meios de pagamento | O8: Documentação Aprovada | P8: Aprovado Diretoria | Q8: Aprovado Caixa | R8: Pago | S8: 134 | T8: Priceless - Bem Mais - Kamino
A9: 185933 | B9: 149 | C9: Priceless | D9: ANDREIA SANTOS FREITAS DUARTE | E9: 299.7 | F9: 46044 | G9: 46044 | H9: 46044 | I9: 46011 | J9: 46017 | K9: Boleto Bancário | L9: Utilidades | M9: Higiene e Limpeza | N9: 2366 | O9: Documentação Aprovada | P9: Aprovado Diretoria | Q9: Aprovado Caixa | R9: Pago | S9: 134 | T9: Priceless - Bem Mais - Kamino
A10: 185664 | B10: 149 | C10: Priceless | D10: V THOME LTDA - CASA DAS FESTAS | E10: 2416.96 | F10: 46044 | G10: 46044 | H10: 46044 | I10: 46008 | J10: 46015 | K10: Boleto Bancário | L10: Custos de Eventos | M10: Locação de Utensílios - Eventos | N10: 245706 | O10: Documentação Aprovada | P10: Aprovado Diretoria | Q10: Aprovado Caixa | R10: Pago | S10: 134 | T10: Priceless - Bem Mais - Kamino
A11: 185669 | B11: 149 | C11: Priceless | D11: V THOME LTDA - CASA DAS FESTAS | E11: 1466.54 | F11: 46044 | G11: 46044 | H11: 46044 | I11: 46008 | J11: 46015 | K11: Boleto Bancário | L11: Custos de Eventos | M11: Locação de Utensílios - Eventos | N11: 245696 | O11: Documentação Aprovada | P11: Aprovado Diretoria | Q11: Aprovado Caixa | R11: Pago | S11: 134 | T11: Priceless - Bem Mais - Kamino
A12: 185936 | B12: 149 | C12: Priceless | D12: AMBEV S. A. - CDD SAO PAULO | E12: 2041.09 | F12: 46044 | G12: 46044 | H12: 46044 | I12: 46013 | J12: 46017 | K12: Boleto Bancário | L12: Custo Mercadoria Vendida | M12: Insumos - Bebidas | N12: 912283 | O12: Documentação Aprovada | P12: Aprovado Diretoria | Q12: Aprovado Caixa | R12: Pago | S12: 134 | T12: Priceless - Bem Mais - Kamino
A13: 185645 | B13: 149 | C13: Priceless | D13: COMERCIAL IMPORTADORA E EXPORTADORA METAPUNTO LTDA | E13: 1677 | F13: 46031 | G13: 46044 | H13: 46044 | I13: 46010 | J13: 46015 | K13: Boleto Bancário | L13: Custo Mercadoria Vendida | M13: Insumos - Alimentos | N13: 41523 | O13: Documentação Aprovada | P13: Aprovado Diretoria | Q13: Aprovado Caixa | R13: Pago | S13: 134 | T13: Priceless - Bem Mais - Kamino
A14: 198395 | B14: 149 | C14: Priceless | D14: KAMINO INSTITUICAO DE PAGAMENTO LTDA | E14: 3 | F14: 46044 | H14: 46044 | I14: 46044 | K14: Debito Automático | L14: Despesas Financeiras | M14: Tarifas Bancárias | O14: Documentação Aprovada | P14: Aprovado Diretoria | Q14: Aprovado Caixa | R14: Pago | S14: 134 | T14: Priceless - Bem Mais - Kamino
A15: 191942 | B15: 149 | C15: Priceless | D15: ESTAFF SOLUCOES TECNOLOGICAS DE AGENCIAMENTO LTDA | E15: 18733 | F15: 46044 | G15: 46044 | H15: 46044 | I15: 46027 | J15: 46036 | K15: Boleto Bancário | L15: Mão de Obra - Extra | M15: Mão de Obra Extra | N15: 28460 | O15: Documentação Aprovada | P15: Aprovado Diretoria | Q15: Aprovado Caixa | R15: Pago | S15: 134 | T15: Priceless - Bem Mais - Kamino
A16: 190484 | B16: 149 | C16: Priceless | D16: MULTIFRANGOS COMERCIO DE ALIMENTOS LTDA | E16: 758.13 | F16: 46044 | G16: 46044 | H16: 46044 | I16: 46031 | J16: 46031 | K16: Boleto Bancário | L16: Custo Mercadoria Vendida | M16: Insumos - Alimentos | N16: 938260 | O16: Documentação Aprovada | P16: Aprovado Diretoria | Q16: Aprovado Caixa | R16: Pago | S16: 134 | T16: Priceless - Bem Mais - Kamino
A17: 190494 | B17: 149 | C17: Priceless | D17: V THOME LTDA - CASA DAS FESTAS | E17: 1322.13 | F17: 46044 | G17: 46044 | H17: 46044 | I17: 46022 | J17: 46031 | K17: Boleto Bancário | L17: Custos de Eventos | M17: Locação de Utensílios - Eventos | N17: 245707 | O17: Documentação Aprovada | P17: Aprovado Diretoria | Q17: Aprovado Caixa | R17: Pago | S17: 134 | T17: Priceless - Bem Mais - Kamino
A18: 189171 | B18: 149 | C18: Priceless | D18: BATARD PADARIA ARTESANAL LTDA | E18: 256.5 | F18: 46044 | G18: 46044 | H18: 46044 | I18: 46028 | J18: 46028 | K18: Boleto Bancário | L18: Custo Mercadoria Vendida | M18: Insumos - Alimentos | N18: 12941 | O18: Documentação Aprovada | P18: Aprovado Diretoria | Q18: Aprovado Caixa | R18: Pago | S18: 134 | T18: Priceless - Bem Mais - Kamino
A19: 191193 | B19: 149 | C19: Priceless | D19: OSTRAMAR PESCADOS EIRELI-ME | E19: 457.59 | F19: 46038 | G19: 46044 | H19: 46044 | I19: 46034 | J19: 46034 | K19: Boleto Bancário | L19: Custo Mercadoria Vendida | M19: Insumos - Alimentos | N19: 17535 | O19: Documentação Aprovada | P19: Aprovado Diretoria | Q19: Aprovado Caixa | R19: Pago | S19: 134 | T19: Priceless - Bem Mais - Kamino
A20: 191188 | B20: 149 | C20: Priceless | D20: HORTIFRUTI DO CHEF LTDA | E20: 2107.55 | F20: 46044 | G20: 46044 | H20: 46044 | I20: 46034 | J20: 46034 | K20: Boleto Bancário | L20: Custo Mercadoria Vendida | M20: Insumos - Alimentos | N20: 28268 | O20: Documentação Aprovada | P20: Aprovado Diretoria | Q20: Aprovado Caixa | R20: Pago | S20: 134 | T20: Priceless - Bem Mais - Kamino
A21: 191186 | B21: 149 | C21: Priceless | D21: CECILIA TSUYACO ARAKI SILVA LTDA | E21: 753.15 | F21: 46044 | G21: 46044 | H21: 46044 | I21: 46034 | J21: 46034 | K21: Boleto Bancário | L21: Custo Mercadoria Vendida | M21: Insumos - Alimentos | N21: 384724 | O21: Documentação Aprovada | P21: Aprovado Diretoria | Q21: Aprovado Caixa | R21: Pago | S21: 134 | T21: Priceless - Bem Mais - Kamino
A22: 193470 | B22: 149 | C22: Priceless | D22: ESTAFF SOLUCOES TECNOLOGICAS DE AGENCIAMENTO LTDA | E22: 682 | F22: 46044 | G22: 46044 | H22: 46044 | I22: 46027 | J22: 46037 | K22: Boleto Bancário | L22: Custos de Eventos | M22: Serviços Terceirizados - Eventos | N22: 676 | O22: Documentação Aprovada | P22: Aprovado Diretoria | Q22: Aprovado Caixa | R22: Pago | S22: 134 | T22: Priceless - Bem Mais - Kamino
A23: 190436 | B23: 149 | C23: Priceless | D23: V THOME LTDA - CASA DAS FESTAS | E23: 1437.12 | F23: 46043 | G23: 46043 | H23: 46043 | I23: 46022 | J23: 46031 | K23: Boleto Bancário | L23: Custos de Eventos | M23: Locação de Utensílios - Eventos | N23: 245682 | O23: Documentação Aprovada | P23: Aprovado Diretoria | Q23: Aprovado Caixa | R23: Pago | S23: 134 | T23: Priceless - Bem Mais - Kamino
A24: 190485 | B24: 149 | C24: Priceless | D24: NOVA COMERCIAL PESCADOS LTDA | E24: 2485 | F24: 46043 | G24: 46043 | H24: 46043 | I24: 46031 | J24: 46031 | K24: Boleto Bancário | L24: Custo Mercadoria Vendida | M24: Insumos - Alimentos | N24: 30463 | O24: Documentação Aprovada | P24: Aprovado Diretoria | Q24: Aprovado Caixa | R24: Pago | S24: 134 | T24: Priceless - Bem Mais - Kamino
A25: 190488 | B25: 149 | C25: Priceless | D25: V THOME LTDA - CASA DAS FESTAS | E25: 1864.26 | F25: 46043 | G25: 46043 | H25: 46043 | I25: 46022 | J25: 46031 | K25: Boleto Bancário | L25: Custos de Eventos | M25: Locação de Utensílios - Eventos | N25: 245771 | O25: Documentação Aprovada | P25: Aprovado Diretoria | Q25: Aprovado Caixa | R25: Pago | S25: 134 | T25: Priceless - Bem Mais - Kamino
A26: 189192 | B26: 149 | C26: Priceless | D26: MATURY CAJUCULTURA LTDA | E26: 827.2 | F26: 46043 | G26: 46043 | H26: 46043 | I26: 46027 | J26: 46028 | K26: Boleto Bancário | L26: Custo Mercadoria Vendida | M26: Insumos - Bebidas | N26: 968 | O26: Documentação Aprovada | P26: Aprovado Diretoria | Q26: Aprovado Caixa | R26: Pago | S26: 134 | T26: Priceless - Bem Mais - Kamino
A27: 189193 | B27: 149 | C27: Priceless | D27: NA MORADA INDÚSTRIA E COMÉRCIO LTDA | E27: 547.37 | F27: 46042 | G27: 46045 | H27: 46043 | I27: 46028 | J27: 46028 | K27: Boleto Bancário | L27: Custo Mercadoria Vendida | M27: Insumos - Alimentos | N27: 288147 | O27: Documentação Aprovada | P27: Aprovado Diretoria | Q27: Aprovado Caixa | R27: Pago | S27: 134 | T27: Priceless - Bem Mais - Kamino
A28: 198341 | B28: 149 | C28: Priceless | D28: KAMINO INSTITUICAO DE PAGAMENTO LTDA | E28: 2 | F28: 46043 | H28: 46043 | I28: 46043 | K28: Debito Automático | L28: Despesas Financeiras | M28: Tarifas Bancárias | O28: Documentação Aprovada | P28: Aprovado Diretoria | Q28: Aprovado Caixa | R28: Pago | S28: 134 | T28: Priceless - Bem Mais - Kamino
A29: 185661 | B29: 149 | C29: Priceless | D29: V THOME LTDA - CASA DAS FESTAS | E29: 18692.27 | F29: 46043 | G29: 46043 | H29: 46043 | I29: 46007 | J29: 46015 | K29: Boleto Bancário | L29: Custos de Eventos | M29: Locação de Utensílios - Eventos | N29: 245676 | O29: Documentação Aprovada | P29: Aprovado Diretoria | Q29: Aprovado Caixa | R29: Pago | S29: 134 | T29: Priceless - Bem Mais - Kamino
A30: 185947 | B30: 149 | C30: Priceless | D30: WPP COMERCIO DE CARNES LTDA | E30: 1689.58 | F30: 46043 | G30: 46043 | H30: 46043 | I30: 46015 | J30: 46017 | K30: Boleto Bancário | L30: Custo Mercadoria Vendida | M30: Insumos - Alimentos | N30: 76438 | O30: Documentação Aprovada | P30: Aprovado Diretoria | Q30: Aprovado Caixa | R30: Pago | S30: 134 | T30: Priceless - Bem Mais - Kamino
A31: 185937 | B31: 149 | C31: Priceless | D31: AMANTES DO VINHO COMERCIO DE BEBIDAS LTDA | E31: 3383.9 | F31: 46043 | G31: 46043 | H31: 46043 | I31: 46013 | J31: 46017 | K31: Boleto Bancário | L31: Custo Mercadoria Vendida | M31: Insumos - Bebidas | N31: 28137 | O31: Documentação Aprovada | P31: Aprovado Diretoria | Q31: Aprovado Caixa | R31: Pago | S31: 134 | T31: Priceless - Bem Mais - Kamino
A32: 185938 | B32: 149 | C32: Priceless | D32: AMANTES DO VINHO COMERCIO DE BEBIDAS LTDA | E32: 779.96 | F32: 46043 | G32: 46043 | H32: 46043 | I32: 46013 | J32: 46017 | K32: Boleto Bancário | L32: Custo Mercadoria Vendida | M32: Insumos - Bebidas | N32: 1087 | O32: Documentação Aprovada | P32: Aprovado Diretoria | Q32: Aprovado Caixa | R32: Pago | S32: 134 | T32: Priceless - Bem Mais - Kamino
A33: 186759 | B33: 149 | C33: Priceless | D33: LEVEDURA SILVESTRE COMERCIO DE VINHOS LTDA | E33: 3408 | F33: 46043 | G33: 46043 | H33: 46043 | I33: 46013 | J33: 46020 | K33: Boleto Bancário | L33: Custo Mercadoria Vendida | M33: Insumos - Bebidas | N33: 1369 | O33: Documentação Aprovada | P33: Aprovado Diretoria | Q33: Aprovado Caixa | R33: Pago | S33: 134 | T33: Priceless - Bem Mais - Kamino
A34: 185226 | B34: 149 | C34: Priceless | D34: TELEFONICA BRASIL S/A | E34: 155.38 | F34: 46043 | G34: 46043 | H34: 46043 | I34: 46023 | J34: 46010 | K34: Boleto Bancário | L34: Informática e TI | M34: Internet | N34: 2014382089 | O34: Documentação Aprovada | P34: Aprovado Diretoria | Q34: Aprovado Caixa | R34: Pago | S34: 134 | T34: Priceless - Bem Mais - Kamino
A35: 185194 | B35: 149 | C35: Priceless | D35: SUFLEX TECNOLOGIA LTDA | E35: 1234.93 | F35: 46042 | G35: 46042 | H35: 46042 | I35: 46023 | J35: 46010 | K35: Boleto Bancário | L35: Informática e TI | M35: Sistemas Gerais - Operacionais | N35: 54288 | O35: Documentação Aprovada | P35: Aprovado Diretoria | Q35: Aprovado Caixa | R35: Pago | S35: 134 | T35: Priceless - Bem Mais - Kamino
A36: 185157 | B36: 149 | C36: Priceless | D36: DDTIZZ DEDETIZADORA E SERVICOS GERAIS LTDA | E36: 1263.73 | F36: 46042 | G36: 46042 | H36: 46042 | I36: 46023 | J36: 46010 | K36: Boleto Bancário | L36: Utilidades | M36: Controle de Pragas | N36: 55339 | O36: Documentação Aprovada | P36: Aprovado Diretoria | Q36: Aprovado Caixa | R36: Pago | S36: 134 | T36: Priceless - Bem Mais - Kamino
A37: 185231 | B37: 149 | C37: Priceless | D37: OPUS CONSULTORIA E PESQUISA LTDA | E37: 300 | F37: 46042 | G37: 46042 | H37: 46042 | I37: 46023 | J37: 46010 | K37: Boleto Bancário | L37: Serviços de Terceiros | M37: Assessoria em Geral | N37: 27 | O37: Documentação Aprovada | P37: Aprovado Diretoria | Q37: Aprovado Caixa | R37: Pago | S37: 134 | T37: Priceless - Bem Mais - Kamino
A38: 185151 | B38: 149 | C38: Priceless | D38: ABRASEL SAO PAULO | E38: 185 | F38: 46042 | G38: 46042 | H38: 46042 | I38: 46023 | J38: 46010 | K38: Boleto Bancário | L38: Serviços de Terceiros | M38: Assessoria Financeira | N38: 174026 | O38: Documentação Aprovada | P38: Aprovado Diretoria | Q38: Aprovado Caixa | R38: Pago | S38: 134 | T38: Priceless - Bem Mais - Kamino
A39: 185168 | B39: 149 | C39: Priceless | D39: KAMINO INSTITUICAO DE PAGAMENTO LTDA | E39: 700 | F39: 46040 | G39: 46041 | H39: 46042 | I39: 46023 | J39: 46010 | K39: Boleto Bancário | L39: Despesas Financeiras | M39: Tarifas Bancárias | N39: PROV | O39: Documentação Aprovada | P39: Aprovado Diretoria | Q39: Aprovado Caixa | R39: Pago | S39: 134 | T39: Priceless - Bem Mais - Kamino
A40: 185662 | B40: 149 | C40: Priceless | D40: V THOME LTDA - CASA DAS FESTAS | E40: 9213.44 | F40: 46042 | G40: 46042 | H40: 46042 | I40: 46007 | J40: 46015 | K40: Boleto Bancário | L40: Custos de Eventos | M40: Locação de Utensílios - Eventos | N40: 245693 | O40: Documentação Aprovada | P40: Aprovado Diretoria | Q40: Aprovado Caixa | R40: Pago | S40: 134 | T40: Priceless - Bem Mais - Kamino
... A43: 185941 | B43: 149 | C43: Priceless | D43: ICE4PROS FABRICA DE GELO LTDA | E43: 973.2 | F43: 46042 | G43: 46042 | H43: 46042 | I43: 46014 | J43: 46017 | K43: Boleto Bancário | L43: Custo Mercadoria Vendida | M43: Insumos - Bebidas | N43: 90731 | O43: Documentação Aprovada | P43: Aprovado Diretoria | Q43: Aprovado Caixa | R43: Pago | S43: 134 | T43: Priceless - Bem Mais - Kamino
A44: 198326 | B44: 149 | C44: Priceless | D44: KAMINO INSTITUICAO DE PAGAMENTO LTDA | E44: 2.5 | F44: 46042 | H44: 46042 | I44: 46042 | K44: Debito Automático | L44: Despesas Financeiras | M44: Tarifas Bancárias | O44: Documentação Aprovada | P44: Aprovado Diretoria | Q44: Aprovado Caixa | R44: Pago | S44: 134 | T44: Priceless - Bem Mais - Kamino
A45: 173870 | B45: 149 | C45: Priceless | D45: NITRON | E45: 756.15 | F45: 46042 | G45: 46042 | H45: 46042 | I45: 46023 | J45: 45971 | K45: Boleto Bancário | L45: Utilidades | M45: Material de Consumo - Gelo/ Gas CO2/ Carvao /Velas | N45: 75615012026 | O45: Documentação Aprovada | P45: Aprovado Diretoria | Q45: Aprovado Caixa | R45: Pago | S45: 134 | T45: Priceless - Bem Mais - Kamino
A46: 189593 | B46: 149 | C46: Priceless | D46: ERVAS FINAS HORTICULTURA LTDA | E46: 554.95 | F46: 46042 | G46: 46042 | H46: 46042 | I46: 46028 | J46: 46029 | K46: Boleto Bancário | L46: Custo Mercadoria Vendida | M46: Insumos - Alimentos | N46: 401576 | O46: Documentação Aprovada | P46: Aprovado Diretoria | Q46: Aprovado Caixa | R46: Pago | S46: 134 | T46: Priceless - Bem Mais - Kamino
A47: 189181 | B47: 149 | C47: Priceless | D47: GIGIO COMÉRCIO DE PRODUTO ALIMENTICIOS LTDA | E47: 186.3 | F47: 46042 | G47: 46042 | H47: 46042 | I47: 46028 | J47: 46028 | K47: Boleto Bancário | L47: Custo Mercadoria Vendida | M47: Insumos - Alimentos | N47: 21960 | O47: Documentação Aprovada | P47: Aprovado Diretoria | Q47: Aprovado Caixa | R47: Pago | S47: 134 | T47: Priceless - Bem Mais - Kamino
A48: 189743 | B48: 149 | C48: Priceless | D48: STAR.FRIO DISTRIBUIDORA DE AR CONDICIONADO E PECAS LTDA EРР | E48: 5000 | F48: 46042 | G48: 46042 | H48: 46042 | I48: 46029 | J48: 46029 | K48: Boleto Bancário | L48: Manutenção | M48: Manutenção de Equipamentos | N48: 41 | O48: Documentação Aprovada | P48: Aprovado Diretoria | Q48: Aprovado Caixa | R48: Pago | S48: 134 | T48: Priceless - Bem Mais - Kamino
A49: 189829 | B49: 149 | C49: Priceless | D49: D.R.O. PRODUTOS ALIMENTICIOS LTDA | E49: 154.68 | F49: 46042 | G49: 46042 | H49: 46042 | I49: 46029 | J49: 46030 | K49: Boleto Bancário | L49: Custo Mercadoria Vendida | M49: Insumos - Alimentos | N49: 50330 | O49: Documentação Aprovada | P49: Aprovado Diretoria | Q49: Aprovado Caixa | R49: Pago | S49: 134 | T49: Priceless - Bem Mais - Kamino
A50: 189828 | B50: 149 | C50: Priceless | D50: CECILIA TSUYACO ARAKI SILVA LTDA | E50: 395.8 | F50: 46042 | G50: 46042 | H50: 46042 | I50: 46030 | J50: 46030 | K50: Boleto Bancário | L50: Custo Mercadoria Vendida | M50: Insumos - Alimentos | N50: 384577 | O50: Documentação Aprovada | P50: Aprovado Diretoria | Q50: Aprovado Caixa | R50: Pago | S50: 134 | T50: Priceless - Bem Mais - Kamino
A51: 189827 | B51: 149 | C51: Priceless | D51: CECILIA TSUYACO ARAKI SILVA LTDA | E51: 13 | F51: 46042 | G51: 46042 | H51: 46042 | I51: 46029 | J51: 46030 | K51: Boleto Bancário | L51: Custo Mercadoria Vendida | M51: Insumos - Alimentos | N51: 384597 | O51: Documentação Aprovada | P51: Aprovado Diretoria | Q51: Aprovado Caixa | R51: Pago | S51: 134 | T51: Priceless - Bem Mais - Kamino
A52: 188835 | B52: 149 | C52: Priceless | D52: MR VACUO COMERCIO DE EMBALAGENS | E52: 1499.99 | F52: 46041 | G52: 46041 | H52: 46042 | I52: 46027 | J52: 46027 | K52: Boleto Bancário | L52: Manutenção | M52: Manutenção de Equipamentos | N52: 3849 | O52: Documentação Aprovada | P52: Aprovado Diretoria | Q52: Aprovado Caixa | R52: Pago | S52: 134 | T52: Priceless - Bem Mais - Kamino
A53: 191718 | B53: 149 | C53: Priceless | D53: OSTRAMAR PESCADOS EIRELI-ME | E53: 435 | F53: 46042 | G53: 46042 | H53: 46042 | I53: 46035 | J53: 46035 | K53: Boleto Bancário | L53: Custo Mercadoria Vendida | M53: Insumos - Alimentos | N53: 17604 | O53: Documentação Aprovada | P53: Aprovado Diretoria | Q53: Aprovado Caixa | R53: Pago | S53: 134 | T53: Priceless - Bem Mais - Kamino
A54: 191195 | B54: 149 | C54: Priceless | D54: HORTIFRUTI DO CHEF LTDA | E54: 390.75 | F54: 46042 | G54: 46042 | H54: 46042 | I54: 46034 | J54: 46034 | K54: Boleto Bancário | L54: Custo Mercadoria Vendida | M54: Insumos - Alimentos | N54: 28227 | O54: Documentação Aprovada | P54: Aprovado Diretoria | Q54: Aprovado Caixa | R54: Pago | S54: 134 | T54: Priceless - Bem Mais - Kamino
A55: 101681 | B55: 149 | C55: Priceless | D55: IRRF | E55: 12.63 | F55: 46042 | G55: 46042 | H55: 46042 | I55: 46021 | K55: Boleto Bancário | L55: Serviços de Terceiros | M55: Assessoria Contabil | N55: Dezembro/2025 | O55: Documentação Aprovada | P55: Aprovado Diretoria | Q55: Aprovado Caixa | R55: Pago | S55: 134 | T55: Priceless - Bem Mais - Kamino
A56: 111287 | B56: 149 | C56: Priceless | D56: ICMS | E56: 26379.34 | F56: 46042 | G56: 46042 | H56: 46042 | I56: 46021 | K56: Boleto Bancário | L56: Impostos sobre Venda | M56: ICMS | N56: DEZ2025 | O56: Documentação Aprovada | P56: Aprovado Diretoria | Q56: Aprovado Caixa | R56: Pago | S56: 134 | T56: Priceless - Bem Mais - Kamino
A57: 188702 | B57: 149 | C57: Priceless | D57: PJ 61410375000114 | E57: 300 | F57: 46041 | G57: 46041 | H57: 46041 | I57: 46002 | J57: 46027 | K57: Transferência Bancária ou Pix | L57: Custos de Eventos | M57: Serviços Terceirizados - Eventos | N57: 34 | O57: Documentação Aprovada | P57: Aprovado Diretoria | Q57: Aprovado Caixa | R57: Pago | S57: 134 | T57: Priceless - Bem Mais - Kamino
A58: 188698 | B58: 149 | C58: Priceless | D58: PJ 61410375000114 | E58: 200 | F58: 46041 | G58: 46041 | H58: 46041 | I58: 46009 | J58: 46027 | K58: Transferência Bancária ou Pix | L58: Custos de Eventos | M58: Serviços Terceirizados - Eventos | N58: 37 | O58: Documentação Aprovada | P58: Aprovado Diretoria | Q58: Aprovado Caixa | R58: Pago | S58: 134 | T58: Priceless - Bem Mais - Kamino
A59: 188700 | B59: 149 | C59: Priceless | D59: PJ 61410375000114 | E59: 200 | F59: 46041 | G59: 46041 | H59: 46041 | I59: 46003 | J59: 46027 | K59: Transferência Bancária ou Pix | L59: Custos de Eventos | M59: Serviços Terceirizados - Eventos | N59: 35 | O59: Documentação Aprovada | P59: Aprovado Diretoria | Q59: Aprovado Caixa | R59: Pago | S59: 134 | T59: Priceless - Bem Mais - Kamino
A60: 188739 | B60: 149 | C60: Priceless | D60: B.B DISTRIBUIDORA DE CARNES LTDA | E60: 218.16 | F60: 46041 | G60: 46041 | H60: 46041 | I60: 46013 | J60: 46027 | K60: Boleto Bancário | L60: Custo Mercadoria Vendida | M60: Insumos - Alimentos | N60: 410876 | O60: Documentação Aprovada | P60: Aprovado Diretoria | Q60: Aprovado Caixa | R60: Pago | S60: 134 | T60: Priceless - Bem Mais - Kamino
A61: 189187 | B61: 149 | C61: Priceless | D61: HORTA NOVA DISTRIBUIDORA DE HORTIFRUTI LTDA | E61: 969.98 | F61: 46041 | G61: 46041 | H61: 46041 | I61: 46028 | J61: 46028 | K61: Boleto Bancário | L61: Custo Mercadoria Vendida | M61: Insumos - Alimentos | N61: 8325 | O61: Documentação Aprovada | P61: Aprovado Diretoria | Q61: Aprovado Caixa | R61: Pago | S61: 134 | T61: Priceless - Bem Mais - Kamino
A62: 189194 | B62: 149 | C62: Priceless | D62: OSTRAMAR PESCADOS EIRELI-ME | E62: 1425 | F62: 46041 | G62: 46041 | H62: 46041 | I62: 46028 | J62: 46028 | K62: Boleto Bancário | L62: Custo Mercadoria Vendida | M62: Insumos - Alimentos | N62: 17467 | O62: Documentação Aprovada | P62: Aprovado Diretoria | Q62: Aprovado Caixa | R62: Pago | S62: 134 | T62: Priceless - Bem Mais - Kamino
A63: 189195 | B63: 149 | C63: Priceless | D63: PSSS LTDA | E63: 1757.22 | F63: 46041 | G63: 46041 | H63: 46041 | I63: 46028 | J63: 46028 | K63: Boleto Bancário | L63: Utilidades | M63: Higiene e Limpeza | N63: 2882 | O63: Documentação Aprovada | P63: Aprovado Diretoria | Q63: Aprovado Caixa | R63: Pago | S63: 134 | T63: Priceless - Bem Mais - Kamino
A64: 189196 | B64: 149 | C64: Priceless | D64: PSSS LTDA | E64: 348 | F64: 46041 | G64: 46041 | H64: 46041 | I64: 46028 | J64: 46028 | K64: Boleto Bancário | L64: Utilidades | M64: Higiene e Limpeza | N64: 2893 | O64: Documentação Aprovada | P64: Aprovado Diretoria | Q64: Aprovado Caixa | R64: Pago | S64: 134 | T64: Priceless - Bem Mais - Kamino
A65: 189173 | B65: 149 | C65: Priceless | D65: D.R.O. PRODUTOS ALIMENTICIOS LTDA | E65: 589.75 | F65: 46041 | G65: 46041 | H65: 46041 | I65: 46028 | J65: 46028 | K65: Boleto Bancário | L65: Custo Mercadoria Vendida | M65: Insumos - Alimentos | N65: 50247 | O65: Documentação Aprovada | P65: Aprovado Diretoria | Q65: Aprovado Caixa | R65: Pago | S65: 134 | T65: Priceless - Bem Mais - Kamino
A66: 189172 | B66: 149 | C66: Priceless | D66: CECILIA TSUYACO ARAKI SILVA LTDA | E66: 756.7 | F66: 46041 | G66: 46041 | H66: 46041 | I66: 46028 | J66: 46028 | K66: Boleto Bancário | L66: Custo Mercadoria Vendida | M66: Insumos - Alimentos | N66: 384439 | O66: Documentação Aprovada | P66: Aprovado Diretoria | Q66: Aprovado Caixa | R66: Pago | S66: 134 | T66: Priceless - Bem Mais - Kamino
A67: 189179 | B67: 149 | C67: Priceless | D67: Fermentare BNC LTDA | E67: 275 | F67: 46041 | G67: 46041 | H67: 46041 | I67: 46028 | J67: 46028 | K67: Boleto Bancário | L67: Custo Mercadoria Vendida | M67: Insumos - Alimentos | N67: 24667 | O67: Documentação Aprovada | P67: Aprovado Diretoria | Q67: Aprovado Caixa | R67: Pago | S67: 134 | T67: Priceless - Bem Mais - Kamino
A68: 190472 | B68: 149 | C68: Priceless | D68: V THOME LTDA - CASA DAS FESTAS | E68: 2215.77 | F68: 46041 | G68: 46041 | H68: 46041 | I68: 46022 | J68: 46031 | K68: Boleto Bancário | L68: Custos de Eventos | M68: Locação de Utensílios - Eventos | N68: 244906 | O68: Documentação Aprovada | P68: Aprovado Diretoria | Q68: Aprovado Caixa | R68: Pago | S68: 134 | T68: Priceless - Bem Mais - Kamino
... A80: 186749 | B80: 149 | C80: Priceless | D80: MAR DIRETO POC COMERCIO DE PEIXES LTDA | E80: 6894.3 | F80: 46041 | G80: 46041 | H80: 46041 | I80: 46018 | J80: 46020 | K80: Boleto Bancário | L80: Custo Mercadoria Vendida | M80: Insumos - Alimentos | N80: 113851 | O80: Documentação Aprovada | P80: Aprovado Diretoria | Q80: Aprovado Caixa | R80: Pago | S80: 134 | T80: Priceless - Bem Mais - Kamino
A81: 198280 | B81: 149 | C81: Priceless | D81: KAMINO INSTITUICAO DE PAGAMENTO LTDA | E81: 4 | F81: 46041 | H81: 46041 | I81: 46041 | K81: Debito Automático | L81: Despesas Financeiras | M81: Tarifas Bancárias | O81: Documentação Aprovada | P81: Aprovado Diretoria | Q81: Aprovado Caixa | R81: Pago | S81: 134 | T81: Priceless - Bem Mais - Kamino
A82: 198255 | B82: 149 | C82: Priceless | D82: KAMINO INSTITUICAO DE PAGAMENTO LTDA | E82: 2 | F82: 46038 | H82: 46038 | I82: 46038 | K82: Debito Automático | L82: Despesas Financeiras | M82: Tarifas Bancárias | O82: Documentação Aprovada | P82: Aprovado Diretoria | Q82: Aprovado Caixa | R82: Pago | S82: 134 | T82: Priceless - Bem Mais - Kamino
A83: 184805 | B83: 149 | C83: Priceless | D83: EMPORIO M&L COMERCIO DE ALIM E BEBIDAS LTDA | E83: 773.98 | F83: 46038 | G83: 46038 | H83: 46038 | I83: 46008 | J83: 46009 | K83: Boleto Bancário | L83: Custo Mercadoria Vendida | M83: Insumos - Alimentos | N83: 487548 | O83: Documentação Aprovada | P83: Aprovado Diretoria | Q83: Aprovado Caixa | R83: Pago | S83: 134 | T83: Priceless - Bem Mais - Kamino
A84: 185520 | B84: 149 | C84: Priceless | D84: EMPORIO M&L COMERCIO DE ALIM E BEBIDAS LTDA | E84: 307.9 | F84: 46038 | G84: 46038 | H84: 46038 | I84: 46010 | J84: 46014 | K84: Boleto Bancário | L84: Custo Mercadoria Vendida | M84: Insumos - Alimentos | N84: 488244 | O84: Documentação Aprovada | P84: Aprovado Diretoria | Q84: Aprovado Caixa | R84: Pago | S84: 134 | T84: Priceless - Bem Mais - Kamino
A85: 185413 | B85: 149 | C85: Priceless | D85: CI EQUIPAMENTOS DE COMUNICACAO LTDA ME | E85: 450 | F85: 46038 | G85: 46038 | H85: 46038 | I85: 46007 | J85: 46013 | K85: Transferência Bancária ou Pix | L85: Custos de Eventos | M85: Locação de Equipamentos - Eventos | N85: 14563 | O85: Documentação Aprovada | P85: Aprovado Diretoria | Q85: Aprovado Caixa | R85: Pago | S85: 134 | T85: Priceless - Bem Mais - Kamino
A86: 185414 | B86: 149 | C86: Priceless | D86: CI EQUIPAMENTOS DE COMUNICACAO LTDA ME | E86: 200 | F86: 46038 | G86: 46038 | H86: 46038 | I86: 46007 | J86: 46013 | K86: Transferência Bancária ou Pix | L86: Custos de Eventos | M86: Locação de Equipamentos - Eventos | N86: 14564 | O86: Documentação Aprovada | P86: Aprovado Diretoria | Q86: Aprovado Caixa | R86: Pago | S86: 134 | T86: Priceless - Bem Mais - Kamino
A87: 185515 | B87: 149 | C87: Priceless | D87: MARIO PEDRO FELICIANO - HORTIFRUTI | E87: 181.2 | F87: 46038 | G87: 46038 | H87: 46038 | I87: 46010 | J87: 46014 | K87: Boleto Bancário | L87: Custo Mercadoria Vendida | M87: Insumos - Alimentos | N87: 462561 | O87: Documentação Aprovada | P87: Aprovado Diretoria | Q87: Aprovado Caixa | R87: Pago | S87: 134 | T87: Priceless - Bem Mais - Kamino
A88: 183965 | B88: 149 | C88: Priceless | D88: LPQBR RESTAURANTES E PADARIAS LTDA | E88: 1890 | F88: 46031 | G88: 46038 | H88: 46038 | I88: 46003 | J88: 46008 | K88: Boleto Bancário | L88: Custo Mercadoria Vendida | M88: Insumos - Alimentos | N88: 87555 | O88: Documentação Aprovada | P88: Aprovado Diretoria | Q88: Aprovado Caixa | R88: Pago | S88: 134 | T88: Priceless - Bem Mais - Kamino
A89: 183940 | B89: 149 | C89: Priceless | D89: KING COMERCIO E IMPORTACAO DE BEBIDAS LTDA | E89: 3105.76 | F89: 46028 | G89: 46037 | H89: 46037 | I89: 46007 | J89: 46008 | K89: Boleto Bancário | L89: Custo Mercadoria Vendida | M89: Insumos - Bebidas | N89: 124161 | O89: Documentação Aprovada | P89: Aprovado Diretoria | Q89: Aprovado Caixa | R89: Pago | S89: 134 | T89: Priceless - Bem Mais - Kamino
A90: 183961 | B90: 149 | C90: Priceless | D90: JOTAO COMERCIO DE ALIMENTOS LTDA | E90: 1695.6 | F90: 46037 | G90: 46037 | H90: 46037 | I90: 46007 | J90: 46008 | K90: Boleto Bancário | L90: Custo Mercadoria Vendida | M90: Insumos - Alimentos | N90: 8015 | O90: Documentação Aprovada | P90: Aprovado Diretoria | Q90: Aprovado Caixa | R90: Pago | S90: 134 | T90: Priceless - Bem Mais - Kamino
A91: 185408 | B91: 149 | C91: Priceless | D91: CLT GERADORES | E91: 3750 | F91: 46037 | G91: 46037 | H91: 46037 | I91: 46007 | J91: 46013 | K91: Boleto Bancário | L91: Custos de Eventos | M91: Locação de Equipamentos - Eventos | N91: 2328 | O91: Documentação Aprovada | P91: Aprovado Diretoria | Q91: Aprovado Caixa | R91: Pago | S91: 134 | T91: Priceless - Bem Mais - Kamino
A92: 185682 | B92: 149 | C92: Priceless | D92: SAYEGH MATERIAIS PARA CONSTRUCAO | E92: 248.81 | F92: 46037 | G92: 46037 | H92: 46037 | I92: 46007 | J92: 46015 | K92: Boleto Bancário | L92: Custos de Eventos | M92: Material de Manutenção - Eventos | N92: 33315 | O92: Documentação Aprovada | P92: Aprovado Diretoria | Q92: Aprovado Caixa | R92: Pago | S92: 134 | T92: Priceless - Bem Mais - Kamino
A93: 185755 | B93: 149 | C93: Priceless | D93: PJ 44194738000102 | E93: 4000 | F93: 46037 | G93: 46037 | H93: 46037 | I93: 45992 | J93: 46015 | K93: Transferência Bancária ou Pix | L93: Mão de Obra - PJ | M93: MDO PJ Fixo | N93: 79 | O93: Documentação Aprovada | P93: Aprovado Diretoria | Q93: Aprovado Caixa | R93: Pago | S93: 149 | T93: Priceless - Duroc Filial Dois - Kamino
A94: 185756 | B94: 149 | C94: Priceless | D94: PJ 45581249000176 | E94: 4000 | F94: 46037 | G94: 46037 | H94: 46037 | I94: 45992 | J94: 46015 | K94: Transferência Bancária ou Pix | L94: Mão de Obra - PJ | M94: MDO PJ Fixo | N94: 70 | O94: Documentação Aprovada | P94: Aprovado Diretoria | Q94: Aprovado Caixa | R94: Pago | S94: 149 | T94: Priceless - Duroc Filial Dois - Kamino
... A125: 179567 | B125: 149 | C125: Priceless | D125: GAZIT MALLS FUNDO DE INVESTIMENTO IMOBILIARIO - REPASSE LOCACAO | E125: 4000 | F125: 46020 | G125: 46038 | H125: 46037 | I125: 45962 | J125: 45993 | K125: Boleto Bancário | L125: Custos de Eventos | M125: Repasse Gazit - Locação Aroo | N125: 4000112025 | O125: Documentação Aprovada | P125: Aprovado Diretoria | Q125: Aprovado Caixa | R125: Pago | S125: 134 | T125: Priceless - Bem Mais - Kamino
A126: 78028 | B126: 149 | C126: Priceless | D126: BANCO SANTANDER BRASIL S.A. | E126: 49278.71 | F126: 46032 | G126: 46037 | H126: 46037 | I126: 46032 | K126: Debito Automático | L126: Endividamento | M126: Empréstimos Gerais | N126: 38/44 | O126: Documentação Aprovada | P126: Aprovado Diretoria | Q126: Aprovado Caixa | R126: Pago | S126: 133 | T126: Priceless - Bem Mais - Itaú
A127: 81809 | B127: 149 | C127: Priceless | D127: CAIXA ECONOMICA FEDERAL | E127: 15711.37 | F127: 46036 | G127: 46035 | H127: 46035 | I127: 46037 | K127: Boleto Bancário | L127: Endividamento | M127: Empréstimos Gerais | N127: BOL 1755486 | O127: Documentação Aprovada | P127: Aprovado Diretoria | Q127: Aprovado Caixa | R127: Pago | S127: 134 | T127: Priceless - Bem Mais - Kamino
A128: 183790 | B128: 149 | C128: Priceless | D128: AMANTES DO VINHO COMERCIO DE BEBIDAS LTDA | E128: 2519.94 | F128: 46036 | G128: 46035 | H128: 46035 | I128: 46006 | J128: 46007 | K128: Boleto Bancário | L128: Custo Mercadoria Vendida | M128: Insumos - Bebidas | N128: 1000 | O128: Documentação Aprovada | P128: Aprovado Diretoria | Q128: Aprovado Caixa | R128: Pago | S128: 134 | T128: Priceless - Bem Mais - Kamino
A129: 185656 | B129: 149 | C129: Priceless | D129: V THOME LTDA - CASA DAS FESTAS | E129: 4725.61 | F129: 46035 | G129: 46035 | H129: 46035 | I129: 46003 | J129: 46015 | K129: Boleto Bancário | L129: Custos de Eventos | M129: Locação de Utensílios - Eventos | N129: 245405 | O129: Documentação Aprovada | P129: Aprovado Diretoria | Q129: Aprovado Caixa | R129: Pago | S129: 134 | T129: Priceless - Bem Mais - Kamino
A130: 185686 | B130: 149 | C130: Priceless | D130: FLASH AUDIO COMERCIO DE INFORMATICA LTDA - ME | E130: 85 | F130: 46029 | G130: 46035 | H130: 46035 | I130: 46010 | J130: 46015 | K130: Transferência Bancária ou Pix | L130: Manutenção | M130: Manutenção de Equipamentos | N130: 85122025 | O130: Documentação Aprovada | P130: Aprovado Diretoria | Q130: Aprovado Caixa | R130: Pago | S130: 134 | T130: Priceless - Bem Mais - Kamino
A131: 185676 | B131: 149 | C131: Priceless | D131: 62598012000117 PJ | E131: 20.7 | F131: 46029 | G131: 46035 | H131: 46035 | I131: 46007 | J131: 46015 | K131: Transferência Bancária ou Pix | L131: Custos de Eventos | M131: Transporte Equipe - Eventos | N131: 2070122025 | O131: Documentação Aprovada | P131: Aprovado Diretoria | Q131: Aprovado Caixa | R131: Pago | S131: 134 | T131: Priceless - Bem Mais - Kamino
A132: 185407 | B132: 149 | C132: Priceless | D132: CLT GERADORES | E132: 7500 | F132: 46035 | G132: 46035 | H132: 46035 | I132: 46010 | J132: 46013 | K132: Boleto Bancário | L132: Custos de Eventos | M132: Locação de Equipamentos - Eventos | N132: 2325 | O132: Documentação Aprovada | P132: Aprovado Diretoria | Q132: Aprovado Caixa | R132: Pago | S132: 134 | T132: Priceless - Bem Mais - Kamino
A133: 183803 | B133: 149 | C133: Priceless | D133: WPP COMERCIO DE CARNES LTDA | E133: 4199.18 | F133: 46035 | G133: 46035 | H133: 46035 | I133: 46007 | J133: 46007 | K133: Boleto Bancário | L133: Custo Mercadoria Vendida | M133: Insumos - Alimentos | N133: 76253 | O133: Documentação Aprovada | P133: Aprovado Diretoria | Q133: Aprovado Caixa | R133: Pago | S133: 134 | T133: Priceless - Bem Mais - Kamino
A134: 184137 | B134: 149 | C134: Priceless | D134: FRONT BEBIDAS LTDA | E134: 2855.23 | F134: 46035 | G134: 46035 | H134: 46035 | I134: 46010 | J134: 46008 | K134: Boleto Bancário | L134: Custo Mercadoria Vendida | M134: Insumos - Bebidas | N134: 784535 | O134: Documentação Aprovada | P134: Aprovado Diretoria | Q134: Aprovado Caixa | R134: Pago | S134: 134 | T134: Priceless - Bem Mais - Kamino
A135: 184133 | B135: 149 | C135: Priceless | D135: BB BRASIL AZEITES EXTRAVIRGENS LTDA | E135: 2206.5 | F135: 46036 | G135: 46035 | H135: 46035 | I135: 46006 | J135: 46008 | K135: Boleto Bancário | L135: Custo Mercadoria Vendida | M135: Insumos - Alimentos | N135: 312 | O135: Documentação Aprovada | P135: Aprovado Diretoria | Q135: Aprovado Caixa | R135: Pago | S135: 134 | T135: Priceless - Bem Mais - Kamino
A136: 171302 | B136: 149 | C136: Priceless | D136: MACHINE SEGURANCA PATRIMONIAL LTDA | E136: 2470 | F136: 46027 | G136: 46035 | H136: 46035 | I136: 45992 | J136: 45960 | K136: Transferência Bancária ou Pix | L136: Serviços de Terceiros | M136: Serviços de Segurança | N136: 2470122025 | O136: Documentação Aprovada | P136: Aprovado Diretoria | Q136: Aprovado Caixa | R136: Pago | S136: 134 | T136: Priceless - Bem Mais - Kamino
A137: 192113 | B137: 149 | C137: Priceless | D137: KAMINO INSTITUICAO DE PAGAMENTO LTDA | E137: 12 | F137: 46035 | H137: 46035 | I137: 46035 | K137: Debito Automático | L137: Despesas Financeiras | M137: Tarifas Bancárias | O137: Documentação Aprovada | P137: Aprovado Diretoria | Q137: Aprovado Caixa | R137: Pago | S137: 134 | T137: Priceless - Bem Mais - Kamino
A138: 189988 | B138: 149 | C138: Priceless | D138: EMPRESA BRASILEIRA DE CORREIOS E TELEGRAFOS. | E138: 42.43 | F138: 46030 | G138: 46035 | H138: 46035 | I138: 46023 | J138: 46030 | K138: Dinheiro em Espécie | L138: Utilidades | M138: Custas Cartório / Operação | N138: 0 | O138: Documentação Aprovada | P138: Aprovado Diretoria | Q138: Aprovado Caixa | R138: Pago | S138: 143 | T138: Tesouraria
A139: 190467 | B139: 149 | C139: Priceless | D139: PJ 61410375000114 | E139: 3866.57 | F139: 46034 | G139: 46035 | H139: 46035 | I139: 45992 | J139: 46031 | K139: Transferência Bancária ou Pix | L139: Mão de Obra - PJ | M139: MDO PJ Fixo | N139: 39 | O139: Documentação Aprovada | P139: Aprovado Diretoria | Q139: Aprovado Caixa | R139: Pago | S139: 149 | T139: Priceless - Duroc Filial Dois - Kamino
A140: 187155 | B140: 149 | C140: Priceless | D140: RUBENS OLIVEIRA ANDRADE DA SILVA | E140: 6500 | F140: 46035 | G140: 46035 | H140: 46035 | I140: 45992 | J140: 46021 | K140: Transferência Bancária ou Pix | L140: Marketing | M140: Agência de Propaganda | N140: 568 | O140: Documentação Aprovada | P140: Aprovado Diretoria | Q140: Aprovado Caixa | R140: Pago | S140: 134 | T140: Priceless - Bem Mais - Kamino
A141: 187135 | B141: 149 | C141: Priceless | D141: LUIZ FELIPE SILVA DA MOTTA | E141: 400 | F141: 46035 | G141: 46035 | H141: 46034 | I141: 46008 | J141: 46021 | K141: Transferência Bancária ou Pix | L141: Custos de Eventos | M141: Serviços Terceirizados - Eventos | N141: 44 | O141: Documentação Aprovada | P141: Aprovado Diretoria | Q141: Aprovado Caixa | R141: Pago | S141: 134 | T141: Priceless - Bem Mais - Kamino
A142: 187145 | B142: 149 | C142: Priceless | D142: PJ 49710287000132 | E142: 300 | F142: 46035 | G142: 46035 | H142: 46034 | I142: 46007 | J142: 46021 | K142: Transferência Bancária ou Pix | L142: Custos de Eventos | M142: Serviços Terceirizados - Eventos | N142: 71 | O142: Documentação Aprovada | P142: Aprovado Diretoria | Q142: Aprovado Caixa | R142: Pago | S142: 134 | T142: Priceless - Bem Mais - Kamino
A143: 187154 | B143: 149 | C143: Priceless | D143: SOLEDAD EVENTOS LTDA | E143: 1850 | F143: 46035 | G143: 46035 | H143: 46034 | I143: 46021 | J143: 46021 | K143: Transferência Bancária ou Pix | L143: Patrocínio | M143: (-) Despesas de Patrocínio | N143: 275 | O143: Documentação Aprovada | P143: Aprovado Diretoria | Q143: Aprovado Caixa | R143: Pago | S143: 134 | T143: Priceless - Bem Mais - Kamino
...

Sheet df_blueme_com_parcelamento
A1: ID_Parcela | B1: ID_Despesa | C1: ID_Casa | D1: Casa | E1: CNPJ_Loja | F1: Fornecedor | G1: Parcelamento | H1: Qtd_Parcelas | I1: Num_Parcela | J1: Valor_Parcela | K1: Vencimento_Parcela | L1: Previsao_Parcela | M1: Realiz_Parcela | N1: Valor_Original | O1: Valor_Liquido | P1: Data_Lancamento | Q1: Forma_Pagamento | R1: Doc_NF | S1: Class_Cont_1 | T1: Class_Cont_2 | U1: Status_Conf_Document | V1: Status_Aprov_Diret | W1: Status_Aprov_Caixa | X1: Status_Pgto | Y1: ID_Conta_Bancaria | Z1: Conta_Bancaria
A2: 12728 | B2: 187152 | C2: 149 | D2: Priceless | F2: VINICOLA FACCIN EIRELI | G2: True | H2: 2 | I2: 1 | J2: 1125 | K2: 46044 | L2: 46044 | M2: 46044 | N2: 2250 | O2: 2250 | P2: 46021 | Q2: Boleto Bancário | R2: 469 | S2: Custo Mercadoria Vendida | T2: Insumos - Bebidas | U2: Documentação Aprovada | V2: Aprovado Diretoria | W2: Aprovado Caixa | X2: Parcela_Paga | Y2: 134 | Z2: Priceless - Bem Mais - Kamino
A3: 12410 | B3: 182875 | C3: 149 | D3: Priceless | F3: VINICOLA CONCEICAO LTDA | G3: True | H3: 2 | I3: 2 | J3: 592.5 | K3: 46044 | L3: 46044 | M3: 46044 | N3: 1185 | O3: 1185 | P3: 46002 | Q3: Boleto Bancário | R3: 457 | S3: Custo Mercadoria Vendida | T3: Insumos - Bebidas | U3: Documentação Aprovada | V3: Aprovado Diretoria | W3: Aprovado Caixa | X3: Parcela_Paga | Y3: 134 | Z3: Priceless - Bem Mais - Kamino
A4: 12466 | B4: 183780 | C4: 149 | D4: Priceless | F4: EMPORIO M&L COMERCIO DE ALIM E BEBIDAS LTDA | G4: True | H4: 3 | I4: 2 | J4: 3837.55 | K4: 46042 | L4: 46042 | M4: 46042 | N4: 11512.65 | O4: 11512.65 | P4: 46007 | Q4: Boleto Bancário | R4: 486994 | S4: Custo Mercadoria Vendida | T4: Insumos - Alimentos | U4: Documentação Aprovada | V4: Aprovado Diretoria | W4: Aprovado Caixa | X4: Parcela_Paga | Y4: 134 | Z4: Priceless - Bem Mais - Kamino
A5: 12354 | B5: 182324 | C5: 149 | D5: Priceless | F5: EMPORIO M&L COMERCIO DE ALIM E BEBIDAS LTDA | G5: True | H5: 3 | I5: 3 | J5: 3170.29 | K5: 46042 | L5: 46042 | M5: 46042 | N5: 9510.86 | O5: 9510.86 | P5: 46001 | Q5: Boleto Bancário | R5: 485836 | S5: Custo Mercadoria Vendida | T5: Insumos - Alimentos | U5: Documentação Aprovada | V5: Aprovado Diretoria | W5: Aprovado Caixa | X5: Parcela_Paga | Y5: 134 | Z5: Priceless - Bem Mais - Kamino
A6: 12712 | B6: 186007 | C6: 149 | D6: Priceless | F6: ITAUEIRA CAMAROES LTDA. | G6: True | H6: 2 | I6: 1 | J6: 1364 | K6: 46041 | L6: 46041 | M6: 46038 | N6: 2728 | O6: 2728 | P6: 46017 | Q6: Boleto Bancário | R6: 6514 | S6: Custo Mercadoria Vendida | T6: Insumos - Alimentos | U6: Documentação Aprovada | V6: Aprovado Diretoria | W6: Aprovado Caixa | X6: Parcela_Paga | Y6: 134 | Z6: Priceless - Bem Mais - Kamino
A7: 12342 | B7: 182304 | C7: 149 | D7: Priceless | F7: LIDIANE QUEIROZ | G7: True | H7: 11 | I7: 2 | J7: 6000 | K7: 46041 | L7: 46041 | M7: 46038 | N7: 66000 | O7: 66000 | P7: 46001 | Q7: Transferência Bancária ou Pix | R7: 11 PARC-FIM 19/10/2026 | S7: Endividamento | T7: Processo Judicial | U7: Documentação Aprovada | V7: Aprovado Diretoria | W7: Aprovado Caixa | X7: Parcela_Paga | Y7: 134 | Z7: Priceless - Bem Mais - Kamino
A8: 12530 | B8: 185086 | C8: 149 | D8: Priceless | F8: SW BRASIL DISTRIBUIDORA CONSULTORIA E IMPORTADORA LTDA | G8: True | H8: 2 | I8: 2 | J8: 2088 | K8: 46040 | L8: 46041 | M8: 46038 | N8: 4176 | O8: 4176 | P8: 46010 | Q8: Boleto Bancário | R8: 1050 | S8: Custo Mercadoria Vendida | T8: Insumos - Bebidas | U8: Documentação Aprovada | V8: Aprovado Diretoria | W8: Aprovado Caixa | X8: Parcela_Paga | Y8: 134 | Z8: Priceless - Bem Mais - Kamino
A9: 3296 | B9: 63832 | C9: 149 | D9: Priceless | F9: SKY COMERCIO DE PRODUTOS ALIMENTICIOS LTDA | G9: True | H9: 2 | I9: 1 | J9: 282476 | K9: 45489 | L9: 45489 | M9: 46038 | N9: 5649.53 | O9: 5649.53 | P9: 45481 | Q9: Boleto Bancário | R9: 13533 | S9: Insumos - A&B | T9: Insumos - Bebidas | U9: Documentação Aprovada | V9: Aprovado Diretoria | W9: Aprovado Caixa | X9: Parcela_Paga
A10: 3289 | B10: 63828 | C10: 149 | D10: Priceless | F10: SKY COMERCIO DE PRODUTOS ALIMENTICIOS LTDA | G10: True | H10: 2 | I10: 1 | J10: 4078.11 | K10: 45488 | L10: 45488 | M10: 46037 | N10: 8160.23 | O10: 8160.23 | P10: 45481 | Q10: Boleto Bancário | R10: 13282 | S10: Insumos - A&B | T10: Insumos - Bebidas | U10: Documentação Aprovada | V10: Aprovado Diretoria | W10: Aprovado Caixa | X10: Parcela_Paga
A11: 12660 | B11: 185766 | C11: 149 | D11: Priceless | F11: PJ 55911208000154 | G11: True | H11: 2 | I11: 2 | J11: 2100 | K11: 46037 | L11: 46037 | M11: 46037 | N11: 4200 | O11: 4200 | P11: 46015 | Q11: Transferência Bancária ou Pix | R11: 16 | S11: Mão de Obra - PJ | T11: MDO PJ Fixo | U11: Documentação Aprovada | V11: Aprovado Diretoria | W11: Aprovado Caixa | X11: Parcela_Paga | Y11: 149 | Z11: Priceless - Duroc Filial Dois - Kamino
