Workbook

Sheet DRE
A3: NUV GASTROBAR | H3: =J8/H8 | J3: =J8/I8 | K3: =M8/K8 | M3: =M8/L8 | N3: =P8/N8 | P3: =P8/O8 | Q3: =S8/Q8 | S3: =S8/R8 | T3: =V8/T8 | V3: =V8/U8 | W3: =Y8/W8 | Y3: =Y8/X8 | Z3: =AB8/Z8 | AB3: =AB8/AA8 | AC3: =AE8/AC8 | AE3: =AE8/AD8 | AF3: =AH8/AF8 | AH3: =AH8/AG8 | AI3: =AK8/AI8 | AK3: =AK8/AJ8 | AL3: =AN8/AL8 | AN3: =AN8/AM8 | AO3: =AQ8/AO8 | AQ3: =AQ8/AP8 | AR3: =AT8/AR8 | AT3: =AT8/AS8 | AU3: =AW8/AU8 | AW3: =AW8/AV8 | AX3: =AZ8/AX8 | AZ3: =AZ8/AY8 | BA3: =BC8/BA8 | BC3: =BC8/BB8 | BD3: =BF8/BD8 | BF3: =BF8/BE8 | BG3: =BI8/BG8 | BI3: =BI8/BH8
H4: 46023 | K4: 46054 | N4: 46082 | Q4: 46113 | T4: 46143 | W4: 46174 | Z4: 46204 | AC4: 46235 | AF4: 46266 | AI4: 46296 | AL4: 46327 | AO4: 46357 | AR4: Acumulado | AU4: ANO | AX4: 1º TRIMESTRE | BA4: 2º TRIMESTRE | BD4: 3º TRIMESTRE | BG4: 4º TRIMESTRE
H5: 1 | I5: 1 | J5: =MONTH(H4) | K5: 2 | L5: 2 | M5: =MONTH(K4) | N5: 3 | O5: 3 | P5: =MONTH(N4) | Q5: 4 | R5: 4 | S5: =MONTH(Q4) | T5: 5 | U5: 5 | V5: =MONTH(T4) | W5: 6 | X5: 6 | Y5: 6 | Z5: 7 | AA5: 7 | AB5: =MONTH(Z4) | AC5: 8 | AD5: 8 | AE5: =MONTH(AC4) | AF5: 9 | AG5: 9 | AH5: =MONTH(AF4) | AI5: 10 | AJ5: 10 | AK5: =MONTH(AI4) | AL5: 11 | AM5: 11 | AN5: =MONTH(AL4) | AO5: 12 | AP5: 12 | AQ5: =MONTH(AO4)
H6: REAL 25 | I6: ORÇADO | J6: REAL 26 | K6: REAL 25 | L6: ORÇADO | M6: REAL 26 | N6: REAL 25 | O6: ORÇADO | P6: REAL 26 | Q6: REAL 25 | R6: ORÇADO | S6: REAL 26 | T6: REAL 25 | U6: ORÇADO | V6: REAL 26 | W6: REAL 25 | X6: ORÇADO | Y6: REAL 26 | Z6: REAL 25 | AA6: ORÇADO | AB6: REAL 26 | AC6: REAL 25 | AD6: ORÇADO | AE6: REAL 26 | AF6: REAL 25 | AG6: ORÇADO | AH6: REAL 26 | AI6: REAL 25 | AJ6: ORÇADO | AK6: REAL 26 | AL6: REAL 25 | AM6: ORÇADO | AN6: REAL 26 | AO6: REAL 25 | AP6: ORÇADO | AQ6: REAL 26 | AR6: 2025 | AS6: ORÇADO | AT6: REAL 2026 | AU6: 2025 | AV6: ORÇADO | AW6: REAL 2026 | AX6: REAL 25 | AY6: ORÇADO | AZ6: REAL 26 | BA6: REAL 25 | BB6: ORÇADO | BC6: REAL 26 | BD6: REAL 25 | BE6: ORÇADO | BF6: REAL 26 | BG6: REAL 25 | BH6: ORÇADO | BI6: REAL 26
H7: 45658 | I7: 46023 | K7: 45689 | L7: 46054 | N7: 45717 | O7: 46082 | Q7: 45748 | T7: 45778 | W7: 45809 | Z7: 45839 | AC7: 45870 | AF7: 45901 | AI7: 45931 | AL7: 45962 | AO7: 45992
A8: FATURAMENTO BRUTO | C8: PARÂMETROS UTILIZADOS | I8: =SUM(I9:I19) | J8: =SUM(J9:J19) | L8: =SUM(L9:L19) | M8: =SUM(M9:M19)+SUMIFS(Aut_Ajustes_Manuais!$G:$G,Aut_Ajustes_Manuais!$I:$I,DRE!K$4,Aut_Ajustes_Manuais!$F:$F,"FATURAMENTO BRUTO") | O8: =SUM(O9:O19) | P8: =SUM(P9:P19)+SUMIFS(Aut_Ajustes_Manuais!$G:$G,Aut_Ajustes_Manuais!$I:$I,DRE!N$4,Aut_Ajustes_Manuais!$F:$F,"FATURAMENTO BRUTO") | R8: =SUM(R9:R19) | S8: =SUM(S9:S19)+SUMIFS(Aut_Ajustes_Manuais!$G:$G,Aut_Ajustes_Manuais!$I:$I,DRE!Q$4,Aut_Ajustes_Manuais!$F:$F,"FATURAMENTO BRUTO") | U8: =SUM(U9:U19) | V8: =SUM(V9:V19)+SUMIFS(Aut_Ajustes_Manuais!$G:$G,Aut_Ajustes_Manuais!$I:$I,DRE!T$4,Aut_Ajustes_Manuais!$F:$F,"FATURAMENTO BRUTO") | X8: =SUM(X9:X19) | Y8: =SUM(Y9:Y19)+SUMIFS(Aut_Ajustes_Manuais!$G:$G,Aut_Ajustes_Manuais!$I:$I,DRE!W$4,Aut_Ajustes_Manuais!$F:$F,"FATURAMENTO BRUTO") | AA8: =SUM(AA9:AA19) | AB8: =SUM(AB9:AB19)+SUMIFS(Aut_Ajustes_Manuais!$G:$G,Aut_Ajustes_Manuais!$I:$I,DRE!Z$4,Aut_Ajustes_Manuais!$F:$F,"FATURAMENTO BRUTO") | AD8: =SUM(AD9:AD19) | AE8: =SUM(AE9:AE19)+SUMIFS(Aut_Ajustes_Manuais!$G:$G,Aut_Ajustes_Manuais!$I:$I,DRE!AC$4,Aut_Ajustes_Manuais!$F:$F,"FATURAMENTO BRUTO") | AG8: =SUM(AG9:AG19) | AH8: =SUM(AH9:AH19)+SUMIFS(Aut_Ajustes_Manuais!$G:$G,Aut_Ajustes_Manuais!$I:$I,DRE!AF$4,Aut_Ajustes_Manuais!$F:$F,"FATURAMENTO BRUTO") | AJ8: =SUM(AJ9:AJ19) | AK8: =SUM(AK9:AK19)+SUMIFS(Aut_Ajustes_Manuais!$G:$G,Aut_Ajustes_Manuais!$I:$I,DRE!AI$4,Aut_Ajustes_Manuais!$F:$F,"FATURAMENTO BRUTO") | AM8: =SUM(AM9:AM19) | AN8: =SUM(AN9:AN19)+SUMIFS(Aut_Ajustes_Manuais!$G:$G,Aut_Ajustes_Manuais!$I:$I,DRE!AL$4,Aut_Ajustes_Manuais!$F:$F,"FATURAMENTO BRUTO") | AP8: =SUM(AP9:AP19) | AQ8: =SUM(AQ9:AQ19)+SUMIFS(Aut_Ajustes_Manuais!$G:$G,Aut_Ajustes_Manuais!$I:$I,DRE!AO$4,Aut_Ajustes_Manuais!$F:$F,"FATURAMENTO BRUTO") | AR8: =SUM(AR9:AR19) | AS8: =SUM(AS9:AS19) | AT8: =SUM(AT9:AT19) | AU8: =SUM(AU9:AU19) | AV8: =SUM(AV9:AV19) | AW8: =SUM(AW9:AW19) | AX8: =SUM(AX9:AX19) | AY8: =SUM(AY9:AY19) | ... BI8: =SUM(BI9:BI19)
A9: Alimentação | C9: Estim. Mensal | D9: Preencher base de Faturamento A&B&C | I9: =SUMIFS(T_ORCAMENTOS!$E:$E,T_ORCAMENTOS!$C:$C,"Alimentação",T_ORCAMENTOS!$H:$H,"1/2026") | J9: =SUMIFS(Aut_Faturamento_Zig!$F:$F,Aut_Faturamento_Zig!$E:$E,"Alimentos",Aut_Faturamento_Zig!$D:$D,DRE!H$4)-SUMIFS(Aut_Promocoes_Utilizadas!$G:$G,Aut_Promocoes_Utilizadas!$J:$J,DRE!H$4,Aut_Promocoes_Utilizadas!$H:$H,"A",Aut_Promocoes_Utilizadas!$I:$I,"Eventos")-SUMIFS(Aut_Descontos!$I:$I,Aut_Descontos!$L:$L,DRE!H$4)-(SUMIFS(BD_Eventos_Novo!$J:$J,BD_Eventos_Novo!$AB:$AB,DRE!H$4,BD_Eventos_Novo!$G:$G,"Consumação Mínima")*50%)-(SUMIFS(BD_Eventos_Novo!$K:$K,BD_Eventos_Novo!$AB:$AB,DRE!H$4,BD_Eventos_Novo!$G:$G,"Consumação Mínima")*50%)-(SUMIFS(BD_Eventos_Novo!$J:$J,BD_Eventos_Novo!$AB:$AB,DRE!H$4,BD_Eventos_Novo!$G:$G,"Comanda Aberta / Couvert Antecipado")*50%)-(SUMIFS(BD_Eventos_Novo!$K:$K,BD_Eventos_Novo!$AB:$AB,DRE!H$4,BD_Eventos_Novo!$G:$G,"Comanda Aberta / Couvert Antecipado")*50%)+SUMIFS(Aut_Ajustes_Manuais!$G:$G,Aut_Ajustes_Manuais!$I:$I,DRE!H$4,Aut_Ajustes_Manuais!$F:$F,"Alimentação") | L9: =SUMIFS(T_ORCAMENTOS!$E:$E,T_ORCAMENTOS!$C:$C,"Alimentação",T_ORCAMENTOS!$H:$H,"2/2026") | M9: =SUMIFS(Aut_Faturamento_Zig!$F:$F,Aut_Faturamento_Zig!$E:$E,"Alimentos",Aut_Faturamento_Zig!$D:$D,DRE!K$4)-SUMIFS(Aut_Promocoes_Utilizadas!$G:$G,Aut_Promocoes_Utilizadas!$J:$J,DRE!K$4,Aut_Promocoes_Utilizadas!$H:$H,"A",Aut_Promocoes_Utilizadas!$I:$I,"Eventos")-SUMIFS(Aut_Descontos!$I:$I,Aut_Descontos!$L:$L,DRE!K$4)-(SUMIFS(BD_Eventos_Novo!$J:$J,BD_Eventos_Novo!$AB:$AB,DRE!K$4,BD_Eventos_Novo!$G:$G,"Consumação Mínima")*50%)-(SUMIFS(BD_Eventos_Novo!$K:$K,BD_Eventos_Novo!$AB:$AB,DRE!K$4,BD_Eventos_Novo!$G:$G,"Consumação Mínima")*50%)-(SUMIFS(BD_Eventos_Novo!$J:$J,BD_Eventos_Novo!$AB:$AB,DRE!K$4,BD_Eventos_Novo!$G:$G,"Comanda Aberta / Couvert Antecipado")*50%)-(SUMIFS(BD_Eventos_Novo!$K:$K,BD_Eventos_Novo!$AB:$AB,DRE!K$4,BD_Eventos_Novo!$G:$G,"Comanda Aberta / Couvert Antecipado")*50%)+SUMIFS(Aut_Ajustes_Manuais!$G:$G,Aut_Ajustes_Manuais!$I:$I,DRE!K$4,Aut_Ajustes_Manuais!$F:$F,"Alimentação") | O9: =SUMIFS(T_ORCAMENTOS!$E:$E,T_ORCAMENTOS!$C:$C,"Alimentação",T_ORCAMENTOS!$H:$H,"3/2026") | P9: =SUMIFS(Aut_Faturamento_Zig!$F:$F,Aut_Faturamento_Zig!$E:$E,"Alimentos",Aut_Faturamento_Zig!$D:$D,DRE!N$4)-SUMIFS(Aut_Promocoes_Utilizadas!$G:$G,Aut_Promocoes_Utilizadas!$J:$J,DRE!N$4,Aut_Promocoes_Utilizadas!$H:$H,"A",Aut_Promocoes_Utilizadas!$I:$I,"Eventos")-SUMIFS(Aut_Descontos!$I:$I,Aut_Descontos!$L:$L,DRE!N$4)-(SUMIFS(BD_Eventos_Novo!$J:$J,BD_Eventos_Novo!$AB:$AB,DRE!N$4,BD_Eventos_Novo!$G:$G,"Consumação Mínima")*50%)-(SUMIFS(BD_Eventos_Novo!$K:$K,BD_Eventos_Novo!$AB:$AB,DRE!N$4,BD_Eventos_Novo!$G:$G,"Consumação Mínima")*50%)-(SUMIFS(BD_Eventos_Novo!$J:$J,BD_Eventos_Novo!$AB:$AB,DRE!N$4,BD_Eventos_Novo!$G:$G,"Comanda Aberta / Couvert Antecipado")*50%)-(SUMIFS(BD_Eventos_Novo!$K:$K,BD_Eventos_Novo!$AB:$AB,DRE!N$4,BD_Eventos_Novo!$G:$G,"Comanda Aberta / Couvert Antecipado")*50%)+SUMIFS(Aut_Ajustes_Manuais!$G:$G,Aut_Ajustes_Manuais!$I:$I,DRE!N$4,Aut_Ajustes_Manuais!$F:$F,"Alimentação") | R9: =SUMIFS(T_ORCAMENTOS!$E:$E,T_ORCAMENTOS!$C:$C,"Alimentação",T_ORCAMENTOS!$H:$H,"4/2026") | S9: =SUMIFS(Aut_Faturamento_Zig!$F:$F,Aut_Faturamento_Zig!$E:$E,"Alimentos",Aut_Faturamento_Zig!$D:$D,DRE!Q$4)-SUMIFS(Aut_Promocoes_Utilizadas!$G:$G,Aut_Promocoes_Utilizadas!$J:$J,DRE!Q$4,Aut_Promocoes_Utilizadas!$H:$H,"A",Aut_Promocoes_Utilizadas!$I:$I,"Eventos")-SUMIFS(Aut_Descontos!$I:$I,Aut_Descontos!$L:$L,DRE!Q$4)-(SUMIFS(BD_Eventos_Novo!$J:$J,BD_Eventos_Novo!$AB:$AB,DRE!Q$4,BD_Eventos_Novo!$G:$G,"Consumação Mínima")*50%)-(SUMIFS(BD_Eventos_Novo!$K:$K,BD_Eventos_Novo!$AB:$AB,DRE!Q$4,BD_Eventos_Novo!$G:$G,"Consumação Mínima")*50%)-(SUMIFS(BD_Eventos_Novo!$J:$J,BD_Eventos_Novo!$AB:$AB,DRE!Q$4,BD_Eventos_Novo!$G:$G,"Comanda Aberta / Couvert Antecipado")*50%)-(SUMIFS(BD_Eventos_Novo!$K:$K,BD_Eventos_Novo!$AB:$AB,DRE!Q$4,BD_Eventos_Novo!$G:$G,"Comanda Aberta / Couvert Antecipado")*50%)+SUMIFS(Aut_Ajustes_Manuais!$G:$G,Aut_Ajustes_Manuais!$I:$I,DRE!Q$4,Aut_Ajustes_Manuais!$F:$F,"Alimentação") | U9: =SUMIFS(T_ORCAMENTOS!$E:$E,T_ORCAMENTOS!$C:$C,"Alimentação",T_ORCAMENTOS!$H:$H,"5/2026") | V9: =SUMIFS(Aut_Faturamento_Zig!$F:$F,Aut_Faturamento_Zig!$E:$E,"Alimentos",Aut_Faturamento_Zig!$D:$D,DRE!T$4)-SUMIFS(Aut_Promocoes_Utilizadas!$G:$G,Aut_Promocoes_Utilizadas!$J:$J,DRE!T$4,Aut_Promocoes_Utilizadas!$H:$H,"A",Aut_Promocoes_Utilizadas!$I:$I,"Eventos")-SUMIFS(Aut_Descontos!$I:$I,Aut_Descontos!$L:$L,DRE!T$4)-(SUMIFS(BD_Eventos_Novo!$J:$J,BD_Eventos_Novo!$AB:$AB,DRE!T$4,BD_Eventos_Novo!$G:$G,"Consumação Mínima")*50%)-(SUMIFS(BD_Eventos_Novo!$K:$K,BD_Eventos_Novo!$AB:$AB,DRE!T$4,BD_Eventos_Novo!$G:$G,"Consumação Mínima")*50%)-(SUMIFS(BD_Eventos_Novo!$J:$J,BD_Eventos_Novo!$AB:$AB,DRE!T$4,BD_Eventos_Novo!$G:$G,"Comanda Aberta / Couvert Antecipado")*50%)-(SUMIFS(BD_Eventos_Novo!$K:$K,BD_Eventos_Novo!$AB:$AB,DRE!T$4,BD_Eventos_Novo!$G:$G,"Comanda Aberta / Couvert Antecipado")*50%)+SUMIFS(Aut_Ajustes_Manuais!$G:$G,Aut_Ajustes_Manuais!$I:$I,DRE!T$4,Aut_Ajustes_Manuais!$F:$F,"Alimentação") | X9: =SUMIFS(T_ORCAMENTOS!$E:$E,T_ORCAMENTOS!$C:$C,"Alimentação",T_ORCAMENTOS!$H:$H,"6/2026") | Y9: =SUMIFS(Aut_Faturamento_Zig!$F:$F,Aut_Faturamento_Zig!$E:$E,"Alimentos",Aut_Faturamento_Zig!$D:$D,DRE!W$4)-SUMIFS(Aut_Promocoes_Utilizadas!$G:$G,Aut_Promocoes_Utilizadas!$J:$J,DRE!W$4,Aut_Promocoes_Utilizadas!$H:$H,"A",Aut_Promocoes_Utilizadas!$I:$I,"Eventos")-SUMIFS(Aut_Descontos!$I:$I,Aut_Descontos!$L:$L,DRE!W$4)-(SUMIFS(BD_Eventos_Novo!$J:$J,BD_Eventos_Novo!$AB:$AB,DRE!W$4,BD_Eventos_Novo!$G:$G,"Consumação Mínima")*50%)-(SUMIFS(BD_Eventos_Novo!$K:$K,BD_Eventos_Novo!$AB:$AB,DRE!W$4,BD_Eventos_Novo!$G:$G,"Consumação Mínima")*50%)-(SUMIFS(BD_Eventos_Novo!$J:$J,BD_Eventos_Novo!$AB:$AB,DRE!W$4,BD_Eventos_Novo!$G:$G,"Comanda Aberta / Couvert Antecipado")*50%)-(SUMIFS(BD_Eventos_Novo!$K:$K,BD_Eventos_Novo!$AB:$AB,DRE!W$4,BD_Eventos_Novo!$G:$G,"Comanda Aberta / Couvert Antecipado")*50%)+SUMIFS(Aut_Ajustes_Manuais!$G:$G,Aut_Ajustes_Manuais!$I:$I,DRE!W$4,Aut_Ajustes_Manuais!$F:$F,"Alimentação") | AA9: =SUMIFS(T_ORCAMENTOS!$E:$E,T_ORCAMENTOS!$C:$C,"Alimentação",T_ORCAMENTOS!$H:$H,"7/2026") | AB9: =SUMIFS(Aut_Faturamento_Zig!$F:$F,Aut_Faturamento_Zig!$E:$E,"Alimentos",Aut_Faturamento_Zig!$D:$D,DRE!Z$4)-SUMIFS(Aut_Promocoes_Utilizadas!$G:$G,Aut_Promocoes_Utilizadas!$J:$J,DRE!Z$4,Aut_Promocoes_Utilizadas!$H:$H,"A",Aut_Promocoes_Utilizadas!$I:$I,"Eventos")-SUMIFS(Aut_Descontos!$I:$I,Aut_Descontos!$L:$L,DRE!Z$4)-(SUMIFS(BD_Eventos_Novo!$J:$J,BD_Eventos_Novo!$AB:$AB,DRE!Z$4,BD_Eventos_Novo!$G:$G,"Consumação Mínima")*50%)-(SUMIFS(BD_Eventos_Novo!$K:$K,BD_Eventos_Novo!$AB:$AB,DRE!Z$4,BD_Eventos_Novo!$G:$G,"Consumação Mínima")*50%)-(SUMIFS(BD_Eventos_Novo!$J:$J,BD_Eventos_Novo!$AB:$AB,DRE!Z$4,BD_Eventos_Novo!$G:$G,"Comanda Aberta / Couvert Antecipado")*50%)-(SUMIFS(BD_Eventos_Novo!$K:$K,BD_Eventos_Novo!$AB:$AB,DRE!Z$4,BD_Eventos_Novo!$G:$G,"Comanda Aberta / Couvert Antecipado")*50%)+SUMIFS(Aut_Ajustes_Manuais!$G:$G,Aut_Ajustes_Manuais!$I:$I,DRE!Z$4,Aut_Ajustes_Manuais!$F:$F,"Alimentação") | AD9: =SUMIFS(T_ORCAMENTOS!$E:$E,T_ORCAMENTOS!$C:$C,"Alimentação",T_ORCAMENTOS!$H:$H,"8/2026") | AE9: =SUMIFS(Aut_Faturamento_Zig!$F:$F,Aut_Faturamento_Zig!$E:$E,"Alimentos",Aut_Faturamento_Zig!$D:$D,DRE!AC$4)-SUMIFS(Aut_Promocoes_Utilizadas!$G:$G,Aut_Promocoes_Utilizadas!$J:$J,DRE!AC$4,Aut_Promocoes_Utilizadas!$H:$H,"A",Aut_Promocoes_Utilizadas!$I:$I,"Eventos")-SUMIFS(Aut_Descontos!$I:$I,Aut_Descontos!$L:$L,DRE!AC$4)-(SUMIFS(BD_Eventos_Novo!$J:$J,BD_Eventos_Novo!$AB:$AB,DRE!AC$4,BD_Eventos_Novo!$G:$G,"Consumação Mínima")*50%)-(SUMIFS(BD_Eventos_Novo!$K:$K,BD_Eventos_Novo!$AB:$AB,DRE!AC$4,BD_Eventos_Novo!$G:$G,"Consumação Mínima")*50%)-(SUMIFS(BD_Eventos_Novo!$J:$J,BD_Eventos_Novo!$AB:$AB,DRE!AC$4,BD_Eventos_Novo!$G:$G,"Comanda Aberta / Couvert Antecipado")*50%)-(SUMIFS(BD_Eventos_Novo!$K:$K,BD_Eventos_Novo!$AB:$AB,DRE!AC$4,BD_Eventos_Novo!$G:$G,"Comanda Aberta / Couvert Antecipado")*50%)+SUMIFS(Aut_Ajustes_Manuais!$G:$G,Aut_Ajustes_Manuais!$I:$I,DRE!AC$4,Aut_Ajustes_Manuais!$F:$F,"Alimentação") | AG9: =SUMIFS(T_ORCAMENTOS!$E:$E,T_ORCAMENTOS!$C:$C,"Alimentação",T_ORCAMENTOS!$H:$H,"9/2026") | AH9: =SUMIFS(Aut_Faturamento_Zig!$F:$F,Aut_Faturamento_Zig!$E:$E,"Alimentos",Aut_Faturamento_Zig!$D:$D,DRE!AF$4)-SUMIFS(Aut_Promocoes_Utilizadas!$G:$G,Aut_Promocoes_Utilizadas!$J:$J,DRE!AF$4,Aut_Promocoes_Utilizadas!$H:$H,"A",Aut_Promocoes_Utilizadas!$I:$I,"Eventos")-SUMIFS(Aut_Descontos!$I:$I,Aut_Descontos!$L:$L,DRE!AF$4)-(SUMIFS(BD_Eventos_Novo!$J:$J,BD_Eventos_Novo!$AB:$AB,DRE!AF$4,BD_Eventos_Novo!$G:$G,"Consumação Mínima")*50%)-(SUMIFS(BD_Eventos_Novo!$K:$K,BD_Eventos_Novo!$AB:$AB,DRE!AF$4,BD_Eventos_Novo!$G:$G,"Consumação Mínima")*50%)-(SUMIFS(BD_Eventos_Novo!$J:$J,BD_Eventos_Novo!$AB:$AB,DRE!AF$4,BD_Eventos_Novo!$G:$G,"Comanda Aberta / Couvert Antecipado")*50%)-(SUMIFS(BD_Eventos_Novo!$K:$K,BD_Eventos_Novo!$AB:$AB,DRE!AF$4,BD_Eventos_Novo!$G:$G,"Comanda Aberta / Couvert Antecipado")*50%)+SUMIFS(Aut_Ajustes_Manuais!$G:$G,Aut_Ajustes_Manuais!$I:$I,DRE!AF$4,Aut_Ajustes_Manuais!$F:$F,"Alimentação") | AJ9: =SUMIFS(T_ORCAMENTOS!$E:$E,T_ORCAMENTOS!$C:$C,"Alimentação",T_ORCAMENTOS!$H:$H,"10/2026") | AK9: =SUMIFS(Aut_Faturamento_Zig!$F:$F,Aut_Faturamento_Zig!$E:$E,"Alimentos",Aut_Faturamento_Zig!$D:$D,DRE!AI$4)-SUMIFS(Aut_Promocoes_Utilizadas!$G:$G,Aut_Promocoes_Utilizadas!$J:$J,DRE!AI$4,Aut_Promocoes_Utilizadas!$H:$H,"A",Aut_Promocoes_Utilizadas!$I:$I,"Eventos")-SUMIFS(Aut_Descontos!$I:$I,Aut_Descontos!$L:$L,DRE!AI$4)-(SUMIFS(BD_Eventos_Novo!$J:$J,BD_Eventos_Novo!$AB:$AB,DRE!AI$4,BD_Eventos_Novo!$G:$G,"Consumação Mínima")*50%)-(SUMIFS(BD_Eventos_Novo!$K:$K,BD_Eventos_Novo!$AB:$AB,DRE!AI$4,BD_Eventos_Novo!$G:$G,"Consumação Mínima")*50%)-(SUMIFS(BD_Eventos_Novo!$J:$J,BD_Eventos_Novo!$AB:$AB,DRE!AI$4,BD_Eventos_Novo!$G:$G,"Comanda Aberta / Couvert Antecipado")*50%)-(SUMIFS(BD_Eventos_Novo!$K:$K,BD_Eventos_Novo!$AB:$AB,DRE!AI$4,BD_Eventos_Novo!$G:$G,"Comanda Aberta / Couvert Antecipado")*50%)+SUMIFS(Aut_Ajustes_Manuais!$G:$G,Aut_Ajustes_Manuais!$I:$I,DRE!AI$4,Aut_Ajustes_Manuais!$F:$F,"Alimentação") | AM9: =SUMIFS(T_ORCAMENTOS!$E:$E,T_ORCAMENTOS!$C:$C,"Alimentação",T_ORCAMENTOS!$H:$H,"11/2026") | AN9: =SUMIFS(Aut_Faturamento_Zig!$F:$F,Aut_Faturamento_Zig!$E:$E,"Alimentos",Aut_Faturamento_Zig!$D:$D,DRE!AL$4)-SUMIFS(Aut_Promocoes_Utilizadas!$G:$G,Aut_Promocoes_Utilizadas!$J:$J,DRE!AL$4,Aut_Promocoes_Utilizadas!$H:$H,"A",Aut_Promocoes_Utilizadas!$I:$I,"Eventos")-SUMIFS(Aut_Descontos!$I:$I,Aut_Descontos!$L:$L,DRE!AL$4)-(SUMIFS(BD_Eventos_Novo!$J:$J,BD_Eventos_Novo!$AB:$AB,DRE!AL$4,BD_Eventos_Novo!$G:$G,"Consumação Mínima")*50%)-(SUMIFS(BD_Eventos_Novo!$K:$K,BD_Eventos_Novo!$AB:$AB,DRE!AL$4,BD_Eventos_Novo!$G:$G,"Consumação Mínima")*50%)-(SUMIFS(BD_Eventos_Novo!$J:$J,BD_Eventos_Novo!$AB:$AB,DRE!AL$4,BD_Eventos_Novo!$G:$G,"Comanda Aberta / Couvert Antecipado")*50%)-(SUMIFS(BD_Eventos_Novo!$K:$K,BD_Eventos_Novo!$AB:$AB,DRE!AL$4,BD_Eventos_Novo!$G:$G,"Comanda Aberta / Couvert Antecipado")*50%)+SUMIFS(Aut_Ajustes_Manuais!$G:$G,Aut_Ajustes_Manuais!$I:$I,DRE!AL$4,Aut_Ajustes_Manuais!$F:$F,"Alimentação") | AP9: =SUMIFS(T_ORCAMENTOS!$E:$E,T_ORCAMENTOS!$C:$C,"Alimentação",T_ORCAMENTOS!$H:$H,"12/2026") | AQ9: =SUMIFS(Aut_Faturamento_Zig!$F:$F,Aut_Faturamento_Zig!$E:$E,"Alimentos",Aut_Faturamento_Zig!$D:$D,DRE!AO$4)-SUMIFS(Aut_Promocoes_Utilizadas!$G:$G,Aut_Promocoes_Utilizadas!$J:$J,DRE!AO$4,Aut_Promocoes_Utilizadas!$H:$H,"A",Aut_Promocoes_Utilizadas!$I:$I,"Eventos")-SUMIFS(Aut_Descontos!$I:$I,Aut_Descontos!$L:$L,DRE!AO$4)-(SUMIFS(BD_Eventos_Novo!$J:$J,BD_Eventos_Novo!$AB:$AB,DRE!AO$4,BD_Eventos_Novo!$G:$G,"Consumação Mínima")*50%)-(SUMIFS(BD_Eventos_Novo!$K:$K,BD_Eventos_Novo!$AB:$AB,DRE!AO$4,BD_Eventos_Novo!$G:$G,"Consumação Mínima")*50%)-(SUMIFS(BD_Eventos_Novo!$J:$J,BD_Eventos_Novo!$AB:$AB,DRE!AO$4,BD_Eventos_Novo!$G:$G,"Comanda Aberta / Couvert Antecipado")*50%)-(SUMIFS(BD_Eventos_Novo!$K:$K,BD_Eventos_Novo!$AB:$AB,DRE!AO$4,BD_Eventos_Novo!$G:$G,"Comanda Aberta / Couvert Antecipado")*50%)+SUMIFS(Aut_Ajustes_Manuais!$G:$G,Aut_Ajustes_Manuais!$I:$I,DRE!AO$4,Aut_Ajustes_Manuais!$F:$F,"Alimentação") | AR9: =SUMIFS($H9:$AO9,$H$5:$AO$5,"<"&MONTH(TODAY()),$H$6:$AO$6,"REAL 25") | AS9: =SUMIFS($I9:$AP9,$I$5:$AP$5,"<"&MONTH(TODAY()),$I$6:$AP$6,"ORÇADO ") | AT9: =SUMIFS($J9:$AQ9,$J$5:$AQ$5,"<"&MONTH(TODAY()),$J$6:$AQ$6,"REAL 26") | AU9: =SUM(H9,K9,N9,Q9,T9,W9,Z9,AC9,AF9,AI9,AL9,AO9) | AV9: =SUM(I9,L9,O9,R9,U9,X9,AA9,AD9,AG9,AJ9,AM9,AP9) | AW9: =SUM(J9,M9,P9,S9,V9,Y9,AB9,AE9,AH9,AK9,AN9,AQ9) | AX9: =SUM(H9,K9,N9) | AY9: =SUM(I9,L9,O9) | AZ9: =SUM(J9,M9,P9) | BA9: =SUM(Q9,T9,W9) | BB9: =SUM(R9,U9,X9) | BC9: =SUM(S9,V9,Y9) | BD9: =SUM(Z9,AC9,AF9) | BE9: =SUM(AA9,AD9,AG9) | BF9: =SUM(AB9,AE9,AH9) | BG9: =SUM(AI9,AL9,AO9) | BH9: =SUM(AJ9,AM9,AP9) | BI9: =SUM(AK9,AN9,AQ9)
A10: Bebida | C10: Estim. Mensal | D10: Preencher base de Faturamento A&B&C | I10: =SUMIFS(T_ORCAMENTOS!$E:$E,T_ORCAMENTOS!$C:$C,"Bebida",T_ORCAMENTOS!$H:$H,"1/2026") | J10: =SUMIFS(Aut_Faturamento_Zig!$F:$F,Aut_Faturamento_Zig!$E:$E,"Bebidas",Aut_Faturamento_Zig!$D:$D,DRE!H$4)-SUMIFS(Aut_Promocoes_Utilizadas!$G:$G,Aut_Promocoes_Utilizadas!$J:$J,DRE!H$4,Aut_Promocoes_Utilizadas!$H:$H,"B",Aut_Promocoes_Utilizadas!$I:$I,"Eventos")-SUMIFS(Aut_Descontos!$J:$J,Aut_Descontos!$L:$L,DRE!H$4)-(SUMIFS(BD_Eventos_Novo!$J:$J,BD_Eventos_Novo!$AB:$AB,DRE!H$4,BD_Eventos_Novo!$G:$G,"Consumação Mínima")*50%)-(SUMIFS(BD_Eventos_Novo!$K:$K,BD_Eventos_Novo!$AB:$AB,DRE!H$4,BD_Eventos_Novo!$G:$G,"Consumação Mínima")*50%)-(SUMIFS(BD_Eventos_Novo!$J:$J,BD_Eventos_Novo!$AB:$AB,DRE!H$4,BD_Eventos_Novo!$G:$G,"Comanda Aberta / Couvert Antecipado")*50%)-(SUMIFS(BD_Eventos_Novo!$K:$K,BD_Eventos_Novo!$AB:$AB,DRE!H$4,BD_Eventos_Novo!$G:$G,"Comanda Aberta / Couvert Antecipado")*50%)+SUMIFS(Aut_Ajustes_Manuais!$G:$G,Aut_Ajustes_Manuais!$I:$I,DRE!H$4,Aut_Ajustes_Manuais!$F:$F,"Bebida") | L10: =SUMIFS(T_ORCAMENTOS!$E:$E,T_ORCAMENTOS!$C:$C,"Bebida",T_ORCAMENTOS!$H:$H,"2/2026") | M10: =SUMIFS(Aut_Faturamento_Zig!$F:$F,Aut_Faturamento_Zig!$E:$E,"Bebidas",Aut_Faturamento_Zig!$D:$D,DRE!K$4)-SUMIFS(Aut_Promocoes_Utilizadas!$G:$G,Aut_Promocoes_Utilizadas!$J:$J,DRE!K$4,Aut_Promocoes_Utilizadas!$H:$H,"B",Aut_Promocoes_Utilizadas!$I:$I,"Eventos")-SUMIFS(Aut_Descontos!$J:$J,Aut_Descontos!$L:$L,DRE!K$4)-(SUMIFS(BD_Eventos_Novo!$J:$J,BD_Eventos_Novo!$AB:$AB,DRE!K$4,BD_Eventos_Novo!$G:$G,"Consumação Mínima")*50%)-(SUMIFS(BD_Eventos_Novo!$K:$K,BD_Eventos_Novo!$AB:$AB,DRE!K$4,BD_Eventos_Novo!$G:$G,"Consumação Mínima")*50%)-(SUMIFS(BD_Eventos_Novo!$J:$J,BD_Eventos_Novo!$AB:$AB,DRE!K$4,BD_Eventos_Novo!$G:$G,"Comanda Aberta / Couvert Antecipado")*50%)-(SUMIFS(BD_Eventos_Novo!$K:$K,BD_Eventos_Novo!$AB:$AB,DRE!K$4,BD_Eventos_Novo!$G:$G,"Comanda Aberta / Couvert Antecipado")*50%)+SUMIFS(Aut_Ajustes_Manuais!$G:$G,Aut_Ajustes_Manuais!$I:$I,DRE!K$4,Aut_Ajustes_Manuais!$F:$F,"Bebida") | O10: =SUMIFS(T_ORCAMENTOS!$E:$E,T_ORCAMENTOS!$C:$C,"Bebida",T_ORCAMENTOS!$H:$H,"3/2026") | P10: =SUMIFS(Aut_Faturamento_Zig!$F:$F,Aut_Faturamento_Zig!$E:$E,"Bebidas",Aut_Faturamento_Zig!$D:$D,DRE!N$4)-SUMIFS(Aut_Promocoes_Utilizadas!$G:$G,Aut_Promocoes_Utilizadas!$J:$J,DRE!N$4,Aut_Promocoes_Utilizadas!$H:$H,"B",Aut_Promocoes_Utilizadas!$I:$I,"Eventos")-SUMIFS(Aut_Descontos!$J:$J,Aut_Descontos!$L:$L,DRE!N$4)-(SUMIFS(BD_Eventos_Novo!$J:$J,BD_Eventos_Novo!$AB:$AB,DRE!N$4,BD_Eventos_Novo!$G:$G,"Consumação Mínima")*50%)-(SUMIFS(BD_Eventos_Novo!$K:$K,BD_Eventos_Novo!$AB:$AB,DRE!N$4,BD_Eventos_Novo!$G:$G,"Consumação Mínima")*50%)-(SUMIFS(BD_Eventos_Novo!$J:$J,BD_Eventos_Novo!$AB:$AB,DRE!N$4,BD_Eventos_Novo!$G:$G,"Comanda Aberta / Couvert Antecipado")*50%)-(SUMIFS(BD_Eventos_Novo!$K:$K,BD_Eventos_Novo!$AB:$AB,DRE!N$4,BD_Eventos_Novo!$G:$G,"Comanda Aberta / Couvert Antecipado")*50%)+SUMIFS(Aut_Ajustes_Manuais!$G:$G,Aut_Ajustes_Manuais!$I:$I,DRE!N$4,Aut_Ajustes_Manuais!$F:$F,"Bebida") | R10: =SUMIFS(T_ORCAMENTOS!$E:$E,T_ORCAMENTOS!$C:$C,"Bebida",T_ORCAMENTOS!$H:$H,"4/2026") | S10: =SUMIFS(Aut_Faturamento_Zig!$F:$F,Aut_Faturamento_Zig!$E:$E,"Bebidas",Aut_Faturamento_Zig!$D:$D,DRE!Q$4)-SUMIFS(Aut_Promocoes_Utilizadas!$G:$G,Aut_Promocoes_Utilizadas!$J:$J,DRE!Q$4,Aut_Promocoes_Utilizadas!$H:$H,"B",Aut_Promocoes_Utilizadas!$I:$I,"Eventos")-SUMIFS(Aut_Descontos!$J:$J,Aut_Descontos!$L:$L,DRE!Q$4)-(SUMIFS(BD_Eventos_Novo!$J:$J,BD_Eventos_Novo!$AB:$AB,DRE!Q$4,BD_Eventos_Novo!$G:$G,"Consumação Mínima")*50%)-(SUMIFS(BD_Eventos_Novo!$K:$K,BD_Eventos_Novo!$AB:$AB,DRE!Q$4,BD_Eventos_Novo!$G:$G,"Consumação Mínima")*50%)-(SUMIFS(BD_Eventos_Novo!$J:$J,BD_Eventos_Novo!$AB:$AB,DRE!Q$4,BD_Eventos_Novo!$G:$G,"Comanda Aberta / Couvert Antecipado")*50%)-(SUMIFS(BD_Eventos_Novo!$K:$K,BD_Eventos_Novo!$AB:$AB,DRE!Q$4,BD_Eventos_Novo!$G:$G,"Comanda Aberta / Couvert Antecipado")*50%)+SUMIFS(Aut_Ajustes_Manuais!$G:$G,Aut_Ajustes_Manuais!$I:$I,DRE!Q$4,Aut_Ajustes_Manuais!$F:$F,"Bebida") | U10: =SUMIFS(T_ORCAMENTOS!$E:$E,T_ORCAMENTOS!$C:$C,"Bebida",T_ORCAMENTOS!$H:$H,"5/2026") | V10: =SUMIFS(Aut_Faturamento_Zig!$F:$F,Aut_Faturamento_Zig!$E:$E,"Bebidas",Aut_Faturamento_Zig!$D:$D,DRE!T$4)-SUMIFS(Aut_Promocoes_Utilizadas!$G:$G,Aut_Promocoes_Utilizadas!$J:$J,DRE!T$4,Aut_Promocoes_Utilizadas!$H:$H,"B",Aut_Promocoes_Utilizadas!$I:$I,"Eventos")-SUMIFS(Aut_Descontos!$J:$J,Aut_Descontos!$L:$L,DRE!T$4)-(SUMIFS(BD_Eventos_Novo!$J:$J,BD_Eventos_Novo!$AB:$AB,DRE!T$4,BD_Eventos_Novo!$G:$G,"Consumação Mínima")*50%)-(SUMIFS(BD_Eventos_Novo!$K:$K,BD_Eventos_Novo!$AB:$AB,DRE!T$4,BD_Eventos_Novo!$G:$G,"Consumação Mínima")*50%)-(SUMIFS(BD_Eventos_Novo!$J:$J,BD_Eventos_Novo!$AB:$AB,DRE!T$4,BD_Eventos_Novo!$G:$G,"Comanda Aberta / Couvert Antecipado")*50%)-(SUMIFS(BD_Eventos_Novo!$K:$K,BD_Eventos_Novo!$AB:$AB,DRE!T$4,BD_Eventos_Novo!$G:$G,"Comanda Aberta / Couvert Antecipado")*50%)+SUMIFS(Aut_Ajustes_Manuais!$G:$G,Aut_Ajustes_Manuais!$I:$I,DRE!T$4,Aut_Ajustes_Manuais!$F:$F,"Bebida") | X10: =SUMIFS(T_ORCAMENTOS!$E:$E,T_ORCAMENTOS!$C:$C,"Bebida",T_ORCAMENTOS!$H:$H,"6/2026") | Y10: =SUMIFS(Aut_Faturamento_Zig!$F:$F,Aut_Faturamento_Zig!$E:$E,"Bebidas",Aut_Faturamento_Zig!$D:$D,DRE!W$4)-SUMIFS(Aut_Promocoes_Utilizadas!$G:$G,Aut_Promocoes_Utilizadas!$J:$J,DRE!W$4,Aut_Promocoes_Utilizadas!$H:$H,"B",Aut_Promocoes_Utilizadas!$I:$I,"Eventos")-SUMIFS(Aut_Descontos!$J:$J,Aut_Descontos!$L:$L,DRE!W$4)-(SUMIFS(BD_Eventos_Novo!$J:$J,BD_Eventos_Novo!$AB:$AB,DRE!W$4,BD_Eventos_Novo!$G:$G,"Consumação Mínima")*50%)-(SUMIFS(BD_Eventos_Novo!$K:$K,BD_Eventos_Novo!$AB:$AB,DRE!W$4,BD_Eventos_Novo!$G:$G,"Consumação Mínima")*50%)-(SUMIFS(BD_Eventos_Novo!$J:$J,BD_Eventos_Novo!$AB:$AB,DRE!W$4,BD_Eventos_Novo!$G:$G,"Comanda Aberta / Couvert Antecipado")*50%)-(SUMIFS(BD_Eventos_Novo!$K:$K,BD_Eventos_Novo!$AB:$AB,DRE!W$4,BD_Eventos_Novo!$G:$G,"Comanda Aberta / Couvert Antecipado")*50%)+SUMIFS(Aut_Ajustes_Manuais!$G:$G,Aut_Ajustes_Manuais!$I:$I,DRE!W$4,Aut_Ajustes_Manuais!$F:$F,"Bebida") | AA10: =SUMIFS(T_ORCAMENTOS!$E:$E,T_ORCAMENTOS!$C:$C,"Bebida",T_ORCAMENTOS!$H:$H,"7/2026") | AB10: =SUMIFS(Aut_Faturamento_Zig!$F:$F,Aut_Faturamento_Zig!$E:$E,"Bebidas",Aut_Faturamento_Zig!$D:$D,DRE!Z$4)-SUMIFS(Aut_Promocoes_Utilizadas!$G:$G,Aut_Promocoes_Utilizadas!$J:$J,DRE!Z$4,Aut_Promocoes_Utilizadas!$H:$H,"B",Aut_Promocoes_Utilizadas!$I:$I,"Eventos")-SUMIFS(Aut_Descontos!$J:$J,Aut_Descontos!$L:$L,DRE!Z$4)-(SUMIFS(BD_Eventos_Novo!$J:$J,BD_Eventos_Novo!$AB:$AB,DRE!Z$4,BD_Eventos_Novo!$G:$G,"Consumação Mínima")*50%)-(SUMIFS(BD_Eventos_Novo!$K:$K,BD_Eventos_Novo!$AB:$AB,DRE!Z$4,BD_Eventos_Novo!$G:$G,"Consumação Mínima")*50%)-(SUMIFS(BD_Eventos_Novo!$J:$J,BD_Eventos_Novo!$AB:$AB,DRE!Z$4,BD_Eventos_Novo!$G:$G,"Comanda Aberta / Couvert Antecipado")*50%)-(SUMIFS(BD_Eventos_Novo!$K:$K,BD_Eventos_Novo!$AB:$AB,DRE!Z$4,BD_Eventos_Novo!$G:$G,"Comanda Aberta / Couvert Antecipado")*50%)+SUMIFS(Aut_Ajustes_Manuais!$G:$G,Aut_Ajustes_Manuais!$I:$I,DRE!Z$4,Aut_Ajustes_Manuais!$F:$F,"Bebida") | AD10: =SUMIFS(T_ORCAMENTOS!$E:$E,T_ORCAMENTOS!$C:$C,"Bebida",T_ORCAMENTOS!$H:$H,"8/2026") | AE10: =SUMIFS(Aut_Faturamento_Zig!$F:$F,Aut_Faturamento_Zig!$E:$E,"Bebidas",Aut_Faturamento_Zig!$D:$D,DRE!AC$4)-SUMIFS(Aut_Promocoes_Utilizadas!$G:$G,Aut_Promocoes_Utilizadas!$J:$J,DRE!AC$4,Aut_Promocoes_Utilizadas!$H:$H,"B",Aut_Promocoes_Utilizadas!$I:$I,"Eventos")-SUMIFS(Aut_Descontos!$J:$J,Aut_Descontos!$L:$L,DRE!AC$4)-(SUMIFS(BD_Eventos_Novo!$J:$J,BD_Eventos_Novo!$AB:$AB,DRE!AC$4,BD_Eventos_Novo!$G:$G,"Consumação Mínima")*50%)-(SUMIFS(BD_Eventos_Novo!$K:$K,BD_Eventos_Novo!$AB:$AB,DRE!AC$4,BD_Eventos_Novo!$G:$G,"Consumação Mínima")*50%)-(SUMIFS(BD_Eventos_Novo!$J:$J,BD_Eventos_Novo!$AB:$AB,DRE!AC$4,BD_Eventos_Novo!$G:$G,"Comanda Aberta / Couvert Antecipado")*50%)-(SUMIFS(BD_Eventos_Novo!$K:$K,BD_Eventos_Novo!$AB:$AB,DRE!AC$4,BD_Eventos_Novo!$G:$G,"Comanda Aberta / Couvert Antecipado")*50%)+SUMIFS(Aut_Ajustes_Manuais!$G:$G,Aut_Ajustes_Manuais!$I:$I,DRE!AC$4,Aut_Ajustes_Manuais!$F:$F,"Bebida") | AG10: =SUMIFS(T_ORCAMENTOS!$E:$E,T_ORCAMENTOS!$C:$C,"Bebida",T_ORCAMENTOS!$H:$H,"9/2026") | AH10: =SUMIFS(Aut_Faturamento_Zig!$F:$F,Aut_Faturamento_Zig!$E:$E,"Bebidas",Aut_Faturamento_Zig!$D:$D,DRE!AF$4)-SUMIFS(Aut_Promocoes_Utilizadas!$G:$G,Aut_Promocoes_Utilizadas!$J:$J,DRE!AF$4,Aut_Promocoes_Utilizadas!$H:$H,"B",Aut_Promocoes_Utilizadas!$I:$I,"Eventos")-SUMIFS(Aut_Descontos!$J:$J,Aut_Descontos!$L:$L,DRE!AF$4)-(SUMIFS(BD_Eventos_Novo!$J:$J,BD_Eventos_Novo!$AB:$AB,DRE!AF$4,BD_Eventos_Novo!$G:$G,"Consumação Mínima")*50%)-(SUMIFS(BD_Eventos_Novo!$K:$K,BD_Eventos_Novo!$AB:$AB,DRE!AF$4,BD_Eventos_Novo!$G:$G,"Consumação Mínima")*50%)-(SUMIFS(BD_Eventos_Novo!$J:$J,BD_Eventos_Novo!$AB:$AB,DRE!AF$4,BD_Eventos_Novo!$G:$G,"Comanda Aberta / Couvert Antecipado")*50%)-(SUMIFS(BD_Eventos_Novo!$K:$K,BD_Eventos_Novo!$AB:$AB,DRE!AF$4,BD_Eventos_Novo!$G:$G,"Comanda Aberta / Couvert Antecipado")*50%)+SUMIFS(Aut_Ajustes_Manuais!$G:$G,Aut_Ajustes_Manuais!$I:$I,DRE!AF$4,Aut_Ajustes_Manuais!$F:$F,"Bebida") | AJ10: =SUMIFS(T_ORCAMENTOS!$E:$E,T_ORCAMENTOS!$C:$C,"Bebida",T_ORCAMENTOS!$H:$H,"10/2026") | AK10: =SUMIFS(Aut_Faturamento_Zig!$F:$F,Aut_Faturamento_Zig!$E:$E,"Bebidas",Aut_Faturamento_Zig!$D:$D,DRE!AI$4)-SUMIFS(Aut_Promocoes_Utilizadas!$G:$G,Aut_Promocoes_Utilizadas!$J:$J,DRE!AI$4,Aut_Promocoes_Utilizadas!$H:$H,"B",Aut_Promocoes_Utilizadas!$I:$I,"Eventos")-SUMIFS(Aut_Descontos!$J:$J,Aut_Descontos!$L:$L,DRE!AI$4)-(SUMIFS(BD_Eventos_Novo!$J:$J,BD_Eventos_Novo!$AB:$AB,DRE!AI$4,BD_Eventos_Novo!$G:$G,"Consumação Mínima")*50%)-(SUMIFS(BD_Eventos_Novo!$K:$K,BD_Eventos_Novo!$AB:$AB,DRE!AI$4,BD_Eventos_Novo!$G:$G,"Consumação Mínima")*50%)-(SUMIFS(BD_Eventos_Novo!$J:$J,BD_Eventos_Novo!$AB:$AB,DRE!AI$4,BD_Eventos_Novo!$G:$G,"Comanda Aberta / Couvert Antecipado")*50%)-(SUMIFS(BD_Eventos_Novo!$K:$K,BD_Eventos_Novo!$AB:$AB,DRE!AI$4,BD_Eventos_Novo!$G:$G,"Comanda Aberta / Couvert Antecipado")*50%)+SUMIFS(Aut_Ajustes_Manuais!$G:$G,Aut_Ajustes_Manuais!$I:$I,DRE!AI$4,Aut_Ajustes_Manuais!$F:$F,"Bebida") | AM10: =SUMIFS(T_ORCAMENTOS!$E:$E,T_ORCAMENTOS!$C:$C,"Bebida",T_ORCAMENTOS!$H:$H,"11/2026") | AN10: =SUMIFS(Aut_Faturamento_Zig!$F:$F,Aut_Faturamento_Zig!$E:$E,"Bebidas",Aut_Faturamento_Zig!$D:$D,DRE!AL$4)-SUMIFS(Aut_Promocoes_Utilizadas!$G:$G,Aut_Promocoes_Utilizadas!$J:$J,DRE!AL$4,Aut_Promocoes_Utilizadas!$H:$H,"B",Aut_Promocoes_Utilizadas!$I:$I,"Eventos")-SUMIFS(Aut_Descontos!$J:$J,Aut_Descontos!$L:$L,DRE!AL$4)-(SUMIFS(BD_Eventos_Novo!$J:$J,BD_Eventos_Novo!$AB:$AB,DRE!AL$4,BD_Eventos_Novo!$G:$G,"Consumação Mínima")*50%)-(SUMIFS(BD_Eventos_Novo!$K:$K,BD_Eventos_Novo!$AB:$AB,DRE!AL$4,BD_Eventos_Novo!$G:$G,"Consumação Mínima")*50%)-(SUMIFS(BD_Eventos_Novo!$J:$J,BD_Eventos_Novo!$AB:$AB,DRE!AL$4,BD_Eventos_Novo!$G:$G,"Comanda Aberta / Couvert Antecipado")*50%)-(SUMIFS(BD_Eventos_Novo!$K:$K,BD_Eventos_Novo!$AB:$AB,DRE!AL$4,BD_Eventos_Novo!$G:$G,"Comanda Aberta / Couvert Antecipado")*50%)+SUMIFS(Aut_Ajustes_Manuais!$G:$G,Aut_Ajustes_Manuais!$I:$I,DRE!AL$4,Aut_Ajustes_Manuais!$F:$F,"Bebida") | AP10: =SUMIFS(T_ORCAMENTOS!$E:$E,T_ORCAMENTOS!$C:$C,"Bebida",T_ORCAMENTOS!$H:$H,"12/2026") | AQ10: =SUMIFS(Aut_Faturamento_Zig!$F:$F,Aut_Faturamento_Zig!$E:$E,"Bebidas",Aut_Faturamento_Zig!$D:$D,DRE!AO$4)-SUMIFS(Aut_Promocoes_Utilizadas!$G:$G,Aut_Promocoes_Utilizadas!$J:$J,DRE!AO$4,Aut_Promocoes_Utilizadas!$H:$H,"B",Aut_Promocoes_Utilizadas!$I:$I,"Eventos")-SUMIFS(Aut_Descontos!$J:$J,Aut_Descontos!$L:$L,DRE!AO$4)-(SUMIFS(BD_Eventos_Novo!$J:$J,BD_Eventos_Novo!$AB:$AB,DRE!AO$4,BD_Eventos_Novo!$G:$G,"Consumação Mínima")*50%)-(SUMIFS(BD_Eventos_Novo!$K:$K,BD_Eventos_Novo!$AB:$AB,DRE!AO$4,BD_Eventos_Novo!$G:$G,"Consumação Mínima")*50%)-(SUMIFS(BD_Eventos_Novo!$J:$J,BD_Eventos_Novo!$AB:$AB,DRE!AO$4,BD_Eventos_Novo!$G:$G,"Comanda Aberta / Couvert Antecipado")*50%)-(SUMIFS(BD_Eventos_Novo!$K:$K,BD_Eventos_Novo!$AB:$AB,DRE!AO$4,BD_Eventos_Novo!$G:$G,"Comanda Aberta / Couvert Antecipado")*50%)+SUMIFS(Aut_Ajustes_Manuais!$G:$G,Aut_Ajustes_Manuais!$I:$I,DRE!AO$4,Aut_Ajustes_Manuais!$F:$F,"Bebida") | AR10: =SUMIFS($H10:$AO10,$H$5:$AO$5,"<"&MONTH(TODAY()),$H$6:$AO$6,"REAL 25") | AS10: =SUMIFS($I10:$AP10,$I$5:$AP$5,"<"&MONTH(TODAY()),$I$6:$AP$6,"ORÇADO ") | AT10: =SUMIFS($J10:$AQ10,$J$5:$AQ$5,"<"&MONTH(TODAY()),$J$6:$AQ$6,"REAL 26") | AU10: =SUM(H10,K10,N10,Q10,T10,W10,Z10,AC10,AF10,AI10,AL10,AO10) | AV10: =SUM(I10,L10,O10,R10,U10,X10,AA10,AD10,AG10,AJ10,AM10,AP10) | AW10: =SUM(J10,M10,P10,S10,V10,Y10,AB10,AE10,AH10,AK10,AN10,AQ10) | AX10: =SUM(H10,K10,N10) | AY10: =SUM(I10,L10,O10) | AZ10: =SUM(J10,M10,P10) | BA10: =SUM(Q10,T10,W10) | BB10: =SUM(R10,U10,X10) | BC10: =SUM(S10,V10,Y10) | BD10: =SUM(Z10,AC10,AF10) | BE10: =SUM(AA10,AD10,AG10) | BF10: =SUM(AB10,AE10,AH10) | BG10: =SUM(AI10,AL10,AO10) | BH10: =SUM(AJ10,AM10,AP10) | BI10: =SUM(AK10,AN10,AQ10)
A11: Artístico (couvert/shows) | C11: Estim. Mensal | D11: Preencher base de Faturamento A&B&C | I11: =SUMIFS(T_ORCAMENTOS!$E:$E,T_ORCAMENTOS!$C:$C,"Artístico (couvert/shows)",T_ORCAMENTOS!$H:$H,"1/2026") | J11: =SUMIFS(Aut_Faturamento_Zig!$F:$F,Aut_Faturamento_Zig!$E:$E,"Couvert",Aut_Faturamento_Zig!$D:$D,DRE!H$4)+SUMIFS(Aut_Ajustes_Manuais!$G:$G,Aut_Ajustes_Manuais!$I:$I,DRE!H$4,Aut_Ajustes_Manuais!$F:$F,"Artístico (couvert/shows)") | L11: =SUMIFS(T_ORCAMENTOS!$E:$E,T_ORCAMENTOS!$C:$C,"Artístico (couvert/shows)",T_ORCAMENTOS!$H:$H,"2/2026") | M11: =SUMIFS(Aut_Faturamento_Zig!$F:$F,Aut_Faturamento_Zig!$E:$E,"Couvert",Aut_Faturamento_Zig!$D:$D,DRE!K$4)+SUMIFS(Aut_Ajustes_Manuais!$G:$G,Aut_Ajustes_Manuais!$I:$I,DRE!K$4,Aut_Ajustes_Manuais!$F:$F,"Artístico (couvert/shows)") | O11: =SUMIFS(T_ORCAMENTOS!$E:$E,T_ORCAMENTOS!$C:$C,"Artístico (couvert/shows)",T_ORCAMENTOS!$H:$H,"3/2026") | P11: =SUMIFS(Aut_Faturamento_Zig!$F:$F,Aut_Faturamento_Zig!$E:$E,"Couvert",Aut_Faturamento_Zig!$D:$D,DRE!N$4)+SUMIFS(Aut_Ajustes_Manuais!$G:$G,Aut_Ajustes_Manuais!$I:$I,DRE!N$4,Aut_Ajustes_Manuais!$F:$F,"Artístico (couvert/shows)") | R11: =SUMIFS(T_ORCAMENTOS!$E:$E,T_ORCAMENTOS!$C:$C,"Artístico (couvert/shows)",T_ORCAMENTOS!$H:$H,"4/2026") | S11: =SUMIFS(Aut_Faturamento_Zig!$F:$F,Aut_Faturamento_Zig!$E:$E,"Couvert",Aut_Faturamento_Zig!$D:$D,DRE!Q$4)+SUMIFS(Aut_Ajustes_Manuais!$G:$G,Aut_Ajustes_Manuais!$I:$I,DRE!Q$4,Aut_Ajustes_Manuais!$F:$F,"Artístico (couvert/shows)") | U11: =SUMIFS(T_ORCAMENTOS!$E:$E,T_ORCAMENTOS!$C:$C,"Artístico (couvert/shows)",T_ORCAMENTOS!$H:$H,"5/2026") | V11: =SUMIFS(Aut_Faturamento_Zig!$F:$F,Aut_Faturamento_Zig!$E:$E,"Couvert",Aut_Faturamento_Zig!$D:$D,DRE!T$4)+SUMIFS(Aut_Ajustes_Manuais!$G:$G,Aut_Ajustes_Manuais!$I:$I,DRE!T$4,Aut_Ajustes_Manuais!$F:$F,"Artístico (couvert/shows)") | X11: =SUMIFS(T_ORCAMENTOS!$E:$E,T_ORCAMENTOS!$C:$C,"Artístico (couvert/shows)",T_ORCAMENTOS!$H:$H,"6/2026") | Y11: =SUMIFS(Aut_Faturamento_Zig!$F:$F,Aut_Faturamento_Zig!$E:$E,"Couvert",Aut_Faturamento_Zig!$D:$D,DRE!W$4)+SUMIFS(Aut_Ajustes_Manuais!$G:$G,Aut_Ajustes_Manuais!$I:$I,DRE!W$4,Aut_Ajustes_Manuais!$F:$F,"Artístico (couvert/shows)") | AA11: =SUMIFS(T_ORCAMENTOS!$E:$E,T_ORCAMENTOS!$C:$C,"Artístico (couvert/shows)",T_ORCAMENTOS!$H:$H,"7/2026") | AB11: =SUMIFS(Aut_Faturamento_Zig!$F:$F,Aut_Faturamento_Zig!$E:$E,"Couvert",Aut_Faturamento_Zig!$D:$D,DRE!Z$4)+SUMIFS(Aut_Ajustes_Manuais!$G:$G,Aut_Ajustes_Manuais!$I:$I,DRE!Z$4,Aut_Ajustes_Manuais!$F:$F,"Artístico (couvert/shows)") | AD11: =SUMIFS(T_ORCAMENTOS!$E:$E,T_ORCAMENTOS!$C:$C,"Artístico (couvert/shows)",T_ORCAMENTOS!$H:$H,"8/2026") | AE11: =SUMIFS(Aut_Faturamento_Zig!$F:$F,Aut_Faturamento_Zig!$E:$E,"Couvert",Aut_Faturamento_Zig!$D:$D,DRE!AC$4)+SUMIFS(Aut_Ajustes_Manuais!$G:$G,Aut_Ajustes_Manuais!$I:$I,DRE!AC$4,Aut_Ajustes_Manuais!$F:$F,"Artístico (couvert/shows)") | AG11: =SUMIFS(T_ORCAMENTOS!$E:$E,T_ORCAMENTOS!$C:$C,"Artístico (couvert/shows)",T_ORCAMENTOS!$H:$H,"9/2026") | AH11: =SUMIFS(Aut_Faturamento_Zig!$F:$F,Aut_Faturamento_Zig!$E:$E,"Couvert",Aut_Faturamento_Zig!$D:$D,DRE!AF$4)+SUMIFS(Aut_Ajustes_Manuais!$G:$G,Aut_Ajustes_Manuais!$I:$I,DRE!AF$4,Aut_Ajustes_Manuais!$F:$F,"Artístico (couvert/shows)") | AJ11: =SUMIFS(T_ORCAMENTOS!$E:$E,T_ORCAMENTOS!$C:$C,"Artístico (couvert/shows)",T_ORCAMENTOS!$H:$H,"10/2026") | AK11: =SUMIFS(Aut_Faturamento_Zig!$F:$F,Aut_Faturamento_Zig!$E:$E,"Couvert",Aut_Faturamento_Zig!$D:$D,DRE!AI$4)+SUMIFS(Aut_Ajustes_Manuais!$G:$G,Aut_Ajustes_Manuais!$I:$I,DRE!AI$4,Aut_Ajustes_Manuais!$F:$F,"Artístico (couvert/shows)") | AM11: =SUMIFS(T_ORCAMENTOS!$E:$E,T_ORCAMENTOS!$C:$C,"Artístico (couvert/shows)",T_ORCAMENTOS!$H:$H,"11/2026") | AN11: =SUMIFS(Aut_Faturamento_Zig!$F:$F,Aut_Faturamento_Zig!$E:$E,"Couvert",Aut_Faturamento_Zig!$D:$D,DRE!AL$4)+SUMIFS(Aut_Ajustes_Manuais!$G:$G,Aut_Ajustes_Manuais!$I:$I,DRE!AL$4,Aut_Ajustes_Manuais!$F:$F,"Artístico (couvert/shows)") | AP11: =SUMIFS(T_ORCAMENTOS!$E:$E,T_ORCAMENTOS!$C:$C,"Artístico (couvert/shows)",T_ORCAMENTOS!$H:$H,"12/2026") | AQ11: =SUMIFS(Aut_Faturamento_Zig!$F:$F,Aut_Faturamento_Zig!$E:$E,"Couvert",Aut_Faturamento_Zig!$D:$D,DRE!AO$4)+SUMIFS(Aut_Ajustes_Manuais!$G:$G,Aut_Ajustes_Manuais!$I:$I,DRE!AO$4,Aut_Ajustes_Manuais!$F:$F,"Artístico (couvert/shows)") | AR11: =SUMIFS($H11:$AO11,$H$5:$AO$5,"<"&MONTH(TODAY()),$H$6:$AO$6,"REAL 25") | AS11: =SUMIFS($I11:$AP11,$I$5:$AP$5,"<"&MONTH(TODAY()),$I$6:$AP$6,"ORÇADO ") | AT11: =SUMIFS($J11:$AQ11,$J$5:$AQ$5,"<"&MONTH(TODAY()),$J$6:$AQ$6,"REAL 26") | AU11: =SUM(H11,K11,N11,Q11,T11,W11,Z11,AC11,AF11,AI11,AL11,AO11) | AV11: =SUM(I11,L11,O11,R11,U11,X11,AA11,AD11,AG11,AJ11,AM11,AP11) | AW11: =SUM(J11,M11,P11,S11,V11,Y11,AB11,AE11,AH11,AK11,AN11,AQ11) | AX11: =SUM(H11,K11,N11) | AY11: =SUM(I11,L11,O11) | AZ11: =SUM(J11,M11,P11) | BA11: =SUM(Q11,T11,W11) | BB11: =SUM(R11,U11,X11) | BC11: =SUM(S11,V11,Y11) | BD11: =SUM(Z11,AC11,AF11) | BE11: =SUM(AA11,AD11,AG11) | BF11: =SUM(AB11,AE11,AH11) | BG11: =SUM(AI11,AL11,AO11) | BH11: =SUM(AJ11,AM11,AP11) | BI11: =SUM(AK11,AN11,AQ11)
A12: Gifts | C12: Estim. Mensal | D12: Vendas Lojinha | I12: =SUMIFS(T_ORCAMENTOS!$E:$E,T_ORCAMENTOS!$C:$C,"Gifts",T_ORCAMENTOS!$H:$H,"1/2026") | J12: =SUMIFS(Aut_Faturamento_Zig!$F:$F,Aut_Faturamento_Zig!$E:$E,"Gifts",Aut_Faturamento_Zig!$D:$D,DRE!H$4)+SUMIFS(Aut_Receitas_Extraord!$L:$L,Aut_Receitas_Extraord!$U:$U,DRE!H$4,Aut_Receitas_Extraord!$D:$D,"Lojinha")+SUMIFS(Aut_Ajustes_Manuais!$G:$G,Aut_Ajustes_Manuais!$I:$I,DRE!H$4,Aut_Ajustes_Manuais!$F:$F,"Gifts") | L12: =SUMIFS(T_ORCAMENTOS!$E:$E,T_ORCAMENTOS!$C:$C,"Gifts",T_ORCAMENTOS!$H:$H,"2/2026") | M12: =SUMIFS(Aut_Faturamento_Zig!$F:$F,Aut_Faturamento_Zig!$E:$E,"Gifts",Aut_Faturamento_Zig!$D:$D,DRE!K$4)+SUMIFS(Aut_Receitas_Extraord!$L:$L,Aut_Receitas_Extraord!$U:$U,DRE!K$4,Aut_Receitas_Extraord!$D:$D,"Lojinha")+SUMIFS(Aut_Ajustes_Manuais!$G:$G,Aut_Ajustes_Manuais!$I:$I,DRE!K$4,Aut_Ajustes_Manuais!$F:$F,"Gifts") | O12: =SUMIFS(T_ORCAMENTOS!$E:$E,T_ORCAMENTOS!$C:$C,"Gifts",T_ORCAMENTOS!$H:$H,"3/2026") | P12: =SUMIFS(Aut_Faturamento_Zig!$F:$F,Aut_Faturamento_Zig!$E:$E,"Gifts",Aut_Faturamento_Zig!$D:$D,DRE!N$4)+SUMIFS(Aut_Receitas_Extraord!$L:$L,Aut_Receitas_Extraord!$U:$U,DRE!N$4,Aut_Receitas_Extraord!$D:$D,"Lojinha")+SUMIFS(Aut_Ajustes_Manuais!$G:$G,Aut_Ajustes_Manuais!$I:$I,DRE!N$4,Aut_Ajustes_Manuais!$F:$F,"Gifts") | R12: =SUMIFS(T_ORCAMENTOS!$E:$E,T_ORCAMENTOS!$C:$C,"Gifts",T_ORCAMENTOS!$H:$H,"4/2026") | S12: =SUMIFS(Aut_Faturamento_Zig!$F:$F,Aut_Faturamento_Zig!$E:$E,"Gifts",Aut_Faturamento_Zig!$D:$D,DRE!Q$4)+SUMIFS(Aut_Receitas_Extraord!$L:$L,Aut_Receitas_Extraord!$U:$U,DRE!Q$4,Aut_Receitas_Extraord!$D:$D,"Lojinha")+SUMIFS(Aut_Ajustes_Manuais!$G:$G,Aut_Ajustes_Manuais!$I:$I,DRE!Q$4,Aut_Ajustes_Manuais!$F:$F,"Gifts") | U12: =SUMIFS(T_ORCAMENTOS!$E:$E,T_ORCAMENTOS!$C:$C,"Gifts",T_ORCAMENTOS!$H:$H,"5/2026") | V12: =SUMIFS(Aut_Faturamento_Zig!$F:$F,Aut_Faturamento_Zig!$E:$E,"Gifts",Aut_Faturamento_Zig!$D:$D,DRE!T$4)+SUMIFS(Aut_Receitas_Extraord!$L:$L,Aut_Receitas_Extraord!$U:$U,DRE!T$4,Aut_Receitas_Extraord!$D:$D,"Lojinha")+SUMIFS(Aut_Ajustes_Manuais!$G:$G,Aut_Ajustes_Manuais!$I:$I,DRE!T$4,Aut_Ajustes_Manuais!$F:$F,"Gifts") | X12: =SUMIFS(T_ORCAMENTOS!$E:$E,T_ORCAMENTOS!$C:$C,"Gifts",T_ORCAMENTOS!$H:$H,"6/2026") | Y12: =SUMIFS(Aut_Faturamento_Zig!$F:$F,Aut_Faturamento_Zig!$E:$E,"Gifts",Aut_Faturamento_Zig!$D:$D,DRE!W$4)+SUMIFS(Aut_Receitas_Extraord!$L:$L,Aut_Receitas_Extraord!$U:$U,DRE!W$4,Aut_Receitas_Extraord!$D:$D,"Lojinha")+SUMIFS(Aut_Ajustes_Manuais!$G:$G,Aut_Ajustes_Manuais!$I:$I,DRE!W$4,Aut_Ajustes_Manuais!$F:$F,"Gifts") | AA12: =SUMIFS(T_ORCAMENTOS!$E:$E,T_ORCAMENTOS!$C:$C,"Gifts",T_ORCAMENTOS!$H:$H,"7/2026") | AB12: =SUMIFS(Aut_Faturamento_Zig!$F:$F,Aut_Faturamento_Zig!$E:$E,"Gifts",Aut_Faturamento_Zig!$D:$D,DRE!Z$4)+SUMIFS(Aut_Receitas_Extraord!$L:$L,Aut_Receitas_Extraord!$U:$U,DRE!Z$4,Aut_Receitas_Extraord!$D:$D,"Lojinha")+SUMIFS(Aut_Ajustes_Manuais!$G:$G,Aut_Ajustes_Manuais!$I:$I,DRE!Z$4,Aut_Ajustes_Manuais!$F:$F,"Gifts") | AD12: =SUMIFS(T_ORCAMENTOS!$E:$E,T_ORCAMENTOS!$C:$C,"Gifts",T_ORCAMENTOS!$H:$H,"8/2026") | AE12: =SUMIFS(Aut_Faturamento_Zig!$F:$F,Aut_Faturamento_Zig!$E:$E,"Gifts",Aut_Faturamento_Zig!$D:$D,DRE!AC$4)+SUMIFS(Aut_Receitas_Extraord!$L:$L,Aut_Receitas_Extraord!$U:$U,DRE!AC$4,Aut_Receitas_Extraord!$D:$D,"Lojinha")+SUMIFS(Aut_Ajustes_Manuais!$G:$G,Aut_Ajustes_Manuais!$I:$I,DRE!AC$4,Aut_Ajustes_Manuais!$F:$F,"Gifts") | AG12: =SUMIFS(T_ORCAMENTOS!$E:$E,T_ORCAMENTOS!$C:$C,"Gifts",T_ORCAMENTOS!$H:$H,"9/2026") | AH12: =SUMIFS(Aut_Faturamento_Zig!$F:$F,Aut_Faturamento_Zig!$E:$E,"Gifts",Aut_Faturamento_Zig!$D:$D,DRE!AF$4)+SUMIFS(Aut_Receitas_Extraord!$L:$L,Aut_Receitas_Extraord!$U:$U,DRE!AF$4,Aut_Receitas_Extraord!$D:$D,"Lojinha")+SUMIFS(Aut_Ajustes_Manuais!$G:$G,Aut_Ajustes_Manuais!$I:$I,DRE!AF$4,Aut_Ajustes_Manuais!$F:$F,"Gifts") | AJ12: =SUMIFS(T_ORCAMENTOS!$E:$E,T_ORCAMENTOS!$C:$C,"Gifts",T_ORCAMENTOS!$H:$H,"10/2026") | AK12: =SUMIFS(Aut_Faturamento_Zig!$F:$F,Aut_Faturamento_Zig!$E:$E,"Gifts",Aut_Faturamento_Zig!$D:$D,DRE!AI$4)+SUMIFS(Aut_Receitas_Extraord!$L:$L,Aut_Receitas_Extraord!$U:$U,DRE!AI$4,Aut_Receitas_Extraord!$D:$D,"Lojinha")+SUMIFS(Aut_Ajustes_Manuais!$G:$G,Aut_Ajustes_Manuais!$I:$I,DRE!AI$4,Aut_Ajustes_Manuais!$F:$F,"Gifts") | AM12: =SUMIFS(T_ORCAMENTOS!$E:$E,T_ORCAMENTOS!$C:$C,"Gifts",T_ORCAMENTOS!$H:$H,"11/2026") | AN12: =SUMIFS(Aut_Faturamento_Zig!$F:$F,Aut_Faturamento_Zig!$E:$E,"Gifts",Aut_Faturamento_Zig!$D:$D,DRE!AL$4)+SUMIFS(Aut_Receitas_Extraord!$L:$L,Aut_Receitas_Extraord!$U:$U,DRE!AL$4,Aut_Receitas_Extraord!$D:$D,"Lojinha")+SUMIFS(Aut_Ajustes_Manuais!$G:$G,Aut_Ajustes_Manuais!$I:$I,DRE!AL$4,Aut_Ajustes_Manuais!$F:$F,"Gifts") | AP12: =SUMIFS(T_ORCAMENTOS!$E:$E,T_ORCAMENTOS!$C:$C,"Gifts",T_ORCAMENTOS!$H:$H,"12/2026") | AQ12: =SUMIFS(Aut_Faturamento_Zig!$F:$F,Aut_Faturamento_Zig!$E:$E,"Gifts",Aut_Faturamento_Zig!$D:$D,DRE!AO$4)+SUMIFS(Aut_Receitas_Extraord!$L:$L,Aut_Receitas_Extraord!$U:$U,DRE!AO$4,Aut_Receitas_Extraord!$D:$D,"Lojinha")+SUMIFS(Aut_Ajustes_Manuais!$G:$G,Aut_Ajustes_Manuais!$I:$I,DRE!AO$4,Aut_Ajustes_Manuais!$F:$F,"Gifts") | AR12: =SUMIFS($H12:$AO12,$H$5:$AO$5,"<"&MONTH(TODAY()),$H$6:$AO$6,"REAL 25") | AS12: =SUMIFS($I12:$AP12,$I$5:$AP$5,"<"&MONTH(TODAY()),$I$6:$AP$6,"ORÇADO ") | AT12: =SUMIFS($J12:$AQ12,$J$5:$AQ$5,"<"&MONTH(TODAY()),$J$6:$AQ$6,"REAL 26") | AU12: =SUM(H12,K12,N12,Q12,T12,W12,Z12,AC12,AF12,AI12,AL12,AO12) | AV12: =SUM(I12,L12,O12,R12,U12,X12,AA12,AD12,AG12,AJ12,AM12,AP12) | AW12: =SUM(J12,M12,P12,S12,V12,Y12,AB12,AE12,AH12,AK12,AN12,AQ12) | AX12: =SUM(H12,K12,N12) | AY12: =SUM(I12,L12,O12) | AZ12: =SUM(J12,M12,P12) | BA12: =SUM(Q12,T12,W12) | BB12: =SUM(R12,U12,X12) | BC12: =SUM(S12,V12,Y12) | BD12: =SUM(Z12,AC12,AF12) | BE12: =SUM(AA12,AD12,AG12) | BF12: =SUM(AB12,AE12,AH12) | BG12: =SUM(AI12,AL12,AO12) | BH12: =SUM(AJ12,AM12,AP12) | BI12: =SUM(AK12,AN12,AQ12)
A13: Serviço | C13: Estim. Mensal | D13: Gorjeta Fórmula | E13: 13% sobre A&B&C | I13: =SUMIFS(T_ORCAMENTOS!$E:$E,T_ORCAMENTOS!$C:$C,"Serviço",T_ORCAMENTOS!$H:$H,"1/2026") | J13: =SUMIFS(Aut_Faturamento_Zig!$F:$F,Aut_Faturamento_Zig!$E:$E,"Serviço",Aut_Faturamento_Zig!$D:$D,DRE!H$4)+SUMIFS(Aut_Ajustes_Manuais!$G:$G,Aut_Ajustes_Manuais!$I:$I,DRE!H$4,Aut_Ajustes_Manuais!$F:$F,"Serviço") | L13: =SUMIFS(T_ORCAMENTOS!$E:$E,T_ORCAMENTOS!$C:$C,"Serviço",T_ORCAMENTOS!$H:$H,"2/2026") | M13: =SUMIFS(Aut_Faturamento_Zig!$F:$F,Aut_Faturamento_Zig!$E:$E,"Serviço",Aut_Faturamento_Zig!$D:$D,DRE!K$4)+SUMIFS(Aut_Ajustes_Manuais!$G:$G,Aut_Ajustes_Manuais!$I:$I,DRE!K$4,Aut_Ajustes_Manuais!$F:$F,"Serviço") | O13: =SUMIFS(T_ORCAMENTOS!$E:$E,T_ORCAMENTOS!$C:$C,"Serviço",T_ORCAMENTOS!$H:$H,"3/2026") | P13: =SUMIFS(Aut_Faturamento_Zig!$F:$F,Aut_Faturamento_Zig!$E:$E,"Serviço",Aut_Faturamento_Zig!$D:$D,DRE!N$4)+SUMIFS(Aut_Ajustes_Manuais!$G:$G,Aut_Ajustes_Manuais!$I:$I,DRE!N$4,Aut_Ajustes_Manuais!$F:$F,"Serviço") | R13: =SUMIFS(T_ORCAMENTOS!$E:$E,T_ORCAMENTOS!$C:$C,"Serviço",T_ORCAMENTOS!$H:$H,"4/2026") | S13: =SUMIFS(Aut_Faturamento_Zig!$F:$F,Aut_Faturamento_Zig!$E:$E,"Serviço",Aut_Faturamento_Zig!$D:$D,DRE!Q$4)+SUMIFS(Aut_Ajustes_Manuais!$G:$G,Aut_Ajustes_Manuais!$I:$I,DRE!Q$4,Aut_Ajustes_Manuais!$F:$F,"Serviço") | U13: =SUMIFS(T_ORCAMENTOS!$E:$E,T_ORCAMENTOS!$C:$C,"Serviço",T_ORCAMENTOS!$H:$H,"5/2026") | V13: =SUMIFS(Aut_Faturamento_Zig!$F:$F,Aut_Faturamento_Zig!$E:$E,"Serviço",Aut_Faturamento_Zig!$D:$D,DRE!T$4)+SUMIFS(Aut_Ajustes_Manuais!$G:$G,Aut_Ajustes_Manuais!$I:$I,DRE!T$4,Aut_Ajustes_Manuais!$F:$F,"Serviço") | X13: =SUMIFS(T_ORCAMENTOS!$E:$E,T_ORCAMENTOS!$C:$C,"Serviço",T_ORCAMENTOS!$H:$H,"6/2026") | Y13: =SUMIFS(Aut_Faturamento_Zig!$F:$F,Aut_Faturamento_Zig!$E:$E,"Serviço",Aut_Faturamento_Zig!$D:$D,DRE!W$4)+SUMIFS(Aut_Ajustes_Manuais!$G:$G,Aut_Ajustes_Manuais!$I:$I,DRE!W$4,Aut_Ajustes_Manuais!$F:$F,"Serviço") | AA13: =SUMIFS(T_ORCAMENTOS!$E:$E,T_ORCAMENTOS!$C:$C,"Serviço",T_ORCAMENTOS!$H:$H,"7/2026") | AB13: =SUMIFS(Aut_Faturamento_Zig!$F:$F,Aut_Faturamento_Zig!$E:$E,"Serviço",Aut_Faturamento_Zig!$D:$D,DRE!Z$4)+SUMIFS(Aut_Ajustes_Manuais!$G:$G,Aut_Ajustes_Manuais!$I:$I,DRE!Z$4,Aut_Ajustes_Manuais!$F:$F,"Serviço") | AD13: =SUMIFS(T_ORCAMENTOS!$E:$E,T_ORCAMENTOS!$C:$C,"Serviço",T_ORCAMENTOS!$H:$H,"8/2026") | AE13: =SUMIFS(Aut_Faturamento_Zig!$F:$F,Aut_Faturamento_Zig!$E:$E,"Serviço",Aut_Faturamento_Zig!$D:$D,DRE!AC$4)+SUMIFS(Aut_Ajustes_Manuais!$G:$G,Aut_Ajustes_Manuais!$I:$I,DRE!AC$4,Aut_Ajustes_Manuais!$F:$F,"Serviço") | AG13: =SUMIFS(T_ORCAMENTOS!$E:$E,T_ORCAMENTOS!$C:$C,"Serviço",T_ORCAMENTOS!$H:$H,"9/2026") | AH13: =SUMIFS(Aut_Faturamento_Zig!$F:$F,Aut_Faturamento_Zig!$E:$E,"Serviço",Aut_Faturamento_Zig!$D:$D,DRE!AF$4)+SUMIFS(Aut_Ajustes_Manuais!$G:$G,Aut_Ajustes_Manuais!$I:$I,DRE!AF$4,Aut_Ajustes_Manuais!$F:$F,"Serviço") | AJ13: =SUMIFS(T_ORCAMENTOS!$E:$E,T_ORCAMENTOS!$C:$C,"Serviço",T_ORCAMENTOS!$H:$H,"10/2026") | AK13: =SUMIFS(Aut_Faturamento_Zig!$F:$F,Aut_Faturamento_Zig!$E:$E,"Serviço",Aut_Faturamento_Zig!$D:$D,DRE!AI$4)+SUMIFS(Aut_Ajustes_Manuais!$G:$G,Aut_Ajustes_Manuais!$I:$I,DRE!AI$4,Aut_Ajustes_Manuais!$F:$F,"Serviço") | AM13: =SUMIFS(T_ORCAMENTOS!$E:$E,T_ORCAMENTOS!$C:$C,"Serviço",T_ORCAMENTOS!$H:$H,"11/2026") | AN13: =SUMIFS(Aut_Faturamento_Zig!$F:$F,Aut_Faturamento_Zig!$E:$E,"Serviço",Aut_Faturamento_Zig!$D:$D,DRE!AL$4)+SUMIFS(Aut_Ajustes_Manuais!$G:$G,Aut_Ajustes_Manuais!$I:$I,DRE!AL$4,Aut_Ajustes_Manuais!$F:$F,"Serviço") | AP13: =SUMIFS(T_ORCAMENTOS!$E:$E,T_ORCAMENTOS!$C:$C,"Serviço",T_ORCAMENTOS!$H:$H,"12/2026") | AQ13: =SUMIFS(Aut_Faturamento_Zig!$F:$F,Aut_Faturamento_Zig!$E:$E,"Serviço",Aut_Faturamento_Zig!$D:$D,DRE!AO$4)+SUMIFS(Aut_Ajustes_Manuais!$G:$G,Aut_Ajustes_Manuais!$I:$I,DRE!AO$4,Aut_Ajustes_Manuais!$F:$F,"Serviço") | AR13: =SUMIFS($H13:$AO13,$H$5:$AO$5,"<"&MONTH(TODAY()),$H$6:$AO$6,"REAL 25") | AS13: =SUMIFS($I13:$AP13,$I$5:$AP$5,"<"&MONTH(TODAY()),$I$6:$AP$6,"ORÇADO ") | AT13: =SUMIFS($J13:$AQ13,$J$5:$AQ$5,"<"&MONTH(TODAY()),$J$6:$AQ$6,"REAL 26") | AU13: =SUM(H13,K13,N13,Q13,T13,W13,Z13,AC13,AF13,AI13,AL13,AO13) | AV13: =SUM(I13,L13,O13,R13,U13,X13,AA13,AD13,AG13,AJ13,AM13,AP13) | AW13: =SUM(J13,M13,P13,S13,V13,Y13,AB13,AE13,AH13,AK13,AN13,AQ13) | AX13: =SUM(H13,K13,N13) | AY13: =SUM(I13,L13,O13) | AZ13: =SUM(J13,M13,P13) | BA13: =SUM(Q13,T13,W13) | BB13: =SUM(R13,U13,X13) | BC13: =SUM(S13,V13,Y13) | BD13: =SUM(Z13,AC13,AF13) | BE13: =SUM(AA13,AD13,AG13) | BF13: =SUM(AB13,AE13,AH13) | BG13: =SUM(AI13,AL13,AO13) | BH13: =SUM(AJ13,AM13,AP13) | BI13: =SUM(AK13,AN13,AQ13)
A14: Eventos A&B | C14: Estim. Mensal | D14: Preencher base de Eventos | I14: =SUMIFS(T_ORCAMENTOS!$E:$E,T_ORCAMENTOS!$C:$C,"Eventos A&B",T_ORCAMENTOS!$H:$H,"1/2026") | J14: =SUMIFS(BD_Eventos_Novo!$J:$J,BD_Eventos_Novo!$AB:$AB,DRE!H$4)+SUMIFS(BD_Eventos_Novo!$K:$K,BD_Eventos_Novo!$AB:$AB,DRE!H$4)+SUMIFS(Aut_Ajustes_Manuais!$G:$G,Aut_Ajustes_Manuais!$I:$I,DRE!H$4,Aut_Ajustes_Manuais!$F:$F,"Eventos A&B") | L14: =SUMIFS(T_ORCAMENTOS!$E:$E,T_ORCAMENTOS!$C:$C,"Eventos A&B",T_ORCAMENTOS!$H:$H,"2/2026") | M14: =SUMIFS(BD_Eventos_Novo!$J:$J,BD_Eventos_Novo!$AB:$AB,DRE!K$4)+SUMIFS(BD_Eventos_Novo!$K:$K,BD_Eventos_Novo!$AB:$AB,DRE!K$4)+SUMIFS(Aut_Ajustes_Manuais!$G:$G,Aut_Ajustes_Manuais!$I:$I,DRE!K$4,Aut_Ajustes_Manuais!$F:$F,"Eventos A&B") | O14: =SUMIFS(T_ORCAMENTOS!$E:$E,T_ORCAMENTOS!$C:$C,"Eventos A&B",T_ORCAMENTOS!$H:$H,"3/2026") | P14: =SUMIFS(BD_Eventos_Novo!$J:$J,BD_Eventos_Novo!$AB:$AB,DRE!N$4)+SUMIFS(BD_Eventos_Novo!$K:$K,BD_Eventos_Novo!$AB:$AB,DRE!N$4)+SUMIFS(Aut_Ajustes_Manuais!$G:$G,Aut_Ajustes_Manuais!$I:$I,DRE!N$4,Aut_Ajustes_Manuais!$F:$F,"Eventos A&B") | R14: =SUMIFS(T_ORCAMENTOS!$E:$E,T_ORCAMENTOS!$C:$C,"Eventos A&B",T_ORCAMENTOS!$H:$H,"4/2026") | S14: =SUMIFS(BD_Eventos_Novo!$J:$J,BD_Eventos_Novo!$AB:$AB,DRE!Q$4)+SUMIFS(BD_Eventos_Novo!$K:$K,BD_Eventos_Novo!$AB:$AB,DRE!Q$4)+SUMIFS(Aut_Ajustes_Manuais!$G:$G,Aut_Ajustes_Manuais!$I:$I,DRE!Q$4,Aut_Ajustes_Manuais!$F:$F,"Eventos A&B") | U14: =SUMIFS(T_ORCAMENTOS!$E:$E,T_ORCAMENTOS!$C:$C,"Eventos A&B",T_ORCAMENTOS!$H:$H,"5/2026") | V14: =SUMIFS(BD_Eventos_Novo!$J:$J,BD_Eventos_Novo!$AB:$AB,DRE!T$4)+SUMIFS(BD_Eventos_Novo!$K:$K,BD_Eventos_Novo!$AB:$AB,DRE!T$4)+SUMIFS(Aut_Ajustes_Manuais!$G:$G,Aut_Ajustes_Manuais!$I:$I,DRE!T$4,Aut_Ajustes_Manuais!$F:$F,"Eventos A&B") | X14: =SUMIFS(T_ORCAMENTOS!$E:$E,T_ORCAMENTOS!$C:$C,"Eventos A&B",T_ORCAMENTOS!$H:$H,"6/2026") | Y14: =SUMIFS(BD_Eventos_Novo!$J:$J,BD_Eventos_Novo!$AB:$AB,DRE!W$4)+SUMIFS(BD_Eventos_Novo!$K:$K,BD_Eventos_Novo!$AB:$AB,DRE!W$4)+SUMIFS(Aut_Ajustes_Manuais!$G:$G,Aut_Ajustes_Manuais!$I:$I,DRE!W$4,Aut_Ajustes_Manuais!$F:$F,"Eventos A&B") | AA14: =SUMIFS(T_ORCAMENTOS!$E:$E,T_ORCAMENTOS!$C:$C,"Eventos A&B",T_ORCAMENTOS!$H:$H,"7/2026") | AB14: =SUMIFS(BD_Eventos_Novo!$J:$J,BD_Eventos_Novo!$AB:$AB,DRE!Z$4)+SUMIFS(BD_Eventos_Novo!$K:$K,BD_Eventos_Novo!$AB:$AB,DRE!Z$4)+SUMIFS(Aut_Ajustes_Manuais!$G:$G,Aut_Ajustes_Manuais!$I:$I,DRE!Z$4,Aut_Ajustes_Manuais!$F:$F,"Eventos A&B") | AD14: =SUMIFS(T_ORCAMENTOS!$E:$E,T_ORCAMENTOS!$C:$C,"Eventos A&B",T_ORCAMENTOS!$H:$H,"8/2026") | AE14: =SUMIFS(BD_Eventos_Novo!$J:$J,BD_Eventos_Novo!$AB:$AB,DRE!AC$4)+SUMIFS(BD_Eventos_Novo!$K:$K,BD_Eventos_Novo!$AB:$AB,DRE!AC$4)+SUMIFS(Aut_Ajustes_Manuais!$G:$G,Aut_Ajustes_Manuais!$I:$I,DRE!AC$4,Aut_Ajustes_Manuais!$F:$F,"Eventos A&B") | AG14: =SUMIFS(T_ORCAMENTOS!$E:$E,T_ORCAMENTOS!$C:$C,"Eventos A&B",T_ORCAMENTOS!$H:$H,"9/2026") | AH14: =SUMIFS(BD_Eventos_Novo!$J:$J,BD_Eventos_Novo!$AB:$AB,DRE!AF$4)+SUMIFS(BD_Eventos_Novo!$K:$K,BD_Eventos_Novo!$AB:$AB,DRE!AF$4)+SUMIFS(Aut_Ajustes_Manuais!$G:$G,Aut_Ajustes_Manuais!$I:$I,DRE!AF$4,Aut_Ajustes_Manuais!$F:$F,"Eventos A&B") | AJ14: =SUMIFS(T_ORCAMENTOS!$E:$E,T_ORCAMENTOS!$C:$C,"Eventos A&B",T_ORCAMENTOS!$H:$H,"10/2026") | AK14: =SUMIFS(BD_Eventos_Novo!$J:$J,BD_Eventos_Novo!$AB:$AB,DRE!AI$4)+SUMIFS(BD_Eventos_Novo!$K:$K,BD_Eventos_Novo!$AB:$AB,DRE!AI$4)+SUMIFS(Aut_Ajustes_Manuais!$G:$G,Aut_Ajustes_Manuais!$I:$I,DRE!AI$4,Aut_Ajustes_Manuais!$F:$F,"Eventos A&B") | AM14: =SUMIFS(T_ORCAMENTOS!$E:$E,T_ORCAMENTOS!$C:$C,"Eventos A&B",T_ORCAMENTOS!$H:$H,"11/2026") | AN14: =SUMIFS(BD_Eventos_Novo!$J:$J,BD_Eventos_Novo!$AB:$AB,DRE!AL$4)+SUMIFS(BD_Eventos_Novo!$K:$K,BD_Eventos_Novo!$AB:$AB,DRE!AL$4)+SUMIFS(Aut_Ajustes_Manuais!$G:$G,Aut_Ajustes_Manuais!$I:$I,DRE!AL$4,Aut_Ajustes_Manuais!$F:$F,"Eventos A&B") | AP14: =SUMIFS(T_ORCAMENTOS!$E:$E,T_ORCAMENTOS!$C:$C,"Eventos A&B",T_ORCAMENTOS!$H:$H,"12/2026") | AQ14: =SUMIFS(BD_Eventos_Novo!$J:$J,BD_Eventos_Novo!$AB:$AB,DRE!AO$4)+SUMIFS(BD_Eventos_Novo!$K:$K,BD_Eventos_Novo!$AB:$AB,DRE!AO$4)+SUMIFS(Aut_Ajustes_Manuais!$G:$G,Aut_Ajustes_Manuais!$I:$I,DRE!AO$4,Aut_Ajustes_Manuais!$F:$F,"Eventos A&B") | AR14: =SUMIFS($H14:$AO14,$H$5:$AO$5,"<"&MONTH(TODAY()),$H$6:$AO$6,"REAL 25") | AS14: =SUMIFS($I14:$AP14,$I$5:$AP$5,"<"&MONTH(TODAY()),$I$6:$AP$6,"ORÇADO ") | AT14: =SUMIFS($J14:$AQ14,$J$5:$AQ$5,"<"&MONTH(TODAY()),$J$6:$AQ$6,"REAL 26") | AU14: =SUM(H14,K14,N14,Q14,T14,W14,Z14,AC14,AF14,AI14,AL14,AO14) | AV14: =SUM(I14,L14,O14,R14,U14,X14,AA14,AD14,AG14,AJ14,AM14,AP14) | AW14: =SUM(J14,M14,P14,S14,V14,Y14,AB14,AE14,AH14,AK14,AN14,AQ14) | AX14: =SUM(H14,K14,N14) | AY14: =SUM(I14,L14,O14) | AZ14: =SUM(J14,M14,P14) | BA14: =SUM(Q14,T14,W14) | BB14: =SUM(R14,U14,X14) | BC14: =SUM(S14,V14,Y14) | BD14: =SUM(Z14,AC14,AF14) | BE14: =SUM(AA14,AD14,AG14) | BF14: =SUM(AB14,AE14,AH14) | BG14: =SUM(AI14,AL14,AO14) | BH14: =SUM(AJ14,AM14,AP14) | BI14: =SUM(AK14,AN14,AQ14)
A15: Eventos Couvert | C15: Estim. Mensal | D15: Preencher base de Eventos | I15: =SUMIFS(T_ORCAMENTOS!$E:$E,T_ORCAMENTOS!$C:$C,"Eventos Couvert",T_ORCAMENTOS!$H:$H,"1/2026") | J15: =SUMIFS(BD_Eventos_Novo!$M:$M,BD_Eventos_Novo!$AB:$AB,DRE!H$4)+SUMIFS(BD_Eventos_Novo!$N:$N,BD_Eventos_Novo!$AB:$AB,DRE!H$4)+SUMIFS(BD_Eventos_Novo!$O:$O,BD_Eventos_Novo!$AB:$AB,DRE!H$4)+SUMIFS(Aut_Ajustes_Manuais!$G:$G,Aut_Ajustes_Manuais!$I:$I,DRE!H$4,Aut_Ajustes_Manuais!$F:$F,"Eventos Couvert") | L15: =SUMIFS(T_ORCAMENTOS!$E:$E,T_ORCAMENTOS!$C:$C,"Eventos Couvert",T_ORCAMENTOS!$H:$H,"2/2026") | M15: =SUMIFS(BD_Eventos_Novo!$M:$M,BD_Eventos_Novo!$AB:$AB,DRE!K$4)+SUMIFS(BD_Eventos_Novo!$N:$N,BD_Eventos_Novo!$AB:$AB,DRE!K$4)+SUMIFS(BD_Eventos_Novo!$O:$O,BD_Eventos_Novo!$AB:$AB,DRE!K$4)+SUMIFS(Aut_Ajustes_Manuais!$G:$G,Aut_Ajustes_Manuais!$I:$I,DRE!K$4,Aut_Ajustes_Manuais!$F:$F,"Eventos Couvert") | O15: =SUMIFS(T_ORCAMENTOS!$E:$E,T_ORCAMENTOS!$C:$C,"Eventos Couvert",T_ORCAMENTOS!$H:$H,"3/2026") | P15: =SUMIFS(BD_Eventos_Novo!$M:$M,BD_Eventos_Novo!$AB:$AB,DRE!N$4)+SUMIFS(BD_Eventos_Novo!$N:$N,BD_Eventos_Novo!$AB:$AB,DRE!N$4)+SUMIFS(BD_Eventos_Novo!$O:$O,BD_Eventos_Novo!$AB:$AB,DRE!N$4)+SUMIFS(Aut_Ajustes_Manuais!$G:$G,Aut_Ajustes_Manuais!$I:$I,DRE!N$4,Aut_Ajustes_Manuais!$F:$F,"Eventos Couvert") | R15: =SUMIFS(T_ORCAMENTOS!$E:$E,T_ORCAMENTOS!$C:$C,"Eventos Couvert",T_ORCAMENTOS!$H:$H,"4/2026") | S15: =SUMIFS(BD_Eventos_Novo!$M:$M,BD_Eventos_Novo!$AB:$AB,DRE!Q$4)+SUMIFS(BD_Eventos_Novo!$N:$N,BD_Eventos_Novo!$AB:$AB,DRE!Q$4)+SUMIFS(BD_Eventos_Novo!$O:$O,BD_Eventos_Novo!$AB:$AB,DRE!Q$4)+SUMIFS(Aut_Ajustes_Manuais!$G:$G,Aut_Ajustes_Manuais!$I:$I,DRE!Q$4,Aut_Ajustes_Manuais!$F:$F,"Eventos Couvert") | U15: =SUMIFS(T_ORCAMENTOS!$E:$E,T_ORCAMENTOS!$C:$C,"Eventos Couvert",T_ORCAMENTOS!$H:$H,"5/2026") | V15: =SUMIFS(BD_Eventos_Novo!$M:$M,BD_Eventos_Novo!$AB:$AB,DRE!T$4)+SUMIFS(BD_Eventos_Novo!$N:$N,BD_Eventos_Novo!$AB:$AB,DRE!T$4)+SUMIFS(BD_Eventos_Novo!$O:$O,BD_Eventos_Novo!$AB:$AB,DRE!T$4)+SUMIFS(Aut_Ajustes_Manuais!$G:$G,Aut_Ajustes_Manuais!$I:$I,DRE!T$4,Aut_Ajustes_Manuais!$F:$F,"Eventos Couvert") | X15: =SUMIFS(T_ORCAMENTOS!$E:$E,T_ORCAMENTOS!$C:$C,"Eventos Couvert",T_ORCAMENTOS!$H:$H,"6/2026") | Y15: =SUMIFS(BD_Eventos_Novo!$M:$M,BD_Eventos_Novo!$AB:$AB,DRE!W$4)+SUMIFS(BD_Eventos_Novo!$N:$N,BD_Eventos_Novo!$AB:$AB,DRE!W$4)+SUMIFS(BD_Eventos_Novo!$O:$O,BD_Eventos_Novo!$AB:$AB,DRE!W$4)+SUMIFS(Aut_Ajustes_Manuais!$G:$G,Aut_Ajustes_Manuais!$I:$I,DRE!W$4,Aut_Ajustes_Manuais!$F:$F,"Eventos Couvert") | AA15: =SUMIFS(T_ORCAMENTOS!$E:$E,T_ORCAMENTOS!$C:$C,"Eventos Couvert",T_ORCAMENTOS!$H:$H,"7/2026") | AB15: =SUMIFS(BD_Eventos_Novo!$M:$M,BD_Eventos_Novo!$AB:$AB,DRE!Z$4)+SUMIFS(BD_Eventos_Novo!$N:$N,BD_Eventos_Novo!$AB:$AB,DRE!Z$4)+SUMIFS(BD_Eventos_Novo!$O:$O,BD_Eventos_Novo!$AB:$AB,DRE!Z$4)+SUMIFS(Aut_Ajustes_Manuais!$G:$G,Aut_Ajustes_Manuais!$I:$I,DRE!Z$4,Aut_Ajustes_Manuais!$F:$F,"Eventos Couvert") | AD15: =SUMIFS(T_ORCAMENTOS!$E:$E,T_ORCAMENTOS!$C:$C,"Eventos Couvert",T_ORCAMENTOS!$H:$H,"8/2026") | AE15: =SUMIFS(BD_Eventos_Novo!$M:$M,BD_Eventos_Novo!$AB:$AB,DRE!AC$4)+SUMIFS(BD_Eventos_Novo!$N:$N,BD_Eventos_Novo!$AB:$AB,DRE!AC$4)+SUMIFS(BD_Eventos_Novo!$O:$O,BD_Eventos_Novo!$AB:$AB,DRE!AC$4)+SUMIFS(Aut_Ajustes_Manuais!$G:$G,Aut_Ajustes_Manuais!$I:$I,DRE!AC$4,Aut_Ajustes_Manuais!$F:$F,"Eventos Couvert") | AG15: =SUMIFS(T_ORCAMENTOS!$E:$E,T_ORCAMENTOS!$C:$C,"Eventos Couvert",T_ORCAMENTOS!$H:$H,"9/2026") | AH15: =SUMIFS(BD_Eventos_Novo!$M:$M,BD_Eventos_Novo!$AB:$AB,DRE!AF$4)+SUMIFS(BD_Eventos_Novo!$N:$N,BD_Eventos_Novo!$AB:$AB,DRE!AF$4)+SUMIFS(BD_Eventos_Novo!$O:$O,BD_Eventos_Novo!$AB:$AB,DRE!AF$4)+SUMIFS(Aut_Ajustes_Manuais!$G:$G,Aut_Ajustes_Manuais!$I:$I,DRE!AF$4,Aut_Ajustes_Manuais!$F:$F,"Eventos Couvert") | AJ15: =SUMIFS(T_ORCAMENTOS!$E:$E,T_ORCAMENTOS!$C:$C,"Eventos Couvert",T_ORCAMENTOS!$H:$H,"10/2026") | AK15: =SUMIFS(BD_Eventos_Novo!$M:$M,BD_Eventos_Novo!$AB:$AB,DRE!AI$4)+SUMIFS(BD_Eventos_Novo!$N:$N,BD_Eventos_Novo!$AB:$AB,DRE!AI$4)+SUMIFS(BD_Eventos_Novo!$O:$O,BD_Eventos_Novo!$AB:$AB,DRE!AI$4)+SUMIFS(Aut_Ajustes_Manuais!$G:$G,Aut_Ajustes_Manuais!$I:$I,DRE!AI$4,Aut_Ajustes_Manuais!$F:$F,"Eventos Couvert") | AM15: =SUMIFS(T_ORCAMENTOS!$E:$E,T_ORCAMENTOS!$C:$C,"Eventos Couvert",T_ORCAMENTOS!$H:$H,"11/2026") | AN15: =SUMIFS(BD_Eventos_Novo!$M:$M,BD_Eventos_Novo!$AB:$AB,DRE!AL$4)+SUMIFS(BD_Eventos_Novo!$N:$N,BD_Eventos_Novo!$AB:$AB,DRE!AL$4)+SUMIFS(BD_Eventos_Novo!$O:$O,BD_Eventos_Novo!$AB:$AB,DRE!AL$4)+SUMIFS(Aut_Ajustes_Manuais!$G:$G,Aut_Ajustes_Manuais!$I:$I,DRE!AL$4,Aut_Ajustes_Manuais!$F:$F,"Eventos Couvert") | AP15: =SUMIFS(T_ORCAMENTOS!$E:$E,T_ORCAMENTOS!$C:$C,"Eventos Couvert",T_ORCAMENTOS!$H:$H,"12/2026") | AQ15: =SUMIFS(BD_Eventos_Novo!$M:$M,BD_Eventos_Novo!$AB:$AB,DRE!AO$4)+SUMIFS(BD_Eventos_Novo!$N:$N,BD_Eventos_Novo!$AB:$AB,DRE!AO$4)+SUMIFS(BD_Eventos_Novo!$O:$O,BD_Eventos_Novo!$AB:$AB,DRE!AO$4)+SUMIFS(Aut_Ajustes_Manuais!$G:$G,Aut_Ajustes_Manuais!$I:$I,DRE!AO$4,Aut_Ajustes_Manuais!$F:$F,"Eventos Couvert") | AR15: =SUMIFS($H15:$AO15,$H$5:$AO$5,"<"&MONTH(TODAY()),$H$6:$AO$6,"REAL 25") | AS15: =SUMIFS($I15:$AP15,$I$5:$AP$5,"<"&MONTH(TODAY()),$I$6:$AP$6,"ORÇADO ") | AT15: =SUMIFS($J15:$AQ15,$J$5:$AQ$5,"<"&MONTH(TODAY()),$J$6:$AQ$6,"REAL 26") | AU15: =SUM(H15,K15,N15,Q15,T15,W15,Z15,AC15,AF15,AI15,AL15,AO15) | AV15: =SUM(I15,L15,O15,R15,U15,X15,AA15,AD15,AG15,AJ15,AM15,AP15) | AW15: =SUM(J15,M15,P15,S15,V15,Y15,AB15,AE15,AH15,AK15,AN15,AQ15) | AX15: =SUM(H15,K15,N15) | AY15: =SUM(I15,L15,O15) | AZ15: =SUM(J15,M15,P15) | BA15: =SUM(Q15,T15,W15) | BB15: =SUM(R15,U15,X15) | BC15: =SUM(S15,V15,Y15) | BD15: =SUM(Z15,AC15,AF15) | BE15: =SUM(AA15,AD15,AG15) | BF15: =SUM(AB15,AE15,AH15) | BG15: =SUM(AI15,AL15,AO15) | BH15: =SUM(AJ15,AM15,AP15) | BI15: =SUM(AK15,AN15,AQ15)
A16: Eventos Locações | C16: Estim. Mensal | D16: Preencher base de Eventos | I16: =SUMIFS(T_ORCAMENTOS!$E:$E,T_ORCAMENTOS!$C:$C,"Eventos Locações",T_ORCAMENTOS!$H:$H,"1/2026") | J16: =SUMIFS(BD_Eventos_Novo!$L:$L,BD_Eventos_Novo!$AB:$AB,DRE!H$4)+SUMIFS(BD_Eventos_Novo!$P:$P,BD_Eventos_Novo!$AB:$AB,DRE!H$4)+SUMIFS(BD_Eventos_Novo!$Q:$Q,BD_Eventos_Novo!$AB:$AB,DRE!H$4)+SUMIFS(BD_Eventos_Novo!$R:$R,BD_Eventos_Novo!$AB:$AB,DRE!H$4)+SUMIFS(BD_Eventos_Novo!$S:$S,BD_Eventos_Novo!$AB:$AB,DRE!H$4)+SUMIFS(BD_Eventos_Novo!$T:$T,BD_Eventos_Novo!$AB:$AB,DRE!H$4)+SUMIFS(BD_Eventos_Novo!$U:$U,BD_Eventos_Novo!$AB:$AB,DRE!H$4)+SUMIFS(BD_Eventos_Novo!$V:$V,BD_Eventos_Novo!$AB:$AB,DRE!H$4)+SUMIFS(BD_Eventos_Novo!$W:$W,BD_Eventos_Novo!$AB:$AB,DRE!H$4)+SUMIFS(BD_Eventos_Novo!$X:$X,BD_Eventos_Novo!$AB:$AB,DRE!H$4)+SUMIFS(Aut_Ajustes_Manuais!$G:$G,Aut_Ajustes_Manuais!$I:$I,DRE!H$4,Aut_Ajustes_Manuais!$F:$F,"Eventos Locações") | L16: =SUMIFS(T_ORCAMENTOS!$E:$E,T_ORCAMENTOS!$C:$C,"Eventos Locações",T_ORCAMENTOS!$H:$H,"2/2026") | M16: =SUMIFS(BD_Eventos_Novo!$L:$L,BD_Eventos_Novo!$AB:$AB,DRE!K$4)+SUMIFS(BD_Eventos_Novo!$P:$P,BD_Eventos_Novo!$AB:$AB,DRE!K$4)+SUMIFS(BD_Eventos_Novo!$Q:$Q,BD_Eventos_Novo!$AB:$AB,DRE!K$4)+SUMIFS(BD_Eventos_Novo!$R:$R,BD_Eventos_Novo!$AB:$AB,DRE!K$4)+SUMIFS(BD_Eventos_Novo!$S:$S,BD_Eventos_Novo!$AB:$AB,DRE!K$4)+SUMIFS(BD_Eventos_Novo!$T:$T,BD_Eventos_Novo!$AB:$AB,DRE!K$4)+SUMIFS(BD_Eventos_Novo!$U:$U,BD_Eventos_Novo!$AB:$AB,DRE!K$4)+SUMIFS(BD_Eventos_Novo!$V:$V,BD_Eventos_Novo!$AB:$AB,DRE!K$4)+SUMIFS(BD_Eventos_Novo!$W:$W,BD_Eventos_Novo!$AB:$AB,DRE!K$4)+SUMIFS(BD_Eventos_Novo!$X:$X,BD_Eventos_Novo!$AB:$AB,DRE!K$4)+SUMIFS(Aut_Ajustes_Manuais!$G:$G,Aut_Ajustes_Manuais!$I:$I,DRE!K$4,Aut_Ajustes_Manuais!$F:$F,"Eventos Locações") | O16: =SUMIFS(T_ORCAMENTOS!$E:$E,T_ORCAMENTOS!$C:$C,"Eventos Locações",T_ORCAMENTOS!$H:$H,"3/2026") | P16: =SUMIFS(BD_Eventos_Novo!$L:$L,BD_Eventos_Novo!$AB:$AB,DRE!N$4)+SUMIFS(BD_Eventos_Novo!$P:$P,BD_Eventos_Novo!$AB:$AB,DRE!N$4)+SUMIFS(BD_Eventos_Novo!$Q:$Q,BD_Eventos_Novo!$AB:$AB,DRE!N$4)+SUMIFS(BD_Eventos_Novo!$R:$R,BD_Eventos_Novo!$AB:$AB,DRE!N$4)+SUMIFS(BD_Eventos_Novo!$S:$S,BD_Eventos_Novo!$AB:$AB,DRE!N$4)+SUMIFS(BD_Eventos_Novo!$T:$T,BD_Eventos_Novo!$AB:$AB,DRE!N$4)+SUMIFS(BD_Eventos_Novo!$U:$U,BD_Eventos_Novo!$AB:$AB,DRE!N$4)+SUMIFS(BD_Eventos_Novo!$V:$V,BD_Eventos_Novo!$AB:$AB,DRE!N$4)+SUMIFS(BD_Eventos_Novo!$W:$W,BD_Eventos_Novo!$AB:$AB,DRE!N$4)+SUMIFS(BD_Eventos_Novo!$X:$X,BD_Eventos_Novo!$AB:$AB,DRE!N$4)+SUMIFS(Aut_Ajustes_Manuais!$G:$G,Aut_Ajustes_Manuais!$I:$I,DRE!N$4,Aut_Ajustes_Manuais!$F:$F,"Eventos Locações") | R16: =SUMIFS(T_ORCAMENTOS!$E:$E,T_ORCAMENTOS!$C:$C,"Eventos Locações",T_ORCAMENTOS!$H:$H,"4/2026") | S16: =SUMIFS(BD_Eventos_Novo!$L:$L,BD_Eventos_Novo!$AB:$AB,DRE!Q$4)+SUMIFS(BD_Eventos_Novo!$P:$P,BD_Eventos_Novo!$AB:$AB,DRE!Q$4)+SUMIFS(BD_Eventos_Novo!$Q:$Q,BD_Eventos_Novo!$AB:$AB,DRE!Q$4)+SUMIFS(BD_Eventos_Novo!$R:$R,BD_Eventos_Novo!$AB:$AB,DRE!Q$4)+SUMIFS(BD_Eventos_Novo!$S:$S,BD_Eventos_Novo!$AB:$AB,DRE!Q$4)+SUMIFS(BD_Eventos_Novo!$T:$T,BD_Eventos_Novo!$AB:$AB,DRE!Q$4)+SUMIFS(BD_Eventos_Novo!$U:$U,BD_Eventos_Novo!$AB:$AB,DRE!Q$4)+SUMIFS(BD_Eventos_Novo!$V:$V,BD_Eventos_Novo!$AB:$AB,DRE!Q$4)+SUMIFS(BD_Eventos_Novo!$W:$W,BD_Eventos_Novo!$AB:$AB,DRE!Q$4)+SUMIFS(BD_Eventos_Novo!$X:$X,BD_Eventos_Novo!$AB:$AB,DRE!Q$4)+SUMIFS(Aut_Ajustes_Manuais!$G:$G,Aut_Ajustes_Manuais!$I:$I,DRE!Q$4,Aut_Ajustes_Manuais!$F:$F,"Eventos Locações") | U16: =SUMIFS(T_ORCAMENTOS!$E:$E,T_ORCAMENTOS!$C:$C,"Eventos Locações",T_ORCAMENTOS!$H:$H,"5/2026") | V16: =SUMIFS(BD_Eventos_Novo!$L:$L,BD_Eventos_Novo!$AB:$AB,DRE!T$4)+SUMIFS(BD_Eventos_Novo!$P:$P,BD_Eventos_Novo!$AB:$AB,DRE!T$4)+SUMIFS(BD_Eventos_Novo!$Q:$Q,BD_Eventos_Novo!$AB:$AB,DRE!T$4)+SUMIFS(BD_Eventos_Novo!$R:$R,BD_Eventos_Novo!$AB:$AB,DRE!T$4)+SUMIFS(BD_Eventos_Novo!$S:$S,BD_Eventos_Novo!$AB:$AB,DRE!T$4)+SUMIFS(BD_Eventos_Novo!$T:$T,BD_Eventos_Novo!$AB:$AB,DRE!T$4)+SUMIFS(BD_Eventos_Novo!$U:$U,BD_Eventos_Novo!$AB:$AB,DRE!T$4)+SUMIFS(BD_Eventos_Novo!$V:$V,BD_Eventos_Novo!$AB:$AB,DRE!T$4)+SUMIFS(BD_Eventos_Novo!$W:$W,BD_Eventos_Novo!$AB:$AB,DRE!T$4)+SUMIFS(BD_Eventos_Novo!$X:$X,BD_Eventos_Novo!$AB:$AB,DRE!T$4)+SUMIFS(Aut_Ajustes_Manuais!$G:$G,Aut_Ajustes_Manuais!$I:$I,DRE!T$4,Aut_Ajustes_Manuais!$F:$F,"Eventos Locações") | X16: =SUMIFS(T_ORCAMENTOS!$E:$E,T_ORCAMENTOS!$C:$C,"Eventos Locações",T_ORCAMENTOS!$H:$H,"6/2026") | Y16: =SUMIFS(BD_Eventos_Novo!$L:$L,BD_Eventos_Novo!$AB:$AB,DRE!W$4)+SUMIFS(BD_Eventos_Novo!$P:$P,BD_Eventos_Novo!$AB:$AB,DRE!W$4)+SUMIFS(BD_Eventos_Novo!$Q:$Q,BD_Eventos_Novo!$AB:$AB,DRE!W$4)+SUMIFS(BD_Eventos_Novo!$R:$R,BD_Eventos_Novo!$AB:$AB,DRE!W$4)+SUMIFS(BD_Eventos_Novo!$S:$S,BD_Eventos_Novo!$AB:$AB,DRE!W$4)+SUMIFS(BD_Eventos_Novo!$T:$T,BD_Eventos_Novo!$AB:$AB,DRE!W$4)+SUMIFS(BD_Eventos_Novo!$U:$U,BD_Eventos_Novo!$AB:$AB,DRE!W$4)+SUMIFS(BD_Eventos_Novo!$V:$V,BD_Eventos_Novo!$AB:$AB,DRE!W$4)+SUMIFS(BD_Eventos_Novo!$W:$W,BD_Eventos_Novo!$AB:$AB,DRE!W$4)+SUMIFS(BD_Eventos_Novo!$X:$X,BD_Eventos_Novo!$AB:$AB,DRE!W$4)+SUMIFS(Aut_Ajustes_Manuais!$G:$G,Aut_Ajustes_Manuais!$I:$I,DRE!W$4,Aut_Ajustes_Manuais!$F:$F,"Eventos Locações") | AA16: =SUMIFS(T_ORCAMENTOS!$E:$E,T_ORCAMENTOS!$C:$C,"Eventos Locações",T_ORCAMENTOS!$H:$H,"7/2026") | AB16: =SUMIFS(BD_Eventos_Novo!$L:$L,BD_Eventos_Novo!$AB:$AB,DRE!Z$4)+SUMIFS(BD_Eventos_Novo!$P:$P,BD_Eventos_Novo!$AB:$AB,DRE!Z$4)+SUMIFS(BD_Eventos_Novo!$Q:$Q,BD_Eventos_Novo!$AB:$AB,DRE!Z$4)+SUMIFS(BD_Eventos_Novo!$R:$R,BD_Eventos_Novo!$AB:$AB,DRE!Z$4)+SUMIFS(BD_Eventos_Novo!$S:$S,BD_Eventos_Novo!$AB:$AB,DRE!Z$4)+SUMIFS(BD_Eventos_Novo!$T:$T,BD_Eventos_Novo!$AB:$AB,DRE!Z$4)+SUMIFS(BD_Eventos_Novo!$U:$U,BD_Eventos_Novo!$AB:$AB,DRE!Z$4)+SUMIFS(BD_Eventos_Novo!$V:$V,BD_Eventos_Novo!$AB:$AB,DRE!Z$4)+SUMIFS(BD_Eventos_Novo!$W:$W,BD_Eventos_Novo!$AB:$AB,DRE!Z$4)+SUMIFS(BD_Eventos_Novo!$X:$X,BD_Eventos_Novo!$AB:$AB,DRE!Z$4)+SUMIFS(Aut_Ajustes_Manuais!$G:$G,Aut_Ajustes_Manuais!$I:$I,DRE!Z$4,Aut_Ajustes_Manuais!$F:$F,"Eventos Locações") | AD16: =SUMIFS(T_ORCAMENTOS!$E:$E,T_ORCAMENTOS!$C:$C,"Eventos Locações",T_ORCAMENTOS!$H:$H,"8/2026") | AE16: =SUMIFS(BD_Eventos_Novo!$L:$L,BD_Eventos_Novo!$AB:$AB,DRE!AC$4)+SUMIFS(BD_Eventos_Novo!$P:$P,BD_Eventos_Novo!$AB:$AB,DRE!AC$4)+SUMIFS(BD_Eventos_Novo!$Q:$Q,BD_Eventos_Novo!$AB:$AB,DRE!AC$4)+SUMIFS(BD_Eventos_Novo!$R:$R,BD_Eventos_Novo!$AB:$AB,DRE!AC$4)+SUMIFS(BD_Eventos_Novo!$S:$S,BD_Eventos_Novo!$AB:$AB,DRE!AC$4)+SUMIFS(BD_Eventos_Novo!$T:$T,BD_Eventos_Novo!$AB:$AB,DRE!AC$4)+SUMIFS(BD_Eventos_Novo!$U:$U,BD_Eventos_Novo!$AB:$AB,DRE!AC$4)+SUMIFS(BD_Eventos_Novo!$V:$V,BD_Eventos_Novo!$AB:$AB,DRE!AC$4)+SUMIFS(BD_Eventos_Novo!$W:$W,BD_Eventos_Novo!$AB:$AB,DRE!AC$4)+SUMIFS(BD_Eventos_Novo!$X:$X,BD_Eventos_Novo!$AB:$AB,DRE!AC$4)+SUMIFS(Aut_Ajustes_Manuais!$G:$G,Aut_Ajustes_Manuais!$I:$I,DRE!AC$4,Aut_Ajustes_Manuais!$F:$F,"Eventos Locações") | AG16: =SUMIFS(T_ORCAMENTOS!$E:$E,T_ORCAMENTOS!$C:$C,"Eventos Locações",T_ORCAMENTOS!$H:$H,"9/2026") | AH16: =SUMIFS(BD_Eventos_Novo!$L:$L,BD_Eventos_Novo!$AB:$AB,DRE!AF$4)+SUMIFS(BD_Eventos_Novo!$P:$P,BD_Eventos_Novo!$AB:$AB,DRE!AF$4)+SUMIFS(BD_Eventos_Novo!$Q:$Q,BD_Eventos_Novo!$AB:$AB,DRE!AF$4)+SUMIFS(BD_Eventos_Novo!$R:$R,BD_Eventos_Novo!$AB:$AB,DRE!AF$4)+SUMIFS(BD_Eventos_Novo!$S:$S,BD_Eventos_Novo!$AB:$AB,DRE!AF$4)+SUMIFS(BD_Eventos_Novo!$T:$T,BD_Eventos_Novo!$AB:$AB,DRE!AF$4)+SUMIFS(BD_Eventos_Novo!$U:$U,BD_Eventos_Novo!$AB:$AB,DRE!AF$4)+SUMIFS(BD_Eventos_Novo!$V:$V,BD_Eventos_Novo!$AB:$AB,DRE!AF$4)+SUMIFS(BD_Eventos_Novo!$W:$W,BD_Eventos_Novo!$AB:$AB,DRE!AF$4)+SUMIFS(BD_Eventos_Novo!$X:$X,BD_Eventos_Novo!$AB:$AB,DRE!AF$4)+SUMIFS(Aut_Ajustes_Manuais!$G:$G,Aut_Ajustes_Manuais!$I:$I,DRE!AF$4,Aut_Ajustes_Manuais!$F:$F,"Eventos Locações") | AJ16: =SUMIFS(T_ORCAMENTOS!$E:$E,T_ORCAMENTOS!$C:$C,"Eventos Locações",T_ORCAMENTOS!$H:$H,"10/2026") | AK16: =SUMIFS(BD_Eventos_Novo!$L:$L,BD_Eventos_Novo!$AB:$AB,DRE!AI$4)+SUMIFS(BD_Eventos_Novo!$P:$P,BD_Eventos_Novo!$AB:$AB,DRE!AI$4)+SUMIFS(BD_Eventos_Novo!$Q:$Q,BD_Eventos_Novo!$AB:$AB,DRE!AI$4)+SUMIFS(BD_Eventos_Novo!$R:$R,BD_Eventos_Novo!$AB:$AB,DRE!AI$4)+SUMIFS(BD_Eventos_Novo!$S:$S,BD_Eventos_Novo!$AB:$AB,DRE!AI$4)+SUMIFS(BD_Eventos_Novo!$T:$T,BD_Eventos_Novo!$AB:$AB,DRE!AI$4)+SUMIFS(BD_Eventos_Novo!$U:$U,BD_Eventos_Novo!$AB:$AB,DRE!AI$4)+SUMIFS(BD_Eventos_Novo!$V:$V,BD_Eventos_Novo!$AB:$AB,DRE!AI$4)+SUMIFS(BD_Eventos_Novo!$W:$W,BD_Eventos_Novo!$AB:$AB,DRE!AI$4)+SUMIFS(BD_Eventos_Novo!$X:$X,BD_Eventos_Novo!$AB:$AB,DRE!AI$4)+SUMIFS(Aut_Ajustes_Manuais!$G:$G,Aut_Ajustes_Manuais!$I:$I,DRE!AI$4,Aut_Ajustes_Manuais!$F:$F,"Eventos Locações") | AM16: =SUMIFS(T_ORCAMENTOS!$E:$E,T_ORCAMENTOS!$C:$C,"Eventos Locações",T_ORCAMENTOS!$H:$H,"11/2026") | AN16: =SUMIFS(BD_Eventos_Novo!$L:$L,BD_Eventos_Novo!$AB:$AB,DRE!AL$4)+SUMIFS(BD_Eventos_Novo!$P:$P,BD_Eventos_Novo!$AB:$AB,DRE!AL$4)+SUMIFS(BD_Eventos_Novo!$Q:$Q,BD_Eventos_Novo!$AB:$AB,DRE!AL$4)+SUMIFS(BD_Eventos_Novo!$R:$R,BD_Eventos_Novo!$AB:$AB,DRE!AL$4)+SUMIFS(BD_Eventos_Novo!$S:$S,BD_Eventos_Novo!$AB:$AB,DRE!AL$4)+SUMIFS(BD_Eventos_Novo!$T:$T,BD_Eventos_Novo!$AB:$AB,DRE!AL$4)+SUMIFS(BD_Eventos_Novo!$U:$U,BD_Eventos_Novo!$AB:$AB,DRE!AL$4)+SUMIFS(BD_Eventos_Novo!$V:$V,BD_Eventos_Novo!$AB:$AB,DRE!AL$4)+SUMIFS(BD_Eventos_Novo!$W:$W,BD_Eventos_Novo!$AB:$AB,DRE!AL$4)+SUMIFS(BD_Eventos_Novo!$X:$X,BD_Eventos_Novo!$AB:$AB,DRE!AL$4)+SUMIFS(Aut_Ajustes_Manuais!$G:$G,Aut_Ajustes_Manuais!$I:$I,DRE!AL$4,Aut_Ajustes_Manuais!$F:$F,"Eventos Locações") | AP16: =SUMIFS(T_ORCAMENTOS!$E:$E,T_ORCAMENTOS!$C:$C,"Eventos Locações",T_ORCAMENTOS!$H:$H,"12/2026") | AQ16: =SUMIFS(BD_Eventos_Novo!$L:$L,BD_Eventos_Novo!$AB:$AB,DRE!AO$4)+SUMIFS(BD_Eventos_Novo!$P:$P,BD_Eventos_Novo!$AB:$AB,DRE!AO$4)+SUMIFS(BD_Eventos_Novo!$Q:$Q,BD_Eventos_Novo!$AB:$AB,DRE!AO$4)+SUMIFS(BD_Eventos_Novo!$R:$R,BD_Eventos_Novo!$AB:$AB,DRE!AO$4)+SUMIFS(BD_Eventos_Novo!$S:$S,BD_Eventos_Novo!$AB:$AB,DRE!AO$4)+SUMIFS(BD_Eventos_Novo!$T:$T,BD_Eventos_Novo!$AB:$AB,DRE!AO$4)+SUMIFS(BD_Eventos_Novo!$U:$U,BD_Eventos_Novo!$AB:$AB,DRE!AO$4)+SUMIFS(BD_Eventos_Novo!$V:$V,BD_Eventos_Novo!$AB:$AB,DRE!AO$4)+SUMIFS(BD_Eventos_Novo!$W:$W,BD_Eventos_Novo!$AB:$AB,DRE!AO$4)+SUMIFS(BD_Eventos_Novo!$X:$X,BD_Eventos_Novo!$AB:$AB,DRE!AO$4)+SUMIFS(Aut_Ajustes_Manuais!$G:$G,Aut_Ajustes_Manuais!$I:$I,DRE!AO$4,Aut_Ajustes_Manuais!$F:$F,"Eventos Locações") | AR16: =SUMIFS($H16:$AO16,$H$5:$AO$5,"<"&MONTH(TODAY()),$H$6:$AO$6,"REAL 25") | AS16: =SUMIFS($I16:$AP16,$I$5:$AP$5,"<"&MONTH(TODAY()),$I$6:$AP$6,"ORÇADO ") | AT16: =SUMIFS($J16:$AQ16,$J$5:$AQ$5,"<"&MONTH(TODAY()),$J$6:$AQ$6,"REAL 26") | AU16: =SUM(H16,K16,N16,Q16,T16,W16,Z16,AC16,AF16,AI16,AL16,AO16) | AV16: =SUM(I16,L16,O16,R16,U16,X16,AA16,AD16,AG16,AJ16,AM16,AP16) | AW16: =SUM(J16,M16,P16,S16,V16,Y16,AB16,AE16,AH16,AK16,AN16,AQ16) | AX16: =SUM(H16,K16,N16) | AY16: =SUM(I16,L16,O16) | AZ16: =SUM(J16,M16,P16) | BA16: =SUM(Q16,T16,W16) | BB16: =SUM(R16,U16,X16) | BC16: =SUM(S16,V16,Y16) | BD16: =SUM(Z16,AC16,AF16) | BE16: =SUM(AA16,AD16,AG16) | BF16: =SUM(AB16,AE16,AH16) | BG16: =SUM(AI16,AL16,AO16) | BH16: =SUM(AJ16,AM16,AP16) | BI16: =SUM(AK16,AN16,AQ16)
A17: Eventos Rebate Fornecedores - Premium Corp | C17: Estim. Mensal | D17: Comissão sobre venda dos fornecedores homologados | I17: =SUMIFS(T_ORCAMENTOS!$E:$E,T_ORCAMENTOS!$C:$C,"Eventos Rebate Fornecedores",T_ORCAMENTOS!$H:$H,"1/2026") | J17: =SUMIFS(Aut_Ajustes_Manuais!$G:$G,Aut_Ajustes_Manuais!$I:$I,DRE!H$4,Aut_Ajustes_Manuais!$F:$F,"Eventos Rebate Fornecedores - Premium Corp") | L17: =SUMIFS(T_ORCAMENTOS!$E:$E,T_ORCAMENTOS!$C:$C,"Eventos Rebate Fornecedores",T_ORCAMENTOS!$H:$H,"2/2026") | M17: =SUMIFS(Aut_Ajustes_Manuais!$G:$G,Aut_Ajustes_Manuais!$I:$I,DRE!K$4,Aut_Ajustes_Manuais!$F:$F,"Eventos Rebate Fornecedores - Premium Corp") | O17: =SUMIFS(T_ORCAMENTOS!$E:$E,T_ORCAMENTOS!$C:$C,"Eventos Rebate Fornecedores",T_ORCAMENTOS!$H:$H,"3/2026") | P17: =SUMIFS(Aut_Ajustes_Manuais!$G:$G,Aut_Ajustes_Manuais!$I:$I,DRE!N$4,Aut_Ajustes_Manuais!$F:$F,"Eventos Rebate Fornecedores - Premium Corp") | R17: =SUMIFS(T_ORCAMENTOS!$E:$E,T_ORCAMENTOS!$C:$C,"Eventos Rebate Fornecedores",T_ORCAMENTOS!$H:$H,"4/2026") | S17: =SUMIFS(Aut_Ajustes_Manuais!$G:$G,Aut_Ajustes_Manuais!$I:$I,DRE!Q$4,Aut_Ajustes_Manuais!$F:$F,"Eventos Rebate Fornecedores - Premium Corp") | U17: =SUMIFS(T_ORCAMENTOS!$E:$E,T_ORCAMENTOS!$C:$C,"Eventos Rebate Fornecedores",T_ORCAMENTOS!$H:$H,"5/2026") | V17: =SUMIFS(Aut_Ajustes_Manuais!$G:$G,Aut_Ajustes_Manuais!$I:$I,DRE!T$4,Aut_Ajustes_Manuais!$F:$F,"Eventos Rebate Fornecedores - Premium Corp") | X17: =SUMIFS(T_ORCAMENTOS!$E:$E,T_ORCAMENTOS!$C:$C,"Eventos Rebate Fornecedores",T_ORCAMENTOS!$H:$H,"6/2026") | Y17: =SUMIFS(Aut_Ajustes_Manuais!$G:$G,Aut_Ajustes_Manuais!$I:$I,DRE!W$4,Aut_Ajustes_Manuais!$F:$F,"Eventos Rebate Fornecedores - Premium Corp") | AA17: =SUMIFS(T_ORCAMENTOS!$E:$E,T_ORCAMENTOS!$C:$C,"Eventos Rebate Fornecedores",T_ORCAMENTOS!$H:$H,"7/2026") | AB17: =SUMIFS(Aut_Ajustes_Manuais!$G:$G,Aut_Ajustes_Manuais!$I:$I,DRE!Z$4,Aut_Ajustes_Manuais!$F:$F,"Eventos Rebate Fornecedores - Premium Corp") | AD17: =SUMIFS(T_ORCAMENTOS!$E:$E,T_ORCAMENTOS!$C:$C,"Eventos Rebate Fornecedores",T_ORCAMENTOS!$H:$H,"8/2026") | AE17: =SUMIFS(Aut_Ajustes_Manuais!$G:$G,Aut_Ajustes_Manuais!$I:$I,DRE!AC$4,Aut_Ajustes_Manuais!$F:$F,"Eventos Rebate Fornecedores - Premium Corp") | AG17: =SUMIFS(T_ORCAMENTOS!$E:$E,T_ORCAMENTOS!$C:$C,"Eventos Rebate Fornecedores",T_ORCAMENTOS!$H:$H,"9/2026") | AH17: =SUMIFS(Aut_Ajustes_Manuais!$G:$G,Aut_Ajustes_Manuais!$I:$I,DRE!AF$4,Aut_Ajustes_Manuais!$F:$F,"Eventos Rebate Fornecedores - Premium Corp") | AJ17: =SUMIFS(T_ORCAMENTOS!$E:$E,T_ORCAMENTOS!$C:$C,"Eventos Rebate Fornecedores",T_ORCAMENTOS!$H:$H,"10/2026") | AK17: =SUMIFS(Aut_Ajustes_Manuais!$G:$G,Aut_Ajustes_Manuais!$I:$I,DRE!AI$4,Aut_Ajustes_Manuais!$F:$F,"Eventos Rebate Fornecedores - Premium Corp") | AM17: =SUMIFS(T_ORCAMENTOS!$E:$E,T_ORCAMENTOS!$C:$C,"Eventos Rebate Fornecedores",T_ORCAMENTOS!$H:$H,"11/2026") | AN17: =SUMIFS(Aut_Ajustes_Manuais!$G:$G,Aut_Ajustes_Manuais!$I:$I,DRE!AL$4,Aut_Ajustes_Manuais!$F:$F,"Eventos Rebate Fornecedores - Premium Corp") | AP17: =SUMIFS(T_ORCAMENTOS!$E:$E,T_ORCAMENTOS!$C:$C,"Eventos Rebate Fornecedores",T_ORCAMENTOS!$H:$H,"12/2026") | AQ17: =SUMIFS(Aut_Ajustes_Manuais!$G:$G,Aut_Ajustes_Manuais!$I:$I,DRE!AO$4,Aut_Ajustes_Manuais!$F:$F,"Eventos Rebate Fornecedores - Premium Corp") | AR17: =SUMIFS($H17:$AO17,$H$5:$AO$5,"<"&MONTH(TODAY()),$H$6:$AO$6,"REAL 25") | AS17: =SUMIFS($I17:$AP17,$I$5:$AP$5,"<"&MONTH(TODAY()),$I$6:$AP$6,"ORÇADO ") | AT17: =SUMIFS($J17:$AQ17,$J$5:$AQ$5,"<"&MONTH(TODAY()),$J$6:$AQ$6,"REAL 26") | AU17: =SUM(H17,K17,N17,Q17,T17,W17,Z17,AC17,AF17,AI17,AL17,AO17) | AV17: =SUM(I17,L17,O17,R17,U17,X17,AA17,AD17,AG17,AJ17,AM17,AP17) | AW17: =SUM(J17,M17,P17,S17,V17,Y17,AB17,AE17,AH17,AK17,AN17,AQ17) | AX17: =SUM(H17,K17,N17) | AY17: =SUM(I17,L17,O17) | AZ17: =SUM(J17,M17,P17) | BA17: =SUM(Q17,T17,W17) | BB17: =SUM(R17,U17,X17) | BC17: =SUM(S17,V17,Y17) | BD17: =SUM(Z17,AC17,AF17) | BE17: =SUM(AA17,AD17,AG17) | BF17: =SUM(AB17,AE17,AH17) | BG17: =SUM(AI17,AL17,AO17) | BH17: =SUM(AJ17,AM17,AP17) | BI17: =SUM(AK17,AN17,AQ17)
A18: Membership | C18: Estim. Mensal | D18: Preencher base de Delivery | I18: =SUMIFS(T_ORCAMENTOS!$E:$E,T_ORCAMENTOS!$C:$C,"Membership",T_ORCAMENTOS!$H:$H,"1/2026") | J18: =SUMIFS(Aut_Ajustes_Manuais!$G:$G,Aut_Ajustes_Manuais!$I:$I,DRE!H$4,Aut_Ajustes_Manuais!$F:$F,"Membership") | L18: =SUMIFS(T_ORCAMENTOS!$E:$E,T_ORCAMENTOS!$C:$C,"Membership",T_ORCAMENTOS!$H:$H,"2/2026") | M18: =SUMIFS(Aut_Ajustes_Manuais!$G:$G,Aut_Ajustes_Manuais!$I:$I,DRE!K$4,Aut_Ajustes_Manuais!$F:$F,"Membership") | O18: =SUMIFS(T_ORCAMENTOS!$E:$E,T_ORCAMENTOS!$C:$C,"Membership",T_ORCAMENTOS!$H:$H,"3/2026") | P18: =SUMIFS(Aut_Ajustes_Manuais!$G:$G,Aut_Ajustes_Manuais!$I:$I,DRE!N$4,Aut_Ajustes_Manuais!$F:$F,"Membership") | R18: =SUMIFS(T_ORCAMENTOS!$E:$E,T_ORCAMENTOS!$C:$C,"Membership",T_ORCAMENTOS!$H:$H,"4/2026") | S18: =SUMIFS(Aut_Ajustes_Manuais!$G:$G,Aut_Ajustes_Manuais!$I:$I,DRE!Q$4,Aut_Ajustes_Manuais!$F:$F,"Membership") | U18: =SUMIFS(T_ORCAMENTOS!$E:$E,T_ORCAMENTOS!$C:$C,"Membership",T_ORCAMENTOS!$H:$H,"5/2026") | V18: =SUMIFS(Aut_Ajustes_Manuais!$G:$G,Aut_Ajustes_Manuais!$I:$I,DRE!T$4,Aut_Ajustes_Manuais!$F:$F,"Membership") | X18: =SUMIFS(T_ORCAMENTOS!$E:$E,T_ORCAMENTOS!$C:$C,"Membership",T_ORCAMENTOS!$H:$H,"6/2026") | Y18: =SUMIFS(Aut_Ajustes_Manuais!$G:$G,Aut_Ajustes_Manuais!$I:$I,DRE!W$4,Aut_Ajustes_Manuais!$F:$F,"Membership") | AA18: =SUMIFS(T_ORCAMENTOS!$E:$E,T_ORCAMENTOS!$C:$C,"Membership",T_ORCAMENTOS!$H:$H,"7/2026") | AB18: =SUMIFS(Aut_Ajustes_Manuais!$G:$G,Aut_Ajustes_Manuais!$I:$I,DRE!Z$4,Aut_Ajustes_Manuais!$F:$F,"Membership") | AD18: =SUMIFS(T_ORCAMENTOS!$E:$E,T_ORCAMENTOS!$C:$C,"Membership",T_ORCAMENTOS!$H:$H,"8/2026") | AE18: =SUMIFS(Aut_Ajustes_Manuais!$G:$G,Aut_Ajustes_Manuais!$I:$I,DRE!AC$4,Aut_Ajustes_Manuais!$F:$F,"Membership") | AG18: =SUMIFS(T_ORCAMENTOS!$E:$E,T_ORCAMENTOS!$C:$C,"Membership",T_ORCAMENTOS!$H:$H,"9/2026") | AH18: =SUMIFS(Aut_Ajustes_Manuais!$G:$G,Aut_Ajustes_Manuais!$I:$I,DRE!AF$4,Aut_Ajustes_Manuais!$F:$F,"Membership") | AJ18: =SUMIFS(T_ORCAMENTOS!$E:$E,T_ORCAMENTOS!$C:$C,"Membership",T_ORCAMENTOS!$H:$H,"10/2026") | AK18: =SUMIFS(Aut_Ajustes_Manuais!$G:$G,Aut_Ajustes_Manuais!$I:$I,DRE!AI$4,Aut_Ajustes_Manuais!$F:$F,"Membership") | AM18: =SUMIFS(T_ORCAMENTOS!$E:$E,T_ORCAMENTOS!$C:$C,"Membership",T_ORCAMENTOS!$H:$H,"11/2026") | AN18: =SUMIFS(Aut_Ajustes_Manuais!$G:$G,Aut_Ajustes_Manuais!$I:$I,DRE!AL$4,Aut_Ajustes_Manuais!$F:$F,"Membership") | AP18: =SUMIFS(T_ORCAMENTOS!$E:$E,T_ORCAMENTOS!$C:$C,"Membership",T_ORCAMENTOS!$H:$H,"12/2026") | AQ18: =SUMIFS(Aut_Ajustes_Manuais!$G:$G,Aut_Ajustes_Manuais!$I:$I,DRE!AO$4,Aut_Ajustes_Manuais!$F:$F,"Membership") | AR18: =SUMIFS($H18:$AO18,$H$5:$AO$5,"<"&MONTH(TODAY()),$H$6:$AO$6,"REAL 25") | AS18: =SUMIFS($I18:$AP18,$I$5:$AP$5,"<"&MONTH(TODAY()),$I$6:$AP$6,"ORÇADO ") | AT18: =SUMIFS($J18:$AQ18,$J$5:$AQ$5,"<"&MONTH(TODAY()),$J$6:$AQ$6,"REAL 26") | AU18: =SUM(H18,K18,N18,Q18,T18,W18,Z18,AC18,AF18,AI18,AL18,AO18) | AV18: =SUM(I18,L18,O18,R18,U18,X18,AA18,AD18,AG18,AJ18,AM18,AP18) | AW18: =SUM(J18,M18,P18,S18,V18,Y18,AB18,AE18,AH18,AK18,AN18,AQ18) | AX18: =SUM(H18,K18,N18) | AY18: =SUM(I18,L18,O18) | AZ18: =SUM(J18,M18,P18) | BA18: =SUM(Q18,T18,W18) | BB18: =SUM(R18,U18,X18) | BC18: =SUM(S18,V18,Y18) | BD18: =SUM(Z18,AC18,AF18) | BE18: =SUM(AA18,AD18,AG18) | BF18: =SUM(AB18,AE18,AH18) | BG18: =SUM(AI18,AL18,AO18) | BH18: =SUM(AJ18,AM18,AP18) | BI18: =SUM(AK18,AN18,AQ18)
A19: Outras Receitas | C19: Estim. Mensal | D19: Coleta de Oleo e etc | I19: =SUMIFS(T_ORCAMENTOS!$E:$E,T_ORCAMENTOS!$C:$C,"Outras Receitas",T_ORCAMENTOS!$H:$H,"1/2026") | J19: =SUMIFS(Aut_Receitas_Extraord!$I:$I,Aut_Receitas_Extraord!$S:$S,DRE!H$4,Aut_Receitas_Extraord!$D:$D,"Coleta de Óleo")+SUMIFS(Aut_Ajustes_Manuais!$G:$G,Aut_Ajustes_Manuais!$I:$I,DRE!H$4,Aut_Ajustes_Manuais!$F:$F,"Outras Receitas ") | L19: =SUMIFS(T_ORCAMENTOS!$E:$E,T_ORCAMENTOS!$C:$C,"Outras Receitas",T_ORCAMENTOS!$H:$H,"2/2026") | M19: =SUMIFS(Aut_Receitas_Extraord!$I:$I,Aut_Receitas_Extraord!$S:$S,DRE!K$4,Aut_Receitas_Extraord!$D:$D,"Coleta de Óleo")+SUMIFS(Aut_Ajustes_Manuais!$G:$G,Aut_Ajustes_Manuais!$I:$I,DRE!K$4,Aut_Ajustes_Manuais!$F:$F,"Outras Receitas ") | O19: =SUMIFS(T_ORCAMENTOS!$E:$E,T_ORCAMENTOS!$C:$C,"Outras Receitas",T_ORCAMENTOS!$H:$H,"3/2026") | P19: =SUMIFS(Aut_Receitas_Extraord!$I:$I,Aut_Receitas_Extraord!$S:$S,DRE!N$4,Aut_Receitas_Extraord!$D:$D,"Coleta de Óleo")+SUMIFS(Aut_Ajustes_Manuais!$G:$G,Aut_Ajustes_Manuais!$I:$I,DRE!N$4,Aut_Ajustes_Manuais!$F:$F,"Outras Receitas ") | R19: =SUMIFS(T_ORCAMENTOS!$E:$E,T_ORCAMENTOS!$C:$C,"Outras Receitas",T_ORCAMENTOS!$H:$H,"4/2026") | S19: =SUMIFS(Aut_Receitas_Extraord!$I:$I,Aut_Receitas_Extraord!$S:$S,DRE!Q$4,Aut_Receitas_Extraord!$D:$D,"Coleta de Óleo")+SUMIFS(Aut_Ajustes_Manuais!$G:$G,Aut_Ajustes_Manuais!$I:$I,DRE!Q$4,Aut_Ajustes_Manuais!$F:$F,"Outras Receitas ") | U19: =SUMIFS(T_ORCAMENTOS!$E:$E,T_ORCAMENTOS!$C:$C,"Outras Receitas",T_ORCAMENTOS!$H:$H,"5/2026") | V19: =SUMIFS(Aut_Receitas_Extraord!$I:$I,Aut_Receitas_Extraord!$S:$S,DRE!T$4,Aut_Receitas_Extraord!$D:$D,"Coleta de Óleo")+SUMIFS(Aut_Ajustes_Manuais!$G:$G,Aut_Ajustes_Manuais!$I:$I,DRE!T$4,Aut_Ajustes_Manuais!$F:$F,"Outras Receitas ") | X19: =SUMIFS(T_ORCAMENTOS!$E:$E,T_ORCAMENTOS!$C:$C,"Outras Receitas",T_ORCAMENTOS!$H:$H,"6/2026") | Y19: =SUMIFS(Aut_Receitas_Extraord!$I:$I,Aut_Receitas_Extraord!$S:$S,DRE!W$4,Aut_Receitas_Extraord!$D:$D,"Coleta de Óleo")+SUMIFS(Aut_Ajustes_Manuais!$G:$G,Aut_Ajustes_Manuais!$I:$I,DRE!W$4,Aut_Ajustes_Manuais!$F:$F,"Outras Receitas ") | AA19: =SUMIFS(T_ORCAMENTOS!$E:$E,T_ORCAMENTOS!$C:$C,"Outras Receitas",T_ORCAMENTOS!$H:$H,"7/2026") | AB19: =SUMIFS(Aut_Receitas_Extraord!$I:$I,Aut_Receitas_Extraord!$S:$S,DRE!Z$4,Aut_Receitas_Extraord!$D:$D,"Coleta de Óleo")+SUMIFS(Aut_Ajustes_Manuais!$G:$G,Aut_Ajustes_Manuais!$I:$I,DRE!Z$4,Aut_Ajustes_Manuais!$F:$F,"Outras Receitas ") | AD19: =SUMIFS(T_ORCAMENTOS!$E:$E,T_ORCAMENTOS!$C:$C,"Outras Receitas",T_ORCAMENTOS!$H:$H,"8/2026") | AE19: =SUMIFS(Aut_Receitas_Extraord!$I:$I,Aut_Receitas_Extraord!$S:$S,DRE!AC$4,Aut_Receitas_Extraord!$D:$D,"Coleta de Óleo")+SUMIFS(Aut_Ajustes_Manuais!$G:$G,Aut_Ajustes_Manuais!$I:$I,DRE!AC$4,Aut_Ajustes_Manuais!$F:$F,"Outras Receitas ") | AG19: =SUMIFS(T_ORCAMENTOS!$E:$E,T_ORCAMENTOS!$C:$C,"Outras Receitas",T_ORCAMENTOS!$H:$H,"9/2026") | AH19: =SUMIFS(Aut_Receitas_Extraord!$I:$I,Aut_Receitas_Extraord!$S:$S,DRE!AF$4,Aut_Receitas_Extraord!$D:$D,"Coleta de Óleo")+SUMIFS(Aut_Ajustes_Manuais!$G:$G,Aut_Ajustes_Manuais!$I:$I,DRE!AF$4,Aut_Ajustes_Manuais!$F:$F,"Outras Receitas ") | AJ19: =SUMIFS(T_ORCAMENTOS!$E:$E,T_ORCAMENTOS!$C:$C,"Outras Receitas",T_ORCAMENTOS!$H:$H,"10/2026") | AK19: =SUMIFS(Aut_Receitas_Extraord!$I:$I,Aut_Receitas_Extraord!$S:$S,DRE!AI$4,Aut_Receitas_Extraord!$D:$D,"Coleta de Óleo")+SUMIFS(Aut_Ajustes_Manuais!$G:$G,Aut_Ajustes_Manuais!$I:$I,DRE!AI$4,Aut_Ajustes_Manuais!$F:$F,"Outras Receitas ") | AM19: =SUMIFS(T_ORCAMENTOS!$E:$E,T_ORCAMENTOS!$C:$C,"Outras Receitas",T_ORCAMENTOS!$H:$H,"11/2026") | AN19: =SUMIFS(Aut_Receitas_Extraord!$I:$I,Aut_Receitas_Extraord!$S:$S,DRE!AL$4,Aut_Receitas_Extraord!$D:$D,"Coleta de Óleo")+SUMIFS(Aut_Ajustes_Manuais!$G:$G,Aut_Ajustes_Manuais!$I:$I,DRE!AL$4,Aut_Ajustes_Manuais!$F:$F,"Outras Receitas ") | AP19: =SUMIFS(T_ORCAMENTOS!$E:$E,T_ORCAMENTOS!$C:$C,"Outras Receitas",T_ORCAMENTOS!$H:$H,"12/2026") | AQ19: =SUMIFS(Aut_Receitas_Extraord!$I:$I,Aut_Receitas_Extraord!$S:$S,DRE!AO$4,Aut_Receitas_Extraord!$D:$D,"Coleta de Óleo")+SUMIFS(Aut_Ajustes_Manuais!$G:$G,Aut_Ajustes_Manuais!$I:$I,DRE!AO$4,Aut_Ajustes_Manuais!$F:$F,"Outras Receitas ") | AR19: =SUMIFS($H19:$AO19,$H$5:$AO$5,"<"&MONTH(TODAY()),$H$6:$AO$6,"REAL 25") | AS19: =SUMIFS($I19:$AP19,$I$5:$AP$5,"<"&MONTH(TODAY()),$I$6:$AP$6,"ORÇADO ") | AT19: =SUMIFS($J19:$AQ19,$J$5:$AQ$5,"<"&MONTH(TODAY()),$J$6:$AQ$6,"REAL 26") | AU19: =SUM(H19,K19,N19,Q19,T19,W19,Z19,AC19,AF19,AI19,AL19,AO19) | AV19: =SUM(I19,L19,O19,R19,U19,X19,AA19,AD19,AG19,AJ19,AM19,AP19) | AW19: =SUM(J19,M19,P19,S19,V19,Y19,AB19,AE19,AH19,AK19,AN19,AQ19) | AX19: =SUM(H19,K19,N19) | AY19: =SUM(I19,L19,O19) | AZ19: =SUM(J19,M19,P19) | BA19: =SUM(Q19,T19,W19) | BB19: =SUM(R19,U19,X19) | BC19: =SUM(S19,V19,Y19) | BD19: =SUM(Z19,AC19,AF19) | BE19: =SUM(AA19,AD19,AG19) | BF19: =SUM(AB19,AE19,AH19) | BG19: =SUM(AI19,AL19,AO19) | BH19: =SUM(AJ19,AM19,AP19) | BI19: =SUM(AK19,AN19,AQ19)
A20: Eventos | I20: =SUM(I14:I17) | J20: =SUM(J14:J17)+SUMIFS(Aut_Ajustes_Manuais!$G:$G,Aut_Ajustes_Manuais!$I:$I,DRE!H$4,Aut_Ajustes_Manuais!$F:$F,"Eventos") | L20: =SUM(L14:L17) | M20: =SUM(M14:M17)+SUMIFS(Aut_Ajustes_Manuais!$G:$G,Aut_Ajustes_Manuais!$I:$I,DRE!K$4,Aut_Ajustes_Manuais!$F:$F,"Eventos") | O20: =SUM(O14:O17) | P20: =SUM(P14:P17)+SUMIFS(Aut_Ajustes_Manuais!$G:$G,Aut_Ajustes_Manuais!$I:$I,DRE!N$4,Aut_Ajustes_Manuais!$F:$F,"Eventos") | R20: =SUM(R14:R17) | S20: =SUM(S14:S17)+SUMIFS(Aut_Ajustes_Manuais!$G:$G,Aut_Ajustes_Manuais!$I:$I,DRE!Q$4,Aut_Ajustes_Manuais!$F:$F,"Eventos") | U20: =SUM(U14:U17) | V20: =SUM(V14:V17)+SUMIFS(Aut_Ajustes_Manuais!$G:$G,Aut_Ajustes_Manuais!$I:$I,DRE!T$4,Aut_Ajustes_Manuais!$F:$F,"Eventos") | X20: =SUM(X14:X17) | Y20: =SUM(Y14:Y17)+SUMIFS(Aut_Ajustes_Manuais!$G:$G,Aut_Ajustes_Manuais!$I:$I,DRE!W$4,Aut_Ajustes_Manuais!$F:$F,"Eventos") | AA20: =SUM(AA14:AA17) | AB20: =SUM(AB14:AB17)+SUMIFS(Aut_Ajustes_Manuais!$G:$G,Aut_Ajustes_Manuais!$I:$I,DRE!Z$4,Aut_Ajustes_Manuais!$F:$F,"Eventos") | AD20: =SUM(AD14:AD17) | AE20: =SUM(AE14:AE17)+SUMIFS(Aut_Ajustes_Manuais!$G:$G,Aut_Ajustes_Manuais!$I:$I,DRE!AC$4,Aut_Ajustes_Manuais!$F:$F,"Eventos") | AG20: =SUM(AG14:AG17) | AH20: =SUM(AH14:AH17)+SUMIFS(Aut_Ajustes_Manuais!$G:$G,Aut_Ajustes_Manuais!$I:$I,DRE!AF$4,Aut_Ajustes_Manuais!$F:$F,"Eventos") | AJ20: =SUM(AJ14:AJ17) | AK20: =SUM(AK14:AK17)+SUMIFS(Aut_Ajustes_Manuais!$G:$G,Aut_Ajustes_Manuais!$I:$I,DRE!AI$4,Aut_Ajustes_Manuais!$F:$F,"Eventos") | AM20: =SUM(AM14:AM17) | AN20: =SUM(AN14:AN17)+SUMIFS(Aut_Ajustes_Manuais!$G:$G,Aut_Ajustes_Manuais!$I:$I,DRE!AL$4,Aut_Ajustes_Manuais!$F:$F,"Eventos") | AP20: =SUM(AP14:AP17) | AQ20: =SUM(AQ14:AQ17)+SUMIFS(Aut_Ajustes_Manuais!$G:$G,Aut_Ajustes_Manuais!$I:$I,DRE!AO$4,Aut_Ajustes_Manuais!$F:$F,"Eventos") | AR20: =SUMIFS($H20:$AO20,$H$5:$AO$5,"<"&MONTH(TODAY()),$H$6:$AO$6,"REAL 25") | AS20: =SUMIFS($I20:$AP20,$I$5:$AP$5,"<"&MONTH(TODAY()),$I$6:$AP$6,"ORÇADO ") | AT20: =SUMIFS($J20:$AQ20,$J$5:$AQ$5,"<"&MONTH(TODAY()),$J$6:$AQ$6,"REAL 26") | AU20: =SUM(AU14:AU17) | AV20: =SUM(AV14:AV17) | AW20: =SUM(AW14:AW17) | AX20: =SUM(AX14:AX17) | AY20: =SUM(AY14:AY17) | AZ20: =SUM(AZ14:AZ17) | BA20: =SUM(BA14:BA17) | BB20: =SUM(BB14:BB17) | ... BI20: =SUM(BI14:BI17)
A21: (-) Desconto sobre Venda | C21: Premissas | D21: Valores | E21: % Incid | I21: =SUM(I22:I24) | J21: =SUM(J22:J24)+SUMIFS(Aut_Ajustes_Manuais!$G:$G,Aut_Ajustes_Manuais!$I:$I,DRE!H$4,Aut_Ajustes_Manuais!$F:$F,"(-) Desconto sobre Venda") | L21: =SUM(L22:L24) | M21: =SUM(M22:M24)+SUMIFS(Aut_Ajustes_Manuais!$G:$G,Aut_Ajustes_Manuais!$I:$I,DRE!K$4,Aut_Ajustes_Manuais!$F:$F,"(-) Desconto sobre Venda") | O21: =SUM(O22:O24) | P21: =SUM(P22:P24)+SUMIFS(Aut_Ajustes_Manuais!$G:$G,Aut_Ajustes_Manuais!$I:$I,DRE!N$4,Aut_Ajustes_Manuais!$F:$F,"(-) Desconto sobre Venda") | R21: =SUM(R22:R24) | S21: =SUM(S22:S24)+SUMIFS(Aut_Ajustes_Manuais!$G:$G,Aut_Ajustes_Manuais!$I:$I,DRE!Q$4,Aut_Ajustes_Manuais!$F:$F,"(-) Desconto sobre Venda") | U21: =SUM(U22:U24) | V21: =SUM(V22:V24)+SUMIFS(Aut_Ajustes_Manuais!$G:$G,Aut_Ajustes_Manuais!$I:$I,DRE!T$4,Aut_Ajustes_Manuais!$F:$F,"(-) Desconto sobre Venda") | X21: =SUM(X22:X24) | Y21: =SUM(Y22:Y24)+SUMIFS(Aut_Ajustes_Manuais!$G:$G,Aut_Ajustes_Manuais!$I:$I,DRE!W$4,Aut_Ajustes_Manuais!$F:$F,"(-) Desconto sobre Venda") | AA21: =SUM(AA22:AA24) | AB21: =SUM(AB22:AB24)+SUMIFS(Aut_Ajustes_Manuais!$G:$G,Aut_Ajustes_Manuais!$I:$I,DRE!Z$4,Aut_Ajustes_Manuais!$F:$F,"(-) Desconto sobre Venda") | AD21: =SUM(AD22:AD24) | AE21: =SUM(AE22:AE24)+SUMIFS(Aut_Ajustes_Manuais!$G:$G,Aut_Ajustes_Manuais!$I:$I,DRE!AC$4,Aut_Ajustes_Manuais!$F:$F,"(-) Desconto sobre Venda") | AG21: =SUM(AG22:AG24) | AH21: =SUM(AH22:AH24)+SUMIFS(Aut_Ajustes_Manuais!$G:$G,Aut_Ajustes_Manuais!$I:$I,DRE!AF$4,Aut_Ajustes_Manuais!$F:$F,"(-) Desconto sobre Venda") | AJ21: =SUM(AJ22:AJ24) | AK21: =SUM(AK22:AK24)+SUMIFS(Aut_Ajustes_Manuais!$G:$G,Aut_Ajustes_Manuais!$I:$I,DRE!AI$4,Aut_Ajustes_Manuais!$F:$F,"(-) Desconto sobre Venda") | AM21: =SUM(AM22:AM24) | AN21: =SUM(AN22:AN24)+SUMIFS(Aut_Ajustes_Manuais!$G:$G,Aut_Ajustes_Manuais!$I:$I,DRE!AL$4,Aut_Ajustes_Manuais!$F:$F,"(-) Desconto sobre Venda") | AP21: =SUM(AP22:AP24) | AQ21: =SUM(AQ22:AQ24)+SUMIFS(Aut_Ajustes_Manuais!$G:$G,Aut_Ajustes_Manuais!$I:$I,DRE!AO$4,Aut_Ajustes_Manuais!$F:$F,"(-) Desconto sobre Venda") | AR21: =SUM(AR22:AR24) | AS21: =SUM(AS22:AS24) | AT21: =SUM(AT22:AT24) | AU21: =SUM(AU22:AU24) | AV21: =SUM(AV22:AV24) | AW21: =SUM(AW22:AW24) | AX21: =SUM(AX22:AX24) | AY21: =SUM(AY22:AY24) | ... BI21: =SUM(BI22:BI24)
A22: Descontos - Operação | C22: Estim. Mensal | D22: Alimentação OP/ Correção de Problemas | E22: 0.025 | I22: =-SUMIFS(T_ORCAMENTOS!$E:$E,T_ORCAMENTOS!$C:$C,"Descontos - Operação",T_ORCAMENTOS!$H:$H,"1/2026") | J22: =-SUMIFS(Aut_Descontos!$F:$F,Aut_Descontos!$L:$L,DRE!H$4,Aut_Descontos!$K:$K,DRE!$A22)+SUMIFS(Aut_Ajustes_Manuais!$G:$G,Aut_Ajustes_Manuais!$I:$I,DRE!H$4,Aut_Ajustes_Manuais!$F:$F,"Descontos - Operação") | L22: =-SUMIFS(T_ORCAMENTOS!$E:$E,T_ORCAMENTOS!$C:$C,"Descontos - Operação",T_ORCAMENTOS!$H:$H,"2/2026") | M22: =-SUMIFS(Aut_Descontos!$F:$F,Aut_Descontos!$L:$L,DRE!K$4,Aut_Descontos!$K:$K,DRE!$A22)+SUMIFS(Aut_Ajustes_Manuais!$G:$G,Aut_Ajustes_Manuais!$I:$I,DRE!K$4,Aut_Ajustes_Manuais!$F:$F,"Descontos - Operação") | O22: =-SUMIFS(T_ORCAMENTOS!$E:$E,T_ORCAMENTOS!$C:$C,"Descontos - Operação",T_ORCAMENTOS!$H:$H,"3/2026") | P22: =-SUMIFS(Aut_Descontos!$F:$F,Aut_Descontos!$L:$L,DRE!N$4,Aut_Descontos!$K:$K,DRE!$A22)+SUMIFS(Aut_Ajustes_Manuais!$G:$G,Aut_Ajustes_Manuais!$I:$I,DRE!N$4,Aut_Ajustes_Manuais!$F:$F,"Descontos - Operação") | R22: =-SUMIFS(T_ORCAMENTOS!$E:$E,T_ORCAMENTOS!$C:$C,"Descontos - Operação",T_ORCAMENTOS!$H:$H,"4/2026") | S22: =-SUMIFS(Aut_Descontos!$F:$F,Aut_Descontos!$L:$L,DRE!Q$4,Aut_Descontos!$K:$K,DRE!$A22)+SUMIFS(Aut_Ajustes_Manuais!$G:$G,Aut_Ajustes_Manuais!$I:$I,DRE!Q$4,Aut_Ajustes_Manuais!$F:$F,"Descontos - Operação") | U22: =-SUMIFS(T_ORCAMENTOS!$E:$E,T_ORCAMENTOS!$C:$C,"Descontos - Operação",T_ORCAMENTOS!$H:$H,"5/2026") | V22: =-SUMIFS(Aut_Descontos!$F:$F,Aut_Descontos!$L:$L,DRE!T$4,Aut_Descontos!$K:$K,DRE!$A22)+SUMIFS(Aut_Ajustes_Manuais!$G:$G,Aut_Ajustes_Manuais!$I:$I,DRE!T$4,Aut_Ajustes_Manuais!$F:$F,"Descontos - Operação") | X22: =-SUMIFS(T_ORCAMENTOS!$E:$E,T_ORCAMENTOS!$C:$C,"Descontos - Operação",T_ORCAMENTOS!$H:$H,"6/2026") | Y22: =-SUMIFS(Aut_Descontos!$F:$F,Aut_Descontos!$L:$L,DRE!W$4,Aut_Descontos!$K:$K,DRE!$A22)+SUMIFS(Aut_Ajustes_Manuais!$G:$G,Aut_Ajustes_Manuais!$I:$I,DRE!W$4,Aut_Ajustes_Manuais!$F:$F,"Descontos - Operação") | AA22: =-SUMIFS(T_ORCAMENTOS!$E:$E,T_ORCAMENTOS!$C:$C,"Descontos - Operação",T_ORCAMENTOS!$H:$H,"7/2026") | AB22: =-SUMIFS(Aut_Descontos!$F:$F,Aut_Descontos!$L:$L,DRE!Z$4,Aut_Descontos!$K:$K,DRE!$A22)+SUMIFS(Aut_Ajustes_Manuais!$G:$G,Aut_Ajustes_Manuais!$I:$I,DRE!Z$4,Aut_Ajustes_Manuais!$F:$F,"Descontos - Operação") | AD22: =-SUMIFS(T_ORCAMENTOS!$E:$E,T_ORCAMENTOS!$C:$C,"Descontos - Operação",T_ORCAMENTOS!$H:$H,"8/2026") | AE22: =-SUMIFS(Aut_Descontos!$F:$F,Aut_Descontos!$L:$L,DRE!AC$4,Aut_Descontos!$K:$K,DRE!$A22)+SUMIFS(Aut_Ajustes_Manuais!$G:$G,Aut_Ajustes_Manuais!$I:$I,DRE!AC$4,Aut_Ajustes_Manuais!$F:$F,"Descontos - Operação") | AG22: =-SUMIFS(T_ORCAMENTOS!$E:$E,T_ORCAMENTOS!$C:$C,"Descontos - Operação",T_ORCAMENTOS!$H:$H,"9/2026") | AH22: =-SUMIFS(Aut_Descontos!$F:$F,Aut_Descontos!$L:$L,DRE!AF$4,Aut_Descontos!$K:$K,DRE!$A22)+SUMIFS(Aut_Ajustes_Manuais!$G:$G,Aut_Ajustes_Manuais!$I:$I,DRE!AF$4,Aut_Ajustes_Manuais!$F:$F,"Descontos - Operação") | AJ22: =-SUMIFS(T_ORCAMENTOS!$E:$E,T_ORCAMENTOS!$C:$C,"Descontos - Operação",T_ORCAMENTOS!$H:$H,"10/2026") | AK22: =-SUMIFS(Aut_Descontos!$F:$F,Aut_Descontos!$L:$L,DRE!AI$4,Aut_Descontos!$K:$K,DRE!$A22)+SUMIFS(Aut_Ajustes_Manuais!$G:$G,Aut_Ajustes_Manuais!$I:$I,DRE!AI$4,Aut_Ajustes_Manuais!$F:$F,"Descontos - Operação") | AM22: =-SUMIFS(T_ORCAMENTOS!$E:$E,T_ORCAMENTOS!$C:$C,"Descontos - Operação",T_ORCAMENTOS!$H:$H,"11/2026") | AN22: =-SUMIFS(Aut_Descontos!$F:$F,Aut_Descontos!$L:$L,DRE!AL$4,Aut_Descontos!$K:$K,DRE!$A22)+SUMIFS(Aut_Ajustes_Manuais!$G:$G,Aut_Ajustes_Manuais!$I:$I,DRE!AL$4,Aut_Ajustes_Manuais!$F:$F,"Descontos - Operação") | AP22: =-SUMIFS(T_ORCAMENTOS!$E:$E,T_ORCAMENTOS!$C:$C,"Descontos - Operação",T_ORCAMENTOS!$H:$H,"12/2026") | AQ22: =-SUMIFS(Aut_Descontos!$F:$F,Aut_Descontos!$L:$L,DRE!AO$4,Aut_Descontos!$K:$K,DRE!$A22)+SUMIFS(Aut_Ajustes_Manuais!$G:$G,Aut_Ajustes_Manuais!$I:$I,DRE!AO$4,Aut_Ajustes_Manuais!$F:$F,"Descontos - Operação") | AR22: =SUMIFS($H22:$AO22,$H$5:$AO$5,"<"&MONTH(TODAY()),$H$6:$AO$6,"REAL 25") | AS22: =SUMIFS($I22:$AP22,$I$5:$AP$5,"<"&MONTH(TODAY()),$I$6:$AP$6,"ORÇADO ") | AT22: =SUMIFS($J22:$AQ22,$J$5:$AQ$5,"<"&MONTH(TODAY()),$J$6:$AQ$6,"REAL 26") | AU22: =SUM(H22,K22,N22,Q22,T22,W22,Z22,AC22,AF22,AI22,AL22,AO22) | AV22: =SUM(I22,L22,O22,R22,U22,X22,AA22,AD22,AG22,AJ22,AM22,AP22) | AW22: =SUM(J22,M22,P22,S22,V22,Y22,AB22,AE22,AH22,AK22,AN22,AQ22) | AX22: =SUM(H22,K22,N22) | AY22: =SUM(I22,L22,O22) | AZ22: =SUM(J22,M22,P22) | BA22: =SUM(Q22,T22,W22) | BB22: =SUM(R22,U22,X22) | BC22: =SUM(S22,V22,Y22) | BD22: =SUM(Z22,AC22,AF22) | BE22: =SUM(AA22,AD22,AG22) | BF22: =SUM(AB22,AE22,AH22) | BG22: =SUM(AI22,AL22,AO22) | BH22: =SUM(AJ22,AM22,AP22) | BI22: =SUM(AK22,AN22,AQ22)
A23: Desconto - Alimentação Escritório | C23: Estim. Mensal | D23: Cartão FB / Alimentação Escritório | E23: 0.0198 | I23: =-SUMIFS(T_ORCAMENTOS!$E:$E,T_ORCAMENTOS!$C:$C,"Desconto - Alimentação Escritório",T_ORCAMENTOS!$H:$H,"1/2026") | J23: =-SUMIFS(Aut_Descontos!$F:$F,Aut_Descontos!$L:$L,DRE!H$4,Aut_Descontos!$K:$K,DRE!$A23)+SUMIFS(Aut_Ajustes_Manuais!$G:$G,Aut_Ajustes_Manuais!$I:$I,DRE!H$4,Aut_Ajustes_Manuais!$F:$F,"Desconto - Alimentação Escritório") | L23: =-SUMIFS(T_ORCAMENTOS!$E:$E,T_ORCAMENTOS!$C:$C,"Desconto - Alimentação Escritório",T_ORCAMENTOS!$H:$H,"2/2026") | M23: =-SUMIFS(Aut_Descontos!$F:$F,Aut_Descontos!$L:$L,DRE!K$4,Aut_Descontos!$K:$K,DRE!$A23)+SUMIFS(Aut_Ajustes_Manuais!$G:$G,Aut_Ajustes_Manuais!$I:$I,DRE!K$4,Aut_Ajustes_Manuais!$F:$F,"Desconto - Alimentação Escritório") | O23: =-SUMIFS(T_ORCAMENTOS!$E:$E,T_ORCAMENTOS!$C:$C,"Desconto - Alimentação Escritório",T_ORCAMENTOS!$H:$H,"3/2026") | P23: =-SUMIFS(Aut_Descontos!$F:$F,Aut_Descontos!$L:$L,DRE!N$4,Aut_Descontos!$K:$K,DRE!$A23)+SUMIFS(Aut_Ajustes_Manuais!$G:$G,Aut_Ajustes_Manuais!$I:$I,DRE!N$4,Aut_Ajustes_Manuais!$F:$F,"Desconto - Alimentação Escritório") | R23: =-SUMIFS(T_ORCAMENTOS!$E:$E,T_ORCAMENTOS!$C:$C,"Desconto - Alimentação Escritório",T_ORCAMENTOS!$H:$H,"4/2026") | S23: =-SUMIFS(Aut_Descontos!$F:$F,Aut_Descontos!$L:$L,DRE!Q$4,Aut_Descontos!$K:$K,DRE!$A23)+SUMIFS(Aut_Ajustes_Manuais!$G:$G,Aut_Ajustes_Manuais!$I:$I,DRE!Q$4,Aut_Ajustes_Manuais!$F:$F,"Desconto - Alimentação Escritório") | U23: =-SUMIFS(T_ORCAMENTOS!$E:$E,T_ORCAMENTOS!$C:$C,"Desconto - Alimentação Escritório",T_ORCAMENTOS!$H:$H,"5/2026") | V23: =-SUMIFS(Aut_Descontos!$F:$F,Aut_Descontos!$L:$L,DRE!T$4,Aut_Descontos!$K:$K,DRE!$A23)+SUMIFS(Aut_Ajustes_Manuais!$G:$G,Aut_Ajustes_Manuais!$I:$I,DRE!T$4,Aut_Ajustes_Manuais!$F:$F,"Desconto - Alimentação Escritório") | X23: =-SUMIFS(T_ORCAMENTOS!$E:$E,T_ORCAMENTOS!$C:$C,"Desconto - Alimentação Escritório",T_ORCAMENTOS!$H:$H,"6/2026") | Y23: =-SUMIFS(Aut_Descontos!$F:$F,Aut_Descontos!$L:$L,DRE!W$4,Aut_Descontos!$K:$K,DRE!$A23)+SUMIFS(Aut_Ajustes_Manuais!$G:$G,Aut_Ajustes_Manuais!$I:$I,DRE!W$4,Aut_Ajustes_Manuais!$F:$F,"Desconto - Alimentação Escritório") | AA23: =-SUMIFS(T_ORCAMENTOS!$E:$E,T_ORCAMENTOS!$C:$C,"Desconto - Alimentação Escritório",T_ORCAMENTOS!$H:$H,"7/2026") | AB23: =-SUMIFS(Aut_Descontos!$F:$F,Aut_Descontos!$L:$L,DRE!Z$4,Aut_Descontos!$K:$K,DRE!$A23)+SUMIFS(Aut_Ajustes_Manuais!$G:$G,Aut_Ajustes_Manuais!$I:$I,DRE!Z$4,Aut_Ajustes_Manuais!$F:$F,"Desconto - Alimentação Escritório") | AD23: =-SUMIFS(T_ORCAMENTOS!$E:$E,T_ORCAMENTOS!$C:$C,"Desconto - Alimentação Escritório",T_ORCAMENTOS!$H:$H,"8/2026") | AE23: =-SUMIFS(Aut_Descontos!$F:$F,Aut_Descontos!$L:$L,DRE!AC$4,Aut_Descontos!$K:$K,DRE!$A23)+SUMIFS(Aut_Ajustes_Manuais!$G:$G,Aut_Ajustes_Manuais!$I:$I,DRE!AC$4,Aut_Ajustes_Manuais!$F:$F,"Desconto - Alimentação Escritório") | AG23: =-SUMIFS(T_ORCAMENTOS!$E:$E,T_ORCAMENTOS!$C:$C,"Desconto - Alimentação Escritório",T_ORCAMENTOS!$H:$H,"9/2026") | AH23: =-SUMIFS(Aut_Descontos!$F:$F,Aut_Descontos!$L:$L,DRE!AF$4,Aut_Descontos!$K:$K,DRE!$A23)+SUMIFS(Aut_Ajustes_Manuais!$G:$G,Aut_Ajustes_Manuais!$I:$I,DRE!AF$4,Aut_Ajustes_Manuais!$F:$F,"Desconto - Alimentação Escritório") | AJ23: =-SUMIFS(T_ORCAMENTOS!$E:$E,T_ORCAMENTOS!$C:$C,"Desconto - Alimentação Escritório",T_ORCAMENTOS!$H:$H,"10/2026") | AK23: =-SUMIFS(Aut_Descontos!$F:$F,Aut_Descontos!$L:$L,DRE!AI$4,Aut_Descontos!$K:$K,DRE!$A23)+SUMIFS(Aut_Ajustes_Manuais!$G:$G,Aut_Ajustes_Manuais!$I:$I,DRE!AI$4,Aut_Ajustes_Manuais!$F:$F,"Desconto - Alimentação Escritório") | AM23: =-SUMIFS(T_ORCAMENTOS!$E:$E,T_ORCAMENTOS!$C:$C,"Desconto - Alimentação Escritório",T_ORCAMENTOS!$H:$H,"11/2026") | AN23: =-SUMIFS(Aut_Descontos!$F:$F,Aut_Descontos!$L:$L,DRE!AL$4,Aut_Descontos!$K:$K,DRE!$A23)+SUMIFS(Aut_Ajustes_Manuais!$G:$G,Aut_Ajustes_Manuais!$I:$I,DRE!AL$4,Aut_Ajustes_Manuais!$F:$F,"Desconto - Alimentação Escritório") | AP23: =-SUMIFS(T_ORCAMENTOS!$E:$E,T_ORCAMENTOS!$C:$C,"Desconto - Alimentação Escritório",T_ORCAMENTOS!$H:$H,"12/2026") | AQ23: =-SUMIFS(Aut_Descontos!$F:$F,Aut_Descontos!$L:$L,DRE!AO$4,Aut_Descontos!$K:$K,DRE!$A23)+SUMIFS(Aut_Ajustes_Manuais!$G:$G,Aut_Ajustes_Manuais!$I:$I,DRE!AO$4,Aut_Ajustes_Manuais!$F:$F,"Desconto - Alimentação Escritório") | AR23: =SUMIFS($H23:$AO23,$H$5:$AO$5,"<"&MONTH(TODAY()),$H$6:$AO$6,"REAL 25") | AS23: =SUMIFS($I23:$AP23,$I$5:$AP$5,"<"&MONTH(TODAY()),$I$6:$AP$6,"ORÇADO ") | AT23: =SUMIFS($J23:$AQ23,$J$5:$AQ$5,"<"&MONTH(TODAY()),$J$6:$AQ$6,"REAL 26") | AU23: =SUM(H23,K23,N23,Q23,T23,W23,Z23,AC23,AF23,AI23,AL23,AO23) | AV23: =SUM(I23,L23,O23,R23,U23,X23,AA23,AD23,AG23,AJ23,AM23,AP23) | AW23: =SUM(J23,M23,P23,S23,V23,Y23,AB23,AE23,AH23,AK23,AN23,AQ23) | AX23: =SUM(H23,K23,N23) | AY23: =SUM(I23,L23,O23) | AZ23: =SUM(J23,M23,P23) | BA23: =SUM(Q23,T23,W23) | BB23: =SUM(R23,U23,X23) | BC23: =SUM(S23,V23,Y23) | BD23: =SUM(Z23,AC23,AF23) | BE23: =SUM(AA23,AD23,AG23) | BF23: =SUM(AB23,AE23,AH23) | BG23: =SUM(AI23,AL23,AO23) | BH23: =SUM(AJ23,AM23,AP23) | BI23: =SUM(AK23,AN23,AQ23)
A24: Descontos - Marketing | C24: Estim. Mensal | D24: Permutas e Ações Gerais | E24: 0.0025 | I24: =-SUMIFS(T_ORCAMENTOS!$E:$E,T_ORCAMENTOS!$C:$C,"Descontos - Marketing",T_ORCAMENTOS!$H:$H,"1/2026") | J24: =-SUMIFS(Aut_Descontos!$F:$F,Aut_Descontos!$L:$L,DRE!H$4,Aut_Descontos!$K:$K,DRE!$A24)+SUMIFS(Aut_Ajustes_Manuais!$G:$G,Aut_Ajustes_Manuais!$I:$I,DRE!H$4,Aut_Ajustes_Manuais!$F:$F,"Descontos - Marketing") | L24: =-SUMIFS(T_ORCAMENTOS!$E:$E,T_ORCAMENTOS!$C:$C,"Descontos - Marketing",T_ORCAMENTOS!$H:$H,"2/2026") | M24: =-SUMIFS(Aut_Descontos!$F:$F,Aut_Descontos!$L:$L,DRE!K$4,Aut_Descontos!$K:$K,DRE!$A24)+SUMIFS(Aut_Ajustes_Manuais!$G:$G,Aut_Ajustes_Manuais!$I:$I,DRE!K$4,Aut_Ajustes_Manuais!$F:$F,"Descontos - Marketing") | O24: =-SUMIFS(T_ORCAMENTOS!$E:$E,T_ORCAMENTOS!$C:$C,"Descontos - Marketing",T_ORCAMENTOS!$H:$H,"3/2026") | P24: =-SUMIFS(Aut_Descontos!$F:$F,Aut_Descontos!$L:$L,DRE!N$4,Aut_Descontos!$K:$K,DRE!$A24)+SUMIFS(Aut_Ajustes_Manuais!$G:$G,Aut_Ajustes_Manuais!$I:$I,DRE!N$4,Aut_Ajustes_Manuais!$F:$F,"Descontos - Marketing") | R24: =-SUMIFS(T_ORCAMENTOS!$E:$E,T_ORCAMENTOS!$C:$C,"Descontos - Marketing",T_ORCAMENTOS!$H:$H,"4/2026") | S24: =-SUMIFS(Aut_Descontos!$F:$F,Aut_Descontos!$L:$L,DRE!Q$4,Aut_Descontos!$K:$K,DRE!$A24)+SUMIFS(Aut_Ajustes_Manuais!$G:$G,Aut_Ajustes_Manuais!$I:$I,DRE!Q$4,Aut_Ajustes_Manuais!$F:$F,"Descontos - Marketing") | U24: =-SUMIFS(T_ORCAMENTOS!$E:$E,T_ORCAMENTOS!$C:$C,"Descontos - Marketing",T_ORCAMENTOS!$H:$H,"5/2026") | V24: =-SUMIFS(Aut_Descontos!$F:$F,Aut_Descontos!$L:$L,DRE!T$4,Aut_Descontos!$K:$K,DRE!$A24)+SUMIFS(Aut_Ajustes_Manuais!$G:$G,Aut_Ajustes_Manuais!$I:$I,DRE!T$4,Aut_Ajustes_Manuais!$F:$F,"Descontos - Marketing") | X24: =-SUMIFS(T_ORCAMENTOS!$E:$E,T_ORCAMENTOS!$C:$C,"Descontos - Marketing",T_ORCAMENTOS!$H:$H,"6/2026") | Y24: =-SUMIFS(Aut_Descontos!$F:$F,Aut_Descontos!$L:$L,DRE!W$4,Aut_Descontos!$K:$K,DRE!$A24)+SUMIFS(Aut_Ajustes_Manuais!$G:$G,Aut_Ajustes_Manuais!$I:$I,DRE!W$4,Aut_Ajustes_Manuais!$F:$F,"Descontos - Marketing") | AA24: =-SUMIFS(T_ORCAMENTOS!$E:$E,T_ORCAMENTOS!$C:$C,"Descontos - Marketing",T_ORCAMENTOS!$H:$H,"7/2026") | AB24: =-SUMIFS(Aut_Descontos!$F:$F,Aut_Descontos!$L:$L,DRE!Z$4,Aut_Descontos!$K:$K,DRE!$A24)+SUMIFS(Aut_Ajustes_Manuais!$G:$G,Aut_Ajustes_Manuais!$I:$I,DRE!Z$4,Aut_Ajustes_Manuais!$F:$F,"Descontos - Marketing") | AD24: =-SUMIFS(T_ORCAMENTOS!$E:$E,T_ORCAMENTOS!$C:$C,"Descontos - Marketing",T_ORCAMENTOS!$H:$H,"8/2026") | AE24: =-SUMIFS(Aut_Descontos!$F:$F,Aut_Descontos!$L:$L,DRE!AC$4,Aut_Descontos!$K:$K,DRE!$A24)+SUMIFS(Aut_Ajustes_Manuais!$G:$G,Aut_Ajustes_Manuais!$I:$I,DRE!AC$4,Aut_Ajustes_Manuais!$F:$F,"Descontos - Marketing") | AG24: =-SUMIFS(T_ORCAMENTOS!$E:$E,T_ORCAMENTOS!$C:$C,"Descontos - Marketing",T_ORCAMENTOS!$H:$H,"9/2026") | AH24: =-SUMIFS(Aut_Descontos!$F:$F,Aut_Descontos!$L:$L,DRE!AF$4,Aut_Descontos!$K:$K,DRE!$A24)+SUMIFS(Aut_Ajustes_Manuais!$G:$G,Aut_Ajustes_Manuais!$I:$I,DRE!AF$4,Aut_Ajustes_Manuais!$F:$F,"Descontos - Marketing") | AJ24: =-SUMIFS(T_ORCAMENTOS!$E:$E,T_ORCAMENTOS!$C:$C,"Descontos - Marketing",T_ORCAMENTOS!$H:$H,"10/2026") | AK24: =-SUMIFS(Aut_Descontos!$F:$F,Aut_Descontos!$L:$L,DRE!AI$4,Aut_Descontos!$K:$K,DRE!$A24)+SUMIFS(Aut_Ajustes_Manuais!$G:$G,Aut_Ajustes_Manuais!$I:$I,DRE!AI$4,Aut_Ajustes_Manuais!$F:$F,"Descontos - Marketing") | AM24: =-SUMIFS(T_ORCAMENTOS!$E:$E,T_ORCAMENTOS!$C:$C,"Descontos - Marketing",T_ORCAMENTOS!$H:$H,"11/2026") | AN24: =-SUMIFS(Aut_Descontos!$F:$F,Aut_Descontos!$L:$L,DRE!AL$4,Aut_Descontos!$K:$K,DRE!$A24)+SUMIFS(Aut_Ajustes_Manuais!$G:$G,Aut_Ajustes_Manuais!$I:$I,DRE!AL$4,Aut_Ajustes_Manuais!$F:$F,"Descontos - Marketing") | AP24: =-SUMIFS(T_ORCAMENTOS!$E:$E,T_ORCAMENTOS!$C:$C,"Descontos - Marketing",T_ORCAMENTOS!$H:$H,"12/2026") | AQ24: =-SUMIFS(Aut_Descontos!$F:$F,Aut_Descontos!$L:$L,DRE!AO$4,Aut_Descontos!$K:$K,DRE!$A24)+SUMIFS(Aut_Ajustes_Manuais!$G:$G,Aut_Ajustes_Manuais!$I:$I,DRE!AO$4,Aut_Ajustes_Manuais!$F:$F,"Descontos - Marketing") | AR24: =SUMIFS($H24:$AO24,$H$5:$AO$5,"<"&MONTH(TODAY()),$H$6:$AO$6,"REAL 25") | AS24: =SUMIFS($I24:$AP24,$I$5:$AP$5,"<"&MONTH(TODAY()),$I$6:$AP$6,"ORÇADO ") | AT24: =SUMIFS($J24:$AQ24,$J$5:$AQ$5,"<"&MONTH(TODAY()),$J$6:$AQ$6,"REAL 26") | AU24: =SUM(H24,K24,N24,Q24,T24,W24,Z24,AC24,AF24,AI24,AL24,AO24) | AV24: =SUM(I24,L24,O24,R24,U24,X24,AA24,AD24,AG24,AJ24,AM24,AP24) | AW24: =SUM(J24,M24,P24,S24,V24,Y24,AB24,AE24,AH24,AK24,AN24,AQ24) | AX24: =SUM(H24,K24,N24) | AY24: =SUM(I24,L24,O24) | AZ24: =SUM(J24,M24,P24) | BA24: =SUM(Q24,T24,W24) | BB24: =SUM(R24,U24,X24) | BC24: =SUM(S24,V24,Y24) | BD24: =SUM(Z24,AC24,AF24) | BE24: =SUM(AA24,AD24,AG24) | BF24: =SUM(AB24,AE24,AH24) | BG24: =SUM(AI24,AL24,AO24) | BH24: =SUM(AJ24,AM24,AP24) | BI24: =SUM(AK24,AN24,AQ24)
A25: % sobre Receita Bruta | I25: =IFERROR(I21/I8,0) | J25: =IFERROR(J21/J8,0)+SUMIFS(Aut_Ajustes_Manuais!$G:$G,Aut_Ajustes_Manuais!$I:$I,DRE!H$4,Aut_Ajustes_Manuais!$F:$F,"% sobre Receita Bruta") | L25: =IFERROR(L21/L8,0) | M25: =IFERROR(M21/M8,0)+SUMIFS(Aut_Ajustes_Manuais!$G:$G,Aut_Ajustes_Manuais!$I:$I,DRE!K$4,Aut_Ajustes_Manuais!$F:$F,"% sobre Receita Bruta") | O25: =IFERROR(O21/O8,0) | P25: =IFERROR(P21/P8,0)+SUMIFS(Aut_Ajustes_Manuais!$G:$G,Aut_Ajustes_Manuais!$I:$I,DRE!N$4,Aut_Ajustes_Manuais!$F:$F,"% sobre Receita Bruta") | R25: =IFERROR(R21/R8,0) | S25: =IFERROR(S21/S8,0)+SUMIFS(Aut_Ajustes_Manuais!$G:$G,Aut_Ajustes_Manuais!$I:$I,DRE!Q$4,Aut_Ajustes_Manuais!$F:$F,"% sobre Receita Bruta") | U25: =IFERROR(U21/U8,0) | V25: =IFERROR(V21/V8,0)+SUMIFS(Aut_Ajustes_Manuais!$G:$G,Aut_Ajustes_Manuais!$I:$I,DRE!T$4,Aut_Ajustes_Manuais!$F:$F,"% sobre Receita Bruta") | X25: =IFERROR(X21/X8,0) | Y25: =IFERROR(Y21/Y8,0)+SUMIFS(Aut_Ajustes_Manuais!$G:$G,Aut_Ajustes_Manuais!$I:$I,DRE!W$4,Aut_Ajustes_Manuais!$F:$F,"% sobre Receita Bruta") | AA25: =IFERROR(AA21/AA8,0) | AB25: =IFERROR(AB21/AB8,0)+SUMIFS(Aut_Ajustes_Manuais!$G:$G,Aut_Ajustes_Manuais!$I:$I,DRE!Z$4,Aut_Ajustes_Manuais!$F:$F,"% sobre Receita Bruta") | AD25: =IFERROR(AD21/AD8,0) | AE25: =IFERROR(AE21/AE8,0)+SUMIFS(Aut_Ajustes_Manuais!$G:$G,Aut_Ajustes_Manuais!$I:$I,DRE!AC$4,Aut_Ajustes_Manuais!$F:$F,"% sobre Receita Bruta") | AG25: =IFERROR(AG21/AG8,0) | AH25: =IFERROR(AH21/AH8,0)+SUMIFS(Aut_Ajustes_Manuais!$G:$G,Aut_Ajustes_Manuais!$I:$I,DRE!AF$4,Aut_Ajustes_Manuais!$F:$F,"% sobre Receita Bruta") | AJ25: =IFERROR(AJ21/AJ8,0) | AK25: =IFERROR(AK21/AK8,0)+SUMIFS(Aut_Ajustes_Manuais!$G:$G,Aut_Ajustes_Manuais!$I:$I,DRE!AI$4,Aut_Ajustes_Manuais!$F:$F,"% sobre Receita Bruta") | AM25: =IFERROR(AM21/AM8,0) | AN25: =IFERROR(AN21/AN8,0)+SUMIFS(Aut_Ajustes_Manuais!$G:$G,Aut_Ajustes_Manuais!$I:$I,DRE!AL$4,Aut_Ajustes_Manuais!$F:$F,"% sobre Receita Bruta") | AP25: =IFERROR(AP21/AP8,0) | AQ25: =IFERROR(AQ21/AQ8,0)+SUMIFS(Aut_Ajustes_Manuais!$G:$G,Aut_Ajustes_Manuais!$I:$I,DRE!AO$4,Aut_Ajustes_Manuais!$F:$F,"% sobre Receita Bruta") | AR25: =IFERROR(AR21/AR8,0) | AS25: =IFERROR(AS21/AS8,0) | AT25: =IFERROR(AT21/AT8,0) | AU25: =IFERROR(AU21/AU8,0) | AV25: =IFERROR(AV21/AV8,0) | AW25: =IFERROR(AW21/AW8,0) | AX25: =IFERROR(AX21/AX8,0) | AY25: =IFERROR(AY21/AY8,0) | ... BI25: =IFERROR(BI21/BI8,0)
A27: (-) Impostos sobre Venda | C27: Premissas | D27: Valores | E27: % Incid | I27: =SUM(I28:I30) | J27: =SUM(J28:J30)+SUMIFS(Aut_Ajustes_Manuais!$G:$G,Aut_Ajustes_Manuais!$I:$I,DRE!H$4,Aut_Ajustes_Manuais!$F:$F,"(-) Impostos sobre Venda") | L27: =SUM(L28:L30) | M27: =SUM(M28:M30)+SUMIFS(Aut_Ajustes_Manuais!$G:$G,Aut_Ajustes_Manuais!$I:$I,DRE!K$4,Aut_Ajustes_Manuais!$F:$F,"(-) Impostos sobre Venda") | O27: =SUM(O28:O30) | P27: =SUM(P28:P30)+SUMIFS(Aut_Ajustes_Manuais!$G:$G,Aut_Ajustes_Manuais!$I:$I,DRE!N$4,Aut_Ajustes_Manuais!$F:$F,"(-) Impostos sobre Venda") | R27: =SUM(R28:R30) | S27: =SUM(S28:S30)+SUMIFS(Aut_Ajustes_Manuais!$G:$G,Aut_Ajustes_Manuais!$I:$I,DRE!Q$4,Aut_Ajustes_Manuais!$F:$F,"(-) Impostos sobre Venda") | U27: =SUM(U28:U30) | V27: =SUM(V28:V30)+SUMIFS(Aut_Ajustes_Manuais!$G:$G,Aut_Ajustes_Manuais!$I:$I,DRE!T$4,Aut_Ajustes_Manuais!$F:$F,"(-) Impostos sobre Venda") | X27: =SUM(X28:X30) | Y27: =SUM(Y28:Y30)+SUMIFS(Aut_Ajustes_Manuais!$G:$G,Aut_Ajustes_Manuais!$I:$I,DRE!W$4,Aut_Ajustes_Manuais!$F:$F,"(-) Impostos sobre Venda") | AA27: =SUM(AA28:AA30) | AB27: =SUM(AB28:AB30)+SUMIFS(Aut_Ajustes_Manuais!$G:$G,Aut_Ajustes_Manuais!$I:$I,DRE!Z$4,Aut_Ajustes_Manuais!$F:$F,"(-) Impostos sobre Venda") | AD27: =SUM(AD28:AD30) | AE27: =SUM(AE28:AE30)+SUMIFS(Aut_Ajustes_Manuais!$G:$G,Aut_Ajustes_Manuais!$I:$I,DRE!AC$4,Aut_Ajustes_Manuais!$F:$F,"(-) Impostos sobre Venda") | AG27: =SUM(AG28:AG30) | AH27: =SUM(AH28:AH30)+SUMIFS(Aut_Ajustes_Manuais!$G:$G,Aut_Ajustes_Manuais!$I:$I,DRE!AF$4,Aut_Ajustes_Manuais!$F:$F,"(-) Impostos sobre Venda") | AJ27: =SUM(AJ28:AJ30) | AK27: =SUM(AK28:AK30)+SUMIFS(Aut_Ajustes_Manuais!$G:$G,Aut_Ajustes_Manuais!$I:$I,DRE!AI$4,Aut_Ajustes_Manuais!$F:$F,"(-) Impostos sobre Venda") | AM27: =SUM(AM28:AM30) | AN27: =SUM(AN28:AN30)+SUMIFS(Aut_Ajustes_Manuais!$G:$G,Aut_Ajustes_Manuais!$I:$I,DRE!AL$4,Aut_Ajustes_Manuais!$F:$F,"(-) Impostos sobre Venda") | AP27: =SUM(AP28:AP30) | AQ27: =SUM(AQ28:AQ30)+SUMIFS(Aut_Ajustes_Manuais!$G:$G,Aut_Ajustes_Manuais!$I:$I,DRE!AO$4,Aut_Ajustes_Manuais!$F:$F,"(-) Impostos sobre Venda") | AR27: =SUM(AR28:AR30) | AS27: =SUM(AS28:AS30) | AT27: =SUM(AT28:AT30) | AU27: =SUM(AU28:AU30) | AV27: =SUM(AV28:AV30) | AW27: =SUM(AW28:AW30) | AX27: =SUM(AX28:AX30) | AY27: =SUM(AY28:AY30) | ... BI27: =SUM(BI28:BI30)
A28: PIS / COFINS | C28: Base Fiscal | E28: 0.0365 | I28: =-SUMIFS(T_ORCAMENTOS!$E:$E,T_ORCAMENTOS!$C:$C,"PIS / COFINS",T_ORCAMENTOS!$H:$H,"1/2026") | J28: =-Fiscal!D21-Fiscal!D22+SUMIFS(Aut_Ajustes_Manuais!$G:$G,Aut_Ajustes_Manuais!$I:$I,DRE!H$4,Aut_Ajustes_Manuais!$F:$F,"PIS / COFINS") | L28: =-SUMIFS(T_ORCAMENTOS!$E:$E,T_ORCAMENTOS!$C:$C,"PIS / COFINS",T_ORCAMENTOS!$H:$H,"2/2026") | M28: =-Fiscal!E21-Fiscal!E22+SUMIFS(Aut_Ajustes_Manuais!$G:$G,Aut_Ajustes_Manuais!$I:$I,DRE!K$4,Aut_Ajustes_Manuais!$F:$F,"PIS / COFINS") | O28: =-SUMIFS(T_ORCAMENTOS!$E:$E,T_ORCAMENTOS!$C:$C,"PIS / COFINS",T_ORCAMENTOS!$H:$H,"3/2026") | P28: =-Fiscal!F21-Fiscal!F22+SUMIFS(Aut_Ajustes_Manuais!$G:$G,Aut_Ajustes_Manuais!$I:$I,DRE!N$4,Aut_Ajustes_Manuais!$F:$F,"PIS / COFINS") | R28: =-SUMIFS(T_ORCAMENTOS!$E:$E,T_ORCAMENTOS!$C:$C,"PIS / COFINS",T_ORCAMENTOS!$H:$H,"4/2026") | S28: =-Fiscal!H21-Fiscal!H22+SUMIFS(Aut_Ajustes_Manuais!$G:$G,Aut_Ajustes_Manuais!$I:$I,DRE!Q$4,Aut_Ajustes_Manuais!$F:$F,"PIS / COFINS") | U28: =-SUMIFS(T_ORCAMENTOS!$E:$E,T_ORCAMENTOS!$C:$C,"PIS / COFINS",T_ORCAMENTOS!$H:$H,"5/2026") | V28: =-Fiscal!I21-Fiscal!I22+SUMIFS(Aut_Ajustes_Manuais!$G:$G,Aut_Ajustes_Manuais!$I:$I,DRE!T$4,Aut_Ajustes_Manuais!$F:$F,"PIS / COFINS") | X28: =-SUMIFS(T_ORCAMENTOS!$E:$E,T_ORCAMENTOS!$C:$C,"PIS / COFINS",T_ORCAMENTOS!$H:$H,"6/2026") | Y28: =-Fiscal!J21-Fiscal!J22+SUMIFS(Aut_Ajustes_Manuais!$G:$G,Aut_Ajustes_Manuais!$I:$I,DRE!W$4,Aut_Ajustes_Manuais!$F:$F,"PIS / COFINS") | AA28: =-SUMIFS(T_ORCAMENTOS!$E:$E,T_ORCAMENTOS!$C:$C,"PIS / COFINS",T_ORCAMENTOS!$H:$H,"7/2026") | AB28: =-Fiscal!L21-Fiscal!L22+SUMIFS(Aut_Ajustes_Manuais!$G:$G,Aut_Ajustes_Manuais!$I:$I,DRE!Z$4,Aut_Ajustes_Manuais!$F:$F,"PIS / COFINS") | AD28: =-SUMIFS(T_ORCAMENTOS!$E:$E,T_ORCAMENTOS!$C:$C,"PIS / COFINS",T_ORCAMENTOS!$H:$H,"8/2026") | AE28: =-Fiscal!M21-Fiscal!M22+SUMIFS(Aut_Ajustes_Manuais!$G:$G,Aut_Ajustes_Manuais!$I:$I,DRE!AC$4,Aut_Ajustes_Manuais!$F:$F,"PIS / COFINS") | AG28: =-SUMIFS(T_ORCAMENTOS!$E:$E,T_ORCAMENTOS!$C:$C,"PIS / COFINS",T_ORCAMENTOS!$H:$H,"9/2026") | AH28: =-Fiscal!N21-Fiscal!N22+SUMIFS(Aut_Ajustes_Manuais!$G:$G,Aut_Ajustes_Manuais!$I:$I,DRE!AF$4,Aut_Ajustes_Manuais!$F:$F,"PIS / COFINS") | AJ28: =-SUMIFS(T_ORCAMENTOS!$E:$E,T_ORCAMENTOS!$C:$C,"PIS / COFINS",T_ORCAMENTOS!$H:$H,"10/2026") | AK28: =-Fiscal!P21-Fiscal!P22+SUMIFS(Aut_Ajustes_Manuais!$G:$G,Aut_Ajustes_Manuais!$I:$I,DRE!AI$4,Aut_Ajustes_Manuais!$F:$F,"PIS / COFINS") | AM28: =-SUMIFS(T_ORCAMENTOS!$E:$E,T_ORCAMENTOS!$C:$C,"PIS / COFINS",T_ORCAMENTOS!$H:$H,"11/2026") | AN28: =-Fiscal!Q21-Fiscal!Q22+SUMIFS(Aut_Ajustes_Manuais!$G:$G,Aut_Ajustes_Manuais!$I:$I,DRE!AL$4,Aut_Ajustes_Manuais!$F:$F,"PIS / COFINS") | AP28: =-SUMIFS(T_ORCAMENTOS!$E:$E,T_ORCAMENTOS!$C:$C,"PIS / COFINS",T_ORCAMENTOS!$H:$H,"12/2026") | AQ28: =-Fiscal!R21-Fiscal!R22+SUMIFS(Aut_Ajustes_Manuais!$G:$G,Aut_Ajustes_Manuais!$I:$I,DRE!AO$4,Aut_Ajustes_Manuais!$F:$F,"PIS / COFINS") | AR28: =SUMIFS($H28:$AO28,$H$5:$AO$5,"<"&MONTH(TODAY()),$H$6:$AO$6,"REAL 25") | AS28: =SUMIFS($I28:$AP28,$I$5:$AP$5,"<"&MONTH(TODAY()),$I$6:$AP$6,"ORÇADO ") | AT28: =SUMIFS($J28:$AQ28,$J$5:$AQ$5,"<"&MONTH(TODAY()),$J$6:$AQ$6,"REAL 26") | AU28: =SUM(H28,K28,N28,Q28,T28,W28,Z28,AC28,AF28,AI28,AL28,AO28) | AV28: =SUM(I28,L28,O28,R28,U28,X28,AA28,AD28,AG28,AJ28,AM28,AP28) | AW28: =SUM(J28,M28,P28,S28,V28,Y28,AB28,AE28,AH28,AK28,AN28,AQ28) | AX28: =SUM(H28,K28,N28) | AY28: =SUM(I28,L28,O28) | AZ28: =SUM(J28,M28,P28) | BA28: =SUM(Q28,T28,W28) | BB28: =SUM(R28,U28,X28) | BC28: =SUM(S28,V28,Y28) | BD28: =SUM(Z28,AC28,AF28) | BE28: =SUM(AA28,AD28,AG28) | BF28: =SUM(AB28,AE28,AH28) | BG28: =SUM(AI28,AL28,AO28) | BH28: =SUM(AJ28,AM28,AP28) | BI28: =SUM(AK28,AN28,AQ28)
A29: ICMS | C29: Base Fiscal | E29: 0.04 | I29: =-SUMIFS(T_ORCAMENTOS!$E:$E,T_ORCAMENTOS!$C:$C,"ICMS",T_ORCAMENTOS!$H:$H,"1/2026") | J29: =-Fiscal!D23+SUMIFS(Aut_Ajustes_Manuais!$G:$G,Aut_Ajustes_Manuais!$I:$I,DRE!H$4,Aut_Ajustes_Manuais!$F:$F,"ICMS") | L29: =-SUMIFS(T_ORCAMENTOS!$E:$E,T_ORCAMENTOS!$C:$C,"ICMS",T_ORCAMENTOS!$H:$H,"2/2026") | M29: =-Fiscal!E23+SUMIFS(Aut_Ajustes_Manuais!$G:$G,Aut_Ajustes_Manuais!$I:$I,DRE!K$4,Aut_Ajustes_Manuais!$F:$F,"ICMS") | O29: =-SUMIFS(T_ORCAMENTOS!$E:$E,T_ORCAMENTOS!$C:$C,"ICMS",T_ORCAMENTOS!$H:$H,"3/2026") | P29: =-Fiscal!F23+SUMIFS(Aut_Ajustes_Manuais!$G:$G,Aut_Ajustes_Manuais!$I:$I,DRE!N$4,Aut_Ajustes_Manuais!$F:$F,"ICMS") | R29: =-SUMIFS(T_ORCAMENTOS!$E:$E,T_ORCAMENTOS!$C:$C,"ICMS",T_ORCAMENTOS!$H:$H,"4/2026") | S29: =-Fiscal!H23+SUMIFS(Aut_Ajustes_Manuais!$G:$G,Aut_Ajustes_Manuais!$I:$I,DRE!Q$4,Aut_Ajustes_Manuais!$F:$F,"ICMS") | U29: =-SUMIFS(T_ORCAMENTOS!$E:$E,T_ORCAMENTOS!$C:$C,"ICMS",T_ORCAMENTOS!$H:$H,"5/2026") | V29: =-Fiscal!I23+SUMIFS(Aut_Ajustes_Manuais!$G:$G,Aut_Ajustes_Manuais!$I:$I,DRE!T$4,Aut_Ajustes_Manuais!$F:$F,"ICMS") | X29: =-SUMIFS(T_ORCAMENTOS!$E:$E,T_ORCAMENTOS!$C:$C,"ICMS",T_ORCAMENTOS!$H:$H,"6/2026") | Y29: =-Fiscal!J23+SUMIFS(Aut_Ajustes_Manuais!$G:$G,Aut_Ajustes_Manuais!$I:$I,DRE!W$4,Aut_Ajustes_Manuais!$F:$F,"ICMS") | AA29: =-SUMIFS(T_ORCAMENTOS!$E:$E,T_ORCAMENTOS!$C:$C,"ICMS",T_ORCAMENTOS!$H:$H,"7/2026") | AB29: =-Fiscal!L23+SUMIFS(Aut_Ajustes_Manuais!$G:$G,Aut_Ajustes_Manuais!$I:$I,DRE!Z$4,Aut_Ajustes_Manuais!$F:$F,"ICMS") | AD29: =-SUMIFS(T_ORCAMENTOS!$E:$E,T_ORCAMENTOS!$C:$C,"ICMS",T_ORCAMENTOS!$H:$H,"8/2026") | AE29: =-Fiscal!M23+SUMIFS(Aut_Ajustes_Manuais!$G:$G,Aut_Ajustes_Manuais!$I:$I,DRE!AC$4,Aut_Ajustes_Manuais!$F:$F,"ICMS") | AG29: =-SUMIFS(T_ORCAMENTOS!$E:$E,T_ORCAMENTOS!$C:$C,"ICMS",T_ORCAMENTOS!$H:$H,"9/2026") | AH29: =-Fiscal!N23+SUMIFS(Aut_Ajustes_Manuais!$G:$G,Aut_Ajustes_Manuais!$I:$I,DRE!AF$4,Aut_Ajustes_Manuais!$F:$F,"ICMS") | AJ29: =-SUMIFS(T_ORCAMENTOS!$E:$E,T_ORCAMENTOS!$C:$C,"ICMS",T_ORCAMENTOS!$H:$H,"10/2026") | AK29: =-Fiscal!P23+SUMIFS(Aut_Ajustes_Manuais!$G:$G,Aut_Ajustes_Manuais!$I:$I,DRE!AI$4,Aut_Ajustes_Manuais!$F:$F,"ICMS") | AM29: =-SUMIFS(T_ORCAMENTOS!$E:$E,T_ORCAMENTOS!$C:$C,"ICMS",T_ORCAMENTOS!$H:$H,"11/2026") | AN29: =-Fiscal!Q23+SUMIFS(Aut_Ajustes_Manuais!$G:$G,Aut_Ajustes_Manuais!$I:$I,DRE!AL$4,Aut_Ajustes_Manuais!$F:$F,"ICMS") | AP29: =-SUMIFS(T_ORCAMENTOS!$E:$E,T_ORCAMENTOS!$C:$C,"ICMS",T_ORCAMENTOS!$H:$H,"12/2026") | AQ29: =-Fiscal!R23+SUMIFS(Aut_Ajustes_Manuais!$G:$G,Aut_Ajustes_Manuais!$I:$I,DRE!AO$4,Aut_Ajustes_Manuais!$F:$F,"ICMS") | AR29: =SUMIFS($H29:$AO29,$H$5:$AO$5,"<"&MONTH(TODAY()),$H$6:$AO$6,"REAL 25") | AS29: =SUMIFS($I29:$AP29,$I$5:$AP$5,"<"&MONTH(TODAY()),$I$6:$AP$6,"ORÇADO ") | AT29: =SUMIFS($J29:$AQ29,$J$5:$AQ$5,"<"&MONTH(TODAY()),$J$6:$AQ$6,"REAL 26") | AU29: =SUM(H29,K29,N29,Q29,T29,W29,Z29,AC29,AF29,AI29,AL29,AO29) | AV29: =SUM(I29,L29,O29,R29,U29,X29,AA29,AD29,AG29,AJ29,AM29,AP29) | AW29: =SUM(J29,M29,P29,S29,V29,Y29,AB29,AE29,AH29,AK29,AN29,AQ29) | AX29: =SUM(H29,K29,N29) | AY29: =SUM(I29,L29,O29) | AZ29: =SUM(J29,M29,P29) | BA29: =SUM(Q29,T29,W29) | BB29: =SUM(R29,U29,X29) | BC29: =SUM(S29,V29,Y29) | BD29: =SUM(Z29,AC29,AF29) | BE29: =SUM(AA29,AD29,AG29) | BF29: =SUM(AB29,AE29,AH29) | BG29: =SUM(AI29,AL29,AO29) | BH29: =SUM(AJ29,AM29,AP29) | BI29: =SUM(AK29,AN29,AQ29)
A30: ISS | C30: Base Fiscal | E30: 0.05 | I30: =-SUMIFS(T_ORCAMENTOS!$E:$E,T_ORCAMENTOS!$C:$C,"ISS",T_ORCAMENTOS!$H:$H,"1/2026") | J30: =-Fiscal!D20+SUMIFS(Aut_Ajustes_Manuais!$G:$G,Aut_Ajustes_Manuais!$I:$I,DRE!H$4,Aut_Ajustes_Manuais!$F:$F,"ISS") | L30: =-SUMIFS(T_ORCAMENTOS!$E:$E,T_ORCAMENTOS!$C:$C,"ISS",T_ORCAMENTOS!$H:$H,"2/2026") | M30: =-Fiscal!E20+SUMIFS(Aut_Ajustes_Manuais!$G:$G,Aut_Ajustes_Manuais!$I:$I,DRE!K$4,Aut_Ajustes_Manuais!$F:$F,"ISS") | O30: =-SUMIFS(T_ORCAMENTOS!$E:$E,T_ORCAMENTOS!$C:$C,"ISS",T_ORCAMENTOS!$H:$H,"3/2026") | P30: =-Fiscal!F20+SUMIFS(Aut_Ajustes_Manuais!$G:$G,Aut_Ajustes_Manuais!$I:$I,DRE!N$4,Aut_Ajustes_Manuais!$F:$F,"ISS") | R30: =-SUMIFS(T_ORCAMENTOS!$E:$E,T_ORCAMENTOS!$C:$C,"ISS",T_ORCAMENTOS!$H:$H,"4/2026") | S30: =-Fiscal!H20+SUMIFS(Aut_Ajustes_Manuais!$G:$G,Aut_Ajustes_Manuais!$I:$I,DRE!Q$4,Aut_Ajustes_Manuais!$F:$F,"ISS") | U30: =-SUMIFS(T_ORCAMENTOS!$E:$E,T_ORCAMENTOS!$C:$C,"ISS",T_ORCAMENTOS!$H:$H,"5/2026") | V30: =-Fiscal!I20+SUMIFS(Aut_Ajustes_Manuais!$G:$G,Aut_Ajustes_Manuais!$I:$I,DRE!T$4,Aut_Ajustes_Manuais!$F:$F,"ISS") | X30: =-SUMIFS(T_ORCAMENTOS!$E:$E,T_ORCAMENTOS!$C:$C,"ISS",T_ORCAMENTOS!$H:$H,"6/2026") | Y30: =-Fiscal!J20+SUMIFS(Aut_Ajustes_Manuais!$G:$G,Aut_Ajustes_Manuais!$I:$I,DRE!W$4,Aut_Ajustes_Manuais!$F:$F,"ISS") | AA30: =-SUMIFS(T_ORCAMENTOS!$E:$E,T_ORCAMENTOS!$C:$C,"ISS",T_ORCAMENTOS!$H:$H,"7/2026") | AB30: =-Fiscal!L20+SUMIFS(Aut_Ajustes_Manuais!$G:$G,Aut_Ajustes_Manuais!$I:$I,DRE!Z$4,Aut_Ajustes_Manuais!$F:$F,"ISS") | AD30: =-SUMIFS(T_ORCAMENTOS!$E:$E,T_ORCAMENTOS!$C:$C,"ISS",T_ORCAMENTOS!$H:$H,"8/2026") | AE30: =-Fiscal!M20+SUMIFS(Aut_Ajustes_Manuais!$G:$G,Aut_Ajustes_Manuais!$I:$I,DRE!AC$4,Aut_Ajustes_Manuais!$F:$F,"ISS") | AG30: =-SUMIFS(T_ORCAMENTOS!$E:$E,T_ORCAMENTOS!$C:$C,"ISS",T_ORCAMENTOS!$H:$H,"9/2026") | AH30: =-Fiscal!N20+SUMIFS(Aut_Ajustes_Manuais!$G:$G,Aut_Ajustes_Manuais!$I:$I,DRE!AF$4,Aut_Ajustes_Manuais!$F:$F,"ISS") | AJ30: =-SUMIFS(T_ORCAMENTOS!$E:$E,T_ORCAMENTOS!$C:$C,"ISS",T_ORCAMENTOS!$H:$H,"10/2026") | AK30: =-Fiscal!P20+SUMIFS(Aut_Ajustes_Manuais!$G:$G,Aut_Ajustes_Manuais!$I:$I,DRE!AI$4,Aut_Ajustes_Manuais!$F:$F,"ISS") | AM30: =-SUMIFS(T_ORCAMENTOS!$E:$E,T_ORCAMENTOS!$C:$C,"ISS",T_ORCAMENTOS!$H:$H,"11/2026") | AN30: =-Fiscal!Q20+SUMIFS(Aut_Ajustes_Manuais!$G:$G,Aut_Ajustes_Manuais!$I:$I,DRE!AL$4,Aut_Ajustes_Manuais!$F:$F,"ISS") | AP30: =-SUMIFS(T_ORCAMENTOS!$E:$E,T_ORCAMENTOS!$C:$C,"ISS",T_ORCAMENTOS!$H:$H,"12/2026") | AQ30: =-Fiscal!R20+SUMIFS(Aut_Ajustes_Manuais!$G:$G,Aut_Ajustes_Manuais!$I:$I,DRE!AO$4,Aut_Ajustes_Manuais!$F:$F,"ISS") | AR30: =SUMIFS($H30:$AO30,$H$5:$AO$5,"<"&MONTH(TODAY()),$H$6:$AO$6,"REAL 25") | AS30: =SUMIFS($I30:$AP30,$I$5:$AP$5,"<"&MONTH(TODAY()),$I$6:$AP$6,"ORÇADO ") | AT30: =SUMIFS($J30:$AQ30,$J$5:$AQ$5,"<"&MONTH(TODAY()),$J$6:$AQ$6,"REAL 26") | AU30: =SUM(H30,K30,N30,Q30,T30,W30,Z30,AC30,AF30,AI30,AL30,AO30) | AV30: =SUM(I30,L30,O30,R30,U30,X30,AA30,AD30,AG30,AJ30,AM30,AP30) | AW30: =SUM(J30,M30,P30,S30,V30,Y30,AB30,AE30,AH30,AK30,AN30,AQ30) | AX30: =SUM(H30,K30,N30) | AY30: =SUM(I30,L30,O30) | AZ30: =SUM(J30,M30,P30) | BA30: =SUM(Q30,T30,W30) | BB30: =SUM(R30,U30,X30) | BC30: =SUM(S30,V30,Y30) | BD30: =SUM(Z30,AC30,AF30) | BE30: =SUM(AA30,AD30,AG30) | BF30: =SUM(AB30,AE30,AH30) | BG30: =SUM(AI30,AL30,AO30) | BH30: =SUM(AJ30,AM30,AP30) | BI30: =SUM(AK30,AN30,AQ30)
A32: RECEITA LÍQUIDA | I32: =SUM(I27,I21,I8) | J32: =SUM(J27,J21,J8)+SUMIFS(Aut_Ajustes_Manuais!$G:$G,Aut_Ajustes_Manuais!$I:$I,DRE!H$4,Aut_Ajustes_Manuais!$F:$F,"RECEITA LÍQUIDA") | L32: =SUM(L27,L21,L8) | M32: =SUM(M27,M21,M8)+SUMIFS(Aut_Ajustes_Manuais!$G:$G,Aut_Ajustes_Manuais!$I:$I,DRE!K$4,Aut_Ajustes_Manuais!$F:$F,"RECEITA LÍQUIDA") | O32: =SUM(O27,O21,O8) | P32: =SUM(P27,P21,P8)+SUMIFS(Aut_Ajustes_Manuais!$G:$G,Aut_Ajustes_Manuais!$I:$I,DRE!N$4,Aut_Ajustes_Manuais!$F:$F,"RECEITA LÍQUIDA") | R32: =SUM(R27,R21,R8) | S32: =SUM(S27,S21,S8)+SUMIFS(Aut_Ajustes_Manuais!$G:$G,Aut_Ajustes_Manuais!$I:$I,DRE!Q$4,Aut_Ajustes_Manuais!$F:$F,"RECEITA LÍQUIDA") | U32: =SUM(U27,U21,U8) | V32: =SUM(V27,V21,V8)+SUMIFS(Aut_Ajustes_Manuais!$G:$G,Aut_Ajustes_Manuais!$I:$I,DRE!T$4,Aut_Ajustes_Manuais!$F:$F,"RECEITA LÍQUIDA") | X32: =SUM(X27,X21,X8) | Y32: =SUM(Y27,Y21,Y8)+SUMIFS(Aut_Ajustes_Manuais!$G:$G,Aut_Ajustes_Manuais!$I:$I,DRE!W$4,Aut_Ajustes_Manuais!$F:$F,"RECEITA LÍQUIDA") | AA32: =SUM(AA27,AA21,AA8) | AB32: =SUM(AB27,AB21,AB8)+SUMIFS(Aut_Ajustes_Manuais!$G:$G,Aut_Ajustes_Manuais!$I:$I,DRE!Z$4,Aut_Ajustes_Manuais!$F:$F,"RECEITA LÍQUIDA") | AD32: =SUM(AD27,AD21,AD8) | AE32: =SUM(AE27,AE21,AE8)+SUMIFS(Aut_Ajustes_Manuais!$G:$G,Aut_Ajustes_Manuais!$I:$I,DRE!AC$4,Aut_Ajustes_Manuais!$F:$F,"RECEITA LÍQUIDA") | AG32: =SUM(AG27,AG21,AG8) | AH32: =SUM(AH27,AH21,AH8)+SUMIFS(Aut_Ajustes_Manuais!$G:$G,Aut_Ajustes_Manuais!$I:$I,DRE!AF$4,Aut_Ajustes_Manuais!$F:$F,"RECEITA LÍQUIDA") | AJ32: =SUM(AJ27,AJ21,AJ8) | AK32: =SUM(AK27,AK21,AK8)+SUMIFS(Aut_Ajustes_Manuais!$G:$G,Aut_Ajustes_Manuais!$I:$I,DRE!AI$4,Aut_Ajustes_Manuais!$F:$F,"RECEITA LÍQUIDA") | AM32: =SUM(AM27,AM21,AM8) | AN32: =SUM(AN27,AN21,AN8)+SUMIFS(Aut_Ajustes_Manuais!$G:$G,Aut_Ajustes_Manuais!$I:$I,DRE!AL$4,Aut_Ajustes_Manuais!$F:$F,"RECEITA LÍQUIDA") | AP32: =SUM(AP27,AP21,AP8) | AQ32: =SUM(AQ27,AQ21,AQ8)+SUMIFS(Aut_Ajustes_Manuais!$G:$G,Aut_Ajustes_Manuais!$I:$I,DRE!AO$4,Aut_Ajustes_Manuais!$F:$F,"RECEITA LÍQUIDA") | AR32: =SUM(AR27,AR21,AR8) | AS32: =SUM(AS27,AS21,AS8) | AT32: =SUM(AT27,AT21,AT8) | AU32: =SUM(AU27,AU21,AU8) | AV32: =SUM(AV27,AV21,AV8) | AW32: =SUM(AW27,AW21,AW8) | AX32: =SUM(AX27,AX21,AX8) | AY32: =SUM(AY27,AY21,AY8) | ... BI32: =SUM(BI27,BI21,BI8)
J33: =I39*J2 | M33: =L39*M2 | P33: =O39*P2
A34: (-) Custo Mercadoria Vendida | C34: Premissas | D34: Valores | E34: % Incid | I34: =SUM(I35:I38) | J34: =SUM(J35:J38)+SUMIFS(Aut_Ajustes_Manuais!$G:$G,Aut_Ajustes_Manuais!$I:$I,DRE!H$4,Aut_Ajustes_Manuais!$F:$F,"(-) Custo Mercadoria Vendida") | L34: =SUM(L35:L38) | M34: =SUM(M35:M38)+SUMIFS(Aut_Ajustes_Manuais!$G:$G,Aut_Ajustes_Manuais!$I:$I,DRE!K$4,Aut_Ajustes_Manuais!$F:$F,"(-) Custo Mercadoria Vendida") | O34: =SUM(O35:O38) | P34: =SUM(P35:P38)+SUMIFS(Aut_Ajustes_Manuais!$G:$G,Aut_Ajustes_Manuais!$I:$I,DRE!N$4,Aut_Ajustes_Manuais!$F:$F,"(-) Custo Mercadoria Vendida") | R34: =SUM(R35:R38) | S34: =SUM(S35:S38)+SUMIFS(Aut_Ajustes_Manuais!$G:$G,Aut_Ajustes_Manuais!$I:$I,DRE!Q$4,Aut_Ajustes_Manuais!$F:$F,"(-) Custo Mercadoria Vendida") | U34: =SUM(U35:U38) | V34: =SUM(V35:V38)+SUMIFS(Aut_Ajustes_Manuais!$G:$G,Aut_Ajustes_Manuais!$I:$I,DRE!T$4,Aut_Ajustes_Manuais!$F:$F,"(-) Custo Mercadoria Vendida") | X34: =SUM(X35:X38) | Y34: =SUM(Y35:Y38)+SUMIFS(Aut_Ajustes_Manuais!$G:$G,Aut_Ajustes_Manuais!$I:$I,DRE!W$4,Aut_Ajustes_Manuais!$F:$F,"(-) Custo Mercadoria Vendida") | AA34: =SUM(AA35:AA38) | AB34: =SUM(AB35:AB38)+SUMIFS(Aut_Ajustes_Manuais!$G:$G,Aut_Ajustes_Manuais!$I:$I,DRE!Z$4,Aut_Ajustes_Manuais!$F:$F,"(-) Custo Mercadoria Vendida") | AD34: =SUM(AD35:AD38) | AE34: =SUM(AE35:AE38)+SUMIFS(Aut_Ajustes_Manuais!$G:$G,Aut_Ajustes_Manuais!$I:$I,DRE!AC$4,Aut_Ajustes_Manuais!$F:$F,"(-) Custo Mercadoria Vendida") | AG34: =SUM(AG35:AG38) | AH34: =SUM(AH35:AH38)+SUMIFS(Aut_Ajustes_Manuais!$G:$G,Aut_Ajustes_Manuais!$I:$I,DRE!AF$4,Aut_Ajustes_Manuais!$F:$F,"(-) Custo Mercadoria Vendida") | AJ34: =SUM(AJ35:AJ38) | AK34: =SUM(AK35:AK38)+SUMIFS(Aut_Ajustes_Manuais!$G:$G,Aut_Ajustes_Manuais!$I:$I,DRE!AI$4,Aut_Ajustes_Manuais!$F:$F,"(-) Custo Mercadoria Vendida") | AM34: =SUM(AM35:AM38) | AN34: =SUM(AN35:AN38)+SUMIFS(Aut_Ajustes_Manuais!$G:$G,Aut_Ajustes_Manuais!$I:$I,DRE!AL$4,Aut_Ajustes_Manuais!$F:$F,"(-) Custo Mercadoria Vendida") | AP34: =SUM(AP35:AP38) | AQ34: =SUM(AQ35:AQ38)+SUMIFS(Aut_Ajustes_Manuais!$G:$G,Aut_Ajustes_Manuais!$I:$I,DRE!AO$4,Aut_Ajustes_Manuais!$F:$F,"(-) Custo Mercadoria Vendida") | AR34: =SUM(AR35:AR38) | AS34: =SUM(AS35:AS38) | AT34: =SUM(AT35:AT38) | AU34: =SUM(AU35:AU38) | AV34: =SUM(AV35:AV38) | AW34: =SUM(AW35:AW38) | AX34: =SUM(AX35:AX38) | AY34: =SUM(AY35:AY38) | ... BI34: =SUM(BI35:BI38)
A35: Alimentação D | C35: Estim. Mensal | E35: 0.33 | I35: =-SUMIFS(T_ORCAMENTOS!$E:$E,T_ORCAMENTOS!$C:$C,"Insumos - Alimentos",T_ORCAMENTOS!$H:$H,"1/2026") | J35: =-CMV_Manual!D22+SUMIFS(Aut_Ajustes_Manuais!$G:$G,Aut_Ajustes_Manuais!$I:$I,DRE!H$4,Aut_Ajustes_Manuais!$F:$F,"Insumos - Alimentos") | L35: =-SUMIFS(T_ORCAMENTOS!$E:$E,T_ORCAMENTOS!$C:$C,"Insumos - Alimentos",T_ORCAMENTOS!$H:$H,"2/2026") | M35: =-CMV_Manual!E22+SUMIFS(Aut_Ajustes_Manuais!$G:$G,Aut_Ajustes_Manuais!$I:$I,DRE!K$4,Aut_Ajustes_Manuais!$F:$F,"Insumos - Alimentos") | O35: =-SUMIFS(T_ORCAMENTOS!$E:$E,T_ORCAMENTOS!$C:$C,"Insumos - Alimentos",T_ORCAMENTOS!$H:$H,"3/2026") | P35: =-CMV_Manual!F22+SUMIFS(Aut_Ajustes_Manuais!$G:$G,Aut_Ajustes_Manuais!$I:$I,DRE!N$4,Aut_Ajustes_Manuais!$F:$F,"Insumos - Alimentos") | R35: =-SUMIFS(T_ORCAMENTOS!$E:$E,T_ORCAMENTOS!$C:$C,"Insumos - Alimentos",T_ORCAMENTOS!$H:$H,"4/2026") | S35: =-CMV_Manual!G22+SUMIFS(Aut_Ajustes_Manuais!$G:$G,Aut_Ajustes_Manuais!$I:$I,DRE!Q$4,Aut_Ajustes_Manuais!$F:$F,"Insumos - Alimentos") | U35: =-SUMIFS(T_ORCAMENTOS!$E:$E,T_ORCAMENTOS!$C:$C,"Insumos - Alimentos",T_ORCAMENTOS!$H:$H,"5/2026") | V35: =-CMV_Manual!H22+SUMIFS(Aut_Ajustes_Manuais!$G:$G,Aut_Ajustes_Manuais!$I:$I,DRE!T$4,Aut_Ajustes_Manuais!$F:$F,"Insumos - Alimentos") | X35: =-SUMIFS(T_ORCAMENTOS!$E:$E,T_ORCAMENTOS!$C:$C,"Insumos - Alimentos",T_ORCAMENTOS!$H:$H,"6/2026") | Y35: =-CMV_Manual!I22+SUMIFS(Aut_Ajustes_Manuais!$G:$G,Aut_Ajustes_Manuais!$I:$I,DRE!W$4,Aut_Ajustes_Manuais!$F:$F,"Insumos - Alimentos") | AA35: =-SUMIFS(T_ORCAMENTOS!$E:$E,T_ORCAMENTOS!$C:$C,"Insumos - Alimentos",T_ORCAMENTOS!$H:$H,"7/2026") | AB35: =-CMV_Manual!J22+SUMIFS(Aut_Ajustes_Manuais!$G:$G,Aut_Ajustes_Manuais!$I:$I,DRE!Z$4,Aut_Ajustes_Manuais!$F:$F,"Insumos - Alimentos") | AD35: =-SUMIFS(T_ORCAMENTOS!$E:$E,T_ORCAMENTOS!$C:$C,"Insumos - Alimentos",T_ORCAMENTOS!$H:$H,"8/2026") | AE35: =-CMV_Manual!K22+SUMIFS(Aut_Ajustes_Manuais!$G:$G,Aut_Ajustes_Manuais!$I:$I,DRE!AC$4,Aut_Ajustes_Manuais!$F:$F,"Insumos - Alimentos") | AG35: =-SUMIFS(T_ORCAMENTOS!$E:$E,T_ORCAMENTOS!$C:$C,"Insumos - Alimentos",T_ORCAMENTOS!$H:$H,"9/2026") | AH35: =-CMV_Manual!L22+SUMIFS(Aut_Ajustes_Manuais!$G:$G,Aut_Ajustes_Manuais!$I:$I,DRE!AF$4,Aut_Ajustes_Manuais!$F:$F,"Insumos - Alimentos") | AJ35: =-SUMIFS(T_ORCAMENTOS!$E:$E,T_ORCAMENTOS!$C:$C,"Insumos - Alimentos",T_ORCAMENTOS!$H:$H,"10/2026") | AK35: =-CMV_Manual!M22+SUMIFS(Aut_Ajustes_Manuais!$G:$G,Aut_Ajustes_Manuais!$I:$I,DRE!AI$4,Aut_Ajustes_Manuais!$F:$F,"Insumos - Alimentos") | AM35: =-SUMIFS(T_ORCAMENTOS!$E:$E,T_ORCAMENTOS!$C:$C,"Insumos - Alimentos",T_ORCAMENTOS!$H:$H,"11/2026") | AN35: =-CMV_Manual!N22+SUMIFS(Aut_Ajustes_Manuais!$G:$G,Aut_Ajustes_Manuais!$I:$I,DRE!AL$4,Aut_Ajustes_Manuais!$F:$F,"Insumos - Alimentos") | AP35: =-SUMIFS(T_ORCAMENTOS!$E:$E,T_ORCAMENTOS!$C:$C,"Insumos - Alimentos",T_ORCAMENTOS!$H:$H,"12/2026") | AQ35: =-CMV_Manual!O22+SUMIFS(Aut_Ajustes_Manuais!$G:$G,Aut_Ajustes_Manuais!$I:$I,DRE!AO$4,Aut_Ajustes_Manuais!$F:$F,"Insumos - Alimentos") | AR35: =SUMIFS($H35:$AO35,$H$5:$AO$5,"<"&MONTH(TODAY()),$H$6:$AO$6,"REAL 25") | AS35: =SUMIFS($I35:$AP35,$I$5:$AP$5,"<"&MONTH(TODAY()),$I$6:$AP$6,"ORÇADO ") | AT35: =SUMIFS($J35:$AQ35,$J$5:$AQ$5,"<"&MONTH(TODAY()),$J$6:$AQ$6,"REAL 26") | AU35: =SUM(H35,K35,N35,Q35,T35,W35,Z35,AC35,AF35,AI35,AL35,AO35) | AV35: =SUM(I35,L35,O35,R35,U35,X35,AA35,AD35,AG35,AJ35,AM35,AP35) | AW35: =SUM(J35,M35,P35,S35,V35,Y35,AB35,AE35,AH35,AK35,AN35,AQ35) | AX35: =SUM(H35,K35,N35) | AY35: =SUM(I35,L35,O35) | AZ35: =SUM(J35,M35,P35) | BA35: =SUM(Q35,T35,W35) | BB35: =SUM(R35,U35,X35) | BC35: =SUM(S35,V35,Y35) | BD35: =SUM(Z35,AC35,AF35) | BE35: =SUM(AA35,AD35,AG35) | BF35: =SUM(AB35,AE35,AH35) | BG35: =SUM(AI35,AL35,AO35) | BH35: =SUM(AJ35,AM35,AP35) | BI35: =SUM(AK35,AN35,AQ35)
A36: Bebida D | C36: Estim. Mensal | E36: 0.18 | I36: =-SUMIFS(T_ORCAMENTOS!$E:$E,T_ORCAMENTOS!$C:$C,"Insumos - Bebidas",T_ORCAMENTOS!$H:$H,"1/2026") | J36: =-CMV_Manual!D23+SUMIFS(Aut_Ajustes_Manuais!$G:$G,Aut_Ajustes_Manuais!$I:$I,DRE!H$4,Aut_Ajustes_Manuais!$F:$F,"Insumos - Bebidas") | L36: =-SUMIFS(T_ORCAMENTOS!$E:$E,T_ORCAMENTOS!$C:$C,"Insumos - Bebidas",T_ORCAMENTOS!$H:$H,"2/2026") | M36: =-CMV_Manual!E23+SUMIFS(Aut_Ajustes_Manuais!$G:$G,Aut_Ajustes_Manuais!$I:$I,DRE!K$4,Aut_Ajustes_Manuais!$F:$F,"Insumos - Bebidas") | O36: =-SUMIFS(T_ORCAMENTOS!$E:$E,T_ORCAMENTOS!$C:$C,"Insumos - Bebidas",T_ORCAMENTOS!$H:$H,"3/2026") | P36: =-CMV_Manual!F23+SUMIFS(Aut_Ajustes_Manuais!$G:$G,Aut_Ajustes_Manuais!$I:$I,DRE!N$4,Aut_Ajustes_Manuais!$F:$F,"Insumos - Bebidas") | R36: =-SUMIFS(T_ORCAMENTOS!$E:$E,T_ORCAMENTOS!$C:$C,"Insumos - Bebidas",T_ORCAMENTOS!$H:$H,"4/2026") | S36: =-CMV_Manual!G23+SUMIFS(Aut_Ajustes_Manuais!$G:$G,Aut_Ajustes_Manuais!$I:$I,DRE!Q$4,Aut_Ajustes_Manuais!$F:$F,"Insumos - Bebidas") | U36: =-SUMIFS(T_ORCAMENTOS!$E:$E,T_ORCAMENTOS!$C:$C,"Insumos - Bebidas",T_ORCAMENTOS!$H:$H,"5/2026") | V36: =-CMV_Manual!H23+SUMIFS(Aut_Ajustes_Manuais!$G:$G,Aut_Ajustes_Manuais!$I:$I,DRE!T$4,Aut_Ajustes_Manuais!$F:$F,"Insumos - Bebidas") | X36: =-SUMIFS(T_ORCAMENTOS!$E:$E,T_ORCAMENTOS!$C:$C,"Insumos - Bebidas",T_ORCAMENTOS!$H:$H,"6/2026") | Y36: =-CMV_Manual!I23+SUMIFS(Aut_Ajustes_Manuais!$G:$G,Aut_Ajustes_Manuais!$I:$I,DRE!W$4,Aut_Ajustes_Manuais!$F:$F,"Insumos - Bebidas") | AA36: =-SUMIFS(T_ORCAMENTOS!$E:$E,T_ORCAMENTOS!$C:$C,"Insumos - Bebidas",T_ORCAMENTOS!$H:$H,"7/2026") | AB36: =-CMV_Manual!J23+SUMIFS(Aut_Ajustes_Manuais!$G:$G,Aut_Ajustes_Manuais!$I:$I,DRE!Z$4,Aut_Ajustes_Manuais!$F:$F,"Insumos - Bebidas") | AD36: =-SUMIFS(T_ORCAMENTOS!$E:$E,T_ORCAMENTOS!$C:$C,"Insumos - Bebidas",T_ORCAMENTOS!$H:$H,"8/2026") | AE36: =-CMV_Manual!K23+SUMIFS(Aut_Ajustes_Manuais!$G:$G,Aut_Ajustes_Manuais!$I:$I,DRE!AC$4,Aut_Ajustes_Manuais!$F:$F,"Insumos - Bebidas") | AG36: =-SUMIFS(T_ORCAMENTOS!$E:$E,T_ORCAMENTOS!$C:$C,"Insumos - Bebidas",T_ORCAMENTOS!$H:$H,"9/2026") | AH36: =-CMV_Manual!L23+SUMIFS(Aut_Ajustes_Manuais!$G:$G,Aut_Ajustes_Manuais!$I:$I,DRE!AF$4,Aut_Ajustes_Manuais!$F:$F,"Insumos - Bebidas") | AJ36: =-SUMIFS(T_ORCAMENTOS!$E:$E,T_ORCAMENTOS!$C:$C,"Insumos - Bebidas",T_ORCAMENTOS!$H:$H,"10/2026") | AK36: =-CMV_Manual!M23+SUMIFS(Aut_Ajustes_Manuais!$G:$G,Aut_Ajustes_Manuais!$I:$I,DRE!AI$4,Aut_Ajustes_Manuais!$F:$F,"Insumos - Bebidas") | AM36: =-SUMIFS(T_ORCAMENTOS!$E:$E,T_ORCAMENTOS!$C:$C,"Insumos - Bebidas",T_ORCAMENTOS!$H:$H,"11/2026") | AN36: =-CMV_Manual!N23+SUMIFS(Aut_Ajustes_Manuais!$G:$G,Aut_Ajustes_Manuais!$I:$I,DRE!AL$4,Aut_Ajustes_Manuais!$F:$F,"Insumos - Bebidas") | AP36: =-SUMIFS(T_ORCAMENTOS!$E:$E,T_ORCAMENTOS!$C:$C,"Insumos - Bebidas",T_ORCAMENTOS!$H:$H,"12/2026") | AQ36: =-CMV_Manual!O23+SUMIFS(Aut_Ajustes_Manuais!$G:$G,Aut_Ajustes_Manuais!$I:$I,DRE!AO$4,Aut_Ajustes_Manuais!$F:$F,"Insumos - Bebidas") | AR36: =SUMIFS($H36:$AO36,$H$5:$AO$5,"<"&MONTH(TODAY()),$H$6:$AO$6,"REAL 25") | AS36: =SUMIFS($I36:$AP36,$I$5:$AP$5,"<"&MONTH(TODAY()),$I$6:$AP$6,"ORÇADO ") | AT36: =SUMIFS($J36:$AQ36,$J$5:$AQ$5,"<"&MONTH(TODAY()),$J$6:$AQ$6,"REAL 26") | AU36: =SUM(H36,K36,N36,Q36,T36,W36,Z36,AC36,AF36,AI36,AL36,AO36) | AV36: =SUM(I36,L36,O36,R36,U36,X36,AA36,AD36,AG36,AJ36,AM36,AP36) | AW36: =SUM(J36,M36,P36,S36,V36,Y36,AB36,AE36,AH36,AK36,AN36,AQ36) | AX36: =SUM(H36,K36,N36) | AY36: =SUM(I36,L36,O36) | AZ36: =SUM(J36,M36,P36) | BA36: =SUM(Q36,T36,W36) | BB36: =SUM(R36,U36,X36) | BC36: =SUM(S36,V36,Y36) | BD36: =SUM(Z36,AC36,AF36) | BE36: =SUM(AA36,AD36,AG36) | BF36: =SUM(AB36,AE36,AH36) | BG36: =SUM(AI36,AL36,AO36) | BH36: =SUM(AJ36,AM36,AP36) | BI36: =SUM(AK36,AN36,AQ36)
A37: Embalagens | C37: Estim. Mensal | I37: =-SUMIFS(T_ORCAMENTOS!$E:$E,T_ORCAMENTOS!$C:$C,"Insumos - Embalagens",T_ORCAMENTOS!$H:$H,"1/2026") | J37: =SUMIFS(Aut_BlueMe_Sem_Pedido!$J:$J,Aut_BlueMe_Sem_Pedido!$Q:$Q,DRE!H$4,Aut_BlueMe_Sem_Pedido!$H:$H,DRE!$A37)+SUMIFS(Aut_Ajustes_Manuais!$G:$G,Aut_Ajustes_Manuais!$I:$I,DRE!H$4,Aut_Ajustes_Manuais!$F:$F,"Insumos - Embalagens") | L37: =-SUMIFS(T_ORCAMENTOS!$E:$E,T_ORCAMENTOS!$C:$C,"Insumos - Embalagens",T_ORCAMENTOS!$H:$H,"2/2026") | M37: =SUMIFS(Aut_BlueMe_Sem_Pedido!$J:$J,Aut_BlueMe_Sem_Pedido!$Q:$Q,DRE!K$4,Aut_BlueMe_Sem_Pedido!$H:$H,DRE!$A37)+SUMIFS(Aut_Ajustes_Manuais!$G:$G,Aut_Ajustes_Manuais!$I:$I,DRE!K$4,Aut_Ajustes_Manuais!$F:$F,"Insumos - Embalagens") | O37: =-SUMIFS(T_ORCAMENTOS!$E:$E,T_ORCAMENTOS!$C:$C,"Insumos - Embalagens",T_ORCAMENTOS!$H:$H,"3/2026") | P37: =SUMIFS(Aut_BlueMe_Sem_Pedido!$J:$J,Aut_BlueMe_Sem_Pedido!$Q:$Q,DRE!N$4,Aut_BlueMe_Sem_Pedido!$H:$H,DRE!$A37)+SUMIFS(Aut_Ajustes_Manuais!$G:$G,Aut_Ajustes_Manuais!$I:$I,DRE!N$4,Aut_Ajustes_Manuais!$F:$F,"Insumos - Embalagens") | R37: =-SUMIFS(T_ORCAMENTOS!$E:$E,T_ORCAMENTOS!$C:$C,"Insumos - Embalagens",T_ORCAMENTOS!$H:$H,"4/2026") | S37: =SUMIFS(Aut_BlueMe_Sem_Pedido!$J:$J,Aut_BlueMe_Sem_Pedido!$Q:$Q,DRE!Q$4,Aut_BlueMe_Sem_Pedido!$H:$H,DRE!$A37)+SUMIFS(Aut_Ajustes_Manuais!$G:$G,Aut_Ajustes_Manuais!$I:$I,DRE!Q$4,Aut_Ajustes_Manuais!$F:$F,"Insumos - Embalagens") | U37: =-SUMIFS(T_ORCAMENTOS!$E:$E,T_ORCAMENTOS!$C:$C,"Insumos - Embalagens",T_ORCAMENTOS!$H:$H,"5/2026") | V37: =SUMIFS(Aut_BlueMe_Sem_Pedido!$J:$J,Aut_BlueMe_Sem_Pedido!$Q:$Q,DRE!T$4,Aut_BlueMe_Sem_Pedido!$H:$H,DRE!$A37)+SUMIFS(Aut_Ajustes_Manuais!$G:$G,Aut_Ajustes_Manuais!$I:$I,DRE!T$4,Aut_Ajustes_Manuais!$F:$F,"Insumos - Embalagens") | X37: =-SUMIFS(T_ORCAMENTOS!$E:$E,T_ORCAMENTOS!$C:$C,"Insumos - Embalagens",T_ORCAMENTOS!$H:$H,"6/2026") | Y37: =SUMIFS(Aut_BlueMe_Sem_Pedido!$J:$J,Aut_BlueMe_Sem_Pedido!$Q:$Q,DRE!W$4,Aut_BlueMe_Sem_Pedido!$H:$H,DRE!$A37)+SUMIFS(Aut_Ajustes_Manuais!$G:$G,Aut_Ajustes_Manuais!$I:$I,DRE!W$4,Aut_Ajustes_Manuais!$F:$F,"Insumos - Embalagens") | AA37: =-SUMIFS(T_ORCAMENTOS!$E:$E,T_ORCAMENTOS!$C:$C,"Insumos - Embalagens",T_ORCAMENTOS!$H:$H,"7/2026") | AB37: =SUMIFS(Aut_BlueMe_Sem_Pedido!$J:$J,Aut_BlueMe_Sem_Pedido!$Q:$Q,DRE!Z$4,Aut_BlueMe_Sem_Pedido!$H:$H,DRE!$A37)+SUMIFS(Aut_Ajustes_Manuais!$G:$G,Aut_Ajustes_Manuais!$I:$I,DRE!Z$4,Aut_Ajustes_Manuais!$F:$F,"Insumos - Embalagens") | AD37: =-SUMIFS(T_ORCAMENTOS!$E:$E,T_ORCAMENTOS!$C:$C,"Insumos - Embalagens",T_ORCAMENTOS!$H:$H,"8/2026") | AE37: =SUMIFS(Aut_BlueMe_Sem_Pedido!$J:$J,Aut_BlueMe_Sem_Pedido!$Q:$Q,DRE!AC$4,Aut_BlueMe_Sem_Pedido!$H:$H,DRE!$A37)+SUMIFS(Aut_Ajustes_Manuais!$G:$G,Aut_Ajustes_Manuais!$I:$I,DRE!AC$4,Aut_Ajustes_Manuais!$F:$F,"Insumos - Embalagens") | AG37: =-SUMIFS(T_ORCAMENTOS!$E:$E,T_ORCAMENTOS!$C:$C,"Insumos - Embalagens",T_ORCAMENTOS!$H:$H,"9/2026") | AH37: =SUMIFS(Aut_BlueMe_Sem_Pedido!$J:$J,Aut_BlueMe_Sem_Pedido!$Q:$Q,DRE!AF$4,Aut_BlueMe_Sem_Pedido!$H:$H,DRE!$A37)+SUMIFS(Aut_Ajustes_Manuais!$G:$G,Aut_Ajustes_Manuais!$I:$I,DRE!AF$4,Aut_Ajustes_Manuais!$F:$F,"Insumos - Embalagens") | AJ37: =-SUMIFS(T_ORCAMENTOS!$E:$E,T_ORCAMENTOS!$C:$C,"Insumos - Embalagens",T_ORCAMENTOS!$H:$H,"10/2026") | AK37: =SUMIFS(Aut_BlueMe_Sem_Pedido!$J:$J,Aut_BlueMe_Sem_Pedido!$Q:$Q,DRE!AI$4,Aut_BlueMe_Sem_Pedido!$H:$H,DRE!$A37)+SUMIFS(Aut_Ajustes_Manuais!$G:$G,Aut_Ajustes_Manuais!$I:$I,DRE!AI$4,Aut_Ajustes_Manuais!$F:$F,"Insumos - Embalagens") | AM37: =-SUMIFS(T_ORCAMENTOS!$E:$E,T_ORCAMENTOS!$C:$C,"Insumos - Embalagens",T_ORCAMENTOS!$H:$H,"11/2026") | AN37: =SUMIFS(Aut_BlueMe_Sem_Pedido!$J:$J,Aut_BlueMe_Sem_Pedido!$Q:$Q,DRE!AL$4,Aut_BlueMe_Sem_Pedido!$H:$H,DRE!$A37)+SUMIFS(Aut_Ajustes_Manuais!$G:$G,Aut_Ajustes_Manuais!$I:$I,DRE!AL$4,Aut_Ajustes_Manuais!$F:$F,"Insumos - Embalagens") | AP37: =-SUMIFS(T_ORCAMENTOS!$E:$E,T_ORCAMENTOS!$C:$C,"Insumos - Embalagens",T_ORCAMENTOS!$H:$H,"12/2026") | AQ37: =SUMIFS(Aut_BlueMe_Sem_Pedido!$J:$J,Aut_BlueMe_Sem_Pedido!$Q:$Q,DRE!AO$4,Aut_BlueMe_Sem_Pedido!$H:$H,DRE!$A37)+SUMIFS(Aut_Ajustes_Manuais!$G:$G,Aut_Ajustes_Manuais!$I:$I,DRE!AO$4,Aut_Ajustes_Manuais!$F:$F,"Insumos - Embalagens") | AR37: =SUMIFS($H37:$AO37,$H$5:$AO$5,"<"&MONTH(TODAY()),$H$6:$AO$6,"REAL 25") | AS37: =SUMIFS($I37:$AP37,$I$5:$AP$5,"<"&MONTH(TODAY()),$I$6:$AP$6,"ORÇADO ") | AT37: =SUMIFS($J37:$AQ37,$J$5:$AQ$5,"<"&MONTH(TODAY()),$J$6:$AQ$6,"REAL 26") | AU37: =SUM(H37,K37,N37,Q37,T37,W37,Z37,AC37,AF37,AI37,AL37,AO37) | AV37: =SUM(I37,L37,O37,R37,U37,X37,AA37,AD37,AG37,AJ37,AM37,AP37) | AW37: =SUM(J37,M37,P37,S37,V37,Y37,AB37,AE37,AH37,AK37,AN37,AQ37) | AX37: =SUM(H37,K37,N37) | AY37: =SUM(I37,L37,O37) | AZ37: =SUM(J37,M37,P37) | BA37: =SUM(Q37,T37,W37) | BB37: =SUM(R37,U37,X37) | BC37: =SUM(S37,V37,Y37) | BD37: =SUM(Z37,AC37,AF37) | BE37: =SUM(AA37,AD37,AG37) | BF37: =SUM(AB37,AE37,AH37) | BG37: =SUM(AI37,AL37,AO37) | BH37: =SUM(AJ37,AM37,AP37) | BI37: =SUM(AK37,AN37,AQ37)
A38: Eventos A&B | C38: Estim. Mensal | I38: =-SUMIFS(T_ORCAMENTOS!$E:$E,T_ORCAMENTOS!$C:$C,"Insumos - Eventos A&B",T_ORCAMENTOS!$H:$H,"1/2026") | L38: =-SUMIFS(T_ORCAMENTOS!$E:$E,T_ORCAMENTOS!$C:$C,"Insumos - Eventos A&B",T_ORCAMENTOS!$H:$H,"2/2026") | O38: =-SUMIFS(T_ORCAMENTOS!$E:$E,T_ORCAMENTOS!$C:$C,"Insumos - Eventos A&B",T_ORCAMENTOS!$H:$H,"3/2026") | R38: =-SUMIFS(T_ORCAMENTOS!$E:$E,T_ORCAMENTOS!$C:$C,"Insumos - Eventos A&B",T_ORCAMENTOS!$H:$H,"4/2026") | U38: =-SUMIFS(T_ORCAMENTOS!$E:$E,T_ORCAMENTOS!$C:$C,"Insumos - Eventos A&B",T_ORCAMENTOS!$H:$H,"5/2026") | X38: =-SUMIFS(T_ORCAMENTOS!$E:$E,T_ORCAMENTOS!$C:$C,"Insumos - Eventos A&B",T_ORCAMENTOS!$H:$H,"6/2026") | AA38: =-SUMIFS(T_ORCAMENTOS!$E:$E,T_ORCAMENTOS!$C:$C,"Insumos - Eventos A&B",T_ORCAMENTOS!$H:$H,"7/2026") | AD38: =-SUMIFS(T_ORCAMENTOS!$E:$E,T_ORCAMENTOS!$C:$C,"Insumos - Eventos A&B",T_ORCAMENTOS!$H:$H,"8/2026") | AG38: =-SUMIFS(T_ORCAMENTOS!$E:$E,T_ORCAMENTOS!$C:$C,"Insumos - Eventos A&B",T_ORCAMENTOS!$H:$H,"9/2026") | AJ38: =-SUMIFS(T_ORCAMENTOS!$E:$E,T_ORCAMENTOS!$C:$C,"Insumos - Eventos A&B",T_ORCAMENTOS!$H:$H,"10/2026") | AM38: =-SUMIFS(T_ORCAMENTOS!$E:$E,T_ORCAMENTOS!$C:$C,"Insumos - Eventos A&B",T_ORCAMENTOS!$H:$H,"11/2026") | AP38: =-SUMIFS(T_ORCAMENTOS!$E:$E,T_ORCAMENTOS!$C:$C,"Insumos - Eventos A&B",T_ORCAMENTOS!$H:$H,"12/2026") | AR38: =SUMIFS($H38:$AO38,$H$5:$AO$5,"<"&MONTH(TODAY()),$H$6:$AO$6,"REAL 25") | AS38: =SUMIFS($I38:$AP38,$I$5:$AP$5,"<"&MONTH(TODAY()),$I$6:$AP$6,"ORÇADO ") | AT38: =SUMIFS($J38:$AQ38,$J$5:$AQ$5,"<"&MONTH(TODAY()),$J$6:$AQ$6,"REAL 26")
A39: % sobre Receita Bruta | I39: =IFERROR(I34/(I9+I10+I14+I17),0) | J39: =IFERROR(J34/(J9+J10+J14+J17),0)+SUMIFS(Aut_Ajustes_Manuais!$G:$G,Aut_Ajustes_Manuais!$I:$I,DRE!H$4,Aut_Ajustes_Manuais!$F:$F,"% sobre Receita Bruta") | L39: =IFERROR(L34/(L9+L10+L14+L17),0) | M39: =IFERROR(M34/(M9+M10+M14+M17),0)+SUMIFS(Aut_Ajustes_Manuais!$G:$G,Aut_Ajustes_Manuais!$I:$I,DRE!K$4,Aut_Ajustes_Manuais!$F:$F,"% sobre Receita Bruta") | O39: =IFERROR(O34/(O9+O10+O14+O17),0) | P39: =IFERROR(P34/(P9+P10+P14+P17),0)+SUMIFS(Aut_Ajustes_Manuais!$G:$G,Aut_Ajustes_Manuais!$I:$I,DRE!N$4,Aut_Ajustes_Manuais!$F:$F,"% sobre Receita Bruta") | R39: =IFERROR(R34/(R9+R10+R14+R17),0) | S39: =IFERROR(S34/(S9+S10+S14+S17),0)+SUMIFS(Aut_Ajustes_Manuais!$G:$G,Aut_Ajustes_Manuais!$I:$I,DRE!Q$4,Aut_Ajustes_Manuais!$F:$F,"% sobre Receita Bruta") | U39: =IFERROR(U34/(U9+U10+U14+U17),0) | V39: =IFERROR(V34/(V9+V10+V14+V17),0)+SUMIFS(Aut_Ajustes_Manuais!$G:$G,Aut_Ajustes_Manuais!$I:$I,DRE!T$4,Aut_Ajustes_Manuais!$F:$F,"% sobre Receita Bruta") | X39: =IFERROR(X34/(X9+X10+X14+X17),0) | Y39: =IFERROR(Y34/(Y9+Y10+Y14+Y17),0)+SUMIFS(Aut_Ajustes_Manuais!$G:$G,Aut_Ajustes_Manuais!$I:$I,DRE!W$4,Aut_Ajustes_Manuais!$F:$F,"% sobre Receita Bruta") | AA39: =IFERROR(AA34/(AA9+AA10+AA14+AA17),0) | AB39: =IFERROR(AB34/(AB9+AB10+AB14+AB17),0)+SUMIFS(Aut_Ajustes_Manuais!$G:$G,Aut_Ajustes_Manuais!$I:$I,DRE!Z$4,Aut_Ajustes_Manuais!$F:$F,"% sobre Receita Bruta") | AD39: =IFERROR(AD34/(AD9+AD10+AD14+AD17),0) | AE39: =IFERROR(AE34/(AE9+AE10+AE14+AE17),0)+SUMIFS(Aut_Ajustes_Manuais!$G:$G,Aut_Ajustes_Manuais!$I:$I,DRE!AC$4,Aut_Ajustes_Manuais!$F:$F,"% sobre Receita Bruta") | AG39: =IFERROR(AG34/(AG9+AG10+AG14+AG17),0) | AH39: =IFERROR(AH34/(AH9+AH10+AH14+AH17),0)+SUMIFS(Aut_Ajustes_Manuais!$G:$G,Aut_Ajustes_Manuais!$I:$I,DRE!AF$4,Aut_Ajustes_Manuais!$F:$F,"% sobre Receita Bruta") | AJ39: =IFERROR(AJ34/(AJ9+AJ10+AJ14+AJ17),0) | AK39: =IFERROR(AK34/(AK9+AK10+AK14+AK17),0)+SUMIFS(Aut_Ajustes_Manuais!$G:$G,Aut_Ajustes_Manuais!$I:$I,DRE!AI$4,Aut_Ajustes_Manuais!$F:$F,"% sobre Receita Bruta") | AM39: =IFERROR(AM34/(AM9+AM10+AM14+AM17),0) | AN39: =IFERROR(AN34/(AN9+AN10+AN14+AN17),0)+SUMIFS(Aut_Ajustes_Manuais!$G:$G,Aut_Ajustes_Manuais!$I:$I,DRE!AL$4,Aut_Ajustes_Manuais!$F:$F,"% sobre Receita Bruta") | AP39: =IFERROR(AP34/(AP9+AP10+AP14+AP17),0) | AQ39: =IFERROR(AQ34/(AQ9+AQ10+AQ14+AQ17),0)+SUMIFS(Aut_Ajustes_Manuais!$G:$G,Aut_Ajustes_Manuais!$I:$I,DRE!AO$4,Aut_Ajustes_Manuais!$F:$F,"% sobre Receita Bruta") | AR39: =IFERROR(AR34/(AR9+AR10+AR14+AR18),0) | AS39: =IFERROR(AS34/(AS9+AS10+AS14+AS18),0) | AT39: =IFERROR(AT34/(AT9+AT10+AT14+AT18),0) | AU39: =IFERROR(AU34/(AU9+AU10+AU14+AU17),0) | AV39: =IFERROR(AV34/(AV9+AV10+AV14+AV17),0) | AW39: =IFERROR(AW34/(AW9+AW10+AW14+AW17),0) | AX39: =IFERROR(AX34/(AX9+AX10+AX14+AX17),0) | AY39: =IFERROR(AY34/(AY9+AY10+AY14+AY17),0) | AZ39: =IFERROR(AZ34/(AZ9+AZ10+AZ14+AZ17),0) | BA39: =IFERROR(BA34/(BA9+BA10+BA14+BA17),0) | BB39: =IFERROR(BB34/(BB9+BB10+BB14+BB17),0) | ... BI39: =IFERROR(BI34/(BI9+BI10+BI14+BI17),0)
A40: % sobre Receita Líquida | I40: =IFERROR(I34/I32,0) | J40: =IFERROR(J34/J32,0)+SUMIFS(Aut_Ajustes_Manuais!$G:$G,Aut_Ajustes_Manuais!$I:$I,DRE!H$4,Aut_Ajustes_Manuais!$F:$F,"% sobre Receita Líquida") | L40: =IFERROR(L34/L32,0) | M40: =IFERROR(M34/M32,0)+SUMIFS(Aut_Ajustes_Manuais!$G:$G,Aut_Ajustes_Manuais!$I:$I,DRE!K$4,Aut_Ajustes_Manuais!$F:$F,"% sobre Receita Líquida") | O40: =IFERROR(O34/O32,0) | P40: =IFERROR(P34/P32,0)+SUMIFS(Aut_Ajustes_Manuais!$G:$G,Aut_Ajustes_Manuais!$I:$I,DRE!N$4,Aut_Ajustes_Manuais!$F:$F,"% sobre Receita Líquida") | R40: =IFERROR(R34/R32,0) | S40: =IFERROR(S34/S32,0)+SUMIFS(Aut_Ajustes_Manuais!$G:$G,Aut_Ajustes_Manuais!$I:$I,DRE!Q$4,Aut_Ajustes_Manuais!$F:$F,"% sobre Receita Líquida") | U40: =IFERROR(U34/U32,0) | V40: =IFERROR(V34/V32,0)+SUMIFS(Aut_Ajustes_Manuais!$G:$G,Aut_Ajustes_Manuais!$I:$I,DRE!T$4,Aut_Ajustes_Manuais!$F:$F,"% sobre Receita Líquida") | X40: =IFERROR(X34/X32,0) | Y40: =IFERROR(Y34/Y32,0)+SUMIFS(Aut_Ajustes_Manuais!$G:$G,Aut_Ajustes_Manuais!$I:$I,DRE!W$4,Aut_Ajustes_Manuais!$F:$F,"% sobre Receita Líquida") | AA40: =IFERROR(AA34/AA32,0) | AB40: =IFERROR(AB34/AB32,0)+SUMIFS(Aut_Ajustes_Manuais!$G:$G,Aut_Ajustes_Manuais!$I:$I,DRE!Z$4,Aut_Ajustes_Manuais!$F:$F,"% sobre Receita Líquida") | AD40: =IFERROR(AD34/AD32,0) | AE40: =IFERROR(AE34/AE32,0)+SUMIFS(Aut_Ajustes_Manuais!$G:$G,Aut_Ajustes_Manuais!$I:$I,DRE!AC$4,Aut_Ajustes_Manuais!$F:$F,"% sobre Receita Líquida") | AG40: =IFERROR(AG34/AG32,0) | AH40: =IFERROR(AH34/AH32,0)+SUMIFS(Aut_Ajustes_Manuais!$G:$G,Aut_Ajustes_Manuais!$I:$I,DRE!AF$4,Aut_Ajustes_Manuais!$F:$F,"% sobre Receita Líquida") | AJ40: =IFERROR(AJ34/AJ32,0) | AK40: =IFERROR(AK34/AK32,0)+SUMIFS(Aut_Ajustes_Manuais!$G:$G,Aut_Ajustes_Manuais!$I:$I,DRE!AI$4,Aut_Ajustes_Manuais!$F:$F,"% sobre Receita Líquida") | AM40: =IFERROR(AM34/AM32,0) | AN40: =IFERROR(AN34/AN32,0)+SUMIFS(Aut_Ajustes_Manuais!$G:$G,Aut_Ajustes_Manuais!$I:$I,DRE!AL$4,Aut_Ajustes_Manuais!$F:$F,"% sobre Receita Líquida") | AP40: =IFERROR(AP34/AP32,0) | AQ40: =IFERROR(AQ34/AQ32,0)+SUMIFS(Aut_Ajustes_Manuais!$G:$G,Aut_Ajustes_Manuais!$I:$I,DRE!AO$4,Aut_Ajustes_Manuais!$F:$F,"% sobre Receita Líquida") | AR40: =IFERROR(AR34/AR32,0) | AS40: =IFERROR(AS34/AS32,0) | AT40: =IFERROR(AT34/AT32,0) | AU40: =IFERROR(AU34/AU32,0) | AV40: =IFERROR(AV34/AV32,0) | AW40: =IFERROR(AW34/AW32,0) | AX40: =IFERROR(AX34/AX32,0) | AY40: =IFERROR(AY34/AY32,0) | ... BI40: =IFERROR(BI34/BI32,0)
A42: (-) Custos Artístico Geral | C42: Premissas | D42: Valores | E42: % Incid | I42: =SUM(I43,I49) | J42: =SUM(J43,J49)+SUMIFS(Aut_Ajustes_Manuais!$G:$G,Aut_Ajustes_Manuais!$I:$I,DRE!H$4,Aut_Ajustes_Manuais!$F:$F,"(-) Custos Artístico Geral") | L42: =SUM(L43,L49) | M42: =SUM(M43,M49)+SUMIFS(Aut_Ajustes_Manuais!$G:$G,Aut_Ajustes_Manuais!$I:$I,DRE!K$4,Aut_Ajustes_Manuais!$F:$F,"(-) Custos Artístico Geral") | O42: =SUM(O43,O49) | P42: =SUM(P43,P49)+SUMIFS(Aut_Ajustes_Manuais!$G:$G,Aut_Ajustes_Manuais!$I:$I,DRE!N$4,Aut_Ajustes_Manuais!$F:$F,"(-) Custos Artístico Geral") | R42: =SUM(R43,R49) | S42: =SUM(S43,S49)+SUMIFS(Aut_Ajustes_Manuais!$G:$G,Aut_Ajustes_Manuais!$I:$I,DRE!Q$4,Aut_Ajustes_Manuais!$F:$F,"(-) Custos Artístico Geral") | U42: =SUM(U43,U49) | V42: =SUM(V43,V49)+SUMIFS(Aut_Ajustes_Manuais!$G:$G,Aut_Ajustes_Manuais!$I:$I,DRE!T$4,Aut_Ajustes_Manuais!$F:$F,"(-) Custos Artístico Geral") | X42: =SUM(X43,X49) | Y42: =SUM(Y43,Y49)+SUMIFS(Aut_Ajustes_Manuais!$G:$G,Aut_Ajustes_Manuais!$I:$I,DRE!W$4,Aut_Ajustes_Manuais!$F:$F,"(-) Custos Artístico Geral") | AA42: =SUM(AA43,AA49) | AB42: =SUM(AB43,AB49)+SUMIFS(Aut_Ajustes_Manuais!$G:$G,Aut_Ajustes_Manuais!$I:$I,DRE!Z$4,Aut_Ajustes_Manuais!$F:$F,"(-) Custos Artístico Geral") | AD42: =SUM(AD43,AD49) | AE42: =SUM(AE43,AE49)+SUMIFS(Aut_Ajustes_Manuais!$G:$G,Aut_Ajustes_Manuais!$I:$I,DRE!AC$4,Aut_Ajustes_Manuais!$F:$F,"(-) Custos Artístico Geral") | AG42: =SUM(AG43,AG49) | AH42: =SUM(AH43,AH49)+SUMIFS(Aut_Ajustes_Manuais!$G:$G,Aut_Ajustes_Manuais!$I:$I,DRE!AF$4,Aut_Ajustes_Manuais!$F:$F,"(-) Custos Artístico Geral") | AJ42: =SUM(AJ43,AJ49) | AK42: =SUM(AK43,AK49)+SUMIFS(Aut_Ajustes_Manuais!$G:$G,Aut_Ajustes_Manuais!$I:$I,DRE!AI$4,Aut_Ajustes_Manuais!$F:$F,"(-) Custos Artístico Geral") | AM42: =SUM(AM43,AM49) | AN42: =SUM(AN43,AN49)+SUMIFS(Aut_Ajustes_Manuais!$G:$G,Aut_Ajustes_Manuais!$I:$I,DRE!AL$4,Aut_Ajustes_Manuais!$F:$F,"(-) Custos Artístico Geral") | AP42: =SUM(AP43,AP49) | AQ42: =SUM(AQ43,AQ49)+SUMIFS(Aut_Ajustes_Manuais!$G:$G,Aut_Ajustes_Manuais!$I:$I,DRE!AO$4,Aut_Ajustes_Manuais!$F:$F,"(-) Custos Artístico Geral") | AR42: =SUM(AR43,AR49) | AS42: =SUM(AS43,AS49) | AT42: =SUM(AT43,AT49) | AU42: =SUM(AU43,AU49) | AV42: =SUM(AV43,AV49) | AW42: =SUM(AW43,AW49) | AX42: =SUM(AX43,AX49) | AY42: =SUM(AY43,AY49) | ... BI42: =SUM(BI43,BI49)
A43: Custos Artístico | I43: =SUM(I44:I48) | J43: =SUM(J44:J48)+SUMIFS(Aut_Ajustes_Manuais!$G:$G,Aut_Ajustes_Manuais!$I:$I,DRE!H$4,Aut_Ajustes_Manuais!$F:$F,"Custos Artístico") | L43: =SUM(L44:L48) | M43: =SUM(M44:M48)+SUMIFS(Aut_Ajustes_Manuais!$G:$G,Aut_Ajustes_Manuais!$I:$I,DRE!K$4,Aut_Ajustes_Manuais!$F:$F,"Custos Artístico") | O43: =SUM(O44:O48) | P43: =SUM(P44:P48)+SUMIFS(Aut_Ajustes_Manuais!$G:$G,Aut_Ajustes_Manuais!$I:$I,DRE!N$4,Aut_Ajustes_Manuais!$F:$F,"Custos Artístico") | R43: =SUM(R44:R48) | S43: =SUM(S44:S48)+SUMIFS(Aut_Ajustes_Manuais!$G:$G,Aut_Ajustes_Manuais!$I:$I,DRE!Q$4,Aut_Ajustes_Manuais!$F:$F,"Custos Artístico") | U43: =SUM(U44:U48) | V43: =SUM(V44:V48)+SUMIFS(Aut_Ajustes_Manuais!$G:$G,Aut_Ajustes_Manuais!$I:$I,DRE!T$4,Aut_Ajustes_Manuais!$F:$F,"Custos Artístico") | X43: =SUM(X44:X48) | Y43: =SUM(Y44:Y48)+SUMIFS(Aut_Ajustes_Manuais!$G:$G,Aut_Ajustes_Manuais!$I:$I,DRE!W$4,Aut_Ajustes_Manuais!$F:$F,"Custos Artístico") | AA43: =SUM(AA44:AA48) | AB43: =SUM(AB44:AB48)+SUMIFS(Aut_Ajustes_Manuais!$G:$G,Aut_Ajustes_Manuais!$I:$I,DRE!Z$4,Aut_Ajustes_Manuais!$F:$F,"Custos Artístico") | AD43: =SUM(AD44:AD48) | AE43: =SUM(AE44:AE48)+SUMIFS(Aut_Ajustes_Manuais!$G:$G,Aut_Ajustes_Manuais!$I:$I,DRE!AC$4,Aut_Ajustes_Manuais!$F:$F,"Custos Artístico") | AG43: =SUM(AG44:AG48) | AH43: =SUM(AH44:AH48)+SUMIFS(Aut_Ajustes_Manuais!$G:$G,Aut_Ajustes_Manuais!$I:$I,DRE!AF$4,Aut_Ajustes_Manuais!$F:$F,"Custos Artístico") | AJ43: =SUM(AJ44:AJ48) | AK43: =SUM(AK44:AK48)+SUMIFS(Aut_Ajustes_Manuais!$G:$G,Aut_Ajustes_Manuais!$I:$I,DRE!AI$4,Aut_Ajustes_Manuais!$F:$F,"Custos Artístico") | AM43: =SUM(AM44:AM48) | AN43: =SUM(AN44:AN48)+SUMIFS(Aut_Ajustes_Manuais!$G:$G,Aut_Ajustes_Manuais!$I:$I,DRE!AL$4,Aut_Ajustes_Manuais!$F:$F,"Custos Artístico") | AP43: =SUM(AP44:AP48) | AQ43: =SUM(AQ44:AQ48)+SUMIFS(Aut_Ajustes_Manuais!$G:$G,Aut_Ajustes_Manuais!$I:$I,DRE!AO$4,Aut_Ajustes_Manuais!$F:$F,"Custos Artístico") | AR43: =SUMIFS($H43:$AO43,$H$5:$AO$5,"<"&MONTH(TODAY()),$H$6:$AO$6,"REAL 25") | AS43: =SUMIFS($I43:$AP43,$I$5:$AP$5,"<"&MONTH(TODAY()),$I$6:$AP$6,"ORÇADO ") | AT43: =SUMIFS($J43:$AQ43,$J$5:$AQ$5,"<"&MONTH(TODAY()),$J$6:$AQ$6,"REAL 26") | AU43: =SUM(AU44:AU48) | AV43: =SUM(AV44:AV48) | AW43: =SUM(AW44:AW48) | AX43: =SUM(AX44:AX48) | AY43: =SUM(AY44:AY48) | AZ43: =SUM(AZ44:AZ48) | BA43: =SUM(BA44:BA48) | BB43: =SUM(BB44:BB48) | ... BI43: =SUM(BI44:BI48)
A44: Cachê de Músicos e Artistas | C44: Estim. Mensal | E44: 0.0067 | I44: =-SUMIFS(T_ORCAMENTOS!$E:$E,T_ORCAMENTOS!$C:$C,"Cachê de Músicos e Artistas",T_ORCAMENTOS!$H:$H,"1/2026") | J44: =SUMIFS(Aut_BlueMe_Sem_Pedido!$J:$J,Aut_BlueMe_Sem_Pedido!$Q:$Q,DRE!H$4,Aut_BlueMe_Sem_Pedido!$H:$H,DRE!$A44)+SUMIFS(Aut_Ajustes_Manuais!$G:$G,Aut_Ajustes_Manuais!$I:$I,DRE!H$4,Aut_Ajustes_Manuais!$F:$F,"Cachê de Músicos e Artistas") | L44: =-SUMIFS(T_ORCAMENTOS!$E:$E,T_ORCAMENTOS!$C:$C,"Cachê de Músicos e Artistas",T_ORCAMENTOS!$H:$H,"2/2026") | M44: =SUMIFS(Aut_BlueMe_Sem_Pedido!$J:$J,Aut_BlueMe_Sem_Pedido!$Q:$Q,DRE!K$4,Aut_BlueMe_Sem_Pedido!$H:$H,DRE!$A44)+SUMIFS(Aut_Ajustes_Manuais!$G:$G,Aut_Ajustes_Manuais!$I:$I,DRE!K$4,Aut_Ajustes_Manuais!$F:$F,"Cachê de Músicos e Artistas") | O44: =-SUMIFS(T_ORCAMENTOS!$E:$E,T_ORCAMENTOS!$C:$C,"Cachê de Músicos e Artistas",T_ORCAMENTOS!$H:$H,"3/2026") | P44: =SUMIFS(Aut_BlueMe_Sem_Pedido!$J:$J,Aut_BlueMe_Sem_Pedido!$Q:$Q,DRE!N$4,Aut_BlueMe_Sem_Pedido!$H:$H,DRE!$A44)+SUMIFS(Aut_Ajustes_Manuais!$G:$G,Aut_Ajustes_Manuais!$I:$I,DRE!N$4,Aut_Ajustes_Manuais!$F:$F,"Cachê de Músicos e Artistas") | R44: =-SUMIFS(T_ORCAMENTOS!$E:$E,T_ORCAMENTOS!$C:$C,"Cachê de Músicos e Artistas",T_ORCAMENTOS!$H:$H,"4/2026") | S44: =SUMIFS(Aut_BlueMe_Sem_Pedido!$J:$J,Aut_BlueMe_Sem_Pedido!$Q:$Q,DRE!Q$4,Aut_BlueMe_Sem_Pedido!$H:$H,DRE!$A44)+SUMIFS(Aut_Ajustes_Manuais!$G:$G,Aut_Ajustes_Manuais!$I:$I,DRE!Q$4,Aut_Ajustes_Manuais!$F:$F,"Cachê de Músicos e Artistas") | U44: =-SUMIFS(T_ORCAMENTOS!$E:$E,T_ORCAMENTOS!$C:$C,"Cachê de Músicos e Artistas",T_ORCAMENTOS!$H:$H,"5/2026") | V44: =SUMIFS(Aut_BlueMe_Sem_Pedido!$J:$J,Aut_BlueMe_Sem_Pedido!$Q:$Q,DRE!T$4,Aut_BlueMe_Sem_Pedido!$H:$H,DRE!$A44)+SUMIFS(Aut_Ajustes_Manuais!$G:$G,Aut_Ajustes_Manuais!$I:$I,DRE!T$4,Aut_Ajustes_Manuais!$F:$F,"Cachê de Músicos e Artistas") | X44: =-SUMIFS(T_ORCAMENTOS!$E:$E,T_ORCAMENTOS!$C:$C,"Cachê de Músicos e Artistas",T_ORCAMENTOS!$H:$H,"6/2026") | Y44: =SUMIFS(Aut_BlueMe_Sem_Pedido!$J:$J,Aut_BlueMe_Sem_Pedido!$Q:$Q,DRE!W$4,Aut_BlueMe_Sem_Pedido!$H:$H,DRE!$A44)+SUMIFS(Aut_Ajustes_Manuais!$G:$G,Aut_Ajustes_Manuais!$I:$I,DRE!W$4,Aut_Ajustes_Manuais!$F:$F,"Cachê de Músicos e Artistas") | AA44: =-SUMIFS(T_ORCAMENTOS!$E:$E,T_ORCAMENTOS!$C:$C,"Cachê de Músicos e Artistas",T_ORCAMENTOS!$H:$H,"7/2026") | AB44: =SUMIFS(Aut_BlueMe_Sem_Pedido!$J:$J,Aut_BlueMe_Sem_Pedido!$Q:$Q,DRE!Z$4,Aut_BlueMe_Sem_Pedido!$H:$H,DRE!$A44)+SUMIFS(Aut_Ajustes_Manuais!$G:$G,Aut_Ajustes_Manuais!$I:$I,DRE!Z$4,Aut_Ajustes_Manuais!$F:$F,"Cachê de Músicos e Artistas") | AD44: =-SUMIFS(T_ORCAMENTOS!$E:$E,T_ORCAMENTOS!$C:$C,"Cachê de Músicos e Artistas",T_ORCAMENTOS!$H:$H,"8/2026") | AE44: =SUMIFS(Aut_BlueMe_Sem_Pedido!$J:$J,Aut_BlueMe_Sem_Pedido!$Q:$Q,DRE!AC$4,Aut_BlueMe_Sem_Pedido!$H:$H,DRE!$A44)+SUMIFS(Aut_Ajustes_Manuais!$G:$G,Aut_Ajustes_Manuais!$I:$I,DRE!AC$4,Aut_Ajustes_Manuais!$F:$F,"Cachê de Músicos e Artistas") | AG44: =-SUMIFS(T_ORCAMENTOS!$E:$E,T_ORCAMENTOS!$C:$C,"Cachê de Músicos e Artistas",T_ORCAMENTOS!$H:$H,"9/2026") | AH44: =SUMIFS(Aut_BlueMe_Sem_Pedido!$J:$J,Aut_BlueMe_Sem_Pedido!$Q:$Q,DRE!AF$4,Aut_BlueMe_Sem_Pedido!$H:$H,DRE!$A44)+SUMIFS(Aut_Ajustes_Manuais!$G:$G,Aut_Ajustes_Manuais!$I:$I,DRE!AF$4,Aut_Ajustes_Manuais!$F:$F,"Cachê de Músicos e Artistas") | AJ44: =-SUMIFS(T_ORCAMENTOS!$E:$E,T_ORCAMENTOS!$C:$C,"Cachê de Músicos e Artistas",T_ORCAMENTOS!$H:$H,"10/2026") | AK44: =SUMIFS(Aut_BlueMe_Sem_Pedido!$J:$J,Aut_BlueMe_Sem_Pedido!$Q:$Q,DRE!AI$4,Aut_BlueMe_Sem_Pedido!$H:$H,DRE!$A44)+SUMIFS(Aut_Ajustes_Manuais!$G:$G,Aut_Ajustes_Manuais!$I:$I,DRE!AI$4,Aut_Ajustes_Manuais!$F:$F,"Cachê de Músicos e Artistas") | AM44: =-SUMIFS(T_ORCAMENTOS!$E:$E,T_ORCAMENTOS!$C:$C,"Cachê de Músicos e Artistas",T_ORCAMENTOS!$H:$H,"11/2026") | AN44: =SUMIFS(Aut_BlueMe_Sem_Pedido!$J:$J,Aut_BlueMe_Sem_Pedido!$Q:$Q,DRE!AL$4,Aut_BlueMe_Sem_Pedido!$H:$H,DRE!$A44)+SUMIFS(Aut_Ajustes_Manuais!$G:$G,Aut_Ajustes_Manuais!$I:$I,DRE!AL$4,Aut_Ajustes_Manuais!$F:$F,"Cachê de Músicos e Artistas") | AP44: =-SUMIFS(T_ORCAMENTOS!$E:$E,T_ORCAMENTOS!$C:$C,"Cachê de Músicos e Artistas",T_ORCAMENTOS!$H:$H,"12/2026") | AQ44: =SUMIFS(Aut_BlueMe_Sem_Pedido!$J:$J,Aut_BlueMe_Sem_Pedido!$Q:$Q,DRE!AO$4,Aut_BlueMe_Sem_Pedido!$H:$H,DRE!$A44)+SUMIFS(Aut_Ajustes_Manuais!$G:$G,Aut_Ajustes_Manuais!$I:$I,DRE!AO$4,Aut_Ajustes_Manuais!$F:$F,"Cachê de Músicos e Artistas") | AR44: =SUMIFS($H44:$AO44,$H$5:$AO$5,"<"&MONTH(TODAY()),$H$6:$AO$6,"REAL 25") | AS44: =SUMIFS($I44:$AP44,$I$5:$AP$5,"<"&MONTH(TODAY()),$I$6:$AP$6,"ORÇADO ") | AT44: =SUMIFS($J44:$AQ44,$J$5:$AQ$5,"<"&MONTH(TODAY()),$J$6:$AQ$6,"REAL 26") | AU44: =SUM(H44,K44,N44,Q44,T44,W44,Z44,AC44,AF44,AI44,AL44,AO44) | AV44: =SUM(I44,L44,O44,R44,U44,X44,AA44,AD44,AG44,AJ44,AM44,AP44) | AW44: =SUM(J44,M44,P44,S44,V44,Y44,AB44,AE44,AH44,AK44,AN44,AQ44) | AX44: =SUM(H44,K44,N44) | AY44: =SUM(I44,L44,O44) | AZ44: =SUM(J44,M44,P44) | BA44: =SUM(Q44,T44,W44) | BB44: =SUM(R44,U44,X44) | BC44: =SUM(S44,V44,Y44) | BD44: =SUM(Z44,AC44,AF44) | BE44: =SUM(AA44,AD44,AG44) | BF44: =SUM(AB44,AE44,AH44) | BG44: =SUM(AI44,AL44,AO44) | BH44: =SUM(AJ44,AM44,AP44) | BI44: =SUM(AK44,AN44,AQ44)
A45: Alimentação e Transporte | C45: Estim. Mensal | E45: 0.0067 | I45: =-SUMIFS(T_ORCAMENTOS!$E:$E,T_ORCAMENTOS!$C:$C,"Alimentação e Transporte",T_ORCAMENTOS!$H:$H,"1/2026") | J45: =SUMIFS(Aut_BlueMe_Sem_Pedido!$J:$J,Aut_BlueMe_Sem_Pedido!$Q:$Q,DRE!H$4,Aut_BlueMe_Sem_Pedido!$H:$H,DRE!$A45)-SUMIFS(Aut_Descontos!$G:$G,Aut_Descontos!$H:$H,DRE!$A45,Aut_Descontos!$L:$L,DRE!H$4)+SUMIFS(Aut_Ajustes_Manuais!$G:$G,Aut_Ajustes_Manuais!$I:$I,DRE!H$4,Aut_Ajustes_Manuais!$F:$F,"Alimentação e Transporte") | L45: =-SUMIFS(T_ORCAMENTOS!$E:$E,T_ORCAMENTOS!$C:$C,"Alimentação e Transporte",T_ORCAMENTOS!$H:$H,"2/2026") | M45: =SUMIFS(Aut_BlueMe_Sem_Pedido!$J:$J,Aut_BlueMe_Sem_Pedido!$Q:$Q,DRE!K$4,Aut_BlueMe_Sem_Pedido!$H:$H,DRE!$A45)-SUMIFS(Aut_Descontos!$G:$G,Aut_Descontos!$H:$H,DRE!$A45,Aut_Descontos!$L:$L,DRE!K$4)+SUMIFS(Aut_Ajustes_Manuais!$G:$G,Aut_Ajustes_Manuais!$I:$I,DRE!K$4,Aut_Ajustes_Manuais!$F:$F,"Alimentação e Transporte") | O45: =-SUMIFS(T_ORCAMENTOS!$E:$E,T_ORCAMENTOS!$C:$C,"Alimentação e Transporte",T_ORCAMENTOS!$H:$H,"3/2026") | P45: =SUMIFS(Aut_BlueMe_Sem_Pedido!$J:$J,Aut_BlueMe_Sem_Pedido!$Q:$Q,DRE!N$4,Aut_BlueMe_Sem_Pedido!$H:$H,DRE!$A45)-SUMIFS(Aut_Descontos!$G:$G,Aut_Descontos!$H:$H,DRE!$A45,Aut_Descontos!$L:$L,DRE!N$4)+SUMIFS(Aut_Ajustes_Manuais!$G:$G,Aut_Ajustes_Manuais!$I:$I,DRE!N$4,Aut_Ajustes_Manuais!$F:$F,"Alimentação e Transporte") | R45: =-SUMIFS(T_ORCAMENTOS!$E:$E,T_ORCAMENTOS!$C:$C,"Alimentação e Transporte",T_ORCAMENTOS!$H:$H,"4/2026") | S45: =SUMIFS(Aut_BlueMe_Sem_Pedido!$J:$J,Aut_BlueMe_Sem_Pedido!$Q:$Q,DRE!Q$4,Aut_BlueMe_Sem_Pedido!$H:$H,DRE!$A45)-SUMIFS(Aut_Descontos!$G:$G,Aut_Descontos!$H:$H,DRE!$A45,Aut_Descontos!$L:$L,DRE!Q$4)+SUMIFS(Aut_Ajustes_Manuais!$G:$G,Aut_Ajustes_Manuais!$I:$I,DRE!Q$4,Aut_Ajustes_Manuais!$F:$F,"Alimentação e Transporte") | U45: =-SUMIFS(T_ORCAMENTOS!$E:$E,T_ORCAMENTOS!$C:$C,"Alimentação e Transporte",T_ORCAMENTOS!$H:$H,"5/2026") | V45: =SUMIFS(Aut_BlueMe_Sem_Pedido!$J:$J,Aut_BlueMe_Sem_Pedido!$Q:$Q,DRE!T$4,Aut_BlueMe_Sem_Pedido!$H:$H,DRE!$A45)-SUMIFS(Aut_Descontos!$G:$G,Aut_Descontos!$H:$H,DRE!$A45,Aut_Descontos!$L:$L,DRE!T$4)+SUMIFS(Aut_Ajustes_Manuais!$G:$G,Aut_Ajustes_Manuais!$I:$I,DRE!T$4,Aut_Ajustes_Manuais!$F:$F,"Alimentação e Transporte") | X45: =-SUMIFS(T_ORCAMENTOS!$E:$E,T_ORCAMENTOS!$C:$C,"Alimentação e Transporte",T_ORCAMENTOS!$H:$H,"6/2026") | Y45: =SUMIFS(Aut_BlueMe_Sem_Pedido!$J:$J,Aut_BlueMe_Sem_Pedido!$Q:$Q,DRE!W$4,Aut_BlueMe_Sem_Pedido!$H:$H,DRE!$A45)-SUMIFS(Aut_Descontos!$G:$G,Aut_Descontos!$H:$H,DRE!$A45,Aut_Descontos!$L:$L,DRE!W$4)+SUMIFS(Aut_Ajustes_Manuais!$G:$G,Aut_Ajustes_Manuais!$I:$I,DRE!W$4,Aut_Ajustes_Manuais!$F:$F,"Alimentação e Transporte") | AA45: =-SUMIFS(T_ORCAMENTOS!$E:$E,T_ORCAMENTOS!$C:$C,"Alimentação e Transporte",T_ORCAMENTOS!$H:$H,"7/2026") | AB45: =SUMIFS(Aut_BlueMe_Sem_Pedido!$J:$J,Aut_BlueMe_Sem_Pedido!$Q:$Q,DRE!Z$4,Aut_BlueMe_Sem_Pedido!$H:$H,DRE!$A45)-SUMIFS(Aut_Descontos!$G:$G,Aut_Descontos!$H:$H,DRE!$A45,Aut_Descontos!$L:$L,DRE!Z$4)+SUMIFS(Aut_Ajustes_Manuais!$G:$G,Aut_Ajustes_Manuais!$I:$I,DRE!Z$4,Aut_Ajustes_Manuais!$F:$F,"Alimentação e Transporte") | AD45: =-SUMIFS(T_ORCAMENTOS!$E:$E,T_ORCAMENTOS!$C:$C,"Alimentação e Transporte",T_ORCAMENTOS!$H:$H,"8/2026") | AE45: =SUMIFS(Aut_BlueMe_Sem_Pedido!$J:$J,Aut_BlueMe_Sem_Pedido!$Q:$Q,DRE!AC$4,Aut_BlueMe_Sem_Pedido!$H:$H,DRE!$A45)-SUMIFS(Aut_Descontos!$G:$G,Aut_Descontos!$H:$H,DRE!$A45,Aut_Descontos!$L:$L,DRE!AC$4)+SUMIFS(Aut_Ajustes_Manuais!$G:$G,Aut_Ajustes_Manuais!$I:$I,DRE!AC$4,Aut_Ajustes_Manuais!$F:$F,"Alimentação e Transporte") | AG45: =-SUMIFS(T_ORCAMENTOS!$E:$E,T_ORCAMENTOS!$C:$C,"Alimentação e Transporte",T_ORCAMENTOS!$H:$H,"9/2026") | AH45: =SUMIFS(Aut_BlueMe_Sem_Pedido!$J:$J,Aut_BlueMe_Sem_Pedido!$Q:$Q,DRE!AF$4,Aut_BlueMe_Sem_Pedido!$H:$H,DRE!$A45)-SUMIFS(Aut_Descontos!$G:$G,Aut_Descontos!$H:$H,DRE!$A45,Aut_Descontos!$L:$L,DRE!AF$4)+SUMIFS(Aut_Ajustes_Manuais!$G:$G,Aut_Ajustes_Manuais!$I:$I,DRE!AF$4,Aut_Ajustes_Manuais!$F:$F,"Alimentação e Transporte") | AJ45: =-SUMIFS(T_ORCAMENTOS!$E:$E,T_ORCAMENTOS!$C:$C,"Alimentação e Transporte",T_ORCAMENTOS!$H:$H,"10/2026") | AK45: =SUMIFS(Aut_BlueMe_Sem_Pedido!$J:$J,Aut_BlueMe_Sem_Pedido!$Q:$Q,DRE!AI$4,Aut_BlueMe_Sem_Pedido!$H:$H,DRE!$A45)-SUMIFS(Aut_Descontos!$G:$G,Aut_Descontos!$H:$H,DRE!$A45,Aut_Descontos!$L:$L,DRE!AI$4)+SUMIFS(Aut_Ajustes_Manuais!$G:$G,Aut_Ajustes_Manuais!$I:$I,DRE!AI$4,Aut_Ajustes_Manuais!$F:$F,"Alimentação e Transporte") | AM45: =-SUMIFS(T_ORCAMENTOS!$E:$E,T_ORCAMENTOS!$C:$C,"Alimentação e Transporte",T_ORCAMENTOS!$H:$H,"11/2026") | AN45: =SUMIFS(Aut_BlueMe_Sem_Pedido!$J:$J,Aut_BlueMe_Sem_Pedido!$Q:$Q,DRE!AL$4,Aut_BlueMe_Sem_Pedido!$H:$H,DRE!$A45)-SUMIFS(Aut_Descontos!$G:$G,Aut_Descontos!$H:$H,DRE!$A45,Aut_Descontos!$L:$L,DRE!AL$4)+SUMIFS(Aut_Ajustes_Manuais!$G:$G,Aut_Ajustes_Manuais!$I:$I,DRE!AL$4,Aut_Ajustes_Manuais!$F:$F,"Alimentação e Transporte") | AP45: =-SUMIFS(T_ORCAMENTOS!$E:$E,T_ORCAMENTOS!$C:$C,"Alimentação e Transporte",T_ORCAMENTOS!$H:$H,"12/2026") | AQ45: =SUMIFS(Aut_BlueMe_Sem_Pedido!$J:$J,Aut_BlueMe_Sem_Pedido!$Q:$Q,DRE!AO$4,Aut_BlueMe_Sem_Pedido!$H:$H,DRE!$A45)-SUMIFS(Aut_Descontos!$G:$G,Aut_Descontos!$H:$H,DRE!$A45,Aut_Descontos!$L:$L,DRE!AO$4)+SUMIFS(Aut_Ajustes_Manuais!$G:$G,Aut_Ajustes_Manuais!$I:$I,DRE!AO$4,Aut_Ajustes_Manuais!$F:$F,"Alimentação e Transporte") | AR45: =SUMIFS($H45:$AO45,$H$5:$AO$5,"<"&MONTH(TODAY()),$H$6:$AO$6,"REAL 25") | AS45: =SUMIFS($I45:$AP45,$I$5:$AP$5,"<"&MONTH(TODAY()),$I$6:$AP$6,"ORÇADO ") | AT45: =SUMIFS($J45:$AQ45,$J$5:$AQ$5,"<"&MONTH(TODAY()),$J$6:$AQ$6,"REAL 26") | AU45: =SUM(H45,K45,N45,Q45,T45,W45,Z45,AC45,AF45,AI45,AL45,AO45) | AV45: =SUM(I45,L45,O45,R45,U45,X45,AA45,AD45,AG45,AJ45,AM45,AP45) | AW45: =SUM(J45,M45,P45,S45,V45,Y45,AB45,AE45,AH45,AK45,AN45,AQ45) | AX45: =SUM(H45,K45,N45) | AY45: =SUM(I45,L45,O45) | AZ45: =SUM(J45,M45,P45) | BA45: =SUM(Q45,T45,W45) | BB45: =SUM(R45,U45,X45) | BC45: =SUM(S45,V45,Y45) | BD45: =SUM(Z45,AC45,AF45) | BE45: =SUM(AA45,AD45,AG45) | BF45: =SUM(AB45,AE45,AH45) | BG45: =SUM(AI45,AL45,AO45) | BH45: =SUM(AJ45,AM45,AP45) | BI45: =SUM(AK45,AN45,AQ45)
A46: Viagens e Estadias - Artístico | C46: Estim. Mensal | I46: =-SUMIFS(T_ORCAMENTOS!$E:$E,T_ORCAMENTOS!$C:$C,"Viagens e Estadias - Artístico",T_ORCAMENTOS!$H:$H,"1/2026") | J46: =SUMIFS(Aut_BlueMe_Sem_Pedido!$J:$J,Aut_BlueMe_Sem_Pedido!$Q:$Q,DRE!H$4,Aut_BlueMe_Sem_Pedido!$H:$H,DRE!$A46)+SUMIFS(Aut_Ajustes_Manuais!$G:$G,Aut_Ajustes_Manuais!$I:$I,DRE!H$4,Aut_Ajustes_Manuais!$F:$F,"Viagens e Estadias - Artístico") | L46: =-SUMIFS(T_ORCAMENTOS!$E:$E,T_ORCAMENTOS!$C:$C,"Viagens e Estadias - Artístico",T_ORCAMENTOS!$H:$H,"2/2026") | M46: =SUMIFS(Aut_BlueMe_Sem_Pedido!$J:$J,Aut_BlueMe_Sem_Pedido!$Q:$Q,DRE!K$4,Aut_BlueMe_Sem_Pedido!$H:$H,DRE!$A46)+SUMIFS(Aut_Ajustes_Manuais!$G:$G,Aut_Ajustes_Manuais!$I:$I,DRE!K$4,Aut_Ajustes_Manuais!$F:$F,"Viagens e Estadias - Artístico") | O46: =-SUMIFS(T_ORCAMENTOS!$E:$E,T_ORCAMENTOS!$C:$C,"Viagens e Estadias - Artístico",T_ORCAMENTOS!$H:$H,"3/2026") | P46: =SUMIFS(Aut_BlueMe_Sem_Pedido!$J:$J,Aut_BlueMe_Sem_Pedido!$Q:$Q,DRE!N$4,Aut_BlueMe_Sem_Pedido!$H:$H,DRE!$A46)+SUMIFS(Aut_Ajustes_Manuais!$G:$G,Aut_Ajustes_Manuais!$I:$I,DRE!N$4,Aut_Ajustes_Manuais!$F:$F,"Viagens e Estadias - Artístico") | R46: =-SUMIFS(T_ORCAMENTOS!$E:$E,T_ORCAMENTOS!$C:$C,"Viagens e Estadias - Artístico",T_ORCAMENTOS!$H:$H,"4/2026") | S46: =SUMIFS(Aut_BlueMe_Sem_Pedido!$J:$J,Aut_BlueMe_Sem_Pedido!$Q:$Q,DRE!Q$4,Aut_BlueMe_Sem_Pedido!$H:$H,DRE!$A46)+SUMIFS(Aut_Ajustes_Manuais!$G:$G,Aut_Ajustes_Manuais!$I:$I,DRE!Q$4,Aut_Ajustes_Manuais!$F:$F,"Viagens e Estadias - Artístico") | U46: =-SUMIFS(T_ORCAMENTOS!$E:$E,T_ORCAMENTOS!$C:$C,"Viagens e Estadias - Artístico",T_ORCAMENTOS!$H:$H,"5/2026") | V46: =SUMIFS(Aut_BlueMe_Sem_Pedido!$J:$J,Aut_BlueMe_Sem_Pedido!$Q:$Q,DRE!T$4,Aut_BlueMe_Sem_Pedido!$H:$H,DRE!$A46)+SUMIFS(Aut_Ajustes_Manuais!$G:$G,Aut_Ajustes_Manuais!$I:$I,DRE!T$4,Aut_Ajustes_Manuais!$F:$F,"Viagens e Estadias - Artístico") | X46: =-SUMIFS(T_ORCAMENTOS!$E:$E,T_ORCAMENTOS!$C:$C,"Viagens e Estadias - Artístico",T_ORCAMENTOS!$H:$H,"6/2026") | Y46: =SUMIFS(Aut_BlueMe_Sem_Pedido!$J:$J,Aut_BlueMe_Sem_Pedido!$Q:$Q,DRE!W$4,Aut_BlueMe_Sem_Pedido!$H:$H,DRE!$A46)+SUMIFS(Aut_Ajustes_Manuais!$G:$G,Aut_Ajustes_Manuais!$I:$I,DRE!W$4,Aut_Ajustes_Manuais!$F:$F,"Viagens e Estadias - Artístico") | AA46: =-SUMIFS(T_ORCAMENTOS!$E:$E,T_ORCAMENTOS!$C:$C,"Viagens e Estadias - Artístico",T_ORCAMENTOS!$H:$H,"7/2026") | AB46: =SUMIFS(Aut_BlueMe_Sem_Pedido!$J:$J,Aut_BlueMe_Sem_Pedido!$Q:$Q,DRE!Z$4,Aut_BlueMe_Sem_Pedido!$H:$H,DRE!$A46)+SUMIFS(Aut_Ajustes_Manuais!$G:$G,Aut_Ajustes_Manuais!$I:$I,DRE!Z$4,Aut_Ajustes_Manuais!$F:$F,"Viagens e Estadias - Artístico") | AD46: =-SUMIFS(T_ORCAMENTOS!$E:$E,T_ORCAMENTOS!$C:$C,"Viagens e Estadias - Artístico",T_ORCAMENTOS!$H:$H,"8/2026") | AE46: =SUMIFS(Aut_BlueMe_Sem_Pedido!$J:$J,Aut_BlueMe_Sem_Pedido!$Q:$Q,DRE!AC$4,Aut_BlueMe_Sem_Pedido!$H:$H,DRE!$A46)+SUMIFS(Aut_Ajustes_Manuais!$G:$G,Aut_Ajustes_Manuais!$I:$I,DRE!AC$4,Aut_Ajustes_Manuais!$F:$F,"Viagens e Estadias - Artístico") | AG46: =-SUMIFS(T_ORCAMENTOS!$E:$E,T_ORCAMENTOS!$C:$C,"Viagens e Estadias - Artístico",T_ORCAMENTOS!$H:$H,"9/2026") | AH46: =SUMIFS(Aut_BlueMe_Sem_Pedido!$J:$J,Aut_BlueMe_Sem_Pedido!$Q:$Q,DRE!AF$4,Aut_BlueMe_Sem_Pedido!$H:$H,DRE!$A46)+SUMIFS(Aut_Ajustes_Manuais!$G:$G,Aut_Ajustes_Manuais!$I:$I,DRE!AF$4,Aut_Ajustes_Manuais!$F:$F,"Viagens e Estadias - Artístico") | AJ46: =-SUMIFS(T_ORCAMENTOS!$E:$E,T_ORCAMENTOS!$C:$C,"Viagens e Estadias - Artístico",T_ORCAMENTOS!$H:$H,"10/2026") | AK46: =SUMIFS(Aut_BlueMe_Sem_Pedido!$J:$J,Aut_BlueMe_Sem_Pedido!$Q:$Q,DRE!AI$4,Aut_BlueMe_Sem_Pedido!$H:$H,DRE!$A46)+SUMIFS(Aut_Ajustes_Manuais!$G:$G,Aut_Ajustes_Manuais!$I:$I,DRE!AI$4,Aut_Ajustes_Manuais!$F:$F,"Viagens e Estadias - Artístico") | AM46: =-SUMIFS(T_ORCAMENTOS!$E:$E,T_ORCAMENTOS!$C:$C,"Viagens e Estadias - Artístico",T_ORCAMENTOS!$H:$H,"11/2026") | AN46: =SUMIFS(Aut_BlueMe_Sem_Pedido!$J:$J,Aut_BlueMe_Sem_Pedido!$Q:$Q,DRE!AL$4,Aut_BlueMe_Sem_Pedido!$H:$H,DRE!$A46)+SUMIFS(Aut_Ajustes_Manuais!$G:$G,Aut_Ajustes_Manuais!$I:$I,DRE!AL$4,Aut_Ajustes_Manuais!$F:$F,"Viagens e Estadias - Artístico") | AP46: =-SUMIFS(T_ORCAMENTOS!$E:$E,T_ORCAMENTOS!$C:$C,"Viagens e Estadias - Artístico",T_ORCAMENTOS!$H:$H,"12/2026") | AQ46: =SUMIFS(Aut_BlueMe_Sem_Pedido!$J:$J,Aut_BlueMe_Sem_Pedido!$Q:$Q,DRE!AO$4,Aut_BlueMe_Sem_Pedido!$H:$H,DRE!$A46)+SUMIFS(Aut_Ajustes_Manuais!$G:$G,Aut_Ajustes_Manuais!$I:$I,DRE!AO$4,Aut_Ajustes_Manuais!$F:$F,"Viagens e Estadias - Artístico") | AR46: =SUMIFS($H46:$AO46,$H$5:$AO$5,"<"&MONTH(TODAY()),$H$6:$AO$6,"REAL 25") | AS46: =SUMIFS($I46:$AP46,$I$5:$AP$5,"<"&MONTH(TODAY()),$I$6:$AP$6,"ORÇADO ") | AT46: =SUMIFS($J46:$AQ46,$J$5:$AQ$5,"<"&MONTH(TODAY()),$J$6:$AQ$6,"REAL 26") | AU46: =SUM(H46,K46,N46,Q46,T46,W46,Z46,AC46,AF46,AI46,AL46,AO46) | AV46: =SUM(I46,L46,O46,R46,U46,X46,AA46,AD46,AG46,AJ46,AM46,AP46) | AW46: =SUM(J46,M46,P46,S46,V46,Y46,AB46,AE46,AH46,AK46,AN46,AQ46) | AX46: =SUM(H46,K46,N46) | AY46: =SUM(I46,L46,O46) | AZ46: =SUM(J46,M46,P46) | BA46: =SUM(Q46,T46,W46) | BB46: =SUM(R46,U46,X46) | BC46: =SUM(S46,V46,Y46) | BD46: =SUM(Z46,AC46,AF46) | BE46: =SUM(AA46,AD46,AG46) | BF46: =SUM(AB46,AE46,AH46) | BG46: =SUM(AI46,AL46,AO46) | BH46: =SUM(AJ46,AM46,AP46) | BI46: =SUM(AK46,AN46,AQ46)
A47: Taxas e Licenças - Artístico | C47: Contr/Prov - ECAD Valor Mensal | I47: =-SUMIFS(T_ORCAMENTOS!$E:$E,T_ORCAMENTOS!$C:$C,"Taxas e Licenças - Artístico",T_ORCAMENTOS!$H:$H,"1/2026") | J47: =SUMIFS(Aut_BlueMe_Sem_Pedido!$J:$J,Aut_BlueMe_Sem_Pedido!$Q:$Q,DRE!H$4,Aut_BlueMe_Sem_Pedido!$H:$H,DRE!$A47)+SUMIFS(Aut_Ajustes_Manuais!$G:$G,Aut_Ajustes_Manuais!$I:$I,DRE!H$4,Aut_Ajustes_Manuais!$F:$F,"Taxas e Licenças - Artístico") | L47: =-SUMIFS(T_ORCAMENTOS!$E:$E,T_ORCAMENTOS!$C:$C,"Taxas e Licenças - Artístico",T_ORCAMENTOS!$H:$H,"2/2026") | M47: =SUMIFS(Aut_BlueMe_Sem_Pedido!$J:$J,Aut_BlueMe_Sem_Pedido!$Q:$Q,DRE!K$4,Aut_BlueMe_Sem_Pedido!$H:$H,DRE!$A47)+SUMIFS(Aut_Ajustes_Manuais!$G:$G,Aut_Ajustes_Manuais!$I:$I,DRE!K$4,Aut_Ajustes_Manuais!$F:$F,"Taxas e Licenças - Artístico") | O47: =-SUMIFS(T_ORCAMENTOS!$E:$E,T_ORCAMENTOS!$C:$C,"Taxas e Licenças - Artístico",T_ORCAMENTOS!$H:$H,"3/2026") | P47: =SUMIFS(Aut_BlueMe_Sem_Pedido!$J:$J,Aut_BlueMe_Sem_Pedido!$Q:$Q,DRE!N$4,Aut_BlueMe_Sem_Pedido!$H:$H,DRE!$A47)+SUMIFS(Aut_Ajustes_Manuais!$G:$G,Aut_Ajustes_Manuais!$I:$I,DRE!N$4,Aut_Ajustes_Manuais!$F:$F,"Taxas e Licenças - Artístico") | R47: =-SUMIFS(T_ORCAMENTOS!$E:$E,T_ORCAMENTOS!$C:$C,"Taxas e Licenças - Artístico",T_ORCAMENTOS!$H:$H,"4/2026") | S47: =SUMIFS(Aut_BlueMe_Sem_Pedido!$J:$J,Aut_BlueMe_Sem_Pedido!$Q:$Q,DRE!Q$4,Aut_BlueMe_Sem_Pedido!$H:$H,DRE!$A47)+SUMIFS(Aut_Ajustes_Manuais!$G:$G,Aut_Ajustes_Manuais!$I:$I,DRE!Q$4,Aut_Ajustes_Manuais!$F:$F,"Taxas e Licenças - Artístico") | U47: =-SUMIFS(T_ORCAMENTOS!$E:$E,T_ORCAMENTOS!$C:$C,"Taxas e Licenças - Artístico",T_ORCAMENTOS!$H:$H,"5/2026") | V47: =SUMIFS(Aut_BlueMe_Sem_Pedido!$J:$J,Aut_BlueMe_Sem_Pedido!$Q:$Q,DRE!T$4,Aut_BlueMe_Sem_Pedido!$H:$H,DRE!$A47)+SUMIFS(Aut_Ajustes_Manuais!$G:$G,Aut_Ajustes_Manuais!$I:$I,DRE!T$4,Aut_Ajustes_Manuais!$F:$F,"Taxas e Licenças - Artístico") | X47: =-SUMIFS(T_ORCAMENTOS!$E:$E,T_ORCAMENTOS!$C:$C,"Taxas e Licenças - Artístico",T_ORCAMENTOS!$H:$H,"6/2026") | Y47: =SUMIFS(Aut_BlueMe_Sem_Pedido!$J:$J,Aut_BlueMe_Sem_Pedido!$Q:$Q,DRE!W$4,Aut_BlueMe_Sem_Pedido!$H:$H,DRE!$A47)+SUMIFS(Aut_Ajustes_Manuais!$G:$G,Aut_Ajustes_Manuais!$I:$I,DRE!W$4,Aut_Ajustes_Manuais!$F:$F,"Taxas e Licenças - Artístico") | AA47: =-SUMIFS(T_ORCAMENTOS!$E:$E,T_ORCAMENTOS!$C:$C,"Taxas e Licenças - Artístico",T_ORCAMENTOS!$H:$H,"7/2026") | AB47: =SUMIFS(Aut_BlueMe_Sem_Pedido!$J:$J,Aut_BlueMe_Sem_Pedido!$Q:$Q,DRE!Z$4,Aut_BlueMe_Sem_Pedido!$H:$H,DRE!$A47)+SUMIFS(Aut_Ajustes_Manuais!$G:$G,Aut_Ajustes_Manuais!$I:$I,DRE!Z$4,Aut_Ajustes_Manuais!$F:$F,"Taxas e Licenças - Artístico") | AD47: =-SUMIFS(T_ORCAMENTOS!$E:$E,T_ORCAMENTOS!$C:$C,"Taxas e Licenças - Artístico",T_ORCAMENTOS!$H:$H,"8/2026") | AE47: =SUMIFS(Aut_BlueMe_Sem_Pedido!$J:$J,Aut_BlueMe_Sem_Pedido!$Q:$Q,DRE!AC$4,Aut_BlueMe_Sem_Pedido!$H:$H,DRE!$A47)+SUMIFS(Aut_Ajustes_Manuais!$G:$G,Aut_Ajustes_Manuais!$I:$I,DRE!AC$4,Aut_Ajustes_Manuais!$F:$F,"Taxas e Licenças - Artístico") | AG47: =-SUMIFS(T_ORCAMENTOS!$E:$E,T_ORCAMENTOS!$C:$C,"Taxas e Licenças - Artístico",T_ORCAMENTOS!$H:$H,"9/2026") | AH47: =SUMIFS(Aut_BlueMe_Sem_Pedido!$J:$J,Aut_BlueMe_Sem_Pedido!$Q:$Q,DRE!AF$4,Aut_BlueMe_Sem_Pedido!$H:$H,DRE!$A47)+SUMIFS(Aut_Ajustes_Manuais!$G:$G,Aut_Ajustes_Manuais!$I:$I,DRE!AF$4,Aut_Ajustes_Manuais!$F:$F,"Taxas e Licenças - Artístico") | AJ47: =-SUMIFS(T_ORCAMENTOS!$E:$E,T_ORCAMENTOS!$C:$C,"Taxas e Licenças - Artístico",T_ORCAMENTOS!$H:$H,"10/2026") | AK47: =SUMIFS(Aut_BlueMe_Sem_Pedido!$J:$J,Aut_BlueMe_Sem_Pedido!$Q:$Q,DRE!AI$4,Aut_BlueMe_Sem_Pedido!$H:$H,DRE!$A47)+SUMIFS(Aut_Ajustes_Manuais!$G:$G,Aut_Ajustes_Manuais!$I:$I,DRE!AI$4,Aut_Ajustes_Manuais!$F:$F,"Taxas e Licenças - Artístico") | AM47: =-SUMIFS(T_ORCAMENTOS!$E:$E,T_ORCAMENTOS!$C:$C,"Taxas e Licenças - Artístico",T_ORCAMENTOS!$H:$H,"11/2026") | AN47: =SUMIFS(Aut_BlueMe_Sem_Pedido!$J:$J,Aut_BlueMe_Sem_Pedido!$Q:$Q,DRE!AL$4,Aut_BlueMe_Sem_Pedido!$H:$H,DRE!$A47)+SUMIFS(Aut_Ajustes_Manuais!$G:$G,Aut_Ajustes_Manuais!$I:$I,DRE!AL$4,Aut_Ajustes_Manuais!$F:$F,"Taxas e Licenças - Artístico") | AP47: =-SUMIFS(T_ORCAMENTOS!$E:$E,T_ORCAMENTOS!$C:$C,"Taxas e Licenças - Artístico",T_ORCAMENTOS!$H:$H,"12/2026") | AQ47: =SUMIFS(Aut_BlueMe_Sem_Pedido!$J:$J,Aut_BlueMe_Sem_Pedido!$Q:$Q,DRE!AO$4,Aut_BlueMe_Sem_Pedido!$H:$H,DRE!$A47)+SUMIFS(Aut_Ajustes_Manuais!$G:$G,Aut_Ajustes_Manuais!$I:$I,DRE!AO$4,Aut_Ajustes_Manuais!$F:$F,"Taxas e Licenças - Artístico") | AR47: =SUMIFS($H47:$AO47,$H$5:$AO$5,"<"&MONTH(TODAY()),$H$6:$AO$6,"REAL 25") | AS47: =SUMIFS($I47:$AP47,$I$5:$AP$5,"<"&MONTH(TODAY()),$I$6:$AP$6,"ORÇADO ") | AT47: =SUMIFS($J47:$AQ47,$J$5:$AQ$5,"<"&MONTH(TODAY()),$J$6:$AQ$6,"REAL 26") | AU47: =SUM(H47,K47,N47,Q47,T47,W47,Z47,AC47,AF47,AI47,AL47,AO47) | AV47: =SUM(I47,L47,O47,R47,U47,X47,AA47,AD47,AG47,AJ47,AM47,AP47) | AW47: =SUM(J47,M47,P47,S47,V47,Y47,AB47,AE47,AH47,AK47,AN47,AQ47) | AX47: =SUM(H47,K47,N47) | AY47: =SUM(I47,L47,O47) | AZ47: =SUM(J47,M47,P47) | BA47: =SUM(Q47,T47,W47) | BB47: =SUM(R47,U47,X47) | BC47: =SUM(S47,V47,Y47) | BD47: =SUM(Z47,AC47,AF47) | BE47: =SUM(AA47,AD47,AG47) | BF47: =SUM(AB47,AE47,AH47) | BG47: =SUM(AI47,AL47,AO47) | BH47: =SUM(AJ47,AM47,AP47) | BI47: =SUM(AK47,AN47,AQ47)
A48: MDO Terceirizada - Artístico | I48: =-SUMIFS(T_ORCAMENTOS!$E:$E,T_ORCAMENTOS!$C:$C,"MDO Terceirizada - Artístico",T_ORCAMENTOS!$H:$H,"1/2026") | J48: =SUMIFS(Aut_BlueMe_Sem_Pedido!$J:$J,Aut_BlueMe_Sem_Pedido!$Q:$Q,DRE!H$4,Aut_BlueMe_Sem_Pedido!$H:$H,DRE!$A48)+SUMIFS(Aut_Ajustes_Manuais!$G:$G,Aut_Ajustes_Manuais!$I:$I,DRE!H$4,Aut_Ajustes_Manuais!$F:$F,"MDO Terceirizada - Artístico") | L48: =-SUMIFS(T_ORCAMENTOS!$E:$E,T_ORCAMENTOS!$C:$C,"MDO Terceirizada - Artístico",T_ORCAMENTOS!$H:$H,"2/2026") | M48: =SUMIFS(Aut_BlueMe_Sem_Pedido!$J:$J,Aut_BlueMe_Sem_Pedido!$Q:$Q,DRE!K$4,Aut_BlueMe_Sem_Pedido!$H:$H,DRE!$A48)+SUMIFS(Aut_Ajustes_Manuais!$G:$G,Aut_Ajustes_Manuais!$I:$I,DRE!K$4,Aut_Ajustes_Manuais!$F:$F,"MDO Terceirizada - Artístico") | O48: =-SUMIFS(T_ORCAMENTOS!$E:$E,T_ORCAMENTOS!$C:$C,"MDO Terceirizada - Artístico",T_ORCAMENTOS!$H:$H,"3/2026") | P48: =SUMIFS(Aut_BlueMe_Sem_Pedido!$J:$J,Aut_BlueMe_Sem_Pedido!$Q:$Q,DRE!N$4,Aut_BlueMe_Sem_Pedido!$H:$H,DRE!$A48)+SUMIFS(Aut_Ajustes_Manuais!$G:$G,Aut_Ajustes_Manuais!$I:$I,DRE!N$4,Aut_Ajustes_Manuais!$F:$F,"MDO Terceirizada - Artístico") | R48: =-SUMIFS(T_ORCAMENTOS!$E:$E,T_ORCAMENTOS!$C:$C,"MDO Terceirizada - Artístico",T_ORCAMENTOS!$H:$H,"4/2026") | S48: =SUMIFS(Aut_BlueMe_Sem_Pedido!$J:$J,Aut_BlueMe_Sem_Pedido!$Q:$Q,DRE!Q$4,Aut_BlueMe_Sem_Pedido!$H:$H,DRE!$A48)+SUMIFS(Aut_Ajustes_Manuais!$G:$G,Aut_Ajustes_Manuais!$I:$I,DRE!Q$4,Aut_Ajustes_Manuais!$F:$F,"MDO Terceirizada - Artístico") | U48: =-SUMIFS(T_ORCAMENTOS!$E:$E,T_ORCAMENTOS!$C:$C,"MDO Terceirizada - Artístico",T_ORCAMENTOS!$H:$H,"5/2026") | V48: =SUMIFS(Aut_BlueMe_Sem_Pedido!$J:$J,Aut_BlueMe_Sem_Pedido!$Q:$Q,DRE!T$4,Aut_BlueMe_Sem_Pedido!$H:$H,DRE!$A48)+SUMIFS(Aut_Ajustes_Manuais!$G:$G,Aut_Ajustes_Manuais!$I:$I,DRE!T$4,Aut_Ajustes_Manuais!$F:$F,"MDO Terceirizada - Artístico") | X48: =-SUMIFS(T_ORCAMENTOS!$E:$E,T_ORCAMENTOS!$C:$C,"MDO Terceirizada - Artístico",T_ORCAMENTOS!$H:$H,"6/2026") | Y48: =SUMIFS(Aut_BlueMe_Sem_Pedido!$J:$J,Aut_BlueMe_Sem_Pedido!$Q:$Q,DRE!W$4,Aut_BlueMe_Sem_Pedido!$H:$H,DRE!$A48)+SUMIFS(Aut_Ajustes_Manuais!$G:$G,Aut_Ajustes_Manuais!$I:$I,DRE!W$4,Aut_Ajustes_Manuais!$F:$F,"MDO Terceirizada - Artístico") | AA48: =-SUMIFS(T_ORCAMENTOS!$E:$E,T_ORCAMENTOS!$C:$C,"MDO Terceirizada - Artístico",T_ORCAMENTOS!$H:$H,"7/2026") | AB48: =SUMIFS(Aut_BlueMe_Sem_Pedido!$J:$J,Aut_BlueMe_Sem_Pedido!$Q:$Q,DRE!Z$4,Aut_BlueMe_Sem_Pedido!$H:$H,DRE!$A48)+SUMIFS(Aut_Ajustes_Manuais!$G:$G,Aut_Ajustes_Manuais!$I:$I,DRE!Z$4,Aut_Ajustes_Manuais!$F:$F,"MDO Terceirizada - Artístico") | AD48: =-SUMIFS(T_ORCAMENTOS!$E:$E,T_ORCAMENTOS!$C:$C,"MDO Terceirizada - Artístico",T_ORCAMENTOS!$H:$H,"8/2026") | AE48: =SUMIFS(Aut_BlueMe_Sem_Pedido!$J:$J,Aut_BlueMe_Sem_Pedido!$Q:$Q,DRE!AC$4,Aut_BlueMe_Sem_Pedido!$H:$H,DRE!$A48)+SUMIFS(Aut_Ajustes_Manuais!$G:$G,Aut_Ajustes_Manuais!$I:$I,DRE!AC$4,Aut_Ajustes_Manuais!$F:$F,"MDO Terceirizada - Artístico") | AG48: =-SUMIFS(T_ORCAMENTOS!$E:$E,T_ORCAMENTOS!$C:$C,"MDO Terceirizada - Artístico",T_ORCAMENTOS!$H:$H,"9/2026") | AH48: =SUMIFS(Aut_BlueMe_Sem_Pedido!$J:$J,Aut_BlueMe_Sem_Pedido!$Q:$Q,DRE!AF$4,Aut_BlueMe_Sem_Pedido!$H:$H,DRE!$A48)+SUMIFS(Aut_Ajustes_Manuais!$G:$G,Aut_Ajustes_Manuais!$I:$I,DRE!AF$4,Aut_Ajustes_Manuais!$F:$F,"MDO Terceirizada - Artístico") | AJ48: =-SUMIFS(T_ORCAMENTOS!$E:$E,T_ORCAMENTOS!$C:$C,"MDO Terceirizada - Artístico",T_ORCAMENTOS!$H:$H,"10/2026") | AK48: =SUMIFS(Aut_BlueMe_Sem_Pedido!$J:$J,Aut_BlueMe_Sem_Pedido!$Q:$Q,DRE!AI$4,Aut_BlueMe_Sem_Pedido!$H:$H,DRE!$A48)+SUMIFS(Aut_Ajustes_Manuais!$G:$G,Aut_Ajustes_Manuais!$I:$I,DRE!AI$4,Aut_Ajustes_Manuais!$F:$F,"MDO Terceirizada - Artístico") | AM48: =-SUMIFS(T_ORCAMENTOS!$E:$E,T_ORCAMENTOS!$C:$C,"MDO Terceirizada - Artístico",T_ORCAMENTOS!$H:$H,"11/2026") | AN48: =SUMIFS(Aut_BlueMe_Sem_Pedido!$J:$J,Aut_BlueMe_Sem_Pedido!$Q:$Q,DRE!AL$4,Aut_BlueMe_Sem_Pedido!$H:$H,DRE!$A48)+SUMIFS(Aut_Ajustes_Manuais!$G:$G,Aut_Ajustes_Manuais!$I:$I,DRE!AL$4,Aut_Ajustes_Manuais!$F:$F,"MDO Terceirizada - Artístico") | AP48: =-SUMIFS(T_ORCAMENTOS!$E:$E,T_ORCAMENTOS!$C:$C,"MDO Terceirizada - Artístico",T_ORCAMENTOS!$H:$H,"12/2026") | AQ48: =SUMIFS(Aut_BlueMe_Sem_Pedido!$J:$J,Aut_BlueMe_Sem_Pedido!$Q:$Q,DRE!AO$4,Aut_BlueMe_Sem_Pedido!$H:$H,DRE!$A48)+SUMIFS(Aut_Ajustes_Manuais!$G:$G,Aut_Ajustes_Manuais!$I:$I,DRE!AO$4,Aut_Ajustes_Manuais!$F:$F,"MDO Terceirizada - Artístico") | AR48: =SUMIFS($H48:$AO48,$H$5:$AO$5,"<"&MONTH(TODAY()),$H$6:$AO$6,"REAL 25") | AS48: =SUMIFS($I48:$AP48,$I$5:$AP$5,"<"&MONTH(TODAY()),$I$6:$AP$6,"ORÇADO ") | AT48: =SUMIFS($J48:$AQ48,$J$5:$AQ$5,"<"&MONTH(TODAY()),$J$6:$AQ$6,"REAL 26") | AU48: =SUM(H48,K48,N48,Q48,T48,W48,Z48,AC48,AF48,AI48,AL48,AO48) | AV48: =SUM(I48,L48,O48,R48,U48,X48,AA48,AD48,AG48,AJ48,AM48,AP48) | AW48: =SUM(J48,M48,P48,S48,V48,Y48,AB48,AE48,AH48,AK48,AN48,AQ48) | AX48: =SUM(H48,K48,N48) | AY48: =SUM(I48,L48,O48) | AZ48: =SUM(J48,M48,P48) | BA48: =SUM(Q48,T48,W48) | BB48: =SUM(R48,U48,X48) | BC48: =SUM(S48,V48,Y48) | BD48: =SUM(Z48,AC48,AF48) | BE48: =SUM(AA48,AD48,AG48) | BF48: =SUM(AB48,AE48,AH48) | BG48: =SUM(AI48,AL48,AO48) | BH48: =SUM(AJ48,AM48,AP48) | BI48: =SUM(AK48,AN48,AQ48)
A49: Custos Ténico de Som | I49: =SUM(I50:I52) | J49: =SUM(J50:J52)+SUMIFS(Aut_Ajustes_Manuais!$G:$G,Aut_Ajustes_Manuais!$I:$I,DRE!H$4,Aut_Ajustes_Manuais!$F:$F,"Custos Ténico de Som") | L49: =SUM(L50:L52) | M49: =SUM(M50:M52)+SUMIFS(Aut_Ajustes_Manuais!$G:$G,Aut_Ajustes_Manuais!$I:$I,DRE!K$4,Aut_Ajustes_Manuais!$F:$F,"Custos Ténico de Som") | O49: =SUM(O50:O52) | P49: =SUM(P50:P52)+SUMIFS(Aut_Ajustes_Manuais!$G:$G,Aut_Ajustes_Manuais!$I:$I,DRE!N$4,Aut_Ajustes_Manuais!$F:$F,"Custos Ténico de Som") | R49: =SUM(R50:R52) | S49: =SUM(S50:S52)+SUMIFS(Aut_Ajustes_Manuais!$G:$G,Aut_Ajustes_Manuais!$I:$I,DRE!Q$4,Aut_Ajustes_Manuais!$F:$F,"Custos Ténico de Som") | U49: =SUM(U50:U52) | V49: =SUM(V50:V52)+SUMIFS(Aut_Ajustes_Manuais!$G:$G,Aut_Ajustes_Manuais!$I:$I,DRE!T$4,Aut_Ajustes_Manuais!$F:$F,"Custos Ténico de Som") | X49: =SUM(X50:X52) | Y49: =SUM(Y50:Y52)+SUMIFS(Aut_Ajustes_Manuais!$G:$G,Aut_Ajustes_Manuais!$I:$I,DRE!W$4,Aut_Ajustes_Manuais!$F:$F,"Custos Ténico de Som") | AA49: =SUM(AA50:AA52) | AB49: =SUM(AB50:AB52)+SUMIFS(Aut_Ajustes_Manuais!$G:$G,Aut_Ajustes_Manuais!$I:$I,DRE!Z$4,Aut_Ajustes_Manuais!$F:$F,"Custos Ténico de Som") | AD49: =SUM(AD50:AD52) | AE49: =SUM(AE50:AE52)+SUMIFS(Aut_Ajustes_Manuais!$G:$G,Aut_Ajustes_Manuais!$I:$I,DRE!AC$4,Aut_Ajustes_Manuais!$F:$F,"Custos Ténico de Som") | AG49: =SUM(AG50:AG52) | AH49: =SUM(AH50:AH52)+SUMIFS(Aut_Ajustes_Manuais!$G:$G,Aut_Ajustes_Manuais!$I:$I,DRE!AF$4,Aut_Ajustes_Manuais!$F:$F,"Custos Ténico de Som") | AJ49: =SUM(AJ50:AJ52) | AK49: =SUM(AK50:AK52)+SUMIFS(Aut_Ajustes_Manuais!$G:$G,Aut_Ajustes_Manuais!$I:$I,DRE!AI$4,Aut_Ajustes_Manuais!$F:$F,"Custos Ténico de Som") | AM49: =SUM(AM50:AM52) | AN49: =SUM(AN50:AN52)+SUMIFS(Aut_Ajustes_Manuais!$G:$G,Aut_Ajustes_Manuais!$I:$I,DRE!AL$4,Aut_Ajustes_Manuais!$F:$F,"Custos Ténico de Som") | AP49: =SUM(AP50:AP52) | AQ49: =SUM(AQ50:AQ52)+SUMIFS(Aut_Ajustes_Manuais!$G:$G,Aut_Ajustes_Manuais!$I:$I,DRE!AO$4,Aut_Ajustes_Manuais!$F:$F,"Custos Ténico de Som") | AR49: =SUMIFS($H49:$AO49,$H$5:$AO$5,"<"&MONTH(TODAY()),$H$6:$AO$6,"REAL 25") | AS49: =SUMIFS($I49:$AP49,$I$5:$AP$5,"<"&MONTH(TODAY()),$I$6:$AP$6,"ORÇADO ") | AT49: =SUMIFS($J49:$AQ49,$J$5:$AQ$5,"<"&MONTH(TODAY()),$J$6:$AQ$6,"REAL 26") | AU49: =SUM(AU50:AU52) | AV49: =SUM(AV50:AV52) | AW49: =SUM(AW50:AW52) | AX49: =SUM(AX50:AX52) | AY49: =SUM(AY50:AY52) | AZ49: =SUM(AZ50:AZ52) | BA49: =SUM(BA50:BA52) | BB49: =SUM(BB50:BB52) | ... BI49: =SUM(BI50:BI52)
A50: Técnico de Som / Luz | C50: Contr/Prov | I50: =-SUMIFS(T_ORCAMENTOS!$E:$E,T_ORCAMENTOS!$C:$C,"Técnico de Som / Luz",T_ORCAMENTOS!$H:$H,"1/2026") | J50: =SUMIFS(Aut_BlueMe_Sem_Pedido!$J:$J,Aut_BlueMe_Sem_Pedido!$Q:$Q,DRE!H$4,Aut_BlueMe_Sem_Pedido!$H:$H,DRE!$A50)+SUMIFS(Aut_Ajustes_Manuais!$G:$G,Aut_Ajustes_Manuais!$I:$I,DRE!H$4,Aut_Ajustes_Manuais!$F:$F,"Técnico de Som / Luz") | L50: =-SUMIFS(T_ORCAMENTOS!$E:$E,T_ORCAMENTOS!$C:$C,"Técnico de Som / Luz",T_ORCAMENTOS!$H:$H,"2/2026") | M50: =SUMIFS(Aut_BlueMe_Sem_Pedido!$J:$J,Aut_BlueMe_Sem_Pedido!$Q:$Q,DRE!K$4,Aut_BlueMe_Sem_Pedido!$H:$H,DRE!$A50)+SUMIFS(Aut_Ajustes_Manuais!$G:$G,Aut_Ajustes_Manuais!$I:$I,DRE!K$4,Aut_Ajustes_Manuais!$F:$F,"Técnico de Som / Luz") | O50: =-SUMIFS(T_ORCAMENTOS!$E:$E,T_ORCAMENTOS!$C:$C,"Técnico de Som / Luz",T_ORCAMENTOS!$H:$H,"3/2026") | P50: =SUMIFS(Aut_BlueMe_Sem_Pedido!$J:$J,Aut_BlueMe_Sem_Pedido!$Q:$Q,DRE!N$4,Aut_BlueMe_Sem_Pedido!$H:$H,DRE!$A50)+SUMIFS(Aut_Ajustes_Manuais!$G:$G,Aut_Ajustes_Manuais!$I:$I,DRE!N$4,Aut_Ajustes_Manuais!$F:$F,"Técnico de Som / Luz") | R50: =-SUMIFS(T_ORCAMENTOS!$E:$E,T_ORCAMENTOS!$C:$C,"Técnico de Som / Luz",T_ORCAMENTOS!$H:$H,"4/2026") | S50: =SUMIFS(Aut_BlueMe_Sem_Pedido!$J:$J,Aut_BlueMe_Sem_Pedido!$Q:$Q,DRE!Q$4,Aut_BlueMe_Sem_Pedido!$H:$H,DRE!$A50)+SUMIFS(Aut_Ajustes_Manuais!$G:$G,Aut_Ajustes_Manuais!$I:$I,DRE!Q$4,Aut_Ajustes_Manuais!$F:$F,"Técnico de Som / Luz") | U50: =-SUMIFS(T_ORCAMENTOS!$E:$E,T_ORCAMENTOS!$C:$C,"Técnico de Som / Luz",T_ORCAMENTOS!$H:$H,"5/2026") | V50: =SUMIFS(Aut_BlueMe_Sem_Pedido!$J:$J,Aut_BlueMe_Sem_Pedido!$Q:$Q,DRE!T$4,Aut_BlueMe_Sem_Pedido!$H:$H,DRE!$A50)+SUMIFS(Aut_Ajustes_Manuais!$G:$G,Aut_Ajustes_Manuais!$I:$I,DRE!T$4,Aut_Ajustes_Manuais!$F:$F,"Técnico de Som / Luz") | X50: =-SUMIFS(T_ORCAMENTOS!$E:$E,T_ORCAMENTOS!$C:$C,"Técnico de Som / Luz",T_ORCAMENTOS!$H:$H,"6/2026") | Y50: =SUMIFS(Aut_BlueMe_Sem_Pedido!$J:$J,Aut_BlueMe_Sem_Pedido!$Q:$Q,DRE!W$4,Aut_BlueMe_Sem_Pedido!$H:$H,DRE!$A50)+SUMIFS(Aut_Ajustes_Manuais!$G:$G,Aut_Ajustes_Manuais!$I:$I,DRE!W$4,Aut_Ajustes_Manuais!$F:$F,"Técnico de Som / Luz") | AA50: =-SUMIFS(T_ORCAMENTOS!$E:$E,T_ORCAMENTOS!$C:$C,"Técnico de Som / Luz",T_ORCAMENTOS!$H:$H,"7/2026") | AB50: =SUMIFS(Aut_BlueMe_Sem_Pedido!$J:$J,Aut_BlueMe_Sem_Pedido!$Q:$Q,DRE!Z$4,Aut_BlueMe_Sem_Pedido!$H:$H,DRE!$A50)+SUMIFS(Aut_Ajustes_Manuais!$G:$G,Aut_Ajustes_Manuais!$I:$I,DRE!Z$4,Aut_Ajustes_Manuais!$F:$F,"Técnico de Som / Luz") | AD50: =-SUMIFS(T_ORCAMENTOS!$E:$E,T_ORCAMENTOS!$C:$C,"Técnico de Som / Luz",T_ORCAMENTOS!$H:$H,"8/2026") | AE50: =SUMIFS(Aut_BlueMe_Sem_Pedido!$J:$J,Aut_BlueMe_Sem_Pedido!$Q:$Q,DRE!AC$4,Aut_BlueMe_Sem_Pedido!$H:$H,DRE!$A50)+SUMIFS(Aut_Ajustes_Manuais!$G:$G,Aut_Ajustes_Manuais!$I:$I,DRE!AC$4,Aut_Ajustes_Manuais!$F:$F,"Técnico de Som / Luz") | AG50: =-SUMIFS(T_ORCAMENTOS!$E:$E,T_ORCAMENTOS!$C:$C,"Técnico de Som / Luz",T_ORCAMENTOS!$H:$H,"9/2026") | AH50: =SUMIFS(Aut_BlueMe_Sem_Pedido!$J:$J,Aut_BlueMe_Sem_Pedido!$Q:$Q,DRE!AF$4,Aut_BlueMe_Sem_Pedido!$H:$H,DRE!$A50)+SUMIFS(Aut_Ajustes_Manuais!$G:$G,Aut_Ajustes_Manuais!$I:$I,DRE!AF$4,Aut_Ajustes_Manuais!$F:$F,"Técnico de Som / Luz") | AJ50: =-SUMIFS(T_ORCAMENTOS!$E:$E,T_ORCAMENTOS!$C:$C,"Técnico de Som / Luz",T_ORCAMENTOS!$H:$H,"10/2026") | AK50: =SUMIFS(Aut_BlueMe_Sem_Pedido!$J:$J,Aut_BlueMe_Sem_Pedido!$Q:$Q,DRE!AI$4,Aut_BlueMe_Sem_Pedido!$H:$H,DRE!$A50)+SUMIFS(Aut_Ajustes_Manuais!$G:$G,Aut_Ajustes_Manuais!$I:$I,DRE!AI$4,Aut_Ajustes_Manuais!$F:$F,"Técnico de Som / Luz") | AM50: =-SUMIFS(T_ORCAMENTOS!$E:$E,T_ORCAMENTOS!$C:$C,"Técnico de Som / Luz",T_ORCAMENTOS!$H:$H,"11/2026") | AN50: =SUMIFS(Aut_BlueMe_Sem_Pedido!$J:$J,Aut_BlueMe_Sem_Pedido!$Q:$Q,DRE!AL$4,Aut_BlueMe_Sem_Pedido!$H:$H,DRE!$A50)+SUMIFS(Aut_Ajustes_Manuais!$G:$G,Aut_Ajustes_Manuais!$I:$I,DRE!AL$4,Aut_Ajustes_Manuais!$F:$F,"Técnico de Som / Luz") | AP50: =-SUMIFS(T_ORCAMENTOS!$E:$E,T_ORCAMENTOS!$C:$C,"Técnico de Som / Luz",T_ORCAMENTOS!$H:$H,"12/2026") | AQ50: =SUMIFS(Aut_BlueMe_Sem_Pedido!$J:$J,Aut_BlueMe_Sem_Pedido!$Q:$Q,DRE!AO$4,Aut_BlueMe_Sem_Pedido!$H:$H,DRE!$A50)+SUMIFS(Aut_Ajustes_Manuais!$G:$G,Aut_Ajustes_Manuais!$I:$I,DRE!AO$4,Aut_Ajustes_Manuais!$F:$F,"Técnico de Som / Luz") | AR50: =SUMIFS($H50:$AO50,$H$5:$AO$5,"<"&MONTH(TODAY()),$H$6:$AO$6,"REAL 25") | AS50: =SUMIFS($I50:$AP50,$I$5:$AP$5,"<"&MONTH(TODAY()),$I$6:$AP$6,"ORÇADO ") | AT50: =SUMIFS($J50:$AQ50,$J$5:$AQ$5,"<"&MONTH(TODAY()),$J$6:$AQ$6,"REAL 26") | AU50: =SUM(H50,K50,N50,Q50,T50,W50,Z50,AC50,AF50,AI50,AL50,AO50) | AV50: =SUM(I50,L50,O50,R50,U50,X50,AA50,AD50,AG50,AJ50,AM50,AP50) | AW50: =SUM(J50,M50,P50,S50,V50,Y50,AB50,AE50,AH50,AK50,AN50,AQ50) | AX50: =SUM(H50,K50,N50) | AY50: =SUM(I50,L50,O50) | AZ50: =SUM(J50,M50,P50) | BA50: =SUM(Q50,T50,W50) | BB50: =SUM(R50,U50,X50) | BC50: =SUM(S50,V50,Y50) | BD50: =SUM(Z50,AC50,AF50) | BE50: =SUM(AA50,AD50,AG50) | BF50: =SUM(AB50,AE50,AH50) | BG50: =SUM(AI50,AL50,AO50) | BH50: =SUM(AJ50,AM50,AP50) | BI50: =SUM(AK50,AN50,AQ50)
A51: Locação de Equipamentos Fixo | C51: Contr/Prov | I51: =-SUMIFS(T_ORCAMENTOS!$E:$E,T_ORCAMENTOS!$C:$C,"Locação de Equipamentos Fixo",T_ORCAMENTOS!$H:$H,"1/2026") | J51: =SUMIFS(Aut_BlueMe_Sem_Pedido!$J:$J,Aut_BlueMe_Sem_Pedido!$Q:$Q,DRE!H$4,Aut_BlueMe_Sem_Pedido!$H:$H,DRE!$A51)+SUMIFS(Aut_Ajustes_Manuais!$G:$G,Aut_Ajustes_Manuais!$I:$I,DRE!H$4,Aut_Ajustes_Manuais!$F:$F,"Locação de Equipamentos Fixo") | L51: =-SUMIFS(T_ORCAMENTOS!$E:$E,T_ORCAMENTOS!$C:$C,"Locação de Equipamentos Fixo",T_ORCAMENTOS!$H:$H,"2/2026") | M51: =SUMIFS(Aut_BlueMe_Sem_Pedido!$J:$J,Aut_BlueMe_Sem_Pedido!$Q:$Q,DRE!K$4,Aut_BlueMe_Sem_Pedido!$H:$H,DRE!$A51)+SUMIFS(Aut_Ajustes_Manuais!$G:$G,Aut_Ajustes_Manuais!$I:$I,DRE!K$4,Aut_Ajustes_Manuais!$F:$F,"Locação de Equipamentos Fixo") | O51: =-SUMIFS(T_ORCAMENTOS!$E:$E,T_ORCAMENTOS!$C:$C,"Locação de Equipamentos Fixo",T_ORCAMENTOS!$H:$H,"3/2026") | P51: =SUMIFS(Aut_BlueMe_Sem_Pedido!$J:$J,Aut_BlueMe_Sem_Pedido!$Q:$Q,DRE!N$4,Aut_BlueMe_Sem_Pedido!$H:$H,DRE!$A51)+SUMIFS(Aut_Ajustes_Manuais!$G:$G,Aut_Ajustes_Manuais!$I:$I,DRE!N$4,Aut_Ajustes_Manuais!$F:$F,"Locação de Equipamentos Fixo") | R51: =-SUMIFS(T_ORCAMENTOS!$E:$E,T_ORCAMENTOS!$C:$C,"Locação de Equipamentos Fixo",T_ORCAMENTOS!$H:$H,"4/2026") | S51: =SUMIFS(Aut_BlueMe_Sem_Pedido!$J:$J,Aut_BlueMe_Sem_Pedido!$Q:$Q,DRE!Q$4,Aut_BlueMe_Sem_Pedido!$H:$H,DRE!$A51)+SUMIFS(Aut_Ajustes_Manuais!$G:$G,Aut_Ajustes_Manuais!$I:$I,DRE!Q$4,Aut_Ajustes_Manuais!$F:$F,"Locação de Equipamentos Fixo") | U51: =-SUMIFS(T_ORCAMENTOS!$E:$E,T_ORCAMENTOS!$C:$C,"Locação de Equipamentos Fixo",T_ORCAMENTOS!$H:$H,"5/2026") | V51: =SUMIFS(Aut_BlueMe_Sem_Pedido!$J:$J,Aut_BlueMe_Sem_Pedido!$Q:$Q,DRE!T$4,Aut_BlueMe_Sem_Pedido!$H:$H,DRE!$A51)+SUMIFS(Aut_Ajustes_Manuais!$G:$G,Aut_Ajustes_Manuais!$I:$I,DRE!T$4,Aut_Ajustes_Manuais!$F:$F,"Locação de Equipamentos Fixo") | X51: =-SUMIFS(T_ORCAMENTOS!$E:$E,T_ORCAMENTOS!$C:$C,"Locação de Equipamentos Fixo",T_ORCAMENTOS!$H:$H,"6/2026") | Y51: =SUMIFS(Aut_BlueMe_Sem_Pedido!$J:$J,Aut_BlueMe_Sem_Pedido!$Q:$Q,DRE!W$4,Aut_BlueMe_Sem_Pedido!$H:$H,DRE!$A51)+SUMIFS(Aut_Ajustes_Manuais!$G:$G,Aut_Ajustes_Manuais!$I:$I,DRE!W$4,Aut_Ajustes_Manuais!$F:$F,"Locação de Equipamentos Fixo") | AA51: =-SUMIFS(T_ORCAMENTOS!$E:$E,T_ORCAMENTOS!$C:$C,"Locação de Equipamentos Fixo",T_ORCAMENTOS!$H:$H,"7/2026") | AB51: =SUMIFS(Aut_BlueMe_Sem_Pedido!$J:$J,Aut_BlueMe_Sem_Pedido!$Q:$Q,DRE!Z$4,Aut_BlueMe_Sem_Pedido!$H:$H,DRE!$A51)+SUMIFS(Aut_Ajustes_Manuais!$G:$G,Aut_Ajustes_Manuais!$I:$I,DRE!Z$4,Aut_Ajustes_Manuais!$F:$F,"Locação de Equipamentos Fixo") | AD51: =-SUMIFS(T_ORCAMENTOS!$E:$E,T_ORCAMENTOS!$C:$C,"Locação de Equipamentos Fixo",T_ORCAMENTOS!$H:$H,"8/2026") | AE51: =SUMIFS(Aut_BlueMe_Sem_Pedido!$J:$J,Aut_BlueMe_Sem_Pedido!$Q:$Q,DRE!AC$4,Aut_BlueMe_Sem_Pedido!$H:$H,DRE!$A51)+SUMIFS(Aut_Ajustes_Manuais!$G:$G,Aut_Ajustes_Manuais!$I:$I,DRE!AC$4,Aut_Ajustes_Manuais!$F:$F,"Locação de Equipamentos Fixo") | AG51: =-SUMIFS(T_ORCAMENTOS!$E:$E,T_ORCAMENTOS!$C:$C,"Locação de Equipamentos Fixo",T_ORCAMENTOS!$H:$H,"9/2026") | AH51: =SUMIFS(Aut_BlueMe_Sem_Pedido!$J:$J,Aut_BlueMe_Sem_Pedido!$Q:$Q,DRE!AF$4,Aut_BlueMe_Sem_Pedido!$H:$H,DRE!$A51)+SUMIFS(Aut_Ajustes_Manuais!$G:$G,Aut_Ajustes_Manuais!$I:$I,DRE!AF$4,Aut_Ajustes_Manuais!$F:$F,"Locação de Equipamentos Fixo") | AJ51: =-SUMIFS(T_ORCAMENTOS!$E:$E,T_ORCAMENTOS!$C:$C,"Locação de Equipamentos Fixo",T_ORCAMENTOS!$H:$H,"10/2026") | AK51: =SUMIFS(Aut_BlueMe_Sem_Pedido!$J:$J,Aut_BlueMe_Sem_Pedido!$Q:$Q,DRE!AI$4,Aut_BlueMe_Sem_Pedido!$H:$H,DRE!$A51)+SUMIFS(Aut_Ajustes_Manuais!$G:$G,Aut_Ajustes_Manuais!$I:$I,DRE!AI$4,Aut_Ajustes_Manuais!$F:$F,"Locação de Equipamentos Fixo") | AM51: =-SUMIFS(T_ORCAMENTOS!$E:$E,T_ORCAMENTOS!$C:$C,"Locação de Equipamentos Fixo",T_ORCAMENTOS!$H:$H,"11/2026") | AN51: =SUMIFS(Aut_BlueMe_Sem_Pedido!$J:$J,Aut_BlueMe_Sem_Pedido!$Q:$Q,DRE!AL$4,Aut_BlueMe_Sem_Pedido!$H:$H,DRE!$A51)+SUMIFS(Aut_Ajustes_Manuais!$G:$G,Aut_Ajustes_Manuais!$I:$I,DRE!AL$4,Aut_Ajustes_Manuais!$F:$F,"Locação de Equipamentos Fixo") | AP51: =-SUMIFS(T_ORCAMENTOS!$E:$E,T_ORCAMENTOS!$C:$C,"Locação de Equipamentos Fixo",T_ORCAMENTOS!$H:$H,"12/2026") | AQ51: =SUMIFS(Aut_BlueMe_Sem_Pedido!$J:$J,Aut_BlueMe_Sem_Pedido!$Q:$Q,DRE!AO$4,Aut_BlueMe_Sem_Pedido!$H:$H,DRE!$A51)+SUMIFS(Aut_Ajustes_Manuais!$G:$G,Aut_Ajustes_Manuais!$I:$I,DRE!AO$4,Aut_Ajustes_Manuais!$F:$F,"Locação de Equipamentos Fixo") | AR51: =SUMIFS($H51:$AO51,$H$5:$AO$5,"<"&MONTH(TODAY()),$H$6:$AO$6,"REAL 25") | AS51: =SUMIFS($I51:$AP51,$I$5:$AP$5,"<"&MONTH(TODAY()),$I$6:$AP$6,"ORÇADO ") | AT51: =SUMIFS($J51:$AQ51,$J$5:$AQ$5,"<"&MONTH(TODAY()),$J$6:$AQ$6,"REAL 26") | AU51: =SUM(H51,K51,N51,Q51,T51,W51,Z51,AC51,AF51,AI51,AL51,AO51) | AV51: =SUM(I51,L51,O51,R51,U51,X51,AA51,AD51,AG51,AJ51,AM51,AP51) | AW51: =SUM(J51,M51,P51,S51,V51,Y51,AB51,AE51,AH51,AK51,AN51,AQ51) | AX51: =SUM(H51,K51,N51) | AY51: =SUM(I51,L51,O51) | AZ51: =SUM(J51,M51,P51) | BA51: =SUM(Q51,T51,W51) | BB51: =SUM(R51,U51,X51) | BC51: =SUM(S51,V51,Y51) | BD51: =SUM(Z51,AC51,AF51) | BE51: =SUM(AA51,AD51,AG51) | BF51: =SUM(AB51,AE51,AH51) | BG51: =SUM(AI51,AL51,AO51) | BH51: =SUM(AJ51,AM51,AP51) | BI51: =SUM(AK51,AN51,AQ51)
A52: Locação de Equipamentos Variável | C52: Estim. Mensal | E52: 0 | I52: =-SUMIFS(T_ORCAMENTOS!$E:$E,T_ORCAMENTOS!$C:$C,"Locação de Equipamentos Variável",T_ORCAMENTOS!$H:$H,"1/2026") | J52: =SUMIFS(Aut_BlueMe_Sem_Pedido!$J:$J,Aut_BlueMe_Sem_Pedido!$Q:$Q,DRE!H$4,Aut_BlueMe_Sem_Pedido!$H:$H,DRE!$A52)+SUMIFS(Aut_Ajustes_Manuais!$G:$G,Aut_Ajustes_Manuais!$I:$I,DRE!H$4,Aut_Ajustes_Manuais!$F:$F,"Locação de Equipamentos Variável") | L52: =-SUMIFS(T_ORCAMENTOS!$E:$E,T_ORCAMENTOS!$C:$C,"Locação de Equipamentos Variável",T_ORCAMENTOS!$H:$H,"2/2026") | M52: =SUMIFS(Aut_BlueMe_Sem_Pedido!$J:$J,Aut_BlueMe_Sem_Pedido!$Q:$Q,DRE!K$4,Aut_BlueMe_Sem_Pedido!$H:$H,DRE!$A52)+SUMIFS(Aut_Ajustes_Manuais!$G:$G,Aut_Ajustes_Manuais!$I:$I,DRE!K$4,Aut_Ajustes_Manuais!$F:$F,"Locação de Equipamentos Variável") | O52: =-SUMIFS(T_ORCAMENTOS!$E:$E,T_ORCAMENTOS!$C:$C,"Locação de Equipamentos Variável",T_ORCAMENTOS!$H:$H,"3/2026") | P52: =SUMIFS(Aut_BlueMe_Sem_Pedido!$J:$J,Aut_BlueMe_Sem_Pedido!$Q:$Q,DRE!N$4,Aut_BlueMe_Sem_Pedido!$H:$H,DRE!$A52)+SUMIFS(Aut_Ajustes_Manuais!$G:$G,Aut_Ajustes_Manuais!$I:$I,DRE!N$4,Aut_Ajustes_Manuais!$F:$F,"Locação de Equipamentos Variável") | R52: =-SUMIFS(T_ORCAMENTOS!$E:$E,T_ORCAMENTOS!$C:$C,"Locação de Equipamentos Variável",T_ORCAMENTOS!$H:$H,"4/2026") | S52: =SUMIFS(Aut_BlueMe_Sem_Pedido!$J:$J,Aut_BlueMe_Sem_Pedido!$Q:$Q,DRE!Q$4,Aut_BlueMe_Sem_Pedido!$H:$H,DRE!$A52)+SUMIFS(Aut_Ajustes_Manuais!$G:$G,Aut_Ajustes_Manuais!$I:$I,DRE!Q$4,Aut_Ajustes_Manuais!$F:$F,"Locação de Equipamentos Variável") | U52: =-SUMIFS(T_ORCAMENTOS!$E:$E,T_ORCAMENTOS!$C:$C,"Locação de Equipamentos Variável",T_ORCAMENTOS!$H:$H,"5/2026") | V52: =SUMIFS(Aut_BlueMe_Sem_Pedido!$J:$J,Aut_BlueMe_Sem_Pedido!$Q:$Q,DRE!T$4,Aut_BlueMe_Sem_Pedido!$H:$H,DRE!$A52)+SUMIFS(Aut_Ajustes_Manuais!$G:$G,Aut_Ajustes_Manuais!$I:$I,DRE!T$4,Aut_Ajustes_Manuais!$F:$F,"Locação de Equipamentos Variável") | X52: =-SUMIFS(T_ORCAMENTOS!$E:$E,T_ORCAMENTOS!$C:$C,"Locação de Equipamentos Variável",T_ORCAMENTOS!$H:$H,"6/2026") | Y52: =SUMIFS(Aut_BlueMe_Sem_Pedido!$J:$J,Aut_BlueMe_Sem_Pedido!$Q:$Q,DRE!W$4,Aut_BlueMe_Sem_Pedido!$H:$H,DRE!$A52)+SUMIFS(Aut_Ajustes_Manuais!$G:$G,Aut_Ajustes_Manuais!$I:$I,DRE!W$4,Aut_Ajustes_Manuais!$F:$F,"Locação de Equipamentos Variável") | AA52: =-SUMIFS(T_ORCAMENTOS!$E:$E,T_ORCAMENTOS!$C:$C,"Locação de Equipamentos Variável",T_ORCAMENTOS!$H:$H,"7/2026") | AB52: =SUMIFS(Aut_BlueMe_Sem_Pedido!$J:$J,Aut_BlueMe_Sem_Pedido!$Q:$Q,DRE!Z$4,Aut_BlueMe_Sem_Pedido!$H:$H,DRE!$A52)+SUMIFS(Aut_Ajustes_Manuais!$G:$G,Aut_Ajustes_Manuais!$I:$I,DRE!Z$4,Aut_Ajustes_Manuais!$F:$F,"Locação de Equipamentos Variável") | AD52: =-SUMIFS(T_ORCAMENTOS!$E:$E,T_ORCAMENTOS!$C:$C,"Locação de Equipamentos Variável",T_ORCAMENTOS!$H:$H,"8/2026") | AE52: =SUMIFS(Aut_BlueMe_Sem_Pedido!$J:$J,Aut_BlueMe_Sem_Pedido!$Q:$Q,DRE!AC$4,Aut_BlueMe_Sem_Pedido!$H:$H,DRE!$A52)+SUMIFS(Aut_Ajustes_Manuais!$G:$G,Aut_Ajustes_Manuais!$I:$I,DRE!AC$4,Aut_Ajustes_Manuais!$F:$F,"Locação de Equipamentos Variável") | AG52: =-SUMIFS(T_ORCAMENTOS!$E:$E,T_ORCAMENTOS!$C:$C,"Locação de Equipamentos Variável",T_ORCAMENTOS!$H:$H,"9/2026") | AH52: =SUMIFS(Aut_BlueMe_Sem_Pedido!$J:$J,Aut_BlueMe_Sem_Pedido!$Q:$Q,DRE!AF$4,Aut_BlueMe_Sem_Pedido!$H:$H,DRE!$A52)+SUMIFS(Aut_Ajustes_Manuais!$G:$G,Aut_Ajustes_Manuais!$I:$I,DRE!AF$4,Aut_Ajustes_Manuais!$F:$F,"Locação de Equipamentos Variável") | AJ52: =-SUMIFS(T_ORCAMENTOS!$E:$E,T_ORCAMENTOS!$C:$C,"Locação de Equipamentos Variável",T_ORCAMENTOS!$H:$H,"10/2026") | AK52: =SUMIFS(Aut_BlueMe_Sem_Pedido!$J:$J,Aut_BlueMe_Sem_Pedido!$Q:$Q,DRE!AI$4,Aut_BlueMe_Sem_Pedido!$H:$H,DRE!$A52)+SUMIFS(Aut_Ajustes_Manuais!$G:$G,Aut_Ajustes_Manuais!$I:$I,DRE!AI$4,Aut_Ajustes_Manuais!$F:$F,"Locação de Equipamentos Variável") | AM52: =-SUMIFS(T_ORCAMENTOS!$E:$E,T_ORCAMENTOS!$C:$C,"Locação de Equipamentos Variável",T_ORCAMENTOS!$H:$H,"11/2026") | AN52: =SUMIFS(Aut_BlueMe_Sem_Pedido!$J:$J,Aut_BlueMe_Sem_Pedido!$Q:$Q,DRE!AL$4,Aut_BlueMe_Sem_Pedido!$H:$H,DRE!$A52)+SUMIFS(Aut_Ajustes_Manuais!$G:$G,Aut_Ajustes_Manuais!$I:$I,DRE!AL$4,Aut_Ajustes_Manuais!$F:$F,"Locação de Equipamentos Variável") | AP52: =-SUMIFS(T_ORCAMENTOS!$E:$E,T_ORCAMENTOS!$C:$C,"Locação de Equipamentos Variável",T_ORCAMENTOS!$H:$H,"12/2026") | AQ52: =SUMIFS(Aut_BlueMe_Sem_Pedido!$J:$J,Aut_BlueMe_Sem_Pedido!$Q:$Q,DRE!AO$4,Aut_BlueMe_Sem_Pedido!$H:$H,DRE!$A52)+SUMIFS(Aut_Ajustes_Manuais!$G:$G,Aut_Ajustes_Manuais!$I:$I,DRE!AO$4,Aut_Ajustes_Manuais!$F:$F,"Locação de Equipamentos Variável") | AR52: =SUMIFS($H52:$AO52,$H$5:$AO$5,"<"&MONTH(TODAY()),$H$6:$AO$6,"REAL 25") | AS52: =SUMIFS($I52:$AP52,$I$5:$AP$5,"<"&MONTH(TODAY()),$I$6:$AP$6,"ORÇADO ") | AT52: =SUMIFS($J52:$AQ52,$J$5:$AQ$5,"<"&MONTH(TODAY()),$J$6:$AQ$6,"REAL 26") | AU52: =SUM(H52,K52,N52,Q52,T52,W52,Z52,AC52,AF52,AI52,AL52,AO52) | AV52: =SUM(I52,L52,O52,R52,U52,X52,AA52,AD52,AG52,AJ52,AM52,AP52) | AW52: =SUM(J52,M52,P52,S52,V52,Y52,AB52,AE52,AH52,AK52,AN52,AQ52) | AX52: =SUM(H52,K52,N52) | AY52: =SUM(I52,L52,O52) | AZ52: =SUM(J52,M52,P52) | BA52: =SUM(Q52,T52,W52) | BB52: =SUM(R52,U52,X52) | BC52: =SUM(S52,V52,Y52) | BD52: =SUM(Z52,AC52,AF52) | BE52: =SUM(AA52,AD52,AG52) | BF52: =SUM(AB52,AE52,AH52) | BG52: =SUM(AI52,AL52,AO52) | BH52: =SUM(AJ52,AM52,AP52) | BI52: =SUM(AK52,AN52,AQ52)
A53: % sobre Receita Artístico | I53: =IFERROR(I42/I11,0) | J53: =IFERROR(J42/J11,0)+SUMIFS(Aut_Ajustes_Manuais!$G:$G,Aut_Ajustes_Manuais!$I:$I,DRE!H$4,Aut_Ajustes_Manuais!$F:$F,"% sobre Receita Artístico") | L53: =IFERROR(L42/L11,0) | M53: =IFERROR(M42/M11,0)+SUMIFS(Aut_Ajustes_Manuais!$G:$G,Aut_Ajustes_Manuais!$I:$I,DRE!K$4,Aut_Ajustes_Manuais!$F:$F,"% sobre Receita Artístico") | O53: =IFERROR(O42/O11,0) | P53: =IFERROR(P42/P11,0)+SUMIFS(Aut_Ajustes_Manuais!$G:$G,Aut_Ajustes_Manuais!$I:$I,DRE!N$4,Aut_Ajustes_Manuais!$F:$F,"% sobre Receita Artístico") | R53: =IFERROR(R42/R11,0) | S53: =IFERROR(S42/S11,0)+SUMIFS(Aut_Ajustes_Manuais!$G:$G,Aut_Ajustes_Manuais!$I:$I,DRE!Q$4,Aut_Ajustes_Manuais!$F:$F,"% sobre Receita Artístico") | U53: =IFERROR(U42/U11,0) | V53: =IFERROR(V42/V11,0)+SUMIFS(Aut_Ajustes_Manuais!$G:$G,Aut_Ajustes_Manuais!$I:$I,DRE!T$4,Aut_Ajustes_Manuais!$F:$F,"% sobre Receita Artístico") | X53: =IFERROR(X42/X11,0) | Y53: =IFERROR(Y42/Y11,0)+SUMIFS(Aut_Ajustes_Manuais!$G:$G,Aut_Ajustes_Manuais!$I:$I,DRE!W$4,Aut_Ajustes_Manuais!$F:$F,"% sobre Receita Artístico") | AA53: =IFERROR(AA42/AA11,0) | AB53: =IFERROR(AB42/AB11,0)+SUMIFS(Aut_Ajustes_Manuais!$G:$G,Aut_Ajustes_Manuais!$I:$I,DRE!Z$4,Aut_Ajustes_Manuais!$F:$F,"% sobre Receita Artístico") | AD53: =IFERROR(AD42/AD11,0) | AE53: =IFERROR(AE42/AE11,0)+SUMIFS(Aut_Ajustes_Manuais!$G:$G,Aut_Ajustes_Manuais!$I:$I,DRE!AC$4,Aut_Ajustes_Manuais!$F:$F,"% sobre Receita Artístico") | AG53: =IFERROR(AG42/AG11,0) | AH53: =IFERROR(AH42/AH11,0)+SUMIFS(Aut_Ajustes_Manuais!$G:$G,Aut_Ajustes_Manuais!$I:$I,DRE!AF$4,Aut_Ajustes_Manuais!$F:$F,"% sobre Receita Artístico") | AJ53: =IFERROR(AJ42/AJ11,0) | AK53: =IFERROR(AK42/AK11,0)+SUMIFS(Aut_Ajustes_Manuais!$G:$G,Aut_Ajustes_Manuais!$I:$I,DRE!AI$4,Aut_Ajustes_Manuais!$F:$F,"% sobre Receita Artístico") | AM53: =IFERROR(AM42/AM11,0) | AN53: =IFERROR(AN42/AN11,0)+SUMIFS(Aut_Ajustes_Manuais!$G:$G,Aut_Ajustes_Manuais!$I:$I,DRE!AL$4,Aut_Ajustes_Manuais!$F:$F,"% sobre Receita Artístico") | AP53: =IFERROR(AP42/AP11,0) | AQ53: =IFERROR(AQ42/AQ11,0)+SUMIFS(Aut_Ajustes_Manuais!$G:$G,Aut_Ajustes_Manuais!$I:$I,DRE!AO$4,Aut_Ajustes_Manuais!$F:$F,"% sobre Receita Artístico") | AR53: =IFERROR(AR42/AR11,0) | AS53: =IFERROR(AS42/AS11,0) | AT53: =IFERROR(AT42/AT11,0) | AU53: =IFERROR(AU42/AU11,0) | AV53: =IFERROR(AV42/AV11,0) | AW53: =IFERROR(AW42/AW11,0) | AX53: =IFERROR(AX42/AX11,0) | AY53: =IFERROR(AY42/AY11,0) | ... BI53: =IFERROR(BI42/BI11,0)
A54: % sobre Receita Bruta | I54: =IFERROR(I42/I8,0) | J54: =IFERROR(J42/J8,0)+SUMIFS(Aut_Ajustes_Manuais!$G:$G,Aut_Ajustes_Manuais!$I:$I,DRE!H$4,Aut_Ajustes_Manuais!$F:$F,"% sobre Receita Bruta") | L54: =IFERROR(L42/L8,0) | M54: =IFERROR(M42/M8,0)+SUMIFS(Aut_Ajustes_Manuais!$G:$G,Aut_Ajustes_Manuais!$I:$I,DRE!K$4,Aut_Ajustes_Manuais!$F:$F,"% sobre Receita Bruta") | O54: =IFERROR(O42/O8,0) | P54: =IFERROR(P42/P8,0)+SUMIFS(Aut_Ajustes_Manuais!$G:$G,Aut_Ajustes_Manuais!$I:$I,DRE!N$4,Aut_Ajustes_Manuais!$F:$F,"% sobre Receita Bruta") | R54: =IFERROR(R42/R8,0) | S54: =IFERROR(S42/S8,0)+SUMIFS(Aut_Ajustes_Manuais!$G:$G,Aut_Ajustes_Manuais!$I:$I,DRE!Q$4,Aut_Ajustes_Manuais!$F:$F,"% sobre Receita Bruta") | U54: =IFERROR(U42/U8,0) | V54: =IFERROR(V42/V8,0)+SUMIFS(Aut_Ajustes_Manuais!$G:$G,Aut_Ajustes_Manuais!$I:$I,DRE!T$4,Aut_Ajustes_Manuais!$F:$F,"% sobre Receita Bruta") | X54: =IFERROR(X42/X8,0) | Y54: =IFERROR(Y42/Y8,0)+SUMIFS(Aut_Ajustes_Manuais!$G:$G,Aut_Ajustes_Manuais!$I:$I,DRE!W$4,Aut_Ajustes_Manuais!$F:$F,"% sobre Receita Bruta") | AA54: =IFERROR(AA42/AA8,0) | AB54: =IFERROR(AB42/AB8,0)+SUMIFS(Aut_Ajustes_Manuais!$G:$G,Aut_Ajustes_Manuais!$I:$I,DRE!Z$4,Aut_Ajustes_Manuais!$F:$F,"% sobre Receita Bruta") | AD54: =IFERROR(AD42/AD8,0) | AE54: =IFERROR(AE42/AE8,0)+SUMIFS(Aut_Ajustes_Manuais!$G:$G,Aut_Ajustes_Manuais!$I:$I,DRE!AC$4,Aut_Ajustes_Manuais!$F:$F,"% sobre Receita Bruta") | AG54: =IFERROR(AG42/AG8,0) | AH54: =IFERROR(AH42/AH8,0)+SUMIFS(Aut_Ajustes_Manuais!$G:$G,Aut_Ajustes_Manuais!$I:$I,DRE!AF$4,Aut_Ajustes_Manuais!$F:$F,"% sobre Receita Bruta") | AJ54: =IFERROR(AJ42/AJ8,0) | AK54: =IFERROR(AK42/AK8,0)+SUMIFS(Aut_Ajustes_Manuais!$G:$G,Aut_Ajustes_Manuais!$I:$I,DRE!AI$4,Aut_Ajustes_Manuais!$F:$F,"% sobre Receita Bruta") | AM54: =IFERROR(AM42/AM8,0) | AN54: =IFERROR(AN42/AN8,0)+SUMIFS(Aut_Ajustes_Manuais!$G:$G,Aut_Ajustes_Manuais!$I:$I,DRE!AL$4,Aut_Ajustes_Manuais!$F:$F,"% sobre Receita Bruta") | AP54: =IFERROR(AP42/AP8,0) | AQ54: =IFERROR(AQ42/AQ8,0)+SUMIFS(Aut_Ajustes_Manuais!$G:$G,Aut_Ajustes_Manuais!$I:$I,DRE!AO$4,Aut_Ajustes_Manuais!$F:$F,"% sobre Receita Bruta") | AR54: =IFERROR(AR42/AR8,0) | AS54: =IFERROR(AS42/AS8,0) | AT54: =IFERROR(AT42/AT8,0) | AU54: =IFERROR(AU42/AU8,0) | AV54: =IFERROR(AV42/AV8,0) | AW54: =IFERROR(AW42/AW8,0) | AX54: =IFERROR(AX42/AX8,0) | AY54: =IFERROR(AY42/AY8,0) | ... BI54: =IFERROR(BI42/BI8,0)
A56: (-) Custos Eventos | C56: Premissas | D56: Valores | E56: % Incid | H56: =SUM(H57,H60,H65,H70,H73,H77,H82) | I56: =SUM(I57,I60,I65,I70,I73,I77,I82) | J56: =SUM(J57,J60,J65,J70,J73,J77,J82)+SUMIFS(Aut_Ajustes_Manuais!$G:$G,Aut_Ajustes_Manuais!$I:$I,DRE!H$4,Aut_Ajustes_Manuais!$F:$F,"(-) Custos Eventos") | K56: =SUM(K57,K60,K65,K70,K73,K77,K82) | L56: =SUM(L57,L60,L65,L70,L73,L77,L82) | M56: =SUM(M57,M60,M65,M70,M73,M77,M82)+SUMIFS(Aut_Ajustes_Manuais!$G:$G,Aut_Ajustes_Manuais!$I:$I,DRE!K$4,Aut_Ajustes_Manuais!$F:$F,"(-) Custos Eventos") | N56: =SUM(N57,N60,N65,N70,N73,N77,N82) | O56: =SUM(O57,O60,O65,O70,O73,O77,O82) | P56: =SUM(P57,P60,P65,P70,P73,P77,P82)+SUMIFS(Aut_Ajustes_Manuais!$G:$G,Aut_Ajustes_Manuais!$I:$I,DRE!N$4,Aut_Ajustes_Manuais!$F:$F,"(-) Custos Eventos") | Q56: =SUM(Q57,Q60,Q65,Q70,Q73,Q77,Q82) | R56: =SUM(R57,R60,R65,R70,R73,R77,R82) | S56: =SUM(S57,S60,S65,S70,S73,S77,S82)+SUMIFS(Aut_Ajustes_Manuais!$G:$G,Aut_Ajustes_Manuais!$I:$I,DRE!Q$4,Aut_Ajustes_Manuais!$F:$F,"(-) Custos Eventos") | T56: =SUM(T57,T60,T65,T70,T73,T77,T82) | U56: =SUM(U57,U60,U65,U70,U73,U77,U82) | V56: =SUM(V57,V60,V65,V70,V73,V77,V82)+SUMIFS(Aut_Ajustes_Manuais!$G:$G,Aut_Ajustes_Manuais!$I:$I,DRE!T$4,Aut_Ajustes_Manuais!$F:$F,"(-) Custos Eventos") | W56: =SUM(W57,W60,W65,W70,W73,W77,W82) | X56: =SUM(X57,X60,X65,X70,X73,X77,X82) | Y56: =SUM(Y57,Y60,Y65,Y70,Y73,Y77,Y82)+SUMIFS(Aut_Ajustes_Manuais!$G:$G,Aut_Ajustes_Manuais!$I:$I,DRE!W$4,Aut_Ajustes_Manuais!$F:$F,"(-) Custos Eventos") | Z56: =SUM(Z57,Z60,Z65,Z70,Z73,Z77,Z82) | AA56: =SUM(AA57,AA60,AA65,AA70,AA73,AA77,AA82) | AB56: =SUM(AB57,AB60,AB65,AB70,AB73,AB77,AB82)+SUMIFS(Aut_Ajustes_Manuais!$G:$G,Aut_Ajustes_Manuais!$I:$I,DRE!Z$4,Aut_Ajustes_Manuais!$F:$F,"(-) Custos Eventos") | AC56: =SUM(AC57,AC60,AC65,AC70,AC73,AC77,AC82) | AD56: =SUM(AD57,AD60,AD65,AD70,AD73,AD77,AD82) | AE56: =SUM(AE57,AE60,AE65,AE70,AE73,AE77,AE82)+SUMIFS(Aut_Ajustes_Manuais!$G:$G,Aut_Ajustes_Manuais!$I:$I,DRE!AC$4,Aut_Ajustes_Manuais!$F:$F,"(-) Custos Eventos") | AF56: =SUM(AF57,AF60,AF65,AF70,AF73,AF77,AF82) | AG56: =SUM(AG57,AG60,AG65,AG70,AG73,AG77,AG82) | AH56: =SUM(AH57,AH60,AH65,AH70,AH73,AH77,AH82)+SUMIFS(Aut_Ajustes_Manuais!$G:$G,Aut_Ajustes_Manuais!$I:$I,DRE!AF$4,Aut_Ajustes_Manuais!$F:$F,"(-) Custos Eventos") | AI56: =SUM(AI57,AI60,AI65,AI70,AI73,AI77,AI82) | AJ56: =SUM(AJ57,AJ60,AJ65,AJ70,AJ73,AJ77,AJ82) | AK56: =SUM(AK57,AK60,AK65,AK70,AK73,AK77,AK82)+SUMIFS(Aut_Ajustes_Manuais!$G:$G,Aut_Ajustes_Manuais!$I:$I,DRE!AI$4,Aut_Ajustes_Manuais!$F:$F,"(-) Custos Eventos") | AL56: =SUM(AL57,AL60,AL65,AL70,AL73,AL77,AL82) | AM56: =SUM(AM57,AM60,AM65,AM70,AM73,AM77,AM82) | AN56: =SUM(AN57,AN60,AN65,AN70,AN73,AN77,AN82)+SUMIFS(Aut_Ajustes_Manuais!$G:$G,Aut_Ajustes_Manuais!$I:$I,DRE!AL$4,Aut_Ajustes_Manuais!$F:$F,"(-) Custos Eventos") | AO56: =SUM(AO57,AO60,AO65,AO70,AO73,AO77,AO82) | AP56: =SUM(AP57,AP60,AP65,AP70,AP73,AP77,AP82) | AQ56: =SUM(AQ57,AQ60,AQ65,AQ70,AQ73,AQ77,AQ82)+SUMIFS(Aut_Ajustes_Manuais!$G:$G,Aut_Ajustes_Manuais!$I:$I,DRE!AO$4,Aut_Ajustes_Manuais!$F:$F,"(-) Custos Eventos") | AR56: =SUM(AR57,AR60,AR65,AR73,AR77,AR82,AR70) | AS56: =SUM(AS57,AS60,AS65,AS73,AS77,AS82,AS70) | AT56: =SUM(AT57,AT60,AT65,AT73,AT77,AT82,AT70) | AU56: =SUM(AU57,AU60,AU65,AU70,AU73,AU77,AU82) | AV56: =SUM(AV57,AV60,AV65,AV70,AV73,AV77,AV82) | AW56: =SUM(AW57,AW60,AW65,AW70,AW73,AW77,AW82) | AX56: =SUM(AX57,AX60,AX65,AX70,AX73,AX77,AX82) | AY56: =SUM(AY57,AY60,AY65,AY70,AY73,AY77,AY82) | AZ56: =SUM(AZ57,AZ60,AZ65,AZ70,AZ73,AZ77,AZ82) | BA56: =SUM(BA57,BA60,BA65,BA70,BA73,BA77,BA82) | BB56: =SUM(BB57,BB60,BB65,BB70,BB73,BB77,BB82) | ... BI56: =SUM(BI57,BI60,BI65,BI70,BI73,BI77,BI82)
A57: MDO | I57: =SUM(I58:I59) | J57: =SUM(J58:J59)+SUMIFS(Aut_Ajustes_Manuais!$G:$G,Aut_Ajustes_Manuais!$I:$I,DRE!H$4,Aut_Ajustes_Manuais!$F:$F,"MDO") | L57: =SUM(L58:L59) | M57: =SUM(M58:M59)+SUMIFS(Aut_Ajustes_Manuais!$G:$G,Aut_Ajustes_Manuais!$I:$I,DRE!K$4,Aut_Ajustes_Manuais!$F:$F,"MDO") | O57: =SUM(O58:O59) | P57: =SUM(P58:P59)+SUMIFS(Aut_Ajustes_Manuais!$G:$G,Aut_Ajustes_Manuais!$I:$I,DRE!N$4,Aut_Ajustes_Manuais!$F:$F,"MDO") | R57: =SUM(R58:R59) | S57: =SUM(S58:S59)+SUMIFS(Aut_Ajustes_Manuais!$G:$G,Aut_Ajustes_Manuais!$I:$I,DRE!Q$4,Aut_Ajustes_Manuais!$F:$F,"MDO") | U57: =SUM(U58:U59) | V57: =SUM(V58:V59)+SUMIFS(Aut_Ajustes_Manuais!$G:$G,Aut_Ajustes_Manuais!$I:$I,DRE!T$4,Aut_Ajustes_Manuais!$F:$F,"MDO") | X57: =SUM(X58:X59) | Y57: =SUM(Y58:Y59)+SUMIFS(Aut_Ajustes_Manuais!$G:$G,Aut_Ajustes_Manuais!$I:$I,DRE!W$4,Aut_Ajustes_Manuais!$F:$F,"MDO") | AA57: =SUM(AA58:AA59) | AB57: =SUM(AB58:AB59)+SUMIFS(Aut_Ajustes_Manuais!$G:$G,Aut_Ajustes_Manuais!$I:$I,DRE!Z$4,Aut_Ajustes_Manuais!$F:$F,"MDO") | AD57: =SUM(AD58:AD59) | AE57: =SUM(AE58:AE59)+SUMIFS(Aut_Ajustes_Manuais!$G:$G,Aut_Ajustes_Manuais!$I:$I,DRE!AC$4,Aut_Ajustes_Manuais!$F:$F,"MDO") | AG57: =SUM(AG58:AG59) | AH57: =SUM(AH58:AH59)+SUMIFS(Aut_Ajustes_Manuais!$G:$G,Aut_Ajustes_Manuais!$I:$I,DRE!AF$4,Aut_Ajustes_Manuais!$F:$F,"MDO") | AJ57: =SUM(AJ58:AJ59) | AK57: =SUM(AK58:AK59)+SUMIFS(Aut_Ajustes_Manuais!$G:$G,Aut_Ajustes_Manuais!$I:$I,DRE!AI$4,Aut_Ajustes_Manuais!$F:$F,"MDO") | AM57: =SUM(AM58:AM59) | AN57: =SUM(AN58:AN59)+SUMIFS(Aut_Ajustes_Manuais!$G:$G,Aut_Ajustes_Manuais!$I:$I,DRE!AL$4,Aut_Ajustes_Manuais!$F:$F,"MDO") | AP57: =SUM(AP58:AP59) | AQ57: =SUM(AQ58:AQ59)+SUMIFS(Aut_Ajustes_Manuais!$G:$G,Aut_Ajustes_Manuais!$I:$I,DRE!AO$4,Aut_Ajustes_Manuais!$F:$F,"MDO") | AR57: =SUMIFS($H57:$AO57,$H$5:$AO$5,"<"&MONTH(TODAY()),$H$6:$AO$6,"REAL 25") | AS57: =SUMIFS($I57:$AP57,$I$5:$AP$5,"<"&MONTH(TODAY()),$I$6:$AP$6,"ORÇADO ") | AT57: =SUMIFS($J57:$AQ57,$J$5:$AQ$5,"<"&MONTH(TODAY()),$J$6:$AQ$6,"REAL 26") | AU57: =SUM(AU58:AU59) | AV57: =SUM(AV58:AV59) | AW57: =SUM(AW58:AW59) | AX57: =SUM(AX58:AX59) | AY57: =SUM(AY58:AY59) | AZ57: =SUM(AZ58:AZ59) | BA57: =SUM(BA58:BA59) | BB57: =SUM(BB58:BB59) | ... BI57: =SUM(BI58:BI59)
